Workbook

Sheet Board & Executives
A1: Company | B1: Board | C1: Exec | D1: Employer | E1: Fname | F1: MI | G1: Lname | H1: Gender | I1: State | J1: Age | K1: DOB | L1: Dem | M1: Rep | N1: Neu | O1: Reg | P1: Address
A2: BankofAmerica | B2: Y | C2: Y | D2: BOA CHAIRMAN & CEO | E2: Brian | F2: T. | G2: Moynihan | H2: M | I2: NC | J2: 61 | N2: =+'Brian Moynihan'!AJ2 -> 5000 | P2: 100 N TRYON ST CHARLOTTE NC 28255 | Q2: =+E2&F2&G2 -> Brian T. Moynihan
A3: BankofAmerica | B3: Y | C3: N | D3: LEAD INDEPENDENT DIRECTOR, former COO HCA, BOD Duke U, | E3: Jack | F3: O. | G3: Bovender, Jr. | H3: M | I3: TN | J3: 75 | M3: =+GETPIVOTDATA("contribution_receipt_amount",'Jack O. Bovender'!$A$14) -> 139900 | P3: 620 BELLE MEADE BLVD NASHVILLE TN 372053878 | Q3: =+E3&F3&G3 -> Jack O. Bovender, Jr.
A4: BankofAmerica | B4: Y | C4: N | D4: LEAD INDEPENDENT DIRECTOR SUCCESSOR, former Treasurer Pepsico, CFO & Controller | E4: Lionel | F4: L. | G4: Nowell III | H4: M | J4: 66 | Q4: =+E4&F4&G4 -> Lionel L. Nowell III | R4: No FEC Data
A5: BankofAmerica | B5: Y | C5: N | D5: Director, former chairman of Deloitte, former directory Albertsons | E5: Sharon | F5: L. | G5: Allen | H5: F | J5: 69 | K5: 18908 | Q5: =+E5&F5&G5 -> Sharon L. Allen | R5: No FEC Data
A6: BankofAmerica | B6: Y | C6: N | D6: Director,Former Member, Federal Reserve Board of Governors | E6: Susan | F6: S. | G6: Bies | H6: F | J6: 73 | K6: 17292 | Q6: =+E6&F6&G6 -> Susan S. Bies | R6: No FEC Data
A7: BankofAmerica | B7: Y | C7: N | D7: Director,Former Executive Vice Chairman, MBNA Corporation | E7: Frank | F7: P. | G7: Bramble, Sr. | H7: M | J7: 72 | Q7: =+E7&F7&G7 -> Frank P. Bramble, Sr. | R7: No FEC Data
A8: BankofAmerica | B8: Y | C8: N | D8: Director, Former Chairman and Global Head of Private Wealth Management, Deutsche Bank | E8: Pierre | F8: J.P. | G8: de Weck | H8: M | J8: 70 | Q8: =+E8&F8&G8 -> Pierre J.P. de Weck | R8: No FEC Data
A9: BankofAmerica | B9: Y | C9: N | D9: Director,President and Chief Executive Officer, Carnival | E9: Arnold | F9: W. | G9: Donald | H9: M | I9: MO | J9: 66 | K9: 1954 | P9: St Louis MO | Q9: =+E9&F9&G9 -> Arnold W. Donald | R9: No FEC Data
A10: BankofAmerica | B10: Y | C10: N | D10: Director,Former Chairman and Chief Executive Officer, The Cardea Group, LLC; Former President and Chief Executive Officer, BAE | E10: Linda | F10: P. | G10: Hudson | H10: F | I10: NC | J10: 70 | K10: 18497 | L10: =+'Linda Hudson'!AJ5 -> 2500 | P10: 15611 BALLANTYNE COUNTRY CLUB DR CHARLOTTE NC 282771406 | Q10: =+E10&F10&G10 -> Linda P. Hudson
A11: BankofAmerica | B11: Y | C11: N | D11: Director, Chief Executive Officer, College Futures Foundation; Former Chairman, US Hispanic Media Inc. | E11: Monica | F11: C. | G11: Lozano | H11: F | J11: 65 | K11: 20657 | L11: =+GETPIVOTDATA("contribution_receipt_amount",'Monica Lozano'!$A$39) -> 105036.66 | P11: 5610 GOLDEN GATE AVENUE OAKLAND CA 94618 | Q11: =+E11&F11&G11 -> Monica C. Lozano
A12: BankofAmerica | B12: Y | C12: N | D12: Director,Former Chairman, President, and Chief Executive Officer, Eversource Energy | E12: Thomas | F12: J. | G12: May | H12: M | J12: 74 | Q12: =+E12&F12&G12 -> Thomas J. May | R12: No FEC Data
A13: BankofAmerica | B13: Y | C13: N | D13: Director, Former Chief Executive Officer and President, ITT Inc. | E13: Denise | F13: L. | G13: Ramos | H13: F | J13: 64 | Q13: =+E13&F13&G13 -> Denise L. Ramos | R13: No FEC Data
A14: BankofAmerica | B14: Y | C14: N | D14: Director, President, Bowdoin College | E14: Clayton | F14: S. | G14: Rose | H14: M | I14: MA | J14: 62 | L14: =+GETPIVOTDATA("contribution_receipt_amount",'Clayton Rose'!$A$18) -> 174766.64 | O14: D | P14: 100 FEDERAL STREET BOSTON MA 21101802 | Q14: =+E14&F14&G14 -> Clayton S. Rose
A15: BankofAmerica | B15: Y | C15: N | D15: Director, Former Chairman, President, and Chief Executive Officer, DIRECTV; Lead Director, Kimberly-Clark Corporation | E15: Michael | F15: D. | G15: White | H15: M | J15: 69 | Q15: =+E15&F15&G15 -> Michael D. White | R15: No FEC Data
A16: BankofAmerica | B16: Y | C16: N | D16: Director, Former Vice Chairman and Senior Executive Vice President of CIBC; Former Chairman, Hydro One Limited | E16: Thomas | F16: D. | G16: Woods | H16: M | J16: 68 | Q16: =+E16&F16&G16 -> Thomas D. Woods | R16: No FEC Data
A17: BankofAmerica | B17: Y | C17: N | D17: Director, Former Chief Executive Officer, AmerisourceBergen | E17: R. | F17: David | G17: Yost | H17: M | J17: 73 | M17: =+'R David Yost'!AJ5 -> 2000 | P17: 502 GLENVIEW ROAD BRYN MAWR PA19010 | Q17: =+E17&F17&G17 -> R. David Yost
A18: BankofAmerica | B18: Y | C18: N | D18: Director, Vice President for Research and E. A. Griswold Professor of Geophysics, MIT | E18: Maria | F18: T. | G18: Zuber | H18: F | J18: 62 | K18: 21363 | Q18: =+E18&F18&G18 -> Maria T. Zuber | R18: No FEC Data
A19: BankofAmerica | B19: N | C19: Y | D19: President of Business Banking | E19: Raul | F19: A. | G19: Anaya | H19: M | I19: LA CA | Q19: =+E19&F19&G19 -> Raul A. Anaya | R19: No FEC Data
A20: BankofAmerica | B20: N | C20: Y | D20: Chief Operations and Technology Officer | E20: Catherine | F20: P. | G20: Bessant | H20: F | I20: Charlotte NC | N20: =+GETPIVOTDATA("contribution_receipt_amount",'Catherine Bessant'!$A$52) -> 5060 | P20: 100 N TRYON ST CHARLOTTE NC 28255 | Q20: =+E20&F20&G20 -> Catherine P. Bessant
A21: BankofAmerica | B21: N | C21: Y | D21: Chief Human Resources Officer | E21: Sheri | F21: B | G21: Bronstein | H21: F | I21: NY | N21: =+GETPIVOTDATA("contribution_receipt_amount",'Sheri Bronstein'!$A$46,"committee_name","BANK OF AMERICA CORPORATION FEDERAL PAC") -> 2000 | P21: ONE BRYANT PARK NEW YORK NY 10036 | Q21: Sheri B Bronstein | T21: Sheri B Bronstein
A22: BankofAmerica | B22: N | C22: Y | D22: Chief Financial Officer | E22: Paul | G22: Donofrio | H22: M | I22: NY | N22: =+GETPIVOTDATA("contribution_receipt_amount",'Paul Donofrio'!$A$34) -> 560 | P22: ONE BRYANT PARK NEW YORK NY 10037 | Q22: =+E22&F22&G22 -> Paul Donofrio
A23: BankofAmerica | B23: N | C23: Y | D23: Chief Operating Officer | E23: Thomas | F23: K. | G23: Montag | H23: M | M23: =+GETPIVOTDATA("contribution_receipt_amount",'Thomas Montag'!$A$91) -> 1147497.6 | P23: 127 E 73RD ST NEW YORK NY 100213502 | Q23: =+E23&F23&G23 -> Thomas K. Montag
A24: BankofAmerica | B24: N | C24: Y | D24: Chief Administrative Officer | E24: Andrea | F24: B. | G24: Smith | H24: F | N24: =+GETPIVOTDATA("contribution_receipt_amount",'Andrea Smith'!$A$51,"committee_name","BANK OF AMERICA CORPORATION FEDERAL PAC") -> 9357.88 | P24: 100 N TRYON ST CHARLOTTE NC 28255 | Q24: =+E24&F24&G24 -> Andrea B. Smith
A25: BankofAmerica | B25: N | C25: Y | D25: President, Merrill Lynch Wealth Management | E25: Andy | G25: Sieg | H25: M | I25: Greenwich Conn | Q25: =+E25&F25&G25 -> Andy Sieg | R25: No FEC Data
N29: Note: | P29: Many of the Board and Executives did not appear in the Aristotle DB

Sheet Andrea Smith
A1: committee_id | B1: committee_name | C1: report_year | D1: report_type | E1: image_number | F1: line_number | G1: transaction_id | H1: file_number | I1: committee_name | J1: entity_type | K1: entity_type_desc | L1: unused_contbr_id | M1: contributor_prefix | N1: contributor_name | O1: recipient_committee_type | P1: recipient_committee_org_type | Q1: recipient_committee_designation | R1: contributor_first_name | S1: contributor_middle_name | T1: contributor_last_name | U1: contributor_suffix | V1: contributor_street_1 | W1: contributor_street_2 | X1: contributor_city | Y1: contributor_state | Z1: contributor_zip | AA1: contributor_employer | AB1: contributor_occupation | AC1: contributor_id | AD1: receipt_type | AE1: receipt_type_desc | AF1: receipt_type_full | AG1: memo_code | AH1: memo_code_full | AI1: contribution_receipt_date | AJ1: contribution_receipt_amount | AK1: contributor_aggregate_ytd | AL1: candidate_id | AM1: candidate_name | AN1: candidate_first_name | AO1: candidate_last_name | AP1: candidate_middle_name | AQ1: candidate_prefix | AR1: candidate_suffix | AS1: candidate_office | AT1: candidate_office_full | AU1: candidate_office_state | AV1: candidate_office_state_full | AW1: candidate_office_district | AX1: conduit_committee_id | AY1: conduit_committee_name | AZ1: conduit_committee_street1 | BA1: conduit_committee_street2 | BB1: conduit_committee_city | BC1: conduit_committee_state | BD1: conduit_committee_zip | BE1: donor_committee_name | BF1: national_committee_nonfederal_account | BG1: election_type | BH1: election_type_full | BI1: fec_election_type_desc | BJ1: fec_election_year | BK1: amendment_indicator | BL1: amendment_indicator_desc | BM1: schedule_type_full | BN1: load_date | BO1: original_sub_id | BP1: back_reference_transaction_id | BQ1: back_reference_schedule_name | BR1: filing_form | BS1: link_id | BT1: is_individual | BU1: memo_text | BV1: two_year_transaction_period | BW1: schedule_type | BX1: increased_limit | BY1: sub_id | BZ1: pdf_url | CA1: line_number_label
A2: C00364778 | B2: BANK OF AMERICA CORPORATION FEDERAL PAC | C2: 2019 | D2: M4 | E2: 2.0190413e+17 | F2: 11AI | G2: A2019-517160 | H2: 1324297 | J2: IND | K2: INDIVIDUAL | N2: SMITH, ANDREA B | O2: Q | P2: C | Q2: B | R2: ANDREA | S2: B | T2: SMITH | V2: 100 N TRYON ST | X2: CHARLOTTE | Y2: NC | Z2: 28255 | AA2: BANK OF AMERICA | AB2: CHIEF ADMINISTRATIVE OFFICER | AD2: 15 | AE2: CONTRIBUTION | AI2: 43539 | AJ2: 175 | AK2: 875 | BG2: P | BI2: PRIMARY | BK2: A | BL2: ADD | BM2: ITEMIZED RECEIPTS | BN2: 43568.111 | BR2: F3X | BS2: 4.0412202e+18 | BT2: t | BV2: 2020 | BW2: SA | BY2: 4.0412202e+18 | BZ2: http://docquery.fec.gov/cgi-bin/fecimg/?201904129146103886 | CA2: Contributions From Individuals/Persons Other Than Political Committees
A3: C00364778 | B3: BANK OF AMERICA CORPORATION FEDERAL PAC | C3: 2019 | D3: M3 | E3: 2.0190316e+17 | F3: 11AI | G3: A2019-298508 | H3: 1319532 | J3: IND | K3: INDIVIDUAL | N3: SMITH, ANDREA B | O3: Q | P3: C | Q3: B | R3: ANDREA | S3: B | T3: SMITH | V3: 100 N TRYON ST | X3: CHARLOTTE | Y3: NC | Z3: 28255 | AA3: BANK OF AMERICA | AB3: CHIEF ADMINISTRATIVE OFFICER | AD3: 15 | AE3: CONTRIBUTION | AI3: 43511 | AJ3: 175 | AK3: 525 | BG3: P | BI3: PRIMARY | BK3: A | BL3: ADD | BM3: ITEMIZED RECEIPTS | BN3: 43543.128 | BR3: F3X | BS3: 4.0315202e+18 | BT3: t | BV3: 2020 | BW3: SA | BY3: 4.0318202e+18 | BZ3: http://docquery.fec.gov/cgi-bin/fecimg/?201903159145712554 | CA3: Contributions From Individuals/Persons Other Than Political Committees
A4: C00364778 | B4: BANK OF AMERICA CORPORATION FEDERAL PAC | C4: 2019 | D4: M2 | E4: 2.0190216e+17 | F4: 11AI | G4: A2019-82224 | H4: 1316134 | J4: IND | K4: INDIVIDUAL | N4: SMITH, ANDREA B | O4: Q | P4: C | Q4: B | R4: ANDREA | S4: B | T4: SMITH | V4: 100 N TRYON ST | X4: CHARLOTTE | Y4: NC | Z4: 28255 | AA4: BANK OF AMERICA | AB4: CHIEF ADMINISTRATIVE OFFICER | AD4: 15 | AE4: CONTRIBUTION | AI4: 43496 | AJ4: 175 | AK4: 350 | BG4: P | BI4: PRIMARY | BK4: A | BL4: ADD | BM4: ITEMIZED RECEIPTS | BN4: 43525.144 | BR4: F3X | BS4: 4.0215202e+18 | BT4: t | BV4: 2020 | BW4: SA | BY4: 4.0228202e+18 | BZ4: http://docquery.fec.gov/cgi-bin/fecimg/?201902159145519680 | CA4: Contributions From Individuals/Persons Other Than Political Committees
A5: C00364778 | B5: BANK OF AMERICA CORPORATION FEDERAL PAC | C5: 2019 | D5: M3 | E5: 2.0190316e+17 | F5: 11AI | G5: A2019-339759 | H5: 1319532 | J5: IND | K5: INDIVIDUAL | N5: SMITH, ANDREA B | O5: Q | P5: C | Q5: B | R5: ANDREA | S5: B | T5: SMITH | V5: 100 N TRYON ST | X5: CHARLOTTE | Y5: NC | Z5: 28255 | AA5: BANK OF AMERICA | AB5: CHIEF ADMINISTRATIVE OFFICER | AD5: 15 | AE5: CONTRIBUTION | AI5: 43524 | AJ5: 175 | AK5: 700 | BG5: P | BI5: PRIMARY | BK5: A | BL5: ADD | BM5: ITEMIZED RECEIPTS | BN5: 43543.128 | BR5: F3X | BS5: 4.0315202e+18 | BT5: t | BV5: 2020 | BW5: SA | BY5: 4.0318202e+18 | BZ5: http://docquery.fec.gov/cgi-bin/fecimg/?201903159145712554 | CA5: Contributions From Individuals/Persons Other Than Political Committees
A6: C00364778 | B6: BANK OF AMERICA CORPORATION FEDERAL PAC | C6: 2019 | D6: M4 | E6: 2.0190413e+17 | F6: 11AI | G6: A2019-547990 | H6: 1324297 | J6: IND | K6: INDIVIDUAL | N6: SMITH, ANDREA B | O6: Q | P6: C | Q6: B | R6: ANDREA | S6: B | T6: SMITH | V6: 100 N TRYON ST | X6: CHARLOTTE | Y6: NC | Z6: 28255 | AA6: BANK OF AMERICA | AB6: CHIEF ADMINISTRATIVE OFFICER | AD6: 15 | AE6: CONTRIBUTION | AI6: 43555 | AJ6: 175 | AK6: 1050 | BG6: P | BI6: PRIMARY | BK6: A | BL6: ADD | BM6: ITEMIZED RECEIPTS | BN6: 43568.111 | BR6: F3X | BS6: 4.0412202e+18 | BT6: t | BV6: 2020 | BW6: SA | BY6: 4.0412202e+18 | BZ6: http://docquery.fec.gov/cgi-bin/fecimg/?201904129146103887 | CA6: Contributions From Individuals/Persons Other Than Political Committees
A7: C00364778 | B7: BANK OF AMERICA CORPORATION FEDERAL PAC | C7: 2019 | D7: M5 | E7: 2.0190515e+17 | F7: 11AI | G7: A2019-792099 | H7: 1330608 | J7: IND | K7: INDIVIDUAL | N7: SMITH, ANDREA B | O7: Q | P7: C | Q7: B | R7: ANDREA | S7: B | T7: SMITH | V7: 100 N TRYON ST | X7: CHARLOTTE | Y7: NC | Z7: 28255 | AA7: BANK OF AMERICA | AB7: CHIEF ADMINISTRATIVE OFFICER | AD7: 15 | AE7: CONTRIBUTION | AI7: 43570 | AJ7: 175 | AK7: 1225 | BG7: P | BI7: PRIMARY | BK7: A | BL7: ADD | BM7: ITEMIZED RECEIPTS | BN7: 43600.358 | BR7: F3X | BS7: 4.0514202e+18 | BT7: t | BV7: 2020 | BW7: SA | BY7: 4.0514202e+18 | BZ7: http://docquery.fec.gov/cgi-bin/fecimg/?201905149149695965 | CA7: Contributions From Individuals/Persons Other Than Political Committees
A8: C00364778 | B8: BANK OF AMERICA CORPORATION FEDERAL PAC | C8: 2019 | D8: M5 | E8: 2.0190515e+17 | F8: 11AI | G8: A2019-844091 | H8: 1330608 | J8: IND | K8: INDIVIDUAL | N8: SMITH, ANDREA B | O8: Q | P8: C | Q8: B | R8: ANDREA | S8: B | T8: SMITH | V8: 100 N TRYON ST | X8: CHARLOTTE | Y8: NC | Z8: 28255 | AA8: BANK OF AMERICA | AB8: CHIEF ADMINISTRATIVE OFFICER | AD8: 15 | AE8: CONTRIBUTION | AI8: 43585 | AJ8: 175 | AK8: 1400 | BG8: P | BI8: PRIMARY | BK8: A | BL8: ADD | BM8: ITEMIZED RECEIPTS | BN8: 43600.358 | BR8: F3X | BS8: 4.0514202e+18 | BT8: t | BV8: 2020 | BW8: SA | BY8: 4.0514202e+18 | BZ8: http://docquery.fec.gov/cgi-bin/fecimg/?201905149149695965 | CA8: Contributions From Individuals/Persons Other Than Political Committees
A9: C00364778 | B9: BANK OF AMERICA CORPORATION FEDERAL PAC | C9: 2019 | D9: YE | E9: 2.0200121e+17 | F9: 11AI | G9: A2019-2944190 | H9: 1371432 | J9: IND | K9: INDIVIDUAL | N9: SMITH, ANDREA B | O9: Q | P9: C | Q9: B | R9: ANDREA | S9: B | T9: SMITH | V9: 100 N TRYON ST | X9: CHARLOTTE | Y9: NC | Z9: 28255 | AA9: BANK OF AMERICA | AB9: CHIEF ADMINISTRATIVE OFFICER | AD9: 15 | AE9: CONTRIBUTION | AI9: 43814 | AJ9: 208.32 | AK9: 4324.88 | BG9: P | BI9: PRIMARY | BK9: A | BL9: ADD | BM9: ITEMIZED RECEIPTS | BN9: 43852.068 | BR9: F3X | BS9: 4.0120202e+18 | BT9: t | BV9: 2020 | BW9: SA | BY9: 4.0121202e+18 | BZ9: http://docquery.fec.gov/cgi-bin/fecimg/?202001209167275401 | CA9: Contributions From Individuals/Persons Other Than Political Committees
A10: C00364778 | B10: BANK OF AMERICA CORPORATION FEDERAL PAC | C10: 2019 | D10: M8 | E10: 2.0190817e+17 | F10: 11AI | G10: A2019-1511501 | H10: 1348081 | J10: IND | K10: INDIVIDUAL | N10: SMITH, ANDREA B | O10: Q | P10: C | Q10: B | R10: ANDREA | S10: B | T10: SMITH | V10: 100 N TRYON ST | X10: CHARLOTTE | Y10: NC | Z10: 28255 | AA10: BANK OF AMERICA | AB10: CHIEF ADMINISTRATIVE OFFICER | AD10: 15 | AE10: CONTRIBUTION | AI10: 43661 | AJ10: 175 | AK10: 2275 | BG10: P | BI10: PRIMARY | BK10: A | BL10: ADD | BM10: ITEMIZED RECEIPTS | BN10: 43694.11 | BR10: F3X | BS10: 4.0816202e+18 | BT10: t | BV10: 2020 | BW10: SA | BY10: 4.0816202e+18 | BZ10: http://docquery.fec.gov/cgi-bin/fecimg/?201908169162884688 | CA10: Contributions From Individuals/Persons Other Than Political Committees
A11: C00364778 | B11: BANK OF AMERICA CORPORATION FEDERAL PAC | C11: 2019 | D11: M8 | E11: 2.0190817e+17 | F11: 11AI | G11: A2019-1688431 | H11: 1348081 | J11: IND | K11: INDIVIDUAL | N11: SMITH, ANDREA B | O11: Q | P11: C | Q11: B | R11: ANDREA | S11: B | T11: SMITH | V11: 100 N TRYON ST | X11: CHARLOTTE | Y11: NC | Z11: 28255 | AA11: BANK OF AMERICA | AB11: CHIEF ADMINISTRATIVE OFFICER | AD11: 15 | AE11: CONTRIBUTION | AI11: 43677 | AJ11: 175 | AK11: 2450 | BG11: P | BI11: PRIMARY | BK11: A | BL11: ADD | BM11: ITEMIZED RECEIPTS | BN11: 43694.11 | BR11: F3X | BS11: 4.0816202e+18 | BT11: t | BV11: 2020 | BW11: SA | BY11: 4.0816202e+18 | BZ11: http://docquery.fec.gov/cgi-bin/fecimg/?201908169162884688 | CA11: Contributions From Individuals/Persons Other Than Political Committees
A12: C00364778 | B12: BANK OF AMERICA CORPORATION FEDERAL PAC | C12: 2019 | D12: YE | E12: 2.0200121e+17 | F12: 11AI | G12: A2019-2985172 | H12: 1371432 | J12: IND | K12: INDIVIDUAL | N12: SMITH, ANDREA B | O12: Q | P12: C | Q12: B | R12: ANDREA | S12: B | T12: SMITH | V12: 100 N TRYON ST | X12: CHARLOTTE | Y12: NC | Z12: 28255 | AA12: BANK OF AMERICA | AB12: CHIEF ADMINISTRATIVE OFFICER | AD12: 15 | AE12: CONTRIBUTION | AI12: 43830 | AJ12: 208.32 | AK12: 4533.2 | BG12: P | BI12: PRIMARY | BK12: A | BL12: ADD | BM12: ITEMIZED RECEIPTS | BN12: 43852.068 | BR12: F3X | BS12: 4.0120202e+18 | BT12: t | BV12: 2020 | BW12: SA | BY12: 4.0121202e+18 | BZ12: http://docquery.fec.gov/cgi-bin/fecimg/?202001209167275401 | CA12: Contributions From Individuals/Persons Other Than Political Committees
A13: C00364778 | B13: BANK OF AMERICA CORPORATION FEDERAL PAC | C13: 2019 | D13: M7 | E13: 2.0190803e+17 | F13: 11AI | G13: A2019-1195547 | H13: 1346685 | J13: IND | K13: INDIVIDUAL | N13: SMITH, ANDREA B | O13: Q | P13: C | Q13: B | R13: ANDREA | S13: B | T13: SMITH | V13: 100 N TRYON ST | X13: CHARLOTTE | Y13: NC | Z13: 28255 | AA13: BANK OF AMERICA | AB13: CHIEF ADMINISTRATIVE OFFICER | AD13: 15 | AE13: CONTRIBUTION | AI13: 43631 | AJ13: 175 | AK13: 1925 | BG13: P | BI13: PRIMARY | BK13: N | BL13: NO CHANGE | BM13: ITEMIZED RECEIPTS | BN13: 43680.113 | BR13: F3X | BS13: 4.0802202e+18 | BT13: t | BV13: 2020 | BW13: SA | BY13: 4.0802202e+18 | BZ13: http://docquery.fec.gov/cgi-bin/fecimg/?201908029161351312 | CA13: Contributions From Individuals/Persons Other Than Political Committees
... A48: C00364778 | B48: BANK OF AMERICA CORPORATION FEDERAL PAC | C48: 2020 | D48: YE | E48: 2.0210126e+17 | F48: 11AI | G48: A2020-2739131 | H48: 1490358 | J48: IND | K48: INDIVIDUAL | N48: SMITH, ANDREA B | O48: Q | P48: C | Q48: B | R48: ANDREA | S48: B | T48: SMITH | V48: 100 N TRYON ST | X48: CHARLOTTE | Y48: NC | Z48: 28255 | AA48: BANK OF AMERICA | AB48: CHIEF ADMINISTRATIVE OFFICER | AD48: 15 | AE48: CONTRIBUTION | AI48: 44196 | AJ48: 208.32 | AK48: 4999.68 | BG48: P | BI48: PRIMARY | BK48: A | BL48: ADD | BM48: ITEMIZED RECEIPTS | BN48: 44223.151 | BR48: F3X | BS48: 4.0125202e+18 | BT48: t | BV48: 2020 | BW48: SA | BY48: 4.0127202e+18 | BZ48: https://docquery.fec.gov/cgi-bin/fecimg/?202101259405395219 | CA48: Contributions From Individuals/Persons Other Than Political Committees
V50: =+V48&X48&Y48&Z48 -> 100 N TRYON STCHARLOTTENC28255
A51: Row Labels | B51: Sum of contribution_receipt_amount
A52: BANK OF AMERICA CORPORATION FEDERAL PAC | B52: 9357.88
A53: Grand Total | B53: 9357.88

Sheet Thomas Montag
A1: committee_id | B1: committee_name | C1: report_year | D1: report_type | E1: image_number | F1: line_number | G1: transaction_id | H1: file_number | I1: committee_name | J1: entity_type | K1: entity_type_desc | L1: unused_contbr_id | M1: contributor_prefix | N1: contributor_name | O1: recipient_committee_type | P1: recipient_committee_org_type | Q1: recipient_committee_designation | R1: contributor_first_name | S1: contributor_middle_name | T1: contributor_last_name | U1: contributor_suffix | V1: contributor_street_1 | W1: contributor_street_2 | X1: contributor_city | Y1: contributor_state | Z1: contributor_zip | AA1: contributor_employer | AB1: contributor_occupation | AC1: contributor_id | AD1: receipt_type | AE1: receipt_type_desc | AF1: receipt_type_full | AG1: memo_code | AH1: memo_code_full | AI1: contribution_receipt_date | AJ1: contribution_receipt_amount | AK1: contributor_aggregate_ytd | AL1: candidate_id | AM1: candidate_name | AN1: candidate_first_name | AO1: candidate_last_name | AP1: candidate_middle_name | AQ1: candidate_prefix | AR1: candidate_suffix | AS1: candidate_office | AT1: candidate_office_full | AU1: candidate_office_state | AV1: candidate_office_state_full | AW1: candidate_office_district | AX1: conduit_committee_id | AY1: conduit_committee_name | AZ1: conduit_committee_street1 | BA1: conduit_committee_street2 | BB1: conduit_committee_city | BC1: conduit_committee_state | BD1: conduit_committee_zip | BE1: donor_committee_name | BF1: national_committee_nonfederal_account | BG1: election_type | BH1: election_type_full | BI1: fec_election_type_desc | BJ1: fec_election_year | BK1: amendment_indicator | BL1: amendment_indicator_desc | BM1: schedule_type_full | BN1: load_date | BO1: original_sub_id | BP1: back_reference_transaction_id | BQ1: back_reference_schedule_name | BR1: filing_form | BS1: link_id | BT1: is_individual | BU1: memo_text | BV1: two_year_transaction_period | BW1: schedule_type | BX1: increased_limit | BY1: sub_id | BZ1: pdf_url | CA1: line_number_label
A2: C00370056 | B2: DEVIN NUNES CAMPAIGN COMMITTEE | C2: 2019 | D2: Q1 | E2: 2.0190716e+17 | F2: 12 | G2: A8A06EDE5B6524991B6F | H2: 1339265 | J2: IND | K2: INDIVIDUAL | N2: MONTAG, THOMAS | O2: H | Q2: P | R2: THOMAS | T2: MONTAG | V2: 127 E 73RD ST | X2: NEW YORK | Y2: NY | Z2: 100213502 | AA2: BANK OF AMERICA | AB2: COO | AD2: 15J | AE2: MEMO (FILER'S % OF CONTRIBUTION GIVEN TO JOIN | AG2: X | AI2: 43552 | AJ2: 2800 | AK2: 5600 | BG2: G2020 | BI2: GENERAL | BJ2: 2020 | BK2: N | BL2: NO CHANGE | BM2: ITEMIZED RECEIPTS | BN2: 43662.174 | BP2: AF978B0A2FE2B4C5B9C8 | BQ2: SA12 | BR2: F3 | BS2: 4.0715202e+18 | BT2: t | BV2: 2020 | BW2: SA | BY2: 4.0715202e+18 | BZ2: http://docquery.fec.gov/cgi-bin/fecimg/?201907159150604201 | CA2: Transfers from authorized committees
A3: C00370056 | B3: DEVIN NUNES CAMPAIGN COMMITTEE | C3: 2019 | D3: Q1 | E3: 2.0190716e+17 | F3: 12 | G3: AE8CA03E4223B41728D1 | H3: 1339265 | J3: IND | K3: INDIVIDUAL | N3: MONTAG, THOMAS | O3: H | Q3: P | R3: THOMAS | T3: MONTAG | V3: 127 E 73RD ST | X3: NEW YORK | Y3: NY | Z3: 100213502 | AA3: BANK OF AMERICA | AB3: COO | AD3: 15J | AE3: MEMO (FILER'S % OF CONTRIBUTION GIVEN TO JOIN | AG3: X | AI3: 43552 | AJ3: 2800 | AK3: 5600 | BG3: P2020 | BI3: PRIMARY | BJ3: 2020 | BK3: N | BL3: NO CHANGE | BM3: ITEMIZED RECEIPTS | BN3: 43662.174 | BP3: A0AB6B94AEA1F4BC2AAB | BQ3: SA12 | BR3: F3 | BS3: 4.0715202e+18 | BT3: t | BV3: 2020 | BW3: SA | BY3: 4.0715202e+18 | BZ3: http://docquery.fec.gov/cgi-bin/fecimg/?201907159150604212 | CA3: Transfers from authorized committees
A4: C00551275 | B4: FRENCH HILL FOR ARKANSAS | C4: 2019 | D4: Q1 | E4: 2.0190824e+17 | F4: 12 | G4: SA12.10212 | H4: 1349484 | J4: IND | K4: INDIVIDUAL | M4: MR. | N4: MONTAG, THOMAS MR. | O4: H | Q4: P | R4: THOMAS | T4: MONTAG | V4: 127 EAST 73RD STREET | X4: NEW YORK | Y4: NY | Z4: 100213502 | AA4: BANK OF AMERICA | AB4: COO | AD4: 15J | AE4: MEMO (FILER'S % OF CONTRIBUTION GIVEN TO JOIN | AF4: TRANSFER | AG4: X | AI4: 43539 | AJ4: 2800 | AK4: 5600 | BG4: G2020 | BI4: GENERAL | BJ4: 2020 | BK4: N | BL4: NO CHANGE | BM4: ITEMIZED RECEIPTS | BN4: 43702.107 | BP4: SA12.10143 | BQ4: SA12 | BR4: F3 | BS4: 4.0823202e+18 | BT4: t | BU4: JFC ATTRIB: TAKE BACK THE HOUSE 2020 | BV4: 2020 | BW4: SA | BY4: 4.0824202e+18 | BZ4: http://docquery.fec.gov/cgi-bin/fecimg/?201908239163101342 | CA4: Transfers from authorized committees
A5: C00551275 | B5: FRENCH HILL FOR ARKANSAS | C5: 2019 | D5: Q1 | E5: 2.0190824e+17 | F5: 12 | G5: SA12.10210 | H5: 1349484 | J5: IND | K5: INDIVIDUAL | M5: MR. | N5: MONTAG, THOMAS MR. | O5: H | Q5: P | R5: THOMAS | T5: MONTAG | V5: 127 EAST 73RD STREET | X5: NEW YORK | Y5: NY | Z5: 100213502 | AA5: BANK OF AMERICA | AB5: COO | AD5: 15J | AE5: MEMO (FILER'S % OF CONTRIBUTION GIVEN TO JOIN | AF5: TRANSFER | AG5: X | AI5: 43539 | AJ5: 2800 | AK5: 5600 | BG5: P2020 | BI5: PRIMARY | BJ5: 2020 | BK5: N | BL5: NO CHANGE | BM5: ITEMIZED RECEIPTS | BN5: 43702.107 | BP5: SA12.10144 | BQ5: SA12 | BR5: F3 | BS5: 4.0823202e+18 | BT5: t | BU5: JFC ATTRIB: TAKE BACK THE HOUSE 2020 | BV5: 2020 | BW5: SA | BY5: 4.0824202e+18 | BZ5: http://docquery.fec.gov/cgi-bin/fecimg/?201908239163101357 | CA5: Transfers from authorized committees
A6: C00662650 | B6: BALDERSON FOR CONGRESS | C6: 2019 | D6: Q1 | E6: 2.0190827e+17 | F6: 12 | G6: AF98594688AEF4D63847 | H6: 1349830 | J6: IND | K6: INDIVIDUAL | N6: MONTAG, THOMAS | O6: H | Q6: P | R6: THOMAS | T6: MONTAG | V6: 127 E 73RD ST | X6: NEW YORK | Y6: NY | Z6: 10021 | AA6: BANK OF AMERICA | AB6: COO | AD6: 15J | AE6: MEMO (FILER'S % OF CONTRIBUTION GIVEN TO JOIN | AG6: X | AI6: 43539 | AJ6: 2651.22 | AK6: 2651.22 | BG6: P2020 | BI6: PRIMARY | BJ6: 2020 | BK6: N | BL6: NO CHANGE | BM6: ITEMIZED RECEIPTS | BN6: 43705.109 | BP6: AEC113F4AED7542E1A2E | BQ6: SA12 | BR6: F3 | BS6: 4.0826202e+18 | BT6: t | BV6: 2020 | BW6: SA | BY6: 4.0827202e+18 | BZ6: http://docquery.fec.gov/cgi-bin/fecimg/?201908269163104886 | CA6: Transfers from authorized committees
A7: C00629949 | B7: ALEX MOONEY FOR CONGRESS | C7: 2019 | D7: Q1 | E7: 2.0210405e+17 | F7: 12 | G7: SA12.22557 | H7: 1507515 | J7: IND | K7: INDIVIDUAL | N7: MONTAG, THOMAS | O7: H | Q7: P | R7: THOMAS | T7: MONTAG | V7: 127 E 73RD ST. | W7: NEW YORK | X7: NY | Y7: NY | Z7: 100213502 | AA7: BANK OF AMERICA | AB7: COO | AD7: 15J | AE7: MEMO (FILER'S % OF CONTRIBUTION GIVEN TO JOIN | AF7: TRANSFER | AG7: X | AI7: 43539 | AJ7: 2651.22 | AK7: 2651.22 | BG7: P2020 | BI7: PRIMARY | BJ7: 2020 | BK7: N | BL7: NO CHANGE | BM7: ITEMIZED RECEIPTS | BN7: 44292.174 | BP7: SA12.22462 | BQ7: SA12 | BR7: F3 | BS7: 4.0405202e+18 | BT7: t | BU7: JFC ATTRIB: TAKE BACK THE HOUSE 2020 | BV7: 2020 | BW7: SA | BY7: 4.0406202e+18 | BZ7: https://docquery.fec.gov/cgi-bin/fecimg/?202104049443062349 | CA7: Transfers from authorized committees
A8: C00499236 | B8: GEORGE HOLDING FOR CONGRESS INC. | C8: 2019 | D8: Q1 | E8: 2.0190416e+17 | F8: 12 | G8: SA12-TI68-12 | H8: 1325376 | J8: IND | K8: INDIVIDUAL | N8: MONTAG, THOMAS | O8: H | Q8: P | R8: THOMAS | T8: MONTAG | V8: 127 E 73RD ST | X8: NEW YORK | Y8: NY | Z8: 10021 | AA8: BANK OF AMERICA | AB8: COO | AD8: 15J | AE8: MEMO (FILER'S % OF CONTRIBUTION GIVEN TO JOIN | AF8: TRANSFER IN AFFILIATED | AG8: X | AI8: 43539 | AJ8: 2800 | AK8: 5600 | BG8: G2020 | BI8: GENERAL | BJ8: 2020 | BK8: A | BL8: ADD | BM8: ITEMIZED RECEIPTS | BN8: 43576.149 | BR8: F3 | BS8: 4.0415202e+18 | BT8: t | BU8: TAKE BACK THE HOUSE 2020 | BV8: 2020 | BW8: SA | BY8: 4.0420202e+18 | BZ8: http://docquery.fec.gov/cgi-bin/fecimg/?201904159146156641 | CA8: Transfers from authorized committees
A9: C00200584 | B9: UPTON FOR ALL OF US | C9: 2019 | D9: Q1 | E9: 2.0190416e+17 | F9: 12 | G9: A0F26B28663C24330B76 | H9: 1325998 | J9: IND | K9: INDIVIDUAL | N9: MONTAG, THOMAS | O9: H | Q9: P | R9: THOMAS | T9: MONTAG | V9: 127 E 73RD ST | X9: NEW YORK | Y9: NY | Z9: 100213502 | AA9: BANK OF AMERICA | AB9: COO | AD9: 15J | AE9: MEMO (FILER'S % OF CONTRIBUTION GIVEN TO JOIN | AG9: X | AI9: 43539 | AJ9: 2651.22 | AK9: 2651.22 | BG9: P2020 | BI9: PRIMARY | BJ9: 2020 | BK9: A | BL9: ADD | BM9: ITEMIZED RECEIPTS | BN9: 43576.15 | BP9: A01D3BDD21E974F85ACC | BQ9: SA12 | BR9: F3 | BS9: 4.0415202e+18 | BT9: t | BV9: 2020 | BW9: SA | BY9: 4.0420202e+18 | BZ9: http://docquery.fec.gov/cgi-bin/fecimg/?201904159146201998 | CA9: Transfers from authorized committees
A10: C00509422 | B10: DOUG LAMALFA COMMITTEE | C10: 2019 | D10: Q1 | E10: 2.0190606e+17 | F10: 12 | G10: IDTA382 | H10: 1333095 | J10: IND | K10: INDIVIDUAL | N10: MONTAG, THOMAS | O10: H | Q10: P | R10: THOMAS | T10: MONTAG | V10: 127 E 73RD ST. | X10: NEW YORK | Y10: NY | Z10: 10021 | AA10: BANK OF AMERICA | AB10: COO | AD10: 15J | AE10: MEMO (FILER'S % OF CONTRIBUTION GIVEN TO JOIN | AG10: X | AI10: 43539 | AJ10: 2651.22 | AK10: 2651.22 | AY10: TAKE BACK THE HOUSE 2020 | AZ10: P.O. BOX 30844 | BB10: BETHESDA | BC10: MD | BD10: 20824 | BG10: P2020 | BI10: PRIMARY | BJ10: 2020 | BK10: C | BL10: CHANGE | BM10: ITEMIZED RECEIPTS | BN10: 43623.113 | BP10: INCA6250 | BQ10: SA12 | BR10: F3 | BS10: 4.0605202e+18 | BT10: t | BV10: 2020 | BW10: SA | BY10: 4.0606202e+18 | BZ10: http://docquery.fec.gov/cgi-bin/fecimg/?201906059149930841 | CA10: Transfers from authorized committees
A11: C00660795 | B11: DAN CRENSHAW FOR CONGRESS | C11: 2019 | D11: Q1 | E11: 2.0190416e+17 | F11: 12 | G11: A3FC01698873245299B8 | H11: 1326297 | J11: IND | K11: INDIVIDUAL | N11: MONTAG, THOMAS | O11: H | Q11: P | R11: THOMAS | T11: MONTAG | V11: 127 E 73RD ST | X11: NEW YORK | Y11: NY | Z11: 100213502 | AA11: BANK OF AMERICA | AB11: COO | AD11: 15J | AE11: MEMO (FILER'S % OF CONTRIBUTION GIVEN TO JOIN | AG11: X | AI11: 43539 | AJ11: 2651.22 | AK11: 2651.22 | BG11: P2020 | BI11: PRIMARY | BJ11: 2020 | BK11: A | BL11: ADD | BM11: ITEMIZED RECEIPTS | BN11: 43574.205 | BP11: A1AA4651CF89B4DF0B62 | BQ11: SA12 | BR11: F3 | BS11: 4.0416202e+18 | BT11: t | BV11: 2020 | BW11: SA | BY11: 4.0418202e+18 | BZ11: http://docquery.fec.gov/cgi-bin/fecimg/?201904159146346790 | CA11: Transfers from authorized committees
A12: C00662767 | B12: CHIP ROY FOR CONGRESS | C12: 2019 | D12: Q1 | E12: 2.0190416e+17 | F12: 12 | G12: SA12.12525 | H12: 1325616 | J12: IND | K12: INDIVIDUAL | N12: MONTAG, THOMAS | O12: H | Q12: P | R12: THOMAS | T12: MONTAG | V12: 127 E 73RD ST | X12: NEW YORK | Y12: NY | Z12: 100213502 | AA12: BANK OF AMERICA | AB12: COO | AD12: 15J | AE12: MEMO (FILER'S % OF CONTRIBUTION GIVEN TO JOIN | AF12: TRANSFER | AG12: X | AI12: 43539 | AJ12: 2651.22 | AK12: 2651.22 | BG12: P2020 | BI12: PRIMARY | BJ12: 2020 | BK12: A | BL12: ADD | BM12: ITEMIZED RECEIPTS | BN12: 43574.202 | BP12: SA12.12492 | BQ12: SA12 | BR12: F3 | BS12: 4.0415202e+18 | BT12: t | BU12: JFC ATTRIB: TAKE BACK THE HOUSE 2020 | BV12: 2020 | BW12: SA | BY12: 4.0418202e+18 | BZ12: http://docquery.fec.gov/cgi-bin/fecimg/?201904159146170808 | CA12: Transfers from authorized committees
A13: C00373001 | B13: CITIZENS FOR TURNER | C13: 2019 | D13: Q1 | E13: 2.0190416e+17 | F13: 12 | G13: A90980EB059D34DF08C5 | H13: 1326357 | J13: IND | K13: INDIVIDUAL | N13: MONTAG, THOMAS | O13: H | Q13: P | R13: THOMAS | T13: MONTAG | V13: 127 E 73RD ST | X13: NEW YORK | Y13: NY | Z13: 10021 | AA13: BANK OF AMERICA | AB13: COO | AD13: 15J | AE13: MEMO (FILER'S % OF CONTRIBUTION GIVEN TO JOIN | AG13: X | AI13: 43539 | AJ13: 2651.22 | AK13: 2651.22 | BG13: P2020 | BI13: PRIMARY | BJ13: 2020 | BK13: A | BL13: ADD | BM13: ITEMIZED RECEIPTS | BN13: 43576.15 | BP13: AA5FE2A2980CC458099A | BQ13: SA12 | BR13: F3 | BS13: 4.0416202e+18 | BT13: t | BV13: 2020 | BW13: SA | BY13: 4.0420202e+18 | BZ13: http://docquery.fec.gov/cgi-bin/fecimg/?201904159146360044 | CA13: Transfers from authorized committees
A14: C00527457 | B14: FRIENDS OF DAVE JOYCE | C14: 2019 | D14: Q1 | E14: 2.0190416e+17 | F14: 12 | G14: A786728708555463AA95 | H14: 1325638 | J14: IND | K14: INDIVIDUAL | N14: MONTAG, THOMAS | O14: H | Q14: P | R14: THOMAS | T14: MONTAG | V14: 127 E 73RD ST | X14: NEW YORK | Y14: NY | Z14: 100213502 | AA14: BANK OF AMERICA | AB14: COO | AD14: 15J | AE14: MEMO (FILER'S % OF CONTRIBUTION GIVEN TO JOIN | AG14: X | AI14: 43539 | AJ14: 2800 | AK14: 5600 | BG14: P2020 | BI14: PRIMARY | BJ14: 2020 | BK14: A | BL14: ADD | BM14: ITEMIZED RECEIPTS | BN14: 43576.149 | BP14: A5069661D0E914823955 | BQ14: SA12 | BR14: F3 | BS14: 4.0415202e+18 | BT14: t | BV14: 2020 | BW14: SA | BY14: 4.0420202e+18 | BZ14: http://docquery.fec.gov/cgi-bin/fecimg/?201904159146171979 | CA14: Transfers from authorized committees
A15: C00527457 | B15: FRIENDS OF DAVE JOYCE | C15: 2019 | D15: Q1 | E15: 2.0190416e+17 | F15: 12 | G15: A2B62F90B2B3F42D4985 | H15: 1325638 | J15: IND | K15: INDIVIDUAL | N15: MONTAG, THOMAS | O15: H | Q15: P | R15: THOMAS | T15: MONTAG | V15: 127 E 73RD ST | X15: NEW YORK | Y15: NY | Z15: 100213502 | AA15: BANK OF AMERICA | AB15: COO | AD15: 15J | AE15: MEMO (FILER'S % OF CONTRIBUTION GIVEN TO JOIN | AG15: X | AI15: 43539 | AJ15: 2800 | AK15: 5600 | BG15: G2020 | BI15: GENERAL | BJ15: 2020 | BK15: A | BL15: ADD | BM15: ITEMIZED RECEIPTS | BN15: 43576.149 | BP15: A45D20F100A22429E904 | BQ15: SA12 | BR15: F3 | BS15: 4.0415202e+18 | BT15: t | BV15: 2020 | BW15: SA | BY15: 4.0420202e+18 | BZ15: http://docquery.fec.gov/cgi-bin/fecimg/?201904159146171992 | CA15: Transfers from authorized committees
A16: C00575167 | B16: DON BACON FOR CONGRESS | C16: 2019 | D16: Q1 | E16: 2.0190714e+17 | F16: 12 | G16: AD29701CC3CB140DD8F6 | H16: 1338851 | J16: IND | K16: INDIVIDUAL | N16: MONTAG, THOMAS | O16: H | Q16: P | R16: THOMAS | T16: MONTAG | V16: 127 E 73RD ST | X16: NEW YORK | Y16: NY | Z16: 100213502 | AA16: BANK OF AMERICA | AB16: COO | AD16: 15J | AE16: MEMO (FILER'S % OF CONTRIBUTION GIVEN TO JOIN | AG16: X | AI16: 43553 | AJ16: 2651.22 | AK16: 2651.22 | BG16: P2020 | BI16: PRIMARY | BJ16: 2020 | BK16: N | BL16: NO CHANGE | BM16: ITEMIZED RECEIPTS | BN16: 43673.11 | BP16: AB5ED80FB6E554FF3AC6 | BQ16: SA12 | BR16: F3 | BS16: 4.0713202e+18 | BT16: t | BU16: TAKE BACK THE HOUSE TRANSFER MEMO | BV16: 2020 | BW16: SA | BY16: 4.0726202e+18 | BZ16: http://docquery.fec.gov/cgi-bin/fecimg/?201907139150587553 | CA16: Transfers from authorized committees
A17: C00545467 | B17: HURD FOR CONGRESS | C17: 2019 | D17: Q1 | E17: 2.0190723e+17 | F17: 12 | G17: SA12.58942 | H17: 1343250 | J17: IND | K17: INDIVIDUAL | N17: MONTAG, THOMAS | O17: H | Q17: P | R17: THOMAS | T17: MONTAG | V17: 127 E 73RD ST | X17: NEW YORK | Y17: NY | Z17: 10021 | AA17: BANK OF AMERICA | AB17: COO | AD17: 15J | AE17: MEMO (FILER'S % OF CONTRIBUTION GIVEN TO JOIN | AF17: JFC TRANSFER: TAKE BACK THE HOUSE [SA12.54376] | AG17: X | AI17: 43539 | AJ17: 2651.22 | AK17: 2651.22 | BG17: P2020 | BI17: PRIMARY | BJ17: 2020 | BK17: A | BL17: ADD | BM17: ITEMIZED RECEIPTS | BN17: 43673.11 | BR17: F3 | BS17: 4.0722202e+18 | BT17: t | BV17: 2020 | BW17: SA | BY17: 4.0726202e+18 | BZ17: http://docquery.fec.gov/cgi-bin/fecimg/?201907229151614283 | CA17: Transfers from authorized committees
A18: C00677286 | B18: STEIL FOR WISCONSIN, INC. | C18: 2019 | D18: Q1 | E18: 2.0190716e+17 | F18: 12 | G18: AA92E907DBFFC4575B1D | H18: 1340871 | J18: IND | K18: INDIVIDUAL | N18: MONTAG, THOMAS | O18: H | Q18: P | R18: THOMAS | T18: MONTAG | V18: 127 EAST 73RD STREET | X18: NEW YORK | Y18: NY | Z18: 10021 | AA18: BANK OF AMERICA | AB18: COO | AD18: 15J | AE18: MEMO (FILER'S % OF CONTRIBUTION GIVEN TO JOIN | AG18: X | AI18: 43539 | AJ18: 2800 | AK18: 5600 | BG18: G2020 | BI18: GENERAL | BJ18: 2020 | BK18: N | BL18: NO CHANGE | BM18: ITEMIZED RECEIPTS | BN18: 43673.11 | BP18: A0294E4D1449B4699B4D | BQ18: SA12 | BR18: F3 | BS18: 4.0716202e+18 | BT18: t | BV18: 2020 | BW18: SA | BY18: 4.0726202e+18 | BZ18: http://docquery.fec.gov/cgi-bin/fecimg/?201907159150998463 | CA18: Transfers from authorized committees
A19: C00677286 | B19: STEIL FOR WISCONSIN, INC. | C19: 2019 | D19: Q1 | E19: 2.0190716e+17 | F19: 12 | G19: A0F28D5E6F24245DF908 | H19: 1340871 | J19: IND | K19: INDIVIDUAL | N19: MONTAG, THOMAS | O19: H | Q19: P | R19: THOMAS | T19: MONTAG | V19: 127 EAST 73RD STREET | X19: NEW YORK | Y19: NY | Z19: 10021 | AA19: BANK OF AMERICA | AB19: COO | AD19: 15J | AE19: MEMO (FILER'S % OF CONTRIBUTION GIVEN TO JOIN | AG19: X | AI19: 43539 | AJ19: 2800 | AK19: 5600 | BG19: P2020 | BI19: PRIMARY | BJ19: 2020 | BK19: N | BL19: NO CHANGE | BM19: ITEMIZED RECEIPTS | BN19: 43673.11 | BP19: A325F370CFE854A9D9E8 | BQ19: SA12 | BR19: F3 | BS19: 4.0716202e+18 | BT19: t | BV19: 2020 | BW19: SA | BY19: 4.0726202e+18 | BZ19: http://docquery.fec.gov/cgi-bin/fecimg/?201907159150998471 | CA19: Transfers from authorized committees
A20: C00660050 | B20: COMMITTEE TO RE-ELECT STEVE WATKINS | C20: 2019 | D20: Q1 | E20: 2.0190716e+17 | F20: 12 | G20: AB3926BF1261640379FE | H20: 1340635 | J20: IND | K20: INDIVIDUAL | N20: MONTAG, THOMAS | O20: H | Q20: P | R20: THOMAS | T20: MONTAG | V20: 127 E 73RD ST | X20: NEW YORK | Y20: NY | Z20: 10021 | AA20: BANK OF AMERICA | AB20: COO | AD20: 15J | AE20: MEMO (FILER'S % OF CONTRIBUTION GIVEN TO JOIN | AG20: X | AI20: 43539 | AJ20: 2651.22 | AK20: 2651.22 | BG20: P2020 | BI20: PRIMARY | BJ20: 2020 | BK20: N | BL20: NO CHANGE | BM20: ITEMIZED RECEIPTS | BN20: 43673.11 | BP20: A8C490F2A64184F05BB0 | BQ20: SA12 | BR20: F3 | BS20: 4.0715202e+18 | BT20: t | BV20: 2020 | BW20: SA | BY20: 4.0726202e+18 | BZ20: http://docquery.fec.gov/cgi-bin/fecimg/?201907159150896218 | CA20: Transfers from authorized committees
A21: C00540617 | B21: FRIENDS OF DAVID SCHWEIKERT | C21: 2019 | D21: Q1 | E21: 2.0190416e+17 | F21: 12 | G21: ABFB61C230FC44118826 | H21: 1326169 | J21: IND | K21: INDIVIDUAL | N21: MONTAG, THOMAS | O21: H | Q21: P | R21: THOMAS | T21: MONTAG | V21: 127 EAST 73RD STREET | X21: NEW YORK | Y21: NY | Z21: 10021 | AA21: BANK OF AMERICA | AB21: COO | AD21: 15J | AE21: MEMO (FILER'S % OF CONTRIBUTION GIVEN TO JOIN | AG21: X | AI21: 43539 | AJ21: 2651.22 | AK21: 2651.22 | BG21: P2020 | BI21: PRIMARY | BJ21: 2020 | BK21: A | BL21: ADD | BM21: ITEMIZED RECEIPTS | BN21: 43572.115 | BP21: A701E59EC73974E42961 | BQ21: SA12 | BR21: F3 | BS21: 4.0415202e+18 | BT21: t | BV21: 2020 | BW21: SA | BY21: 4.0416202e+18 | BZ21: http://docquery.fec.gov/cgi-bin/fecimg/?201904159146333859 | CA21: Transfers from authorized committees
A22: C00663914 | B22: DEBBIE LESKO FOR CONGRESS | C22: 2019 | D22: Q1 | E22: 2.0190416e+17 | F22: 12 | G22: ADE9417B3DE9F43F5A55 | H22: 1325492 | J22: IND | K22: INDIVIDUAL | N22: MONTAG, THOMAS | O22: H | Q22: P | R22: THOMAS | T22: MONTAG | V22: 127 E. 73RD STREET | X22: NEW YORK | Y22: NY | Z22: 100213502 | AA22: BANK OF AMERICA | AB22: COO | AD22: 15J | AE22: MEMO (FILER'S % OF CONTRIBUTION GIVEN TO JOIN | AG22: X | AI22: 43552 | AJ22: 2651.22 | AK22: 2651.22 | BG22: P2020 | BI22: PRIMARY | BJ22: 2020 | BK22: A | BL22: ADD | BM22: ITEMIZED RECEIPTS | BN22: 43571.118 | BP22: AEB33E23199684E29A6C | BQ22: SA12 | BR22: F3 | BS22: 4.0415202e+18 | BT22: t | BV22: 2020 | BW22: SA | BY22: 4.0415202e+18 | BZ22: http://docquery.fec.gov/cgi-bin/fecimg/?201904159146162354 | CA22: Transfers from authorized committees
A23: C00096412 | B23: FRIENDS OF CHRIS SMITH | C23: 2019 | D23: Q1 | E23: 2.0190416e+17 | F23: 12 | G23: ACA8ADE04DD5E4AF79D9 | H23: 1326500 | J23: IND | K23: INDIVIDUAL | M23: MR. | N23: MONTAG, THOMAS MR. | O23: H | Q23: P | R23: THOMAS | T23: MONTAG | V23: 127 E 73RD ST. | X23: NEW YORK | Y23: NY | Z23: 100213502 | AA23: BANK OF AMERICA | AB23: COO | AD23: 15J | AE23: MEMO (FILER'S % OF CONTRIBUTION GIVEN TO JOIN | AG23: X | AI23: 43539 | AJ23: 2651.21 | AK23: 2651.21 | BG23: P2020 | BI23: PRIMARY | BJ23: 2020 | BK23: A | BL23: ADD | BM23: ITEMIZED RECEIPTS | BN23: 43576.15 | BP23: A25EB3FD32F174DE4A44 | BQ23: SA12 | BR23: F3 | BS23: 4.0416202e+18 | BT23: t | BV23: 2020 | BW23: SA | BY23: 4.0420202e+18 | BZ23: http://docquery.fec.gov/cgi-bin/fecimg/?201904159146386427 | CA23: Transfers from authorized committees
A24: C00012229 | B24: ALASKANS FOR DON YOUNG | C24: 2019 | D24: Q1 | E24: 2.0200121e+17 | F24: 12 | G24: AB7E50C6ACC224477ADF | H24: 1371459 | J24: IND | K24: INDIVIDUAL | N24: MONTAG, THOMAS | O24: H | Q24: P | R24: THOMAS | T24: MONTAG | V24: 127 E 73RD ST | X24: NEW YORK | Y24: NY | Z24: 100213502 | AA24: BANK OF AMERICA | AB24: COO | AD24: 15J | AE24: MEMO (FILER'S % OF CONTRIBUTION GIVEN TO JOIN | AG24: X | AI24: 43555 | AJ24: 2651.21 | AK24: 2651.21 | BG24: P2020 | BI24: PRIMARY | BJ24: 2020 | BK24: A | BL24: ADD | BM24: ITEMIZED RECEIPTS | BN24: 43852.068 | BP24: A628151178B6E42448F2 | BQ24: SA12 | BR24: F3 | BS24: 4.0120202e+18 | BT24: t | BV24: 2020 | BW24: SA | BY24: 4.0121202e+18 | BZ24: http://docquery.fec.gov/cgi-bin/fecimg/?202001209167277812 | CA24: Transfers from authorized committees
A25: C00546499 | B25: MIKE BOST FOR CONGRESS COMMITTEE | C25: 2019 | D25: Q1 | E25: 2.0190416e+17 | F25: 12 | G25: A10890455726749A3B80 | H25: 1325974 | J25: IND | K25: INDIVIDUAL | N25: MONTAG, THOMAS | O25: H | Q25: P | R25: THOMAS | T25: MONTAG | V25: 127 E 73RD ST | X25: NEW YORK | Y25: NY | Z25: 100213502 | AA25: BANK OF AMERICA | AB25: COO | AD25: 15J | AE25: MEMO (FILER'S % OF CONTRIBUTION GIVEN TO JOIN | AG25: X | AI25: 43539 | AJ25: 2651.22 | AK25: 2651.22 | BG25: P2020 | BI25: PRIMARY | BJ25: 2020 | BK25: A | BL25: ADD | BM25: ITEMIZED RECEIPTS | BN25: 43574.193 | BP25: AEC02A7CB062A491599E | BQ25: SA12 | BR25: F3 | BS25: 4.0415202e+18 | BT25: t | BV25: 2020 | BW25: SA | BY25: 4.0418202e+18 | BZ25: http://docquery.fec.gov/cgi-bin/fecimg/?201904159146199971 | CA25: Transfers from authorized committees
A26: C00547893 | B26: ELISE FOR CONGRESS | C26: 2019 | D26: Q1 | E26: 2.0190416e+17 | F26: 12 | G26: SA12.17706 | H26: 1325632 | J26: IND | K26: INDIVIDUAL | N26: MONTAG, THOMAS | O26: H | Q26: P | R26: THOMAS | T26: MONTAG | V26: 127 E 73RD ST | X26: NEW YORK | Y26: NY | Z26: 100213502 | AA26: BANK OF AMERICA | AB26: COO | AD26: 15J | AE26: MEMO (FILER'S % OF CONTRIBUTION GIVEN TO JOIN | AF26: TRANSFER | AG26: X | AI26: 43539 | AJ26: 2651.22 | AK26: 2651.22 | BG26: P2020 | BI26: PRIMARY | BJ26: 2020 | BK26: A | BL26: ADD | BM26: ITEMIZED RECEIPTS | BN26: 43574.202 | BP26: SA12.17672 | BQ26: SA12 | BR26: F3 | BS26: 4.0415202e+18 | BT26: t | BU26: JFC ATTRIB: TAKE BACK THE HOUSE 2020 | BV26: 2020 | BW26: SA | BY26: 4.0418202e+18 | BZ26: http://docquery.fec.gov/cgi-bin/fecimg/?201904159146171777 | CA26: Transfers from authorized committees
A27: C00390476 | B27: CATHY MCMORRIS RODGERS FOR CONGRESS | C27: 2019 | D27: Q1 | E27: 2.0190416e+17 | F27: 12 | G27: SA12.103478 | H27: 1325593 | J27: IND | K27: INDIVIDUAL | N27: MONTAG, THOMAS | O27: H | Q27: P | R27: THOMAS | T27: MONTAG | V27: 127 E 73RD ST | X27: NEW YORK | Y27: NY | Z27: 100213502 | AA27: BANK OF AMERICA | AB27: COO | AD27: 15J | AE27: MEMO (FILER'S % OF CONTRIBUTION GIVEN TO JOIN | AF27: TRANSFER | AG27: X | AI27: 43539 | AJ27: 2651.22 | AK27: 2651.22 | BG27: P2020 | BI27: PRIMARY | BJ27: 2020 | BK27: A | BL27: ADD | BM27: ITEMIZED RECEIPTS | BN27: 43574.191 | BP27: SA12.103434 | BQ27: SA12 | BR27: F3 | BS27: 4.0415202e+18 | BT27: t | BU27: JFC ATTRIB: TAKE BACK THE HOUSE 2020 | BV27: 2020 | BW27: SA | BY27: 4.0418202e+18 | BZ27: http://docquery.fec.gov/cgi-bin/fecimg/?201904159146170059 | CA27: Transfers from authorized committees
A28: C00390724 | B28: WALBERG FOR CONGRESS | C28: 2019 | D28: Q1 | E28: 2.0190416e+17 | F28: 12 | G28: AB46B891E20634B52831 | H28: 1326263 | J28: IND | K28: INDIVIDUAL | N28: MONTAG, THOMAS | O28: H | Q28: P | R28: THOMAS | T28: MONTAG | V28: 127 E 73RD ST | X28: NEW YORK | Y28: NY | Z28: 100213502 | AA28: BANK OF AMERICA | AB28: COO | AD28: 15J | AE28: MEMO (FILER'S % OF CONTRIBUTION GIVEN TO JOIN | AG28: X | AI28: 43539 | AJ28: 2651.22 | AK28: 2651.22 | BG28: P2020 | BI28: PRIMARY | BJ28: 2020 | BK28: A | BL28: ADD | BM28: ITEMIZED RECEIPTS | BN28: 43574.209 | BP28: A38B2ADE61B754826B93 | BQ28: SA12 | BR28: F3 | BS28: 4.0415202e+18 | BT28: t | BU28: TRANSFER OF JOINT FUNDRAISING PROCEEDS | BV28: 2020 | BW28: SA | BY28: 4.0418202e+18 | BZ28: http://docquery.fec.gov/cgi-bin/fecimg/?201904159146345618 | CA28: Transfers from authorized committees
A29: C00550707 | B29: FRIENDS OF HAGEDORN | C29: 2019 | D29: Q1 | E29: 2.0190412e+17 | F29: 12 | G29: A31DBC6D0AE994E1C8B0 | H29: 1323781 | J29: IND | K29: INDIVIDUAL | N29: MONTAG, THOMAS | O29: H | Q29: P | R29: THOMAS | T29: MONTAG | V29: 127 E 73RD ST | X29: NEW YORK | Y29: NY | Z29: 100213502 | AA29: BANK OF AMERICA | AB29: COO | AD29: 15J | AE29: MEMO (FILER'S % OF CONTRIBUTION GIVEN TO JOIN | AG29: X | AI29: 43539 | AJ29: 2651.22 | AK29: 2651.22 | BG29: P2020 | BI29: PRIMARY | BJ29: 2020 | BK29: A | BL29: ADD | BM29: ITEMIZED RECEIPTS | BN29: 43567.131 | BP29: A29208D256E3F4E7B84E | BQ29: SA12 | BR29: F3 | BS29: 4.0411202e+18 | BT29: t | BV29: 2020 | BW29: SA | BY29: 4.0411202e+18 | BZ29: http://docquery.fec.gov/cgi-bin/fecimg/?201904119146072449 | CA29: Transfers from authorized committees
A30: C00552547 | B30: ZELDIN FOR CONGRESS | C30: 2019 | D30: Q1 | E30: 2.0190416e+17 | F30: 12 | G30: SA12.94023.41 | H30: 1326459 | J30: IND | K30: INDIVIDUAL | N30: MONTAG, THOMAS | O30: H | Q30: P | R30: THOMAS | T30: MONTAG | V30: 127 EAST 73RD STREET | X30: NEW YORK | Y30: NY | Z30: 10021 | AA30: BANK OF AMERICA | AB30: COO | AD30: 15J | AE30: MEMO (FILER'S % OF CONTRIBUTION GIVEN TO JOIN | AF30: JFC-TBTH | AG30: X | AI30: 43551 | AJ30: 2800 | AK30: 2800 | BG30: P2020 | BI30: PRIMARY | BJ30: 2020 | BK30: A | BL30: ADD | BM30: ITEMIZED RECEIPTS | BN30: 43574.197 | BP30: SA12.94023 | BQ30: SA12 | BR30: F3 | BS30: 4.0416202e+18 | BT30: t | BV30: 2020 | BW30: SA | BY30: 4.0418202e+18 | BZ30: http://docquery.fec.gov/cgi-bin/fecimg/?201904159146369644 | CA30: Transfers from authorized committees
A31: C00552547 | B31: ZELDIN FOR CONGRESS | C31: 2019 | D31: Q1 | E31: 2.0190416e+17 | F31: 12 | G31: SA12.94118.18 | H31: 1326459 | J31: IND | K31: INDIVIDUAL | N31: MONTAG, THOMAS | O31: H | Q31: P | R31: THOMAS | T31: MONTAG | V31: 127 EAST 73RD STREET | X31: NEW YORK | Y31: NY | Z31: 10021 | AA31: BANK OF AMERICA | AB31: COO | AD31: 15J | AE31: MEMO (FILER'S % OF CONTRIBUTION GIVEN TO JOIN | AF31: JFC-TBTH | AG31: X | AI31: 43551 | AJ31: 2800 | AK31: 5600 | BG31: G2020 | BI31: GENERAL | BJ31: 2020 | BK31: A | BL31: ADD | BM31: ITEMIZED RECEIPTS | BN31: 43574.197 | BP31: SA12.94118 | BQ31: SA12 | BR31: F3 | BS31: 4.0416202e+18 | BT31: t | BV31: 2020 | BW31: SA | BY31: 4.0418202e+18 | BZ31: http://docquery.fec.gov/cgi-bin/fecimg/?201904159146369653 | CA31: Transfers from authorized committees
A32: C00556365 | B32: KATKO FOR CONGRESS | C32: 2019 | D32: Q1 | E32: 2.0190416e+17 | F32: 12 | G32: AE88D56BC0AF4439E8CD | H32: 1325406 | J32: IND | K32: INDIVIDUAL | N32: MONTAG, THOMAS | O32: H | Q32: P | R32: THOMAS | T32: MONTAG | V32: 127 E 73RD ST. | X32: NEW YORK | Y32: NY | Z32: 100213502 | AA32: BANK OF AMERICA | AB32: COO | AD32: 15J | AE32: MEMO (FILER'S % OF CONTRIBUTION GIVEN TO JOIN | AG32: X | AI32: 43553 | AJ32: 2800 | AK32: 5600 | BG32: G2020 | BI32: GENERAL | BJ32: 2020 | BK32: A | BL32: ADD | BM32: ITEMIZED RECEIPTS | BN32: 43576.149 | BP32: A55B7F7F06EA54E6F8C8 | BQ32: SA12 | BR32: F3 | BS32: 4.0415202e+18 | BT32: t | BU32: TAKE BACK THE HOUSE TRANSFER MEMO | BV32: 2020 | BW32: SA | BY32: 4.0420202e+18 | BZ32: http://docquery.fec.gov/cgi-bin/fecimg/?201904159146157854 | CA32: Transfers from authorized committees
A33: C00556365 | B33: KATKO FOR CONGRESS | C33: 2019 | D33: Q1 | E33: 2.0190416e+17 | F33: 12 | G33: AB7FD990C65E7473AA31 | H33: 1325406 | J33: IND | K33: INDIVIDUAL | N33: MONTAG, THOMAS | O33: H | Q33: P | R33: THOMAS | T33: MONTAG | V33: 127 E 73RD ST. | X33: NEW YORK | Y33: NY | Z33: 100213502 | AA33: BANK OF AMERICA | AB33: COO | AD33: 15J | AE33: MEMO (FILER'S % OF CONTRIBUTION GIVEN TO JOIN | AG33: X | AI33: 43553 | AJ33: 2800 | AK33: 5600 | BG33: P2020 | BI33: PRIMARY | BJ33: 2020 | BK33: A | BL33: ADD | BM33: ITEMIZED RECEIPTS | BN33: 43576.149 | BP33: A4D9FC3FFFA2B442B947 | BQ33: SA12 | BR33: F3 | BS33: 4.0415202e+18 | BT33: t | BU33: TAKE BACK THE HOUSE TRANSFER MEMO | BV33: 2020 | BW33: SA | BY33: 4.0420202e+18 | BZ33: http://docquery.fec.gov/cgi-bin/fecimg/?201904159146157865 | CA33: Transfers from authorized committees
A34: C00392688 | B34: MCCAUL FOR CONGRESS, INC | C34: 2019 | D34: Q1 | E34: 2.0190415e+17 | F34: 12 | G34: SA1958 | H34: 1324776 | J34: IND | K34: INDIVIDUAL | N34: MONTAG, THOMAS | O34: H | Q34: P | R34: THOMAS | T34: MONTAG | V34: 127 E 73RD ST | X34: NEW YORK | Y34: NY | Z34: 10021 | AA34: BANK OF AMERICA | AB34: COO | AD34: 15J | AE34: MEMO (FILER'S % OF CONTRIBUTION GIVEN TO JOIN | AF34: JFC ALLOCATION | AG34: X | AI34: 43539 | AJ34: 2651.22 | AK34: 2651.22 | BG34: P2020 | BI34: PRIMARY | BJ34: 2020 | BK34: A | BL34: ADD | BM34: ITEMIZED RECEIPTS | BN34: 43571.116 | BR34: F3 | BS34: 4.0415202e+18 | BT34: t | BV34: 2020 | BW34: SA | BY34: 4.0415202e+18 | BZ34: http://docquery.fec.gov/cgi-bin/fecimg/?201904149146122893 | CA34: Transfers from authorized committees
A35: C00393348 | B35: KENNY MARCHANT FOR CONGRESS | C35: 2019 | D35: Q1 | E35: 2.0190414e+17 | F35: 12 | G35: AF9F535BBB3B143F9958 | H35: 1324574 | J35: IND | K35: INDIVIDUAL | N35: MONTAG, THOMAS | O35: H | Q35: P | R35: THOMAS | T35: MONTAG | V35: 127 E 73RD ST | X35: NEW YORK | Y35: NY | Z35: 100213502 | AA35: BANK OF AMERICA | AB35: COO | AD35: 15J | AE35: MEMO (FILER'S % OF CONTRIBUTION GIVEN TO JOIN | AG35: X | AI35: 43539 | AJ35: 2651.22 | AK35: 2651.22 | BG35: P2020 | BI35: PRIMARY | BJ35: 2020 | BK35: A | BL35: ADD | BM35: ITEMIZED RECEIPTS | BN35: 43569.114 | BP35: AA8AD42EC02CF413AA9E | BQ35: SA12 | BR35: F3 | BS35: 4.0413202e+18 | BT35: t | BV35: 2020 | BW35: SA | BY35: 4.0413202e+18 | BZ35: http://docquery.fec.gov/cgi-bin/fecimg/?201904139146114506 | CA35: Transfers from authorized committees
A36: C00561597 | B36: GLENN GROTHMAN FOR CONGRESS | C36: 2019 | D36: Q1 | E36: 2.0190416e+17 | F36: 12 | G36: SA12.14817 | H36: 1326246 | J36: IND | K36: INDIVIDUAL | N36: MONTAG, THOMAS | O36: H | Q36: P | R36: THOMAS | T36: MONTAG | V36: 127 E 73RD ST | X36: NEW YORK | Y36: NY | Z36: 100213502 | AA36: BANK OF AMERICA | AB36: COO | AD36: 15J | AE36: MEMO (FILER'S % OF CONTRIBUTION GIVEN TO JOIN | AF36: TRANSFER | AG36: X | AI36: 43539 | AJ36: 2651.22 | AK36: 2651.22 | BG36: P2020 | BI36: PRIMARY | BJ36: 2020 | BK36: A | BL36: ADD | BM36: ITEMIZED RECEIPTS | BN36: 43574.196 | BP36: SA12.14714 | BQ36: SA12 | BR36: F3 | BS36: 4.0415202e+18 | BT36: t | BU36: JFC ATTRIB: TAKE BACK THE HOUSE 2020 | BV36: 2020 | BW36: SA | BY36: 4.0418202e+18 | BZ36: http://docquery.fec.gov/cgi-bin/fecimg/?201904159146344587 | CA36: Transfers from authorized committees
A37: C00412759 | B37: VERN BUCHANAN FOR CONGRESS | C37: 2019 | D37: Q1 | E37: 2.0190416e+17 | F37: 12 | G37: A70C1F47F26594AA48DA | H37: 1326058 | J37: IND | K37: INDIVIDUAL | N37: MONTAG, THOMAS | O37: H | Q37: P | R37: THOMAS | T37: MONTAG | V37: 127 E 73RD ST | X37: NEW YORK | Y37: NY | Z37: 100213502 | AA37: BANK OF AMERICA | AB37: COO | AD37: 15J | AE37: MEMO (FILER'S % OF CONTRIBUTION GIVEN TO JOIN | AG37: X | AI37: 43539 | AJ37: 2651.22 | AK37: 2651.22 | BG37: P2020 | BI37: PRIMARY | BJ37: 2020 | BK37: A | BL37: ADD | BM37: ITEMIZED RECEIPTS | BN37: 43573.117 | BP37: A500C34880A4E4CBC887 | BQ37: SA12 | BR37: F3 | BS37: 4.0415202e+18 | BT37: t | BV37: 2020 | BW37: SA | BY37: 4.0417202e+18 | BZ37: http://docquery.fec.gov/cgi-bin/fecimg/?201904159146217694 | CA37: Transfers from authorized committees
A38: C00420935 | B38: KEVIN MCCARTHY FOR CONGRESS | C38: 2019 | D38: Q1 | E38: 2.0190416e+17 | F38: 12 | G38: ABF69BABA713F406B863 | H38: 1325330 | J38: IND | K38: INDIVIDUAL | N38: MONTAG, THOMAS | O38: H | Q38: P | R38: THOMAS | T38: MONTAG | V38: 127 EAST 73RD STREET | X38: NEW YORK | Y38: NY | Z38: 100213502 | AA38: BANK OF AMERICA | AB38: CHIEF OPERATING OFFICER | AD38: 15J | AE38: MEMO (FILER'S % OF CONTRIBUTION GIVEN TO JOIN | AG38: X | AI38: 43539 | AJ38: 2800 | AK38: 5600 | BG38: P2020 | BI38: PRIMARY | BJ38: 2020 | BK38: A | BL38: ADD | BM38: ITEMIZED RECEIPTS | BN38: 43571.117 | BP38: A3270D63DB83C426399C | BQ38: SA12 | BR38: F3 | BS38: 4.0415202e+18 | BT38: t | BV38: 2020 | BW38: SA | BY38: 4.0415202e+18 | BZ38: http://docquery.fec.gov/cgi-bin/fecimg/?201904159146153334 | CA38: Transfers from authorized committees
A39: C00420935 | B39: KEVIN MCCARTHY FOR CONGRESS | C39: 2019 | D39: Q1 | E39: 2.0190416e+17 | F39: 12 | G39: A063DB580FA8A46FEA02 | H39: 1325330 | J39: IND | K39: INDIVIDUAL | N39: MONTAG, THOMAS | O39: H | Q39: P | R39: THOMAS | T39: MONTAG | V39: 127 EAST 73RD STREET | X39: NEW YORK | Y39: NY | Z39: 100213502 | AA39: BANK OF AMERICA | AB39: CHIEF OPERATING OFFICER | AD39: 15J | AE39: MEMO (FILER'S % OF CONTRIBUTION GIVEN TO JOIN | AG39: X | AI39: 43539 | AJ39: 2800 | AK39: 5600 | BG39: G2020 | BI39: GENERAL | BJ39: 2020 | BK39: A | BL39: ADD | BM39: ITEMIZED RECEIPTS | BN39: 43571.117 | BP39: A145338C3F3664A04BD9 | BQ39: SA12 | BR39: F3 | BS39: 4.0415202e+18 | BT39: t | BV39: 2020 | BW39: SA | BY39: 4.0415202e+18 | BZ39: http://docquery.fec.gov/cgi-bin/fecimg/?201904159146153403 | CA39: Transfers from authorized committees
A40: C00428052 | B40: MAJORITY COMMITTEE PAC--MC PAC | C40: 2019 | D40: M4 | E40: 2.0190419e+17 | F40: 12 | G40: A74F88E3483094E1DACA | H40: 1327356 | J40: IND | K40: INDIVIDUAL | N40: MONTAG, THOMAS | O40: Q | Q40: D | R40: THOMAS | T40: MONTAG | V40: 127 E 73RD ST | X40: NEW YORK | Y40: NY | Z40: 100213502 | AA40: CO-CHIEF OPERATING OFFICER | AB40: BANK OF AMERICA CORPORATION | AD40: 15J | AE40: MEMO (FILER'S % OF CONTRIBUTION GIVEN TO JOIN | AG40: X | AI40: 43539 | AJ40: 5000 | AK40: 5000 | BG40: P | BI40: PRIMARY | BK40: A | BL40: ADD | BM40: ITEMIZED RECEIPTS | BN40: 43574.209 | BP40: A177DC506B74B45869CE | BQ40: SA12 | BR40: F3X | BS40: 4.0418202e+18 | BT40: t | BV40: 2020 | BW40: SA | BY40: 4.0418202e+18 | BZ40: http://docquery.fec.gov/cgi-bin/fecimg/?201904189149494895 | CA40: Transfers from Authorized Committees
A41: C00614776 | B41: TED BUDD FOR CONGRESS | C41: 2019 | D41: Q1 | E41: 2.0190416e+17 | F41: 12 | G41: SA12-TI8-9 | H41: 1325428 | J41: IND | K41: INDIVIDUAL | N41: MONTAG, THOMAS | O41: H | Q41: P | R41: THOMAS | T41: MONTAG | V41: 127 E 73RD ST | X41: NEW YORK | Y41: NY | Z41: 10021 | AA41: BANK OF AMERICA | AB41: COO | AD41: 15J | AE41: MEMO (FILER'S % OF CONTRIBUTION GIVEN TO JOIN | AF41: TRANSFER IN AFFILIATED | AG41: X | AI41: 43539 | AJ41: 2800 | AK41: 2800 | BG41: G2020 | BI41: GENERAL | BJ41: 2020 | BK41: A | BL41: ADD | BM41: ITEMIZED RECEIPTS | BN41: 43576.149 | BR41: F3 | BS41: 4.0415202e+18 | BT41: t | BU41: TAKE BACK THE HOUSE 2020 | BV41: 2020 | BW41: SA | BY41: 4.0420202e+18 | BZ41: http://docquery.fec.gov/cgi-bin/fecimg/?201904159146158485 | CA41: Transfers from authorized committees
A42: C00614776 | B42: TED BUDD FOR CONGRESS | C42: 2019 | D42: Q1 | E42: 2.0190416e+17 | F42: 12 | G42: SA12-TI9-37 | H42: 1325428 | J42: IND | K42: INDIVIDUAL | N42: MONTAG, THOMAS | O42: H | Q42: P | R42: THOMAS | T42: MONTAG | V42: 127 E 73RD ST | X42: NEW YORK | Y42: NY | Z42: 10021 | AA42: BANK OF AMERICA | AB42: COO | AD42: 15J | AE42: MEMO (FILER'S % OF CONTRIBUTION GIVEN TO JOIN | AF42: TRANSFER IN AFFILIATED | AG42: X | AI42: 43539 | AJ42: 2800 | AK42: 5600 | BG42: P2020 | BI42: PRIMARY | BJ42: 2020 | BK42: A | BL42: ADD | BM42: ITEMIZED RECEIPTS | BN42: 43576.149 | BR42: F3 | BS42: 4.0415202e+18 | BT42: t | BU42: TAKE BACK THE HOUSE 2020 | BV42: 2020 | BW42: SA | BY42: 4.0420202e+18 | BZ42: http://docquery.fec.gov/cgi-bin/fecimg/?201904159146158496 | CA42: Transfers from authorized committees
A43: C00437913 | B43: OLSON FOR CONGRESS COMMITTEE | C43: 2019 | D43: Q1 | E43: 2.0190415e+17 | F43: 12 | G43: SA2165 | H43: 1324771 | J43: IND | K43: INDIVIDUAL | N43: MONTAG, THOMAS | O43: H | Q43: P | R43: THOMAS | T43: MONTAG | V43: 127 E 73RD ST | X43: NEW YORK | Y43: NY | Z43: 10021 | AA43: BANK OF AMERICA | AB43: COO | AD43: 15J | AE43: MEMO (FILER'S % OF CONTRIBUTION GIVEN TO JOIN | AF43: JFC ALLOCATION | AG43: X | AI43: 43539 | AJ43: 2651.22 | AK43: 2651.22 | BG43: P2020 | BI43: PRIMARY | BJ43: 2020 | BK43: A | BL43: ADD | BM43: ITEMIZED RECEIPTS | BN43: 43571.116 | BR43: F3 | BS43: 4.0415202e+18 | BT43: t | BV43: 2020 | BW43: SA | BY43: 4.0415202e+18 | BZ43: http://docquery.fec.gov/cgi-bin/fecimg/?201904149146122737 | CA43: Transfers from authorized committees
A44: C00441014 | B44: ROB WITTMAN FOR CONGRESS | C44: 2019 | D44: Q1 | E44: 2.0190416e+17 | F44: 12 | G44: SA12.22913 | H44: 1326512 | J44: IND | K44: INDIVIDUAL | N44: MONTAG, THOMAS | O44: H | Q44: P | R44: THOMAS | T44: MONTAG | V44: 127 E 73RD ST | X44: NEW YORK | Y44: NY | Z44: 10021 | AA44: BANK OF AMERICA | AB44: COO | AD44: 15J | AE44: MEMO (FILER'S % OF CONTRIBUTION GIVEN TO JOIN | AF44: TRANSFER | AG44: X | AI44: 43539 | AJ44: 2651.22 | AK44: 2651.22 | BG44: P2020 | BI44: PRIMARY | BJ44: 2020 | BK44: A | BL44: ADD | BM44: ITEMIZED RECEIPTS | BN44: 43574.197 | BP44: SA12.22807 | BQ44: SA12 | BR44: F3 | BS44: 4.0416202e+18 | BT44: t | BU44: JFC ATTRIB: TAKE BACK THE HOUSE 2020 | BV44: 2020 | BW44: SA | BY44: 4.0418202e+18 | BZ44: http://docquery.fec.gov/cgi-bin/fecimg/?201904159146388250 | CA44: Transfers from authorized committees
A45: C00446815 | B45: MCCLINTOCK FOR CONGRESS | C45: 2019 | D45: Q1 | E45: 2.0190413e+17 | F45: 12 | G45: IDTA55 | H45: 1324116 | J45: IND | K45: INDIVIDUAL | M45: MR. | N45: MONTAG, THOMAS MR. | O45: H | Q45: P | R45: THOMAS | T45: MONTAG | V45: 127 E 73RD ST | X45: NEW YORK | Y45: NY | Z45: 10021 | AA45: BANK OF AMERICA | AB45: COO | AD45: 15J | AE45: MEMO (FILER'S % OF CONTRIBUTION GIVEN TO JOIN | AG45: X | AI45: 43539 | AJ45: 2651.22 | AK45: 2651.22 | AY45: TAKE BACK THE HOUSE 2020 | AZ45: P. O. BOX 30844 | BB45: BETHESDA | BC45: MD | BD45: 20824 | BG45: P2020 | BI45: PRIMARY | BJ45: 2020 | BK45: A | BL45: ADD | BM45: ITEMIZED RECEIPTS | BN45: 43568.111 | BR45: F3 | BS45: 4.0412202e+18 | BT45: t | BV45: 2020 | BW45: SA | BY45: 4.0412202e+18 | BZ45: http://docquery.fec.gov/cgi-bin/fecimg/?201904129146091362 | CA45: Transfers from authorized committees
A46: C00459297 | B46: HUIZENGA FOR CONGRESS | C46: 2019 | D46: Q1 | E46: 2.0190416e+17 | F46: 12 | G46: A26F304C559734768B86 | H46: 1324955 | J46: IND | K46: INDIVIDUAL | N46: MONTAG, THOMAS | O46: H | Q46: P | R46: THOMAS | T46: MONTAG | V46: 127 E 73RD ST | X46: NEW YORK | Y46: NY | Z46: 10021 | AA46: BANK OF AMERICA | AB46: COO | AD46: 15J | AE46: MEMO (FILER'S % OF CONTRIBUTION GIVEN TO JOIN | AG46: X | AI46: 43555 | AJ46: 2800 | AK46: 5600 | BG46: G2020 | BI46: GENERAL | BJ46: 2020 | BK46: A | BL46: ADD | BM46: ITEMIZED RECEIPTS | BN46: 43571.117 | BP46: AFE3E713847894B6BBEE | BQ46: SA12 | BR46: F3 | BS46: 4.0415202e+18 | BT46: t | BV46: 2020 | BW46: SA | BY46: 4.0415202e+18 | BZ46: http://docquery.fec.gov/cgi-bin/fecimg/?201904159146133098 | CA46: Transfers from authorized committees
A47: C00459297 | B47: HUIZENGA FOR CONGRESS | C47: 2019 | D47: Q1 | E47: 2.0190416e+17 | F47: 12 | G47: A898CFE25DA4344F09B7 | H47: 1324955 | J47: IND | K47: INDIVIDUAL | N47: MONTAG, THOMAS | O47: H | Q47: P | R47: THOMAS | T47: MONTAG | V47: 127 E 73RD ST | X47: NEW YORK | Y47: NY | Z47: 10021 | AA47: BANK OF AMERICA | AB47: COO | AD47: 15J | AE47: MEMO (FILER'S % OF CONTRIBUTION GIVEN TO JOIN | AG47: X | AI47: 43555 | AJ47: 2800 | AK47: 5600 | BG47: P2020 | BI47: PRIMARY | BJ47: 2020 | BK47: A | BL47: ADD | BM47: ITEMIZED RECEIPTS | BN47: 43571.117 | BP47: AF2690A4727B441EAB0C | BQ47: SA12 | BR47: F3 | BS47: 4.0415202e+18 | BT47: t | BV47: 2020 | BW47: SA | BY47: 4.0415202e+18 | BZ47: http://docquery.fec.gov/cgi-bin/fecimg/?201904159146133107 | CA47: Transfers from authorized committees
A48: C00631945 | B48: GREG FOR MONTANA | C48: 2019 | D48: Q1 | E48: 2.0190414e+17 | F48: 12 | G48: AE79C6DAE004D4B748A7 | H48: 1324575 | J48: IND | K48: INDIVIDUAL | N48: MONTAG, THOMAS | O48: H | Q48: P | R48: THOMAS | T48: MONTAG | V48: 127 E 73RD ST | X48: NEW YORK | Y48: NY | Z48: 10021 | AA48: COO | AB48: BANK OF AMERICA | AD48: 15J | AE48: MEMO (FILER'S % OF CONTRIBUTION GIVEN TO JOIN | AG48: X | AI48: 43539 | AJ48: 2651.22 | AK48: 2651.22 | BG48: P2020 | BI48: PRIMARY | BJ48: 2020 | BK48: A | BL48: ADD | BM48: ITEMIZED RECEIPTS | BN48: 43569.114 | BP48: A1B6A19F789854265A8E | BQ48: SA12 | BR48: F3 | BS48: 4.0413202e+18 | BT48: t | BV48: 2020 | BW48: SA | BY48: 4.0413202e+18 | BZ48: http://docquery.fec.gov/cgi-bin/fecimg/?201904139146114589 | CA48: Transfers from authorized committees
A49: C00632257 | B49: MAST FOR CONGRESS | C49: 2019 | D49: Q1 | E49: 2.0190412e+17 | F49: 12 | G49: SA12.243793 | H49: 1323775 | J49: IND | K49: INDIVIDUAL | N49: MONTAG, THOMAS | O49: H | Q49: P | R49: THOMAS | T49: MONTAG | V49: 127 E 73RD ST | X49: NEW YORK | Y49: NY | Z49: 100213502 | AA49: BANK OF AMERICA | AB49: CHIEF OPERATING OFFICER | AD49: 15J | AE49: MEMO (FILER'S % OF CONTRIBUTION GIVEN TO JOIN | AF49: TRANSFER | AG49: X | AI49: 43539 | AJ49: 2651.22 | AK49: 2651.22 | BG49: P2020 | BI49: PRIMARY | BJ49: 2020 | BK49: A | BL49: ADD | BM49: ITEMIZED RECEIPTS | BN49: 43567.131 | BP49: SA12.243659 | BQ49: SA12 | BR49: F3 | BS49: 4.0411202e+18 | BT49: t | BU49: JFC ATTRIB: TAKE BACK THE HOUSE 2020 | BV49: 2020 | BW49: SA | BY49: 4.0411202e+18 | BZ49: http://docquery.fec.gov/cgi-bin/fecimg/?201904119146071904 | CA49: Transfers from authorized committees
A50: C00464032 | B50: TOM REED FOR CONGRESS | C50: 2019 | D50: Q1 | E50: 2.0190416e+17 | F50: 12 | G50: AA4BE1ADFBD3E4BC7863 | H50: 1326490 | J50: IND | K50: INDIVIDUAL | N50: MONTAG, THOMAS | O50: H | Q50: P | R50: THOMAS | T50: MONTAG | V50: 127 E 73RD ST | X50: NEW YORK | Y50: NY | Z50: 100213502 | AA50: BANK OF AMERICA | AB50: COO | AD50: 15J | AE50: MEMO (FILER'S % OF CONTRIBUTION GIVEN TO JOIN | AG50: X | AI50: 43539 | AJ50: 2800 | AK50: 5600 | BG50: G2020 | BI50: GENERAL | BJ50: 2020 | BK50: A | BL50: ADD | BM50: ITEMIZED RECEIPTS | BN50: 43576.15 | BP50: A47DDE73C79624F7482E | BQ50: SA12 | BR50: F3 | BS50: 4.0416202e+18 | BT50: t | BV50: 2020 | BW50: SA | BY50: 4.0420202e+18 | BZ50: http://docquery.fec.gov/cgi-bin/fecimg/?201904159146384675 | CA50: Transfers from authorized committees
A51: C00464032 | B51: TOM REED FOR CONGRESS | C51: 2019 | D51: Q1 | E51: 2.0190416e+17 | F51: 12 | G51: A0E72A71E6FE24FD0944 | H51: 1326490 | J51: IND | K51: INDIVIDUAL | N51: MONTAG, THOMAS | O51: H | Q51: P | R51: THOMAS | T51: MONTAG | V51: 127 E 73RD ST | X51: NEW YORK | Y51: NY | Z51: 100213502 | AA51: BANK OF AMERICA | AB51: COO | AD51: 15J | AE51: MEMO (FILER'S % OF CONTRIBUTION GIVEN TO JOIN | AG51: X | AI51: 43539 | AJ51: 2800 | AK51: 5600 | BG51: P2020 | BI51: PRIMARY | BJ51: 2020 | BK51: A | BL51: ADD | BM51: ITEMIZED RECEIPTS | BN51: 43576.15 | BP51: A84AC36A76E694ACEBFE | BQ51: SA12 | BR51: F3 | BS51: 4.0416202e+18 | BT51: t | BV51: 2020 | BW51: SA | BY51: 4.0420202e+18 | BZ51: http://docquery.fec.gov/cgi-bin/fecimg/?201904159146384684 | CA51: Transfers from authorized committees
A52: C00468579 | B52: WALORSKI FOR CONGRESS INC | C52: 2019 | D52: Q1 | E52: 2.0190416e+17 | F52: 12 | G52: SA12.30828 | H52: 1325869 | J52: IND | K52: INDIVIDUAL | N52: MONTAG, THOMAS | O52: H | Q52: P | R52: THOMAS | T52: MONTAG | V52: 127 E 73RD ST | X52: NEW YORK | Y52: NY | Z52: 100213502 | AA52: BANK OF AMERICA | AB52: COO | AD52: 15J | AE52: MEMO (FILER'S % OF CONTRIBUTION GIVEN TO JOIN | AF52: TRANSFER | AG52: X | AI52: 43539 | AJ52: 2800 | AK52: 5600 | BG52: P2020 | BI52: PRIMARY | BJ52: 2020 | BK52: A | BL52: ADD | BM52: ITEMIZED RECEIPTS | BN52: 43574.193 | BP52: SA12.30729 | BQ52: SA12 | BR52: F3 | BS52: 4.0415202e+18 | BT52: t | BU52: JFC ATTRIB: TAKE BACK THE HOUSE 2020 | BV52: 2020 | BW52: SA | BY52: 4.0418202e+18 | BZ52: http://docquery.fec.gov/cgi-bin/fecimg/?201904159146192008 | CA52: Transfers from authorized committees
A53: C00468579 | B53: WALORSKI FOR CONGRESS INC | C53: 2019 | D53: Q1 | E53: 2.0190416e+17 | F53: 12 | G53: SA12.30838 | H53: 1325869 | J53: IND | K53: INDIVIDUAL | N53: MONTAG, THOMAS | O53: H | Q53: P | R53: THOMAS | T53: MONTAG | V53: 127 E 73RD ST | X53: NEW YORK | Y53: NY | Z53: 100213502 | AA53: BANK OF AMERICA | AB53: COO | AD53: 15J | AE53: MEMO (FILER'S % OF CONTRIBUTION GIVEN TO JOIN | AF53: TRANSFER | AG53: X | AI53: 43539 | AJ53: 2800 | AK53: 5600 | BG53: G2020 | BI53: GENERAL | BJ53: 2020 | BK53: A | BL53: ADD | BM53: ITEMIZED RECEIPTS | BN53: 43574.193 | BP53: SA12.30730 | BQ53: SA12 | BR53: F3 | BS53: 4.0415202e+18 | BT53: t | BU53: JFC ATTRIB: TAKE BACK THE HOUSE 2020 | BV53: 2020 | BW53: SA | BY53: 4.0418202e+18 | BZ53: http://docquery.fec.gov/cgi-bin/fecimg/?201904159146192016 | CA53: Transfers from authorized committees
A54: C00272211 | B54: PETE KING FOR CONGRESS COMMITTEE | C54: 2019 | D54: Q1 | E54: 2.0190416e+17 | F54: 12 | G54: SA12-TI1-40 | H54: 1325180 | J54: IND | K54: INDIVIDUAL | M54: MR. | N54: MONTAG, THOMAS MR. | O54: H | Q54: P | R54: THOMAS | T54: MONTAG | V54: 127 EAST 73RD STREET | X54: NEW YORK | Y54: NY | Z54: 10021 | AA54: BANK OF AMERICA | AB54: COO | AD54: 15J | AE54: MEMO (FILER'S % OF CONTRIBUTION GIVEN TO JOIN | AF54: TRANSFER IN AFFILIATED | AG54: X | AI54: 43553 | AJ54: 2651.22 | AK54: 2651.22 | BG54: P2020 | BI54: PRIMARY | BJ54: 2020 | BK54: A | BL54: ADD | BM54: ITEMIZED RECEIPTS | BN54: 43571.117 | BR54: F3 | BS54: 4.0415202e+18 | BT54: t | BU54: TAKE BACK THE HOUSE 2020 | BV54: 2020 | BW54: SA | BY54: 4.0415202e+18 | BZ54: http://docquery.fec.gov/cgi-bin/fecimg/?201904159146141196 | CA54: Transfers from authorized committees
A55: C00472704 | B55: JAIME FOR CONGRESS | C55: 2019 | D55: Q1 | E55: 2.0190416e+17 | F55: 12 | G55: A753958653D0F4A98B6B | H55: 1325785 | J55: IND | K55: INDIVIDUAL | N55: MONTAG, THOMAS | O55: H | Q55: P | R55: THOMAS | T55: MONTAG | V55: 127 E 73RD ST. | X55: NEW YORK | Y55: NY | Z55: 100213502 | AA55: BANK OF AMERICA | AB55: COO | AD55: 15J | AE55: MEMO (FILER'S % OF CONTRIBUTION GIVEN TO JOIN | AG55: X | AI55: 43539 | AJ55: 2651.22 | AK55: 2651.22 | BG55: P2020 | BI55: PRIMARY | BJ55: 2020 | BK55: A | BL55: ADD | BM55: ITEMIZED RECEIPTS | BN55: 43574.195 | BP55: AE6FD3BEB740349EC92D | BQ55: SA12 | BR55: F3 | BS55: 4.0415202e+18 | BT55: t | BU55: CONTRIBUTION | BV55: 2020 | BW55: SA | BY55: 4.0418202e+18 | BZ55: http://docquery.fec.gov/cgi-bin/fecimg/?201904159146184225 | CA55: Transfers from authorized committees
A56: C00474189 | B56: MIKE KELLY FOR CONGRESS | C56: 2019 | D56: Q1 | E56: 2.0190416e+17 | F56: 12 | G56: SA12-TI9-37 | H56: 1325118 | J56: IND | K56: INDIVIDUAL | N56: MONTAG, THOMAS | O56: H | Q56: P | R56: THOMAS | T56: MONTAG | V56: 127 E 73RD ST | X56: NEW YORK | Y56: NY | Z56: 10021 | AA56: BANK OF AMERICA | AB56: COO | AD56: 15J | AE56: MEMO (FILER'S % OF CONTRIBUTION GIVEN TO JOIN | AF56: TRANSFER IN AFFILIATED | AG56: X | AI56: 43539 | AJ56: 2800 | AK56: 2800 | BG56: P2020 | BI56: PRIMARY | BJ56: 2020 | BK56: A | BL56: ADD | BM56: ITEMIZED RECEIPTS | BN56: 43571.117 | BR56: F3 | BS56: 4.0415202e+18 | BT56: t | BU56: TAKE BACK THE HOUSE 2020 | BV56: 2020 | BW56: SA | BY56: 4.0415202e+18 | BZ56: http://docquery.fec.gov/cgi-bin/fecimg/?201904159146138493 | CA56: Transfers from authorized committees
A57: C00474189 | B57: MIKE KELLY FOR CONGRESS | C57: 2019 | D57: Q1 | E57: 2.0190416e+17 | F57: 12 | G57: SA12-TI10-11 | H57: 1325118 | J57: IND | K57: INDIVIDUAL | N57: MONTAG, THOMAS | O57: H | Q57: P | R57: THOMAS | T57: MONTAG | V57: 127 E 73RD ST | X57: NEW YORK | Y57: NY | Z57: 10021 | AA57: BANK OF AMERICA | AB57: COO | AD57: 15J | AE57: MEMO (FILER'S % OF CONTRIBUTION GIVEN TO JOIN | AF57: TRANSFER IN AFFILIATED | AG57: X | AI57: 43539 | AJ57: 2800 | AK57: 5600 | BG57: G2020 | BI57: GENERAL | BJ57: 2020 | BK57: A | BL57: ADD | BM57: ITEMIZED RECEIPTS | BN57: 43571.117 | BR57: F3 | BS57: 4.0415202e+18 | BT57: t | BU57: TAKE BACK THE HOUSE 2020 | BV57: 2020 | BW57: SA | BY57: 4.0415202e+18 | BZ57: http://docquery.fec.gov/cgi-bin/fecimg/?201904159146138500 | CA57: Transfers from authorized committees
A58: C00301838 | B58: STEVE CHABOT FOR CONGRESS | C58: 2019 | D58: Q1 | E58: 2.0190507e+17 | F58: 11AI | G58: A2C70346AE7B44A91A5C | H58: 1329670 | J58: IND | K58: INDIVIDUAL | L58: C00695585 | N58: MONTAG, THOMAS | O58: H | Q58: P | R58: THOMAS | T58: MONTAG | V58: 127 E 73RD ST. | X58: NEW YORK | Y58: NY | Z58: 100213502 | AA58: BANK OF AMERICA | AB58: COO | AC58: C00695585 | AD58: 15E | AE58: EARMARKED CONTRIBUTION | AF58: EARMARKED (NON-DIRECTED) THROUGH TAKE BACK THE HOUSE 2020 | AI58: 43553 | AJ58: 2651.22 | AK58: 2651.22 | BG58: P2020 | BI58: PRIMARY | BJ58: 2020 | BK58: A | BL58: ADD | BM58: ITEMIZED RECEIPTS | BN58: 43593.149 | BR58: F3 | BS58: 4.0506202e+18 | BT58: t | BV58: 2020 | BW58: SA | BY58: 4.0507202e+18 | BZ58: http://docquery.fec.gov/cgi-bin/fecimg/?201905069149632099 | CA58: Contributions From Individuals/Persons Other Than Political Committees
A59: C00650697 | B59: PETE STAUBER FOR CONGRESS | C59: 2019 | D59: Q1 | E59: 2.0190416e+17 | F59: 12 | G59: SA12-TI3-37 | H59: 1326470 | J59: IND | K59: INDIVIDUAL | N59: MONTAG, THOMAS | O59: H | Q59: P | R59: THOMAS | T59: MONTAG | V59: 127 E 73RD ST | X59: NEW YORK | Y59: NY | Z59: 10021 | AA59: BANK OF AMERICA | AB59: COO | AD59: 15J | AE59: MEMO (FILER'S % OF CONTRIBUTION GIVEN TO JOIN | AF59: TRANSFER IN AFFILIATED | AG59: X | AI59: 43539 | AJ59: 2651.22 | AK59: 2651.22 | BG59: P2020 | BI59: PRIMARY | BJ59: 2020 | BK59: A | BL59: ADD | BM59: ITEMIZED RECEIPTS | BN59: 43576.15 | BR59: F3 | BS59: 4.0416202e+18 | BT59: t | BU59: TAKE BACK THE HOUSE 2020 | BV59: 2020 | BW59: SA | BY59: 4.0420202e+18 | BZ59: http://docquery.fec.gov/cgi-bin/fecimg/?201904159146376439 | CA59: Transfers from authorized committees
A60: C00495846 | B60: ANN WAGNER FOR CONGRESS | C60: 2019 | D60: Q1 | E60: 2.0190416e+17 | F60: 12 | G60: SA12.10004 | H60: 1326213 | J60: IND | K60: INDIVIDUAL | N60: MONTAG, THOMAS | O60: H | Q60: P | R60: THOMAS | T60: MONTAG | V60: 127 E 73RD ST | X60: NEW YORK | Y60: NY | Z60: 100213502 | AA60: BANK OF AMERICA | AB60: COO | AD60: 15J | AE60: MEMO (FILER'S % OF CONTRIBUTION GIVEN TO JOIN | AF60: TRANSFER | AG60: X | AI60: 43555 | AJ60: 2800 | AK60: 5600 | BG60: P2020 | BI60: PRIMARY | BJ60: 2020 | BK60: A | BL60: ADD | BM60: ITEMIZED RECEIPTS | BN60: 43576.15 | BP60: SA12.9956 | BQ60: SA12 | BR60: F3 | BS60: 4.0415202e+18 | BT60: t | BU60: JFC ATTRIB: TAKE BACK THE HOUSE 2020 | BV60: 2020 | BW60: SA | BY60: 4.0420202e+18 | BZ60: http://docquery.fec.gov/cgi-bin/fecimg/?201904159146339462 | CA60: Transfers from authorized committees
A61: C00495846 | B61: ANN WAGNER FOR CONGRESS | C61: 2019 | D61: Q1 | E61: 2.0190416e+17 | F61: 12 | G61: SA12.10024 | H61: 1326213 | J61: IND | K61: INDIVIDUAL | N61: MONTAG, THOMAS | O61: H | Q61: P | R61: THOMAS | T61: MONTAG | V61: 127 E 73RD ST | X61: NEW YORK | Y61: NY | Z61: 100213502 | AA61: BANK OF AMERICA | AB61: COO | AD61: 15J | AE61: MEMO (FILER'S % OF CONTRIBUTION GIVEN TO JOIN | AF61: TRANSFER | AG61: X | AI61: 43555 | AJ61: 2800 | AK61: 5600 | BG61: G2020 | BI61: GENERAL | BJ61: 2020 | BK61: A | BL61: ADD | BM61: ITEMIZED RECEIPTS | BN61: 43576.15 | BP61: SA12.9957 | BQ61: SA12 | BR61: F3 | BS61: 4.0415202e+18 | BT61: t | BU61: JFC ATTRIB: TAKE BACK THE HOUSE 2020 | BV61: 2020 | BW61: SA | BY61: 4.0420202e+18 | BZ61: http://docquery.fec.gov/cgi-bin/fecimg/?201904159146339470 | CA61: Transfers from authorized committees
A62: C00499236 | B62: GEORGE HOLDING FOR CONGRESS INC. | C62: 2019 | D62: Q1 | E62: 2.0190416e+17 | F62: 12 | G62: SA12-TI67-36 | H62: 1325376 | J62: IND | K62: INDIVIDUAL | N62: MONTAG, THOMAS | O62: H | Q62: P | R62: THOMAS | T62: MONTAG | V62: 127 E 73RD ST | X62: NEW YORK | Y62: NY | Z62: 10021 | AA62: BANK OF AMERICA | AB62: COO | AD62: 15J | AE62: MEMO (FILER'S % OF CONTRIBUTION GIVEN TO JOIN | AF62: TRANSFER IN AFFILIATED | AG62: X | AI62: 43539 | AJ62: 2800 | AK62: 2800 | BG62: P2020 | BI62: PRIMARY | BJ62: 2020 | BK62: A | BL62: ADD | BM62: ITEMIZED RECEIPTS | BN62: 43576.149 | BR62: F3 | BS62: 4.0415202e+18 | BT62: t | BU62: TAKE BACK THE HOUSE 2020 | BV62: 2020 | BW62: SA | BY62: 4.0420202e+18 | BZ62: http://docquery.fec.gov/cgi-bin/fecimg/?201904159146156634 | CA62: Transfers from authorized committees
A63: C00653634 | B63: VAN TAYLOR CAMPAIGN | C63: 2019 | D63: Q1 | E63: 2.0190416e+17 | F63: 12 | G63: SA12.4801 | H63: 1326235 | J63: IND | K63: INDIVIDUAL | N63: MONTAG, THOMAS | O63: H | Q63: P | R63: THOMAS | T63: MONTAG | V63: 127 E 73RD ST | X63: NEW YORK | Y63: NY | Z63: 100213502 | AA63: BANK OF AMERICA | AB63: COO | AD63: 15J | AE63: MEMO (FILER'S % OF CONTRIBUTION GIVEN TO JOIN | AF63: TRANSFER | AG63: X | AI63: 43555 | AJ63: 2651.22 | AK63: 2651.22 | BG63: P2020 | BI63: PRIMARY | BJ63: 2020 | BK63: A | BL63: ADD | BM63: ITEMIZED RECEIPTS | BN63: 43574.206 | BP63: SA12.4753 | BQ63: SA12 | BR63: F3 | BS63: 4.0415202e+18 | BT63: t | BU63: JFC ATTRIB: TAKE BACK THE HOUSE 2020 | BV63: 2020 | BW63: SA | BY63: 4.0418202e+18 | BZ63: http://docquery.fec.gov/cgi-bin/fecimg/?201904159146344140 | CA63: Transfers from authorized committees
A64: C00501643 | B64: DAVID ROUZER FOR CONGRESS | C64: 2019 | D64: Q1 | E64: 2.0190416e+17 | F64: 12 | G64: SA12-TI6-37 | H64: 1324925 | J64: IND | K64: INDIVIDUAL | N64: MONTAG, THOMAS | O64: H | Q64: P | R64: THOMAS | T64: MONTAG | V64: 127 73RD ST E | X64: NEW YORK | Y64: NY | Z64: 10021 | AA64: BANK OF AMERICA | AB64: COO | AD64: 15J | AE64: MEMO (FILER'S % OF CONTRIBUTION GIVEN TO JOIN | AF64: TRANSFER IN AFFILIATED | AG64: X | AI64: 43539 | AJ64: 2651.22 | AK64: 2651.22 | BG64: P2020 | BI64: PRIMARY | BJ64: 2020 | BK64: A | BL64: ADD | BM64: ITEMIZED RECEIPTS | BN64: 43571.117 | BR64: F3 | BS64: 4.0415202e+18 | BT64: t | BU64: TAKE BACK THE HOUSE 2020 | BV64: 2020 | BW64: SA | BY64: 4.0415202e+18 | BZ64: http://docquery.fec.gov/cgi-bin/fecimg/?201904159146132360 | CA64: Transfers from authorized committees
A65: C00075820 | B65: NRCC | C65: 2019 | D65: M4 | E65: 2.0190829e+17 | F65: 12 | G65: SA12.18032116 | H65: 1350008 | J65: IND | K65: INDIVIDUAL | M65: MR. | N65: MONTAG, THOMAS K. MR. | O65: Y | Q65: U | R65: THOMAS | S65: K. | T65: MONTAG | V65: 127 E. 73RD ST. | X65: NEW YORK | Y65: NY | Z65: 100213502 | AA65: BANK OF AMERICA MERRILL LYNCH | AB65: PRESIDENT | AD65: 15J | AE65: MEMO (FILER'S % OF CONTRIBUTION GIVEN TO JOIN | AF65: TRANSFER | AG65: X | AI65: 43539 | AJ65: 35500 | AK65: 35500 | BG65: P | BI65: PRIMARY | BK65: N | BL65: NO CHANGE | BM65: ITEMIZED RECEIPTS | BN65: 43707.225 | BP65: SA12.18032069 | BQ65: SA12 | BR65: F3X | BS65: 4.0828202e+18 | BT65: t | BU65: JFC ATTRIB: TAKE BACK THE HOUSE 2020 | BV65: 2020 | BW65: SA | BY65: 4.0829202e+18 | BZ65: http://docquery.fec.gov/cgi-bin/fecimg/?201908289163111172 | CA65: Transfers from Authorized Committees
A66: C00662171 | B66: RON WRIGHT FOR CONGRESS | C66: 2019 | D66: Q1 | E66: 2.0190919e+17 | F66: 12 | G66: SA12.7667 | H66: 1352629 | J66: IND | K66: INDIVIDUAL | N66: MONTAG, THOMAS | O66: H | Q66: P | R66: THOMAS | T66: MONTAG | V66: 127 E 73RD STREET | X66: NEW YORK | Y66: NY | Z66: 10021 | AA66: BANK OF AMERICA | AB66: COO | AD66: 15J | AE66: MEMO (FILER'S % OF CONTRIBUTION GIVEN TO JOIN | AG66: X | AI66: 43539 | AJ66: 2651.22 | AK66: 2651.22 | BG66: P2020 | BI66: PRIMARY | BJ66: 2020 | BK66: C | BL66: CHANGE | BM66: ITEMIZED RECEIPTS | BN66: 43728.111 | BR66: F3 | BS66: 4.0918202e+18 | BT66: t | BV66: 2020 | BW66: SA | BY66: 4.0919202e+18 | BZ66: http://docquery.fec.gov/cgi-bin/fecimg/?201909189163373024 | CA66: Transfers from authorized committees
A67: C00467571 | B67: ANDY BARR FOR CONGRESS, INC. | C67: 2019 | D67: Q1 | E67: 2.019092e+17 | F67: 12 | G67: A7CF34CB996424D5B92C | H67: 1352790 | J67: IND | K67: INDIVIDUAL | N67: MONTAG, THOMAS | O67: H | Q67: P | R67: THOMAS | T67: MONTAG | V67: 127 E. 73RD STREET | X67: NEW YORK | Y67: NY | Z67: 100213502 | AA67: BANK OF AMERICA | AB67: CHIEF OPERATING OFFICER | AD67: 15J | AE67: MEMO (FILER'S % OF CONTRIBUTION GIVEN TO JOIN | AG67: X | AI67: 43539 | AJ67: 2800 | AK67: 2800 | BG67: G2020 | BI67: GENERAL | BJ67: 2020 | BK67: N | BL67: NO CHANGE | BM67: ITEMIZED RECEIPTS | BN67: 43729.118 | BP67: A1194E72816804FE8983 | BQ67: SA12 | BR67: F3 | BS67: 4.0919202e+18 | BT67: t | BV67: 2020 | BW67: SA | BY67: 4.0920202e+18 | BZ67: http://docquery.fec.gov/cgi-bin/fecimg/?201909199163407320 | CA67: Transfers from authorized committees
A68: C00467571 | B68: ANDY BARR FOR CONGRESS, INC. | C68: 2019 | D68: Q1 | E68: 2.019092e+17 | F68: 12 | G68: A8C511CAB8E5342F382A | H68: 1352790 | J68: IND | K68: INDIVIDUAL | N68: MONTAG, THOMAS | O68: H | Q68: P | R68: THOMAS | T68: MONTAG | V68: 127 E. 73RD STREET | X68: NEW YORK | Y68: NY | Z68: 100213502 | AA68: BANK OF AMERICA | AB68: CHIEF OPERATING OFFICER | AD68: 15J | AE68: MEMO (FILER'S % OF CONTRIBUTION GIVEN TO JOIN | AG68: X | AI68: 43558 | AJ68: 2800 | AK68: 5600 | BG68: P2020 | BI68: PRIMARY | BJ68: 2020 | BK68: N | BL68: NO CHANGE | BM68: ITEMIZED RECEIPTS | BN68: 43729.118 | BP68: ABC80664D43BF4D4CBEF | BQ68: SA12 | BR68: F3 | BS68: 4.0919202e+18 | BT68: t | BV68: 2020 | BW68: SA | BY68: 4.0920202e+18 | BZ68: http://docquery.fec.gov/cgi-bin/fecimg/?201909199163407334 | CA68: Transfers from authorized committees
A69: C00470757 | B69: VOTETIPTON.COM | C69: 2019 | D69: Q1 | E69: 2.0191016e+17 | F69: 12 | G69: AC0C7E0E6BB004632800 | H69: 1358165 | J69: IND | K69: INDIVIDUAL | N69: MONTAG, THOMAS | O69: H | Q69: P | R69: THOMAS | T69: MONTAG | V69: 127 E 73RD STREET | X69: NEW YORK | Y69: NY | Z69: 100213502 | AA69: BANK OF AMERICA | AB69: COO | AD69: 15J | AE69: MEMO (FILER'S % OF CONTRIBUTION GIVEN TO JOIN | AG69: X | AI69: 43539 | AJ69: 2800 | AK69: 5600 | BG69: G2020 | BI69: GENERAL | BJ69: 2020 | BK69: N | BL69: NO CHANGE | BM69: ITEMIZED RECEIPTS | BN69: 43765.109 | BP69: ABFE69E9ECAF346109CC | BQ69: SA12 | BR69: F3 | BS69: 4.1015202e+18 | BT69: t | BV69: 2020 | BW69: SA | BY69: 4.1026202e+18 | BZ69: http://docquery.fec.gov/cgi-bin/fecimg/?201910159164216954 | CA69: Transfers from authorized committees
A70: C00470757 | B70: VOTETIPTON.COM | C70: 2019 | D70: Q1 | E70: 2.0191016e+17 | F70: 12 | G70: AE8F62567B6344DFF8D0 | H70: 1358165 | J70: IND | K70: INDIVIDUAL | N70: MONTAG, THOMAS | O70: H | Q70: P | R70: THOMAS | T70: MONTAG | V70: 127 E 73RD STREET | X70: NEW YORK | Y70: NY | Z70: 100213502 | AA70: BANK OF AMERICA | AB70: COO | AD70: 15J | AE70: MEMO (FILER'S % OF CONTRIBUTION GIVEN TO JOIN | AG70: X | AI70: 43539 | AJ70: 2800 | AK70: 5600 | BG70: P2020 | BI70: PRIMARY | BJ70: 2020 | BK70: N | BL70: NO CHANGE | BM70: ITEMIZED RECEIPTS | BN70: 43765.109 | BP70: A4AD7DC27A4364A3CA23 | BQ70: SA12 | BR70: F3 | BS70: 4.1015202e+18 | BT70: t | BV70: 2020 | BW70: SA | BY70: 4.1026202e+18 | BZ70: http://docquery.fec.gov/cgi-bin/fecimg/?201910159164216961 | CA70: Transfers from authorized committees
A71: C00607416 | B71: BRIAN FITZPATRICK FOR CONGRESS | C71: 2019 | D71: Q1 | E71: 2.0191016e+17 | F71: 12 | G71: A-78995 | H71: 1358581 | J71: IND | K71: INDIVIDUAL | N71: MONTAG, THOMAS | O71: H | Q71: P | R71: THOMAS | T71: MONTAG | V71: 127 EAST 73RD STREET | X71: NEW YORK | Y71: NY | Z71: 10021 | AA71: COO | AB71: BANK OF AMERICA | AD71: 15J | AE71: MEMO (FILER'S % OF CONTRIBUTION GIVEN TO JOIN | AG71: X | AI71: 43539 | AJ71: 2651.22 | AK71: 2651.22 | BG71: P2020 | BI71: PRIMARY | BJ71: 2020 | BK71: C | BL71: CHANGE | BM71: ITEMIZED RECEIPTS | BN71: 43768.111 | BP71: A-78900 | BR71: F3 | BS71: 4.1016202e+18 | BT71: t | BU71: MEMO TRANSFER FROM JOINT FUNDRAISER-TAKE BACK THE HOUSE 2020 | BV71: 2020 | BW71: SA | BY71: 4.1029202e+18 | BZ71: http://docquery.fec.gov/cgi-bin/fecimg/?201910159164579322 | CA71: Transfers from authorized committees
A72: C00075820 | B72: NRCC | C72: 2019 | D72: M10 | E72: 2.0191021e+17 | F72: 17 | G72: SA17.18428960 | H72: 1360334 | J72: IND | K72: INDIVIDUAL | M72: MR. | N72: MONTAG, THOMAS K. MR. | O72: Y | Q72: U | R72: THOMAS | S72: K. | T72: MONTAG | V72: 127 E. 73RD ST. | X72: NEW YORK | Y72: NY | Z72: 100213502 | AA72: BANK OF AMERICA MERRILL LYNCH | AB72: PRESIDENT | AD72: 32J | AE72: MEMO RECEIPT FROM INDIVIDUAL - JF RECOUNT ACCOUNT | AF72: TRANSFER | AG72: X | AI72: 43735 | AJ72: 43500 | AK72: 43500 | BG72: P | BI72: PRIMARY | BK72: A | BL72: ADD | BM72: ITEMIZED RECEIPTS | BN72: 43770.112 | BP72: SA17.18417298 | BQ72: SA17 | BR72: F3X | BS72: 4.1020202e+18 | BT72: t | BU72: LEGAL PROCEEDINGS ACCOUNT; JFC ATTRIB: MVF | BV72: 2020 | BW72: SA | BY72: 4.1031202e+18 | BZ72: http://docquery.fec.gov/cgi-bin/fecimg/?201910209165195402 | CA72: Other Federal Receipts (Dividends, Interest, etc.).
A73: C00075820 | B73: NRCC | C73: 2019 | D73: M10 | E73: 2.0191021e+17 | F73: 17 | G73: SA17.18428956 | H73: 1360334 | J73: IND | K73: INDIVIDUAL | M73: MR. | N73: MONTAG, THOMAS K. MR. | O73: Y | Q73: U | R73: THOMAS | S73: K. | T73: MONTAG | V73: 127 E. 73RD ST. | X73: NEW YORK | Y73: NY | Z73: 100213502 | AA73: BANK OF AMERICA MERRILL LYNCH | AB73: PRESIDENT | AD73: 31J | AE73: MEMO RECEIPT FROM INDIVIDUAL - JF HEADQUARTERS ACCOUNT | AF73: TRANSFER | AG73: X | AI73: 43735 | AJ73: 106500 | AK73: 106500 | BG73: P | BI73: PRIMARY | BK73: A | BL73: ADD | BM73: ITEMIZED RECEIPTS | BN73: 43770.116 | BP73: SA17.18417297 | BQ73: SA17 | BR73: F3X | BS73: 4.1020202e+18 | BT73: t | BU73: HEADQUARTERS ACCOUNT; JFC ATTRIB: MVF | BV73: 2020 | BW73: SA | BY73: 4.1031202e+18 | BZ73: http://docquery.fec.gov/cgi-bin/fecimg/?201910209165195393 | CA73: Other Federal Receipts (Dividends, Interest, etc.).
A74: C00504522 | B74: HUDSON FOR CONGRESS | C74: 2019 | D74: Q1 | E74: 2.0200819e+17 | F74: 12 | G74: A1EA3B22638F04B48B1F | H74: 1433156 | J74: IND | K74: INDIVIDUAL | N74: MONTAG, THOMAS | O74: H | Q74: P | R74: THOMAS | T74: MONTAG | V74: 127 E 73RD ST | X74: NEW YORK | Y74: NY | Z74: 10021 | AA74: BANK OF AMERICA | AB74: COO | AD74: 15J | AE74: MEMO (FILER'S % OF CONTRIBUTION GIVEN TO JOIN | AG74: X | AI74: 43539 | AJ74: 2800 | AK74: 5600 | BG74: G2020 | BI74: GENERAL | BJ74: 2020 | BK74: N | BL74: NO CHANGE | BM74: ITEMIZED RECEIPTS | BN74: 44064.152 | BP74: A93148AAC20B245B4A36 | BQ74: SA12 | BR74: F3 | BS74: 4.0819202e+18 | BT74: t | BV74: 2020 | BW74: SA | BY74: 4.0821202e+18 | BZ74: http://docquery.fec.gov/cgi-bin/fecimg/?202008189261361232 | CA74: Transfers from authorized committees
A75: C00504522 | B75: HUDSON FOR CONGRESS | C75: 2019 | D75: Q1 | E75: 2.0200819e+17 | F75: 12 | G75: A582343BB349449A1BDC | H75: 1433156 | J75: IND | K75: INDIVIDUAL | N75: MONTAG, THOMAS | O75: H | Q75: P | R75: THOMAS | T75: MONTAG | V75: 127 E 73RD ST | X75: NEW YORK | Y75: NY | Z75: 10021 | AA75: BANK OF AMERICA | AB75: COO | AD75: 15J | AE75: MEMO (FILER'S % OF CONTRIBUTION GIVEN TO JOIN | AG75: X | AI75: 43539 | AJ75: 2800 | AK75: 5600 | BG75: P2020 | BI75: PRIMARY | BJ75: 2020 | BK75: N | BL75: NO CHANGE | BM75: ITEMIZED RECEIPTS | BN75: 44064.152 | BP75: A6FAD0286FA6F4499A06 | BQ75: SA12 | BR75: F3 | BS75: 4.0819202e+18 | BT75: t | BV75: 2020 | BW75: SA | BY75: 4.0821202e+18 | BZ75: http://docquery.fec.gov/cgi-bin/fecimg/?202008189261361245 | CA75: Transfers from authorized committees
A76: C00680488 | B76: FRIENDS OF DENVER RIGGLEMAN, INC. | C76: 2019 | D76: Q1 | E76: 2.0200416e+17 | F76: 12 | G76: ACA8FB1B576E5407889D | H76: 1397621 | J76: IND | K76: INDIVIDUAL | N76: MONTAG, THOMAS | O76: H | Q76: P | R76: THOMAS | T76: MONTAG | V76: 127 E 73RD ST | X76: NEW YORK | Y76: NY | Z76: 100213502 | AA76: BANK OF AMERICA | AB76: COO | AD76: 15J | AE76: MEMO (FILER'S % OF CONTRIBUTION GIVEN TO JOIN | AG76: X | AI76: 43539 | AJ76: 2651.22 | AK76: 2651.22 | BG76: P2020 | BH76: CONVENTION | BI76: PRIMARY | BJ76: 2020 | BK76: A | BL76: ADD | BM76: ITEMIZED RECEIPTS | BN76: 43954.083 | BP76: A8591D8E3D2984A62A9E | BQ76: SA12 | BR76: F3 | BS76: 4.0415202e+18 | BT76: t | BV76: 2020 | BW76: SA | BY76: 4.0502202e+18 | BZ76: http://docquery.fec.gov/cgi-bin/fecimg/?202004159216730032 | CA76: Transfers from authorized committees
A77: C00695585 | B77: TAKE BACK THE HOUSE 2020 | C77: 2019 | D77: Q1 | E77: 2.0190416e+17 | F77: 11AI | G77: A5FBE315022684A1FB05 | H77: 1325317 | J77: IND | K77: INDIVIDUAL | N77: MONTAG, THOMAS | O77: Q | Q77: J | R77: THOMAS | T77: MONTAG | V77: 127 E 73RD ST | X77: NEW YORK | Y77: NY | Z77: 100213502 | AA77: BANK OF AMERICA | AB77: COO | AD77: 15 | AE77: CONTRIBUTION | AI77: 43539 | AJ77: 250000 | AK77: 250000 | BG77: P2019 | BH77: ANNUAL | BI77: PRIMARY | BJ77: 2019 | BK77: A | BL77: ADD | BM77: ITEMIZED RECEIPTS | BN77: 43571.118 | BR77: F3 | BS77: 4.0415202e+18 | BT77: t | BV77: 2020 | BW77: SA | BY77: 4.0415202e+18 | BZ77: http://docquery.fec.gov/cgi-bin/fecimg/?201904159146152024 | CA77: Contributions From Individuals/Persons Other Than Political Committees
A78: C00498121 | B78: ROGER WILLIAMS FOR U S CONGRESS COMMITTEE | C78: 2019 | D78: Q1 | E78: 2.0201016e+17 | F78: 12 | G78: SA12.5077.10 | H78: 1452827 | J78: IND | K78: INDIVIDUAL | N78: MONTAG, THOMAS | O78: H | Q78: P | R78: THOMAS | T78: MONTAG | V78: 127 E 73RD ST | X78: NEW YORK | Y78: NY | Z78: 10021 | AA78: BANK OF AMERICA | AB78: COO | AD78: 15J | AE78: MEMO (FILER'S % OF CONTRIBUTION GIVEN TO JOIN | AF78: JOINT FUNDRAISER - TAKE BACK THE HOUSE 2020 | AG78: X | AI78: 43539 | AJ78: 2800 | AK78: 2800 | BG78: P2020 | BI78: PRIMARY | BJ78: 2020 | BK78: N | BL78: NO CHANGE | BM78: ITEMIZED RECEIPTS | BN78: 44145.15 | BP78: SA12.5077 | BQ78: SA12 | BR78: F3 | BS78: 4.1016202e+18 | BT78: t | BV78: 2020 | BW78: SA | BY78: 4.1110202e+18 | BZ78: http://docquery.fec.gov/cgi-bin/fecimg/?202010159295833582 | CA78: Transfers from authorized committees
A79: C00498121 | B79: ROGER WILLIAMS FOR U S CONGRESS COMMITTEE | C79: 2019 | D79: Q1 | E79: 2.0201016e+17 | F79: 12 | G79: SA12.5078.9 | H79: 1452827 | J79: IND | K79: INDIVIDUAL | N79: MONTAG, THOMAS | O79: H | Q79: P | R79: THOMAS | T79: MONTAG | V79: 127 E 73RD ST | X79: NEW YORK | Y79: NY | Z79: 10021 | AA79: BANK OF AMERICA | AB79: COO | AD79: 15J | AE79: MEMO (FILER'S % OF CONTRIBUTION GIVEN TO JOIN | AF79: JOINT FUNDRAISER - TAKE BACK THE HOUSE 2020 | AG79: X | AI79: 43539 | AJ79: 2800 | AK79: 5600 | BG79: G2020 | BI79: GENERAL | BJ79: 2020 | BK79: N | BL79: NO CHANGE | BM79: ITEMIZED RECEIPTS | BN79: 44145.15 | BP79: SA12.5078 | BQ79: SA12 | BR79: F3 | BS79: 4.1016202e+18 | BT79: t | BV79: 2020 | BW79: SA | BY79: 4.1110202e+18 | BZ79: http://docquery.fec.gov/cgi-bin/fecimg/?202010159295833595 | CA79: Transfers from authorized committees
A80: C00428052 | B80: MAJORITY COMMITTEE PAC--MC PAC | C80: 2020 | D80: M8 | E80: 2.0200821e+17 | F80: 12 | G80: AC8B01995D66144419A3 | H80: 1434318 | J80: IND | K80: INDIVIDUAL | N80: MONTAG, THOMAS | O80: Q | Q80: D | R80: THOMAS | T80: MONTAG | V80: 127 E 73RD ST | X80: NEW YORK | Y80: NY | Z80: 100213502 | AA80: CO-CHIEF OPERATING OFFICER | AB80: BANK OF AMERICA CORPORATION | AD80: 15J | AE80: MEMO (FILER'S % OF CONTRIBUTION GIVEN TO JOIN | AG80: X | AI80: 44012 | AJ80: 5000 | AK80: 5000 | BG80: P | BI80: PRIMARY | BK80: A | BL80: ADD | BM80: ITEMIZED RECEIPTS | BN80: 44079.173 | BP80: A4412B426E290473AA47 | BQ80: SA12 | BR80: F3X | BS80: 4.0821202e+18 | BT80: t | BV80: 2020 | BW80: SA | BY80: 4.0905202e+18 | BZ80: http://docquery.fec.gov/cgi-bin/fecimg/?202008209261592961 | CA80: Transfers from Authorized Committees
A81: C00695585 | B81: TAKE BACK THE HOUSE 2020 | C81: 2020 | D81: Q2 | E81: 2.0200716e+17 | F81: 11AI | G81: A54EE975041974E7FBA8 | H81: 1423331 | J81: IND | K81: INDIVIDUAL | N81: MONTAG, THOMAS | O81: Q | Q81: J | R81: THOMAS | T81: MONTAG | V81: 127 EAST 73RD STREET | X81: NEW YORK | Y81: NY | Z81: 100213502 | AA81: BANK OF AMERICA | AB81: COO | AD81: 15 | AE81: CONTRIBUTION | AI81: 44012 | AJ81: 250000 | AK81: 250000 | BG81: P | BI81: PRIMARY | BK81: A | BL81: ADD | BM81: ITEMIZED RECEIPTS | BN81: 44033.138 | BR81: F3X | BS81: 4.0715202e+18 | BT81: t | BV81: 2020 | BW81: SA | BY81: 4.0720202e+18 | BZ81: http://docquery.fec.gov/cgi-bin/fecimg/?202007159244966543 | CA81: Contributions From Individuals/Persons Other Than Political Committees
A82: C00371203 | B82: JOHN CARTER FOR CONGRESS | C82: 2019 | D82: Q1 | E82: 2.0200716e+17 | F82: 12 | G82: 0030229-0042 | H82: 1423050 | J82: IND | K82: INDIVIDUAL | N82: MONTAG, THOMAS | O82: H | Q82: P | R82: THOMAS | T82: MONTAG | V82: 127 E 73RD STREET | X82: NEW YORK | Y82: NY | Z82: 10021 | AA82: BANK OF AMERICA | AB82: COO | AD82: 15J | AE82: MEMO (FILER'S % OF CONTRIBUTION GIVEN TO JOIN | AG82: X | AI82: 43539 | AJ82: 2651.22 | AK82: 2651.22 | BG82: P2020 | BI82: PRIMARY | BJ82: 2020 | BK82: C | BL82: CHANGE | BM82: ITEMIZED RECEIPTS | BN82: 44043.15 | BR82: F3 | BS82: 4.0715202e+18 | BT82: t | BU82: JOINT FUNDRAISER - TAKE BACK THE HOUSE 2020 (JOINT FUNDRAISER) | BV82: 2020 | BW82: SA | BY82: 4.0731202e+18 | BZ82: http://docquery.fec.gov/cgi-bin/fecimg/?202007159244898889 | CA82: Transfers from authorized committees
A83: C00075820 | B83: NRCC | C83: 2020 | D83: M8 | E83: 2.0200922e+17 | F83: 12 | G83: SA12.20241407 | H83: 1440495 | J83: IND | K83: INDIVIDUAL | N83: MONTAG, THOMAS | O83: Y | Q83: U | R83: THOMAS | T83: MONTAG | V83: 127 E. 73RD ST. | X83: NEW YORK | Y83: NY | Z83: 100213502 | AA83: BANK OF AMERICA MERRILL LYNCH | AB83: PRESIDENT | AD83: 15J | AE83: MEMO (FILER'S % OF CONTRIBUTION GIVEN TO JOIN | AF83: TRANSFER | AG83: X | AI83: 44012 | AJ83: 35500 | AK83: 35500 | BG83: P | BI83: PRIMARY | BK83: A | BL83: ADD | BM83: ITEMIZED RECEIPTS | BN83: 44099.176 | BP83: SA12.20207610 | BQ83: SA12 | BR83: F3X | BS83: 4.0922202e+18 | BT83: t | BU83: JFC ATTRIB: TBTH | BV83: 2020 | BW83: SA | BY83: 4.0925202e+18 | BZ83: http://docquery.fec.gov/cgi-bin/fecimg/?202009219284468682 | CA83: Transfers from Authorized Committees
A84: C00075820 | B84: NRCC | C84: 2020 | D84: M8 | E84: 2.0200922e+17 | F84: 17 | G84: SA17.20241449 | H84: 1440495 | J84: IND | K84: INDIVIDUAL | N84: MONTAG, THOMAS | O84: Y | Q84: U | R84: THOMAS | T84: MONTAG | V84: 127 E. 73RD ST. | X84: NEW YORK | Y84: NY | Z84: 100213502 | AA84: BANK OF AMERICA MERRILL LYNCH | AB84: PRESIDENT | AD84: 32J | AE84: MEMO RECEIPT FROM INDIVIDUAL - JF RECOUNT ACCOUNT | AF84: TRANSFER | AG84: X | AI84: 44012 | AJ84: 106500 | AK84: 106500 | BG84: P | BI84: PRIMARY | BK84: A | BL84: ADD | BM84: ITEMIZED RECEIPTS | BN84: 44099.191 | BP84: SA17.20207606 | BQ84: SA17 | BR84: F3X | BS84: 4.0922202e+18 | BT84: t | BU84: LEGAL PROCEEDINGS ACCOUNT; JFC ATTRIB: TBTH | BV84: 2020 | BW84: SA | BY84: 4.0925202e+18 | BZ84: http://docquery.fec.gov/cgi-bin/fecimg/?202009219284468716 | CA84: Other Federal Receipts (Dividends, Interest, etc.).
A85: C00075820 | B85: NRCC | C85: 2020 | D85: M8 | E85: 2.0200922e+17 | F85: 17 | G85: SA17.20241445 | H85: 1440495 | J85: IND | K85: INDIVIDUAL | N85: MONTAG, THOMAS | O85: Y | Q85: U | R85: THOMAS | T85: MONTAG | V85: 127 E. 73RD ST. | X85: NEW YORK | Y85: NY | Z85: 100213502 | AA85: BANK OF AMERICA MERRILL LYNCH | AB85: PRESIDENT | AD85: 31J | AE85: MEMO RECEIPT FROM INDIVIDUAL - JF HEADQUARTERS ACCOUNT | AF85: TRANSFER | AG85: X | AI85: 44012 | AJ85: 103000 | AK85: 103000 | BG85: P | BI85: PRIMARY | BK85: A | BL85: ADD | BM85: ITEMIZED RECEIPTS | BN85: 44099.191 | BP85: SA17.20207608 | BQ85: SA17 | BR85: F3X | BS85: 4.0922202e+18 | BT85: t | BU85: HEADQUARTERS ACCOUNT; JFC ATTRIB: TBTH | BV85: 2020 | BW85: SA | BY85: 4.0925202e+18 | BZ85: http://docquery.fec.gov/cgi-bin/fecimg/?202009219284468719 | CA85: Other Federal Receipts (Dividends, Interest, etc.).
A86: C00676668 | B86: ROSS SPANO FOR CONGRESS | C86: 2019 | D86: Q1 | E86: 2.0210415e+17 | F86: 12 | G86: SA12.4287.38 | H86: 1510400 | J86: IND | K86: INDIVIDUAL | N86: MONTAG, THOMAS | O86: H | Q86: P | R86: THOMAS | T86: MONTAG | V86: 127 E 73RD STREET | X86: NEW YORK | Y86: NY | Z86: 10021 | AA86: BANK OF AMERICA | AB86: COO | AD86: 15J | AE86: MEMO (FILER'S % OF CONTRIBUTION GIVEN TO JOIN | AG86: X | AI86: 43539 | AJ86: 2651.22 | AK86: 2651.22 | BG86: P2020 | BI86: PRIMARY | BJ86: 2020 | BK86: N | BL86: NO CHANGE | BM86: ITEMIZED RECEIPTS | BN86: 44303.15 | BP86: SA12.4287 | BQ86: SA12 | BR86: F3 | BS86: 4.0415202e+18 | BT86: t | BV86: 2020 | BW86: SA | BY86: 4.0417202e+18 | BZ86: https://docquery.fec.gov/cgi-bin/fecimg/?202104149443332048 | CA86: Transfers from authorized committees
A87: C00370056 | B87: DEVIN NUNES CAMPAIGN COMMITTEE | C87: 2020 | D87: 12P | E87: 2.0210127e+17 | F87: 11AI | G87: A8A06EDE5B6524991B6F | H87: 1491339 | J87: IND | K87: INDIVIDUAL | N87: MONTAG, THOMAS | O87: H | Q87: P | R87: THOMAS | T87: MONTAG | V87: 127 E 73RD ST | X87: NEW YORK | Y87: NY | Z87: 100213502 | AA87: BANK OF AMERICA | AB87: COO | AD87: 15 | AE87: CONTRIBUTION | AG87: X | AI87: 43552 | AJ87: 2800 | AK87: 5600 | BG87: G2020 | BI87: GENERAL | BJ87: 2020 | BK87: N | BL87: NO CHANGE | BM87: ITEMIZED RECEIPTS | BN87: 44226.158 | BR87: F3 | BS87: 4.0128202e+18 | BT87: t | BV87: 2020 | BW87: SA | BY87: 4.0130202e+18 | BZ87: https://docquery.fec.gov/cgi-bin/fecimg/?202101269413414717 | CA87: Contributions From Individuals/Persons Other Than Political Committees
V89: =+V87&X87&Y87&Z87 -> 127 E 73RD STNEW YORKNY100213502
A91: Row Labels | B91: Sum of contribution_receipt_amount
A92: ALASKANS FOR DON YOUNG | B92: 2651.21 | C92: R
A93: ALEX MOONEY FOR CONGRESS | B93: 2651.22 | C93: R
A94: ANDY BARR FOR CONGRESS, INC. | B94: 5600 | C94: R
A95: ANN WAGNER FOR CONGRESS | B95: 5600 | C95: R
A96: BALDERSON FOR CONGRESS | B96: 2651.22 | C96: R
A97: BRIAN FITZPATRICK FOR CONGRESS | B97: 2651.22 | C97: R
A98: CATHY MCMORRIS RODGERS FOR CONGRESS | B98: 2651.22 | C98: R
A99: CHIP ROY FOR CONGRESS | B99: 2651.22 | C99: R
A100: CITIZENS FOR TURNER | B100: 2651.22 | C100: R
A101: COMMITTEE TO RE-ELECT STEVE WATKINS | B101: 2651.22 | C101: R
A102: DAN CRENSHAW FOR CONGRESS | B102: 2651.22 | C102: R
...

Sheet Paul Donofrio
A1: committee_id | B1: committee_name | C1: report_year | D1: report_type | E1: image_number | F1: line_number | G1: transaction_id | H1: file_number | I1: committee_name | J1: entity_type | K1: entity_type_desc | L1: unused_contbr_id | M1: contributor_prefix | N1: contributor_name | O1: recipient_committee_type | P1: recipient_committee_org_type | Q1: recipient_committee_designation | R1: contributor_first_name | S1: contributor_middle_name | T1: contributor_last_name | U1: contributor_suffix | V1: contributor_street_1 | W1: contributor_street_2 | X1: contributor_city | Y1: contributor_state | Z1: contributor_zip | AA1: contributor_employer | AB1: contributor_occupation | AC1: contributor_id | AD1: receipt_type | AE1: receipt_type_desc | AF1: receipt_type_full | AG1: memo_code | AH1: memo_code_full | AI1: contribution_receipt_date | AJ1: contribution_receipt_amount | AK1: contributor_aggregate_ytd | AL1: candidate_id | AM1: candidate_name | AN1: candidate_first_name | AO1: candidate_last_name | AP1: candidate_middle_name | AQ1: candidate_prefix | AR1: candidate_suffix | AS1: candidate_office | AT1: candidate_office_full | AU1: candidate_office_state | AV1: candidate_office_state_full | AW1: candidate_office_district | AX1: conduit_committee_id | AY1: conduit_committee_name | AZ1: conduit_committee_street1 | BA1: conduit_committee_street2 | BB1: conduit_committee_city | BC1: conduit_committee_state | BD1: conduit_committee_zip | BE1: donor_committee_name | BF1: national_committee_nonfederal_account | BG1: election_type | BH1: election_type_full | BI1: fec_election_type_desc | BJ1: fec_election_year | BK1: amendment_indicator | BL1: amendment_indicator_desc | BM1: schedule_type_full | BN1: load_date | BO1: original_sub_id | BP1: back_reference_transaction_id | BQ1: back_reference_schedule_name | BR1: filing_form | BS1: link_id | BT1: is_individual | BU1: memo_text | BV1: two_year_transaction_period | BW1: schedule_type | BX1: increased_limit | BY1: sub_id | BZ1: pdf_url | CA1: line_number_label
A2: C00364778 | B2: BANK OF AMERICA CORPORATION FEDERAL PAC | C2: 2019 | D2: M8 | E2: 2.0190817e+17 | F2: 11AI | G2: A2019-1508788 | H2: 1348081 | J2: IND | K2: INDIVIDUAL | N2: DONOFRIO, PAUL M | O2: Q | P2: C | Q2: B | R2: PAUL | S2: M | T2: DONOFRIO | V2: ONE BRYANT PARK | X2: NEW YORK | Y2: NY | Z2: 10036 | AA2: BANK OF AMERICA | AB2: CHIEF FINANCIAL OFFICER | AD2: 15 | AE2: CONTRIBUTION | AI2: 43661 | AJ2: 20 | AK2: 260 | BG2: P | BI2: PRIMARY | BK2: A | BL2: ADD | BM2: ITEMIZED RECEIPTS | BN2: 43694.11 | BR2: F3X | BS2: 4.0816202e+18 | BT2: t | BV2: 2020 | BW2: SA | BY2: 4.0816202e+18 | BZ2: http://docquery.fec.gov/cgi-bin/fecimg/?201908169162884507 | CA2: Contributions From Individuals/Persons Other Than Political Committees
A3: C00364778 | B3: BANK OF AMERICA CORPORATION FEDERAL PAC | C3: 2019 | D3: M8 | E3: 2.0190817e+17 | F3: 11AI | G3: A2019-1685727 | H3: 1348081 | J3: IND | K3: INDIVIDUAL | N3: DONOFRIO, PAUL M | O3: Q | P3: C | Q3: B | R3: PAUL | S3: M | T3: DONOFRIO | V3: ONE BRYANT PARK | X3: NEW YORK | Y3: NY | Z3: 10036 | AA3: BANK OF AMERICA | AB3: CHIEF FINANCIAL OFFICER | AD3: 15 | AE3: CONTRIBUTION | AI3: 43677 | AJ3: 20 | AK3: 280 | BG3: P | BI3: PRIMARY | BK3: A | BL3: ADD | BM3: ITEMIZED RECEIPTS | BN3: 43694.11 | BR3: F3X | BS3: 4.0816202e+18 | BT3: t | BV3: 2020 | BW3: SA | BY3: 4.0816202e+18 | BZ3: http://docquery.fec.gov/cgi-bin/fecimg/?201908169162884508 | CA3: Contributions From Individuals/Persons Other Than Political Committees
A4: C00364778 | B4: BANK OF AMERICA CORPORATION FEDERAL PAC | C4: 2019 | D4: YE | E4: 2.0200121e+17 | F4: 11AI | G4: A2019-2943870 | H4: 1371432 | J4: IND | K4: INDIVIDUAL | N4: DONOFRIO, PAUL M | O4: Q | P4: C | Q4: B | R4: PAUL | S4: M | T4: DONOFRIO | V4: ONE BRYANT PARK | X4: NEW YORK | Y4: NY | Z4: 10036 | AA4: BANK OF AMERICA | AB4: CHIEF FINANCIAL OFFICER | AD4: 15 | AE4: CONTRIBUTION | AI4: 43814 | AJ4: 20 | AK4: 460 | BG4: P | BI4: PRIMARY | BK4: A | BL4: ADD | BM4: ITEMIZED RECEIPTS | BN4: 43852.068 | BR4: F3X | BS4: 4.0120202e+18 | BT4: t | BV4: 2020 | BW4: SA | BY4: 4.0121202e+18 | BZ4: http://docquery.fec.gov/cgi-bin/fecimg/?202001209167275125 | CA4: Contributions From Individuals/Persons Other Than Political Committees
A5: C00364778 | B5: BANK OF AMERICA CORPORATION FEDERAL PAC | C5: 2019 | D5: YE | E5: 2.0200121e+17 | F5: 11AI | G5: A2019-2984852 | H5: 1371432 | J5: IND | K5: INDIVIDUAL | N5: DONOFRIO, PAUL M | O5: Q | P5: C | Q5: B | R5: PAUL | S5: M | T5: DONOFRIO | V5: ONE BRYANT PARK | X5: NEW YORK | Y5: NY | Z5: 10036 | AA5: BANK OF AMERICA | AB5: CHIEF FINANCIAL OFFICER | AD5: 15 | AE5: CONTRIBUTION | AI5: 43830 | AJ5: 20 | AK5: 480 | BG5: P | BI5: PRIMARY | BK5: A | BL5: ADD | BM5: ITEMIZED RECEIPTS | BN5: 43852.068 | BR5: F3X | BS5: 4.0120202e+18 | BT5: t | BV5: 2020 | BW5: SA | BY5: 4.0121202e+18 | BZ5: http://docquery.fec.gov/cgi-bin/fecimg/?202001209167275126 | CA5: Contributions From Individuals/Persons Other Than Political Committees
A6: C00364778 | B6: BANK OF AMERICA CORPORATION FEDERAL PAC | C6: 2019 | D6: M7 | E6: 2.0190803e+17 | F6: 11AI | G6: A2019-1192810 | H6: 1346685 | J6: IND | K6: INDIVIDUAL | N6: DONOFRIO, PAUL M | O6: Q | P6: C | Q6: B | R6: PAUL | S6: M | T6: DONOFRIO | V6: ONE BRYANT PARK | X6: NEW YORK | Y6: NY | Z6: 10036 | AA6: BANK OF AMERICA | AB6: CHIEF FINANCIAL OFFICER | AD6: 15 | AE6: CONTRIBUTION | AI6: 43631 | AJ6: 20 | AK6: 220 | BG6: P | BI6: PRIMARY | BK6: N | BL6: NO CHANGE | BM6: ITEMIZED RECEIPTS | BN6: 43680.113 | BR6: F3X | BS6: 4.0802202e+18 | BT6: t | BV6: 2020 | BW6: SA | BY6: 4.0802202e+18 | BZ6: http://docquery.fec.gov/cgi-bin/fecimg/?201908029161351150 | CA6: Contributions From Individuals/Persons Other Than Political Committees
A7: C00364778 | B7: BANK OF AMERICA CORPORATION FEDERAL PAC | C7: 2019 | D7: M7 | E7: 2.0190803e+17 | F7: 11AI | G7: A2019-1380201 | H7: 1346685 | J7: IND | K7: INDIVIDUAL | N7: DONOFRIO, PAUL M | O7: Q | P7: C | Q7: B | R7: PAUL | S7: M | T7: DONOFRIO | V7: ONE BRYANT PARK | X7: NEW YORK | Y7: NY | Z7: 10036 | AA7: BANK OF AMERICA | AB7: CHIEF FINANCIAL OFFICER | AD7: 15 | AE7: CONTRIBUTION | AI7: 43646 | AJ7: 20 | AK7: 240 | BG7: P | BI7: PRIMARY | BK7: N | BL7: NO CHANGE | BM7: ITEMIZED RECEIPTS | BN7: 43680.113 | BR7: F3X | BS7: 4.0802202e+18 | BT7: t | BV7: 2020 | BW7: SA | BY7: 4.0802202e+18 | BZ7: http://docquery.fec.gov/cgi-bin/fecimg/?201908029161351150 | CA7: Contributions From Individuals/Persons Other Than Political Committees
A8: C00364778 | B8: BANK OF AMERICA CORPORATION FEDERAL PAC | C8: 2019 | D8: M9 | E8: 2.0190914e+17 | F8: 11AI | G8: A2019-1840982 | H8: 1351825 | J8: IND | K8: INDIVIDUAL | N8: DONOFRIO, PAUL M | O8: Q | P8: C | Q8: B | R8: PAUL | S8: M | T8: DONOFRIO | V8: ONE BRYANT PARK | X8: NEW YORK | Y8: NY | Z8: 10036 | AA8: BANK OF AMERICA | AB8: CHIEF FINANCIAL OFFICER | AD8: 15 | AE8: CONTRIBUTION | AI8: 43692 | AJ8: 20 | AK8: 300 | BG8: P | BI8: PRIMARY | BK8: A | BL8: ADD | BM8: ITEMIZED RECEIPTS | BN8: 43722.125 | BR8: F3X | BS8: 4.0913202e+18 | BT8: t | BV8: 2020 | BW8: SA | BY8: 4.0913202e+18 | BZ8: http://docquery.fec.gov/cgi-bin/fecimg/?201909139163316658 | CA8: Contributions From Individuals/Persons Other Than Political Committees
A9: C00364778 | B9: BANK OF AMERICA CORPORATION FEDERAL PAC | C9: 2019 | D9: M9 | E9: 2.0190914e+17 | F9: 11AI | G9: A2019-1967613 | H9: 1351825 | J9: IND | K9: INDIVIDUAL | N9: DONOFRIO, PAUL M | O9: Q | P9: C | Q9: B | R9: PAUL | S9: M | T9: DONOFRIO | V9: ONE BRYANT PARK | X9: NEW YORK | Y9: NY | Z9: 10036 | AA9: BANK OF AMERICA | AB9: CHIEF FINANCIAL OFFICER | AD9: 15 | AE9: CONTRIBUTION | AI9: 43708 | AJ9: 20 | AK9: 320 | BG9: P | BI9: PRIMARY | BK9: A | BL9: ADD | BM9: ITEMIZED RECEIPTS | BN9: 43722.125 | BR9: F3X | BS9: 4.0913202e+18 | BT9: t | BV9: 2020 | BW9: SA | BY9: 4.0913202e+18 | BZ9: http://docquery.fec.gov/cgi-bin/fecimg/?201909139163316659 | CA9: Contributions From Individuals/Persons Other Than Political Committees
A10: C00364778 | B10: BANK OF AMERICA CORPORATION FEDERAL PAC | C10: 2019 | D10: M10 | E10: 2.0191017e+17 | F10: 11AI | G10: A2019-2193417 | H10: 1359078 | J10: IND | K10: INDIVIDUAL | N10: DONOFRIO, PAUL M | O10: Q | P10: C | Q10: B | R10: PAUL | S10: M | T10: DONOFRIO | V10: ONE BRYANT PARK | X10: NEW YORK | Y10: NY | Z10: 10036 | AA10: BANK OF AMERICA | AB10: CHIEF FINANCIAL OFFICER | AD10: 15 | AE10: CONTRIBUTION | AI10: 43723 | AJ10: 20 | AK10: 340 | BG10: P | BI10: PRIMARY | BK10: A | BL10: ADD | BM10: ITEMIZED RECEIPTS | BN10: 43755.116 | BR10: F3X | BS10: 4.1016202e+18 | BT10: t | BV10: 2020 | BW10: SA | BY10: 4.1016202e+18 | BZ10: http://docquery.fec.gov/cgi-bin/fecimg/?201910169164983864 | CA10: Contributions From Individuals/Persons Other Than Political Committees
A11: C00364778 | B11: BANK OF AMERICA CORPORATION FEDERAL PAC | C11: 2019 | D11: M10 | E11: 2.0191017e+17 | F11: 11AI | G11: A2019-2243068 | H11: 1359078 | J11: IND | K11: INDIVIDUAL | N11: DONOFRIO, PAUL M | O11: Q | P11: C | Q11: B | R11: PAUL | S11: M | T11: DONOFRIO | V11: ONE BRYANT PARK | X11: NEW YORK | Y11: NY | Z11: 10036 | AA11: BANK OF AMERICA | AB11: CHIEF FINANCIAL OFFICER | AD11: 15 | AE11: CONTRIBUTION | AI11: 43738 | AJ11: 20 | AK11: 360 | BG11: P | BI11: PRIMARY | BK11: A | BL11: ADD | BM11: ITEMIZED RECEIPTS | BN11: 43755.116 | BR11: F3X | BS11: 4.1016202e+18 | BT11: t | BV11: 2020 | BW11: SA | BY11: 4.1016202e+18 | BZ11: http://docquery.fec.gov/cgi-bin/fecimg/?201910169164983864 | CA11: Contributions From Individuals/Persons Other Than Political Committees
A12: C00364778 | B12: BANK OF AMERICA CORPORATION FEDERAL PAC | C12: 2019 | D12: M12 | E12: 2.0191217e+17 | F12: 11AI | G12: A2019-2693996 | H12: 1366330 | J12: IND | K12: INDIVIDUAL | N12: DONOFRIO, PAUL M | O12: Q | P12: C | Q12: B | R12: PAUL | S12: M | T12: DONOFRIO | V12: ONE BRYANT PARK | X12: NEW YORK | Y12: NY | Z12: 10036 | AA12: BANK OF AMERICA | AB12: CHIEF FINANCIAL OFFICER | AD12: 15 | AE12: CONTRIBUTION | AI12: 43784 | AJ12: 20 | AK12: 420 | BG12: P | BI12: PRIMARY | BK12: A | BL12: ADD | BM12: ITEMIZED RECEIPTS | BN12: 43816.068 | BR12: F3X | BS12: 4.1216202e+18 | BT12: t | BV12: 2020 | BW12: SA | BY12: 4.1216202e+18 | BZ12: http://docquery.fec.gov/cgi-bin/fecimg/?201912169166292230 | CA12: Contributions From Individuals/Persons Other Than Political Committees
A13: C00364778 | B13: BANK OF AMERICA CORPORATION FEDERAL PAC | C13: 2019 | D13: M12 | E13: 2.0191217e+17 | F13: 11AI | G13: A2019-2731332 | H13: 1366330 | J13: IND | K13: INDIVIDUAL | N13: DONOFRIO, PAUL M | O13: Q | P13: C | Q13: B | R13: PAUL | S13: M | T13: DONOFRIO | V13: ONE BRYANT PARK | X13: NEW YORK | Y13: NY | Z13: 10036 | AA13: BANK OF AMERICA | AB13: CHIEF FINANCIAL OFFICER | AD13: 15 | AE13: CONTRIBUTION | AI13: 43799 | AJ13: 20 | AK13: 440 | BG13: P | BI13: PRIMARY | BK13: A | BL13: ADD | BM13: ITEMIZED RECEIPTS | BN13: 43816.068 | BR13: F3X | BS13: 4.1216202e+18 | BT13: t | BV13: 2020 | BW13: SA | BY13: 4.1216202e+18 | BZ13: http://docquery.fec.gov/cgi-bin/fecimg/?201912169166292230 | CA13: Contributions From Individuals/Persons Other Than Political Committees
... A29: C00364778 | B29: BANK OF AMERICA CORPORATION FEDERAL PAC | C29: 2020 | D29: YE | E29: 2.0210126e+17 | F29: 11AI | G29: A2020-2738826 | H29: 1490358 | J29: IND | K29: INDIVIDUAL | N29: DONOFRIO, PAUL M | O29: Q | P29: C | Q29: B | R29: PAUL | S29: M | T29: DONOFRIO | V29: ONE BRYANT PARK | X29: NEW YORK | Y29: NY | Z29: 10036 | AA29: BANK OF AMERICA | AB29: CHIEF FINANCIAL OFFICER | AD29: 15 | AE29: CONTRIBUTION | AI29: 44196 | AJ29: 20 | AK29: 480 | BG29: P | BI29: PRIMARY | BK29: A | BL29: ADD | BM29: ITEMIZED RECEIPTS | BN29: 44223.151 | BR29: F3X | BS29: 4.0125202e+18 | BT29: t | BV29: 2020 | BW29: SA | BY29: 4.0127202e+18 | BZ29: https://docquery.fec.gov/cgi-bin/fecimg/?202101259405394822 | CA29: Contributions From Individuals/Persons Other Than Political Committees
A34: Row Labels | B34: Sum of contribution_receipt_amount
A35: BANK OF AMERICA CORPORATION FEDERAL PAC | B35: 560
A36: Grand Total | B36: 560

Sheet Sheri Bronstein
A1: committee_id | B1: committee_name | C1: report_year | D1: report_type | E1: image_number | F1: line_number | G1: transaction_id | H1: file_number | I1: committee_name | J1: entity_type | K1: entity_type_desc | L1: unused_contbr_id | M1: contributor_prefix | N1: contributor_name | O1: recipient_committee_type | P1: recipient_committee_org_type | Q1: recipient_committee_designation | R1: contributor_first_name | S1: contributor_middle_name | T1: contributor_last_name | U1: contributor_suffix | V1: contributor_street_1 | W1: contributor_street_2 | X1: contributor_city | Y1: contributor_state | Z1: contributor_zip | AA1: contributor_employer | AB1: contributor_occupation | AC1: contributor_id | AD1: receipt_type | AE1: receipt_type_desc | AF1: receipt_type_full | AG1: memo_code | AH1: memo_code_full | AI1: contribution_receipt_date | AJ1: contribution_receipt_amount | AK1: contributor_aggregate_ytd | AL1: candidate_id | AM1: candidate_name | AN1: candidate_first_name | AO1: candidate_last_name | AP1: candidate_middle_name | AQ1: candidate_prefix | AR1: candidate_suffix | AS1: candidate_office | AT1: candidate_office_full | AU1: candidate_office_state | AV1: candidate_office_state_full | AW1: candidate_office_district | AX1: conduit_committee_id | AY1: conduit_committee_name | AZ1: conduit_committee_street1 | BA1: conduit_committee_street2 | BB1: conduit_committee_city | BC1: conduit_committee_state | BD1: conduit_committee_zip | BE1: donor_committee_name | BF1: national_committee_nonfederal_account | BG1: election_type | BH1: election_type_full | BI1: fec_election_type_desc | BJ1: fec_election_year | BK1: amendment_indicator | BL1: amendment_indicator_desc | BM1: schedule_type_full | BN1: load_date | BO1: original_sub_id | BP1: back_reference_transaction_id | BQ1: back_reference_schedule_name | BR1: filing_form | BS1: link_id | BT1: is_individual | BU1: memo_text | BV1: two_year_transaction_period | BW1: schedule_type | BX1: increased_limit | BY1: sub_id | BZ1: pdf_url | CA1: line_number_label
A2: C00364778 | B2: BANK OF AMERICA CORPORATION FEDERAL PAC | C2: 2019 | D2: M4 | E2: 2.0190413e+17 | F2: 11AI | G2: A2019-519279 | H2: 1324297 | J2: IND | K2: INDIVIDUAL | N2: BRONSTEIN, SHERI | O2: Q | P2: C | Q2: B | R2: SHERI | T2: BRONSTEIN | V2: ONE BRYANT PARK | X2: NEW YORK | Y2: NY | Z2: 10036 | AA2: BANK OF AMERICA | AB2: GLOBAL HUMAN RESOURCES EXEC | AD2: 15 | AE2: CONTRIBUTION | AI2: 43539 | AJ2: 50 | AK2: 250 | BG2: P | BI2: PRIMARY | BK2: A | BL2: ADD | BM2: ITEMIZED RECEIPTS | BN2: 43568.111 | BR2: F3X | BS2: 4.0412202e+18 | BT2: t | BV2: 2020 | BW2: SA | BY2: 4.0412202e+18 | BZ2: http://docquery.fec.gov/cgi-bin/fecimg/?201904129146103819 | CA2: Contributions From Individuals/Persons Other Than Political Committees
A3: C00364778 | B3: BANK OF AMERICA CORPORATION FEDERAL PAC | C3: 2019 | D3: M4 | E3: 2.0190413e+17 | F3: 11AI | G3: A2019-546273 | H3: 1324297 | J3: IND | K3: INDIVIDUAL | N3: BRONSTEIN, SHERI | O3: Q | P3: C | Q3: B | R3: SHERI | T3: BRONSTEIN | V3: ONE BRYANT PARK | X3: NEW YORK | Y3: NY | Z3: 10036 | AA3: BANK OF AMERICA | AB3: GLOBAL HUMAN RESOURCES EXEC | AD3: 15 | AE3: CONTRIBUTION | AI3: 43555 | AJ3: 50 | AK3: 300 | BG3: P | BI3: PRIMARY | BK3: A | BL3: ADD | BM3: ITEMIZED RECEIPTS | BN3: 43568.111 | BR3: F3X | BS3: 4.0412202e+18 | BT3: t | BV3: 2020 | BW3: SA | BY3: 4.0412202e+18 | BZ3: http://docquery.fec.gov/cgi-bin/fecimg/?201904129146103820 | CA3: Contributions From Individuals/Persons Other Than Political Committees
A4: C00364778 | B4: BANK OF AMERICA CORPORATION FEDERAL PAC | C4: 2019 | D4: M5 | E4: 2.0190515e+17 | F4: 11AI | G4: A2019-794436 | H4: 1330608 | J4: IND | K4: INDIVIDUAL | N4: BRONSTEIN, SHERI | O4: Q | P4: C | Q4: B | R4: SHERI | T4: BRONSTEIN | V4: ONE BRYANT PARK | X4: NEW YORK | Y4: NY | Z4: 10036 | AA4: BANK OF AMERICA | AB4: GLOBAL HUMAN RESOURCES EXEC | AD4: 15 | AE4: CONTRIBUTION | AI4: 43570 | AJ4: 50 | AK4: 350 | BG4: P | BI4: PRIMARY | BK4: A | BL4: ADD | BM4: ITEMIZED RECEIPTS | BN4: 43600.358 | BR4: F3X | BS4: 4.0514202e+18 | BT4: t | BV4: 2020 | BW4: SA | BY4: 4.0514202e+18 | BZ4: http://docquery.fec.gov/cgi-bin/fecimg/?201905149149695866 | CA4: Contributions From Individuals/Persons Other Than Political Committees
A5: C00364778 | B5: BANK OF AMERICA CORPORATION FEDERAL PAC | C5: 2019 | D5: M5 | E5: 2.0190515e+17 | F5: 11AI | G5: A2019-844627 | H5: 1330608 | J5: IND | K5: INDIVIDUAL | N5: BRONSTEIN, SHERI | O5: Q | P5: C | Q5: B | R5: SHERI | T5: BRONSTEIN | V5: ONE BRYANT PARK | X5: NEW YORK | Y5: NY | Z5: 10036 | AA5: BANK OF AMERICA | AB5: GLOBAL HUMAN RESOURCES EXEC | AD5: 15 | AE5: CONTRIBUTION | AI5: 43585 | AJ5: 50 | AK5: 400 | BG5: P | BI5: PRIMARY | BK5: A | BL5: ADD | BM5: ITEMIZED RECEIPTS | BN5: 43600.358 | BR5: F3X | BS5: 4.0514202e+18 | BT5: t | BV5: 2020 | BW5: SA | BY5: 4.0514202e+18 | BZ5: http://docquery.fec.gov/cgi-bin/fecimg/?201905149149695866 | CA5: Contributions From Individuals/Persons Other Than Political Committees
A6: C00364778 | B6: BANK OF AMERICA CORPORATION FEDERAL PAC | C6: 2019 | D6: M8 | E6: 2.0190817e+17 | F6: 11AI | G6: A2019-1512024 | H6: 1348081 | J6: IND | K6: INDIVIDUAL | N6: BRONSTEIN, SHERI | O6: Q | P6: C | Q6: B | R6: SHERI | T6: BRONSTEIN | V6: ONE BRYANT PARK | X6: NEW YORK | Y6: NY | Z6: 10036 | AA6: BANK OF AMERICA | AB6: GLOBAL HUMAN RESOURCES EXEC | AD6: 15 | AE6: CONTRIBUTION | AI6: 43661 | AJ6: 50 | AK6: 650 | BG6: P | BI6: PRIMARY | BK6: A | BL6: ADD | BM6: ITEMIZED RECEIPTS | BN6: 43694.11 | BR6: F3X | BS6: 4.0816202e+18 | BT6: t | BV6: 2020 | BW6: SA | BY6: 4.0816202e+18 | BZ6: http://docquery.fec.gov/cgi-bin/fecimg/?201908169162884465 | CA6: Contributions From Individuals/Persons Other Than Political Committees
A7: C00364778 | B7: BANK OF AMERICA CORPORATION FEDERAL PAC | C7: 2019 | D7: M8 | E7: 2.0190817e+17 | F7: 11AI | G7: A2019-1688954 | H7: 1348081 | J7: IND | K7: INDIVIDUAL | N7: BRONSTEIN, SHERI | O7: Q | P7: C | Q7: B | R7: SHERI | T7: BRONSTEIN | V7: ONE BRYANT PARK | X7: NEW YORK | Y7: NY | Z7: 10036 | AA7: BANK OF AMERICA | AB7: GLOBAL HUMAN RESOURCES EXEC | AD7: 15 | AE7: CONTRIBUTION | AI7: 43677 | AJ7: 50 | AK7: 700 | BG7: P | BI7: PRIMARY | BK7: A | BL7: ADD | BM7: ITEMIZED RECEIPTS | BN7: 43694.11 | BR7: F3X | BS7: 4.0816202e+18 | BT7: t | BV7: 2020 | BW7: SA | BY7: 4.0816202e+18 | BZ7: http://docquery.fec.gov/cgi-bin/fecimg/?201908169162884466 | CA7: Contributions From Individuals/Persons Other Than Political Committees
A8: C00364778 | B8: BANK OF AMERICA CORPORATION FEDERAL PAC | C8: 2019 | D8: YE | E8: 2.0200121e+17 | F8: 11AI | G8: A2019-2945254 | H8: 1371432 | J8: IND | K8: INDIVIDUAL | N8: BRONSTEIN, SHERI | O8: Q | P8: C | Q8: B | R8: SHERI | T8: BRONSTEIN | V8: ONE BRYANT PARK | X8: NEW YORK | Y8: NY | Z8: 10036 | AA8: BANK OF AMERICA | AB8: CHIEF HUMAN RESOURCES OFFICER | AD8: 15 | AE8: CONTRIBUTION | AI8: 43814 | AJ8: 50 | AK8: 1150 | BG8: P | BI8: PRIMARY | BK8: A | BL8: ADD | BM8: ITEMIZED RECEIPTS | BN8: 43852.068 | BR8: F3X | BS8: 4.0120202e+18 | BT8: t | BV8: 2020 | BW8: SA | BY8: 4.0121202e+18 | BZ8: http://docquery.fec.gov/cgi-bin/fecimg/?202001209167275059 | CA8: Contributions From Individuals/Persons Other Than Political Committees
A9: C00364778 | B9: BANK OF AMERICA CORPORATION FEDERAL PAC | C9: 2019 | D9: YE | E9: 2.0200121e+17 | F9: 11AI | G9: A2019-2986235 | H9: 1371432 | J9: IND | K9: INDIVIDUAL | N9: BRONSTEIN, SHERI | O9: Q | P9: C | Q9: B | R9: SHERI | T9: BRONSTEIN | V9: ONE BRYANT PARK | X9: NEW YORK | Y9: NY | Z9: 10036 | AA9: BANK OF AMERICA | AB9: CHIEF HUMAN RESOURCES OFFICER | AD9: 15 | AE9: CONTRIBUTION | AI9: 43830 | AJ9: 50 | AK9: 1200 | BG9: P | BI9: PRIMARY | BK9: A | BL9: ADD | BM9: ITEMIZED RECEIPTS | BN9: 43852.068 | BR9: F3X | BS9: 4.0120202e+18 | BT9: t | BV9: 2020 | BW9: SA | BY9: 4.0121202e+18 | BZ9: http://docquery.fec.gov/cgi-bin/fecimg/?202001209167275059 | CA9: Contributions From Individuals/Persons Other Than Political Committees
A10: C00364778 | B10: BANK OF AMERICA CORPORATION FEDERAL PAC | C10: 2019 | D10: M6 | E10: 2.0190803e+17 | F10: 11AI | G10: A2019-952018 | H10: 1346683 | J10: IND | K10: INDIVIDUAL | N10: BRONSTEIN, SHERI | O10: Q | P10: C | Q10: B | R10: SHERI | T10: BRONSTEIN | V10: ONE BRYANT PARK | X10: NEW YORK | Y10: NY | Z10: 10036 | AA10: BANK OF AMERICA | AB10: GLOBAL HUMAN RESOURCES EXEC | AD10: 15 | AE10: CONTRIBUTION | AI10: 43600 | AJ10: 50 | AK10: 450 | BG10: P | BI10: PRIMARY | BK10: N | BL10: NO CHANGE | BM10: ITEMIZED RECEIPTS | BN10: 43680.113 | BR10: F3X | BS10: 4.0802202e+18 | BT10: t | BV10: 2020 | BW10: SA | BY10: 4.0802202e+18 | BZ10: http://docquery.fec.gov/cgi-bin/fecimg/?201908029161350883 | CA10: Contributions From Individuals/Persons Other Than Political Committees
A11: C00364778 | B11: BANK OF AMERICA CORPORATION FEDERAL PAC | C11: 2019 | D11: M6 | E11: 2.0190803e+17 | F11: 11AI | G11: A2019-1108387 | H11: 1346683 | J11: IND | K11: INDIVIDUAL | N11: BRONSTEIN, SHERI | O11: Q | P11: C | Q11: B | R11: SHERI | T11: BRONSTEIN | V11: ONE BRYANT PARK | X11: NEW YORK | Y11: NY | Z11: 10036 | AA11: BANK OF AMERICA | AB11: GLOBAL HUMAN RESOURCES EXEC | AD11: 15 | AE11: CONTRIBUTION | AI11: 43616 | AJ11: 50 | AK11: 500 | BG11: P | BI11: PRIMARY | BK11: N | BL11: NO CHANGE | BM11: ITEMIZED RECEIPTS | BN11: 43680.113 | BR11: F3X | BS11: 4.0802202e+18 | BT11: t | BV11: 2020 | BW11: SA | BY11: 4.0802202e+18 | BZ11: http://docquery.fec.gov/cgi-bin/fecimg/?201908029161350883 | CA11: Contributions From Individuals/Persons Other Than Political Committees
A12: C00364778 | B12: BANK OF AMERICA CORPORATION FEDERAL PAC | C12: 2019 | D12: M7 | E12: 2.0190803e+17 | F12: 11AI | G12: A2019-1196075 | H12: 1346685 | J12: IND | K12: INDIVIDUAL | N12: BRONSTEIN, SHERI | O12: Q | P12: C | Q12: B | R12: SHERI | T12: BRONSTEIN | V12: ONE BRYANT PARK | X12: NEW YORK | Y12: NY | Z12: 10036 | AA12: BANK OF AMERICA | AB12: GLOBAL HUMAN RESOURCES EXEC | AD12: 15 | AE12: CONTRIBUTION | AI12: 43631 | AJ12: 50 | AK12: 550 | BG12: P | BI12: PRIMARY | BK12: N | BL12: NO CHANGE | BM12: ITEMIZED RECEIPTS | BN12: 43680.113 | BR12: F3X | BS12: 4.0802202e+18 | BT12: t | BV12: 2020 | BW12: SA | BY12: 4.0802202e+18 | BZ12: http://docquery.fec.gov/cgi-bin/fecimg/?201908029161351114 | CA12: Contributions From Individuals/Persons Other Than Political Committees
A13: C00364778 | B13: BANK OF AMERICA CORPORATION FEDERAL PAC | C13: 2019 | D13: M7 | E13: 2.0190803e+17 | F13: 11AI | G13: A2019-1383448 | H13: 1346685 | J13: IND | K13: INDIVIDUAL | N13: BRONSTEIN, SHERI | O13: Q | P13: C | Q13: B | R13: SHERI | T13: BRONSTEIN | V13: ONE BRYANT PARK | X13: NEW YORK | Y13: NY | Z13: 10036 | AA13: BANK OF AMERICA | AB13: GLOBAL HUMAN RESOURCES EXEC | AD13: 15 | AE13: CONTRIBUTION | AI13: 43646 | AJ13: 50 | AK13: 600 | BG13: P | BI13: PRIMARY | BK13: N | BL13: NO CHANGE | BM13: ITEMIZED RECEIPTS | BN13: 43680.113 | BR13: F3X | BS13: 4.0802202e+18 | BT13: t | BV13: 2020 | BW13: SA | BY13: 4.0802202e+18 | BZ13: http://docquery.fec.gov/cgi-bin/fecimg/?201908029161351114 | CA13: Contributions From Individuals/Persons Other Than Political Committees
... A41: C00364778 | B41: BANK OF AMERICA CORPORATION FEDERAL PAC | C41: 2020 | D41: YE | E41: 2.0210126e+17 | F41: 11AI | G41: A2020-2741016 | H41: 1490358 | J41: IND | K41: INDIVIDUAL | N41: BRONSTEIN, SHERI | O41: Q | P41: C | Q41: B | R41: SHERI | T41: BRONSTEIN | V41: ONE BRYANT PARK | X41: NEW YORK | Y41: NY | Z41: 10036 | AA41: BANK OF AMERICA | AB41: CHIEF HUMAN RESOURCES OFFICER | AD41: 15 | AE41: CONTRIBUTION | AI41: 44196 | AJ41: 50 | AK41: 1200 | BG41: P | BI41: PRIMARY | BK41: A | BL41: ADD | BM41: ITEMIZED RECEIPTS | BN41: 44223.151 | BR41: F3X | BS41: 4.0125202e+18 | BT41: t | BV41: 2020 | BW41: SA | BY41: 4.0127202e+18 | BZ41: https://docquery.fec.gov/cgi-bin/fecimg/?202101259405394729 | CA41: Contributions From Individuals/Persons Other Than Political Committees
V43: =+V41&X41&Y41&Z41 -> ONE BRYANT PARKNEW YORKNY10036
A46: Row Labels | B46: Sum of contribution_receipt_amount
A47: BANK OF AMERICA CORPORATION FEDERAL PAC | B47: 2000
A48: Grand Total | B48: 2000

Sheet Catherine Bessant
A1: committee_id | B1: committee_name | C1: report_year | D1: report_type | E1: image_number | F1: line_number | G1: transaction_id | H1: file_number | I1: committee_name | J1: entity_type | K1: entity_type_desc | L1: unused_contbr_id | M1: contributor_prefix | N1: contributor_name | O1: recipient_committee_type | P1: recipient_committee_org_type | Q1: recipient_committee_designation | R1: contributor_first_name | S1: contributor_middle_name | T1: contributor_last_name | U1: contributor_suffix | V1: contributor_street_1 | W1: contributor_street_2 | X1: contributor_city | Y1: contributor_state | Z1: contributor_zip | AA1: contributor_employer | AB1: contributor_occupation | AC1: contributor_id | AD1: receipt_type | AE1: receipt_type_desc | AF1: receipt_type_full | AG1: memo_code | AH1: memo_code_full | AI1: contribution_receipt_date | AJ1: contribution_receipt_amount | AK1: contributor_aggregate_ytd | AL1: candidate_id | AM1: candidate_name | AN1: candidate_first_name | AO1: candidate_last_name | AP1: candidate_middle_name | AQ1: candidate_prefix | AR1: candidate_suffix | AS1: candidate_office | AT1: candidate_office_full | AU1: candidate_office_state | AV1: candidate_office_state_full | AW1: candidate_office_district | AX1: conduit_committee_id | AY1: conduit_committee_name | AZ1: conduit_committee_street1 | BA1: conduit_committee_street2 | BB1: conduit_committee_city | BC1: conduit_committee_state | BD1: conduit_committee_zip | BE1: donor_committee_name | BF1: national_committee_nonfederal_account | BG1: election_type | BH1: election_type_full | BI1: fec_election_type_desc | BJ1: fec_election_year | BK1: amendment_indicator | BL1: amendment_indicator_desc | BM1: schedule_type_full | BN1: load_date | BO1: original_sub_id | BP1: back_reference_transaction_id | BQ1: back_reference_schedule_name | BR1: filing_form | BS1: link_id | BT1: is_individual | BU1: memo_text | BV1: two_year_transaction_period | BW1: schedule_type | BX1: increased_limit | BY1: sub_id | BZ1: pdf_url | CA1: line_number_label
A2: C00364778 | B2: BANK OF AMERICA CORPORATION FEDERAL PAC | C2: 2019 | D2: M2 | E2: 2.0190216e+17 | F2: 11AI | G2: A2019-83355 | H2: 1316134 | J2: IND | K2: INDIVIDUAL | N2: BESSANT, CATHERINE P | O2: Q | P2: C | Q2: B | R2: CATHERINE | S2: P | T2: BESSANT | V2: 100 N TRYON ST | X2: CHARLOTTE | Y2: NC | Z2: 28255 | AA2: BANK OF AMERICA | AB2: CHIEF OPS & TECHNOLOGY OFFICER | AD2: 15 | AE2: CONTRIBUTION | AI2: 43496 | AJ2: 110 | AK2: 220 | BG2: P | BI2: PRIMARY | BK2: A | BL2: ADD | BM2: ITEMIZED RECEIPTS | BN2: 43525.144 | BR2: F3X | BS2: 4.0215202e+18 | BT2: t | BV2: 2020 | BW2: SA | BY2: 4.0228202e+18 | BZ2: http://docquery.fec.gov/cgi-bin/fecimg/?201902159145519675 | CA2: Contributions From Individuals/Persons Other Than Political Committees
A3: C00364778 | B3: BANK OF AMERICA CORPORATION FEDERAL PAC | C3: 2019 | D3: M3 | E3: 2.0190316e+17 | F3: 11AI | G3: A2019-299689 | H3: 1319532 | J3: IND | K3: INDIVIDUAL | N3: BESSANT, CATHERINE P | O3: Q | P3: C | Q3: B | R3: CATHERINE | S3: P | T3: BESSANT | V3: 100 N TRYON ST | X3: CHARLOTTE | Y3: NC | Z3: 28255 | AA3: BANK OF AMERICA | AB3: CHIEF OPS & TECHNOLOGY OFFICER | AD3: 15 | AE3: CONTRIBUTION | AI3: 43511 | AJ3: 110 | AK3: 330 | BG3: P | BI3: PRIMARY | BK3: A | BL3: ADD | BM3: ITEMIZED RECEIPTS | BN3: 43543.128 | BR3: F3X | BS3: 4.0315202e+18 | BT3: t | BV3: 2020 | BW3: SA | BY3: 4.0318202e+18 | BZ3: http://docquery.fec.gov/cgi-bin/fecimg/?201903159145712528 | CA3: Contributions From Individuals/Persons Other Than Political Committees
A4: C00364778 | B4: BANK OF AMERICA CORPORATION FEDERAL PAC | C4: 2019 | D4: M3 | E4: 2.0190316e+17 | F4: 11AI | G4: A2019-340858 | H4: 1319532 | J4: IND | K4: INDIVIDUAL | N4: BESSANT, CATHERINE P | O4: Q | P4: C | Q4: B | R4: CATHERINE | S4: P | T4: BESSANT | V4: 100 N TRYON ST | X4: CHARLOTTE | Y4: NC | Z4: 28255 | AA4: BANK OF AMERICA | AB4: CHIEF OPS & TECHNOLOGY OFFICER | AD4: 15 | AE4: CONTRIBUTION | AI4: 43524 | AJ4: 110 | AK4: 440 | BG4: P | BI4: PRIMARY | BK4: A | BL4: ADD | BM4: ITEMIZED RECEIPTS | BN4: 43543.128 | BR4: F3X | BS4: 4.0315202e+18 | BT4: t | BV4: 2020 | BW4: SA | BY4: 4.0318202e+18 | BZ4: http://docquery.fec.gov/cgi-bin/fecimg/?201903159145712528 | CA4: Contributions From Individuals/Persons Other Than Political Committees
A5: C00364778 | B5: BANK OF AMERICA CORPORATION FEDERAL PAC | C5: 2019 | D5: M4 | E5: 2.0190413e+17 | F5: 11AI | G5: A2019-518258 | H5: 1324297 | J5: IND | K5: INDIVIDUAL | N5: BESSANT, CATHERINE P | O5: Q | P5: C | Q5: B | R5: CATHERINE | S5: P | T5: BESSANT | V5: 100 N TRYON ST | X5: CHARLOTTE | Y5: NC | Z5: 28255 | AA5: BANK OF AMERICA | AB5: CHIEF OPS & TECHNOLOGY OFFICER | AD5: 15 | AE5: CONTRIBUTION | AI5: 43539 | AJ5: 110 | AK5: 550 | BG5: P | BI5: PRIMARY | BK5: A | BL5: ADD | BM5: ITEMIZED RECEIPTS | BN5: 43568.111 | BR5: F3X | BS5: 4.0412202e+18 | BT5: t | BV5: 2020 | BW5: SA | BY5: 4.0412202e+18 | BZ5: http://docquery.fec.gov/cgi-bin/fecimg/?201904129146103817 | CA5: Contributions From Individuals/Persons Other Than Political Committees
A6: C00364778 | B6: BANK OF AMERICA CORPORATION FEDERAL PAC | C6: 2019 | D6: M4 | E6: 2.0190413e+17 | F6: 11AI | G6: A2019-545258 | H6: 1324297 | J6: IND | K6: INDIVIDUAL | N6: BESSANT, CATHERINE P | O6: Q | P6: C | Q6: B | R6: CATHERINE | S6: P | T6: BESSANT | V6: 100 N TRYON ST | X6: CHARLOTTE | Y6: NC | Z6: 28255 | AA6: BANK OF AMERICA | AB6: CHIEF OPS & TECHNOLOGY OFFICER | AD6: 15 | AE6: CONTRIBUTION | AI6: 43555 | AJ6: 110 | AK6: 660 | BG6: P | BI6: PRIMARY | BK6: A | BL6: ADD | BM6: ITEMIZED RECEIPTS | BN6: 43568.111 | BR6: F3X | BS6: 4.0412202e+18 | BT6: t | BV6: 2020 | BW6: SA | BY6: 4.0412202e+18 | BZ6: http://docquery.fec.gov/cgi-bin/fecimg/?201904129146103817 | CA6: Contributions From Individuals/Persons Other Than Political Committees
A7: C00364778 | B7: BANK OF AMERICA CORPORATION FEDERAL PAC | C7: 2019 | D7: M5 | E7: 2.0190515e+17 | F7: 11AI | G7: A2019-793285 | H7: 1330608 | J7: IND | K7: INDIVIDUAL | N7: BESSANT, CATHERINE P | O7: Q | P7: C | Q7: B | R7: CATHERINE | S7: P | T7: BESSANT | V7: 100 N TRYON ST | X7: CHARLOTTE | Y7: NC | Z7: 28255 | AA7: BANK OF AMERICA | AB7: CHIEF OPS & TECHNOLOGY OFFICER | AD7: 15 | AE7: CONTRIBUTION | AI7: 43570 | AJ7: 110 | AK7: 770 | BG7: P | BI7: PRIMARY | BK7: A | BL7: ADD | BM7: ITEMIZED RECEIPTS | BN7: 43600.358 | BR7: F3X | BS7: 4.0514202e+18 | BT7: t | BV7: 2020 | BW7: SA | BY7: 4.0514202e+18 | BZ7: http://docquery.fec.gov/cgi-bin/fecimg/?201905149149695863 | CA7: Contributions From Individuals/Persons Other Than Political Committees
A8: C00364778 | B8: BANK OF AMERICA CORPORATION FEDERAL PAC | C8: 2019 | D8: M5 | E8: 2.0190515e+17 | F8: 11AI | G8: A2019-842965 | H8: 1330608 | J8: IND | K8: INDIVIDUAL | N8: BESSANT, CATHERINE P | O8: Q | P8: C | Q8: B | R8: CATHERINE | S8: P | T8: BESSANT | V8: 100 N TRYON ST | X8: CHARLOTTE | Y8: NC | Z8: 28255 | AA8: BANK OF AMERICA | AB8: CHIEF OPS & TECHNOLOGY OFFICER | AD8: 15 | AE8: CONTRIBUTION | AI8: 43585 | AJ8: 110 | AK8: 880 | BG8: P | BI8: PRIMARY | BK8: A | BL8: ADD | BM8: ITEMIZED RECEIPTS | BN8: 43600.358 | BR8: F3X | BS8: 4.0514202e+18 | BT8: t | BV8: 2020 | BW8: SA | BY8: 4.0514202e+18 | BZ8: http://docquery.fec.gov/cgi-bin/fecimg/?201905149149695863 | CA8: Contributions From Individuals/Persons Other Than Political Committees
A9: C00364778 | B9: BANK OF AMERICA CORPORATION FEDERAL PAC | C9: 2019 | D9: M8 | E9: 2.0190817e+17 | F9: 11AI | G9: A2019-1509442 | H9: 1348081 | J9: IND | K9: INDIVIDUAL | N9: BESSANT, CATHERINE P | O9: Q | P9: C | Q9: B | R9: CATHERINE | S9: P | T9: BESSANT | V9: 100 N TRYON ST | X9: CHARLOTTE | Y9: NC | Z9: 28255 | AA9: BANK OF AMERICA | AB9: CHIEF OPS & TECHNOLOGY OFFICER | AD9: 15 | AE9: CONTRIBUTION | AI9: 43661 | AJ9: 110 | AK9: 1430 | BG9: P | BI9: PRIMARY | BK9: A | BL9: ADD | BM9: ITEMIZED RECEIPTS | BN9: 43694.11 | BR9: F3X | BS9: 4.0816202e+18 | BT9: t | BV9: 2020 | BW9: SA | BY9: 4.0816202e+18 | BZ9: http://docquery.fec.gov/cgi-bin/fecimg/?201908169162884457 | CA9: Contributions From Individuals/Persons Other Than Political Committees
A10: C00364778 | B10: BANK OF AMERICA CORPORATION FEDERAL PAC | C10: 2019 | D10: M8 | E10: 2.0190817e+17 | F10: 11AI | G10: A2019-1686379 | H10: 1348081 | J10: IND | K10: INDIVIDUAL | N10: BESSANT, CATHERINE P | O10: Q | P10: C | Q10: B | R10: CATHERINE | S10: P | T10: BESSANT | V10: 100 N TRYON ST | X10: CHARLOTTE | Y10: NC | Z10: 28255 | AA10: BANK OF AMERICA | AB10: CHIEF OPS & TECHNOLOGY OFFICER | AD10: 15 | AE10: CONTRIBUTION | AI10: 43677 | AJ10: 110 | AK10: 1540 | BG10: P | BI10: PRIMARY | BK10: A | BL10: ADD | BM10: ITEMIZED RECEIPTS | BN10: 43694.11 | BR10: F3X | BS10: 4.0816202e+18 | BT10: t | BV10: 2020 | BW10: SA | BY10: 4.0816202e+18 | BZ10: http://docquery.fec.gov/cgi-bin/fecimg/?201908169162884457 | CA10: Contributions From Individuals/Persons Other Than Political Committees
A11: C00364778 | B11: BANK OF AMERICA CORPORATION FEDERAL PAC | C11: 2019 | D11: YE | E11: 2.0200121e+17 | F11: 11AI | G11: A2019-2942847 | H11: 1371432 | J11: IND | K11: INDIVIDUAL | N11: BESSANT, CATHERINE P | O11: Q | P11: C | Q11: B | R11: CATHERINE | S11: P | T11: BESSANT | V11: 100 N TRYON ST | X11: CHARLOTTE | Y11: NC | Z11: 28255 | AA11: BANK OF AMERICA | AB11: CHIEF OPS & TECHNOLOGY OFFICER | AD11: 15 | AE11: CONTRIBUTION | AI11: 43814 | AJ11: 110 | AK11: 2530 | BG11: P | BI11: PRIMARY | BK11: A | BL11: ADD | BM11: ITEMIZED RECEIPTS | BN11: 43852.068 | BR11: F3X | BS11: 4.0120202e+18 | BT11: t | BV11: 2020 | BW11: SA | BY11: 4.0121202e+18 | BZ11: http://docquery.fec.gov/cgi-bin/fecimg/?202001209167275042 | CA11: Contributions From Individuals/Persons Other Than Political Committees
A12: C00364778 | B12: BANK OF AMERICA CORPORATION FEDERAL PAC | C12: 2019 | D12: YE | E12: 2.0200121e+17 | F12: 11AI | G12: A2019-2983832 | H12: 1371432 | J12: IND | K12: INDIVIDUAL | N12: BESSANT, CATHERINE P | O12: Q | P12: C | Q12: B | R12: CATHERINE | S12: P | T12: BESSANT | V12: 100 N TRYON ST | X12: CHARLOTTE | Y12: NC | Z12: 28255 | AA12: BANK OF AMERICA | AB12: CHIEF OPS & TECHNOLOGY OFFICER | AD12: 15 | AE12: CONTRIBUTION | AI12: 43830 | AJ12: 110 | AK12: 2640 | BG12: P | BI12: PRIMARY | BK12: A | BL12: ADD | BM12: ITEMIZED RECEIPTS | BN12: 43852.068 | BR12: F3X | BS12: 4.0120202e+18 | BT12: t | BV12: 2020 | BW12: SA | BY12: 4.0121202e+18 | BZ12: http://docquery.fec.gov/cgi-bin/fecimg/?202001209167275042 | CA12: Contributions From Individuals/Persons Other Than Political Committees
A13: C00364778 | B13: BANK OF AMERICA CORPORATION FEDERAL PAC | C13: 2019 | D13: M6 | E13: 2.0190803e+17 | F13: 11AI | G13: A2019-949366 | H13: 1346683 | J13: IND | K13: INDIVIDUAL | N13: BESSANT, CATHERINE P | O13: Q | P13: C | Q13: B | R13: CATHERINE | S13: P | T13: BESSANT | V13: 100 N TRYON ST | X13: CHARLOTTE | Y13: NC | Z13: 28255 | AA13: BANK OF AMERICA | AB13: CHIEF OPS & TECHNOLOGY OFFICER | AD13: 15 | AE13: CONTRIBUTION | AI13: 43600 | AJ13: 110 | AK13: 990 | BG13: P | BI13: PRIMARY | BK13: N | BL13: NO CHANGE | BM13: ITEMIZED RECEIPTS | BN13: 43680.113 | BR13: F3X | BS13: 4.0802202e+18 | BT13: t | BV13: 2020 | BW13: SA | BY13: 4.0802202e+18 | BZ13: http://docquery.fec.gov/cgi-bin/fecimg/?201908029161350878 | CA13: Contributions From Individuals/Persons Other Than Political Committees
... A47: C00364778 | B47: BANK OF AMERICA CORPORATION FEDERAL PAC | C47: 2020 | D47: YE | E47: 2.0210126e+17 | F47: 11AI | G47: A2020-2739497 | H47: 1490358 | J47: IND | K47: INDIVIDUAL | N47: BESSANT, CATHERINE P | O47: Q | P47: C | Q47: B | R47: CATHERINE | S47: P | T47: BESSANT | V47: 100 N TRYON ST | X47: CHARLOTTE | Y47: NC | Z47: 28255 | AA47: BANK OF AMERICA | AB47: CHIEF OPS & TECHNOLOGY OFFICER | AD47: 15 | AE47: CONTRIBUTION | AI47: 44196 | AJ47: 110 | AK47: 2640 | BG47: P | BI47: PRIMARY | BK47: A | BL47: ADD | BM47: ITEMIZED RECEIPTS | BN47: 44223.151 | BR47: F3X | BS47: 4.0125202e+18 | BT47: t | BV47: 2020 | BW47: SA | BY47: 4.0127202e+18 | BZ47: https://docquery.fec.gov/cgi-bin/fecimg/?202101259405394702 | CA47: Contributions From Individuals/Persons Other Than Political Committees
V49: =+V47&X47&Y47&Z47 -> 100 N TRYON STCHARLOTTENC28255
A52: Row Labels | B52: Sum of contribution_receipt_amount
A53: BANK OF AMERICA CORPORATION FEDERAL PAC | B53: 5060
A54: Grand Total | B54: 5060

Sheet R David Yost
A1: committee_id | B1: committee_name | C1: report_year | D1: report_type | E1: image_number | F1: line_number | G1: transaction_id | H1: file_number | I1: committee_name | J1: entity_type | K1: entity_type_desc | L1: unused_contbr_id | M1: contributor_prefix | N1: contributor_name | O1: recipient_committee_type | P1: recipient_committee_org_type | Q1: recipient_committee_designation | R1: contributor_first_name | S1: contributor_middle_name | T1: contributor_last_name | U1: contributor_suffix | V1: contributor_street_1 | W1: contributor_street_2 | X1: contributor_city | Y1: contributor_state | Z1: contributor_zip | AA1: contributor_employer | AB1: contributor_occupation | AC1: contributor_id | AD1: receipt_type | AE1: receipt_type_desc | AF1: receipt_type_full | AG1: memo_code | AH1: memo_code_full | AI1: contribution_receipt_date | AJ1: contribution_receipt_amount | AK1: contributor_aggregate_ytd | AL1: candidate_id | AM1: candidate_name | AN1: candidate_first_name | AO1: candidate_last_name | AP1: candidate_middle_name | AQ1: candidate_prefix | AR1: candidate_suffix | AS1: candidate_office | AT1: candidate_office_full | AU1: candidate_office_state | AV1: candidate_office_state_full | AW1: candidate_office_district | AX1: conduit_committee_id | AY1: conduit_committee_name | AZ1: conduit_committee_street1 | BA1: conduit_committee_street2 | BB1: conduit_committee_city | BC1: conduit_committee_state | BD1: conduit_committee_zip | BE1: donor_committee_name | BF1: national_committee_nonfederal_account | BG1: election_type | BH1: election_type_full | BI1: fec_election_type_desc | BJ1: fec_election_year | BK1: amendment_indicator | BL1: amendment_indicator_desc | BM1: schedule_type_full | BN1: load_date | BO1: original_sub_id | BP1: back_reference_transaction_id | BQ1: back_reference_schedule_name | BR1: filing_form | BS1: link_id | BT1: is_individual | BU1: memo_text | BV1: two_year_transaction_period | BW1: schedule_type | BX1: increased_limit | BY1: sub_id | BZ1: pdf_url | CA1: line_number_label
A2: C00694323 | B2: WINRED | C2: 2019 | D2: YE | E2: 2.0210108e+17 | F2: 11AI | G2: A82669328F0804D8F988 | H2: 1485974 | J2: IND | K2: INDIVIDUAL | L2: C00719294 | N2: YOST, R DAVID | O2: V | Q2: U | R2: R DAVID | T2: YOST | V2: 502 GLENVIEW RD | X2: BRYN MAWR | Y2: PA | Z2: 190103632 | AA2: RETIRED | AB2: RETIRED | AC2: C00719294 | AD2: 15E | AE2: EARMARKED CONTRIBUTION | AF2: EARMARKED FOR AUGUST PFLUGER FOR CONGRESS (C00719294) | AI2: 43822 | AJ2: 1000 | AK2: 1000 | AL2: H0TX11230 | BG2: P | BI2: PRIMARY | BK2: A | BL2: ADD | BM2: ITEMIZED RECEIPTS | BN2: 44237.518 | BR2: F3X | BS2: 4.0111202e+18 | BT2: t | BV2: 2020 | BW2: SA | BY2: 4.0209202e+18 | BZ2: https://docquery.fec.gov/cgi-bin/fecimg/?202101079395257093 | CA2: Contributions From Individuals/Persons Other Than Political Committees
A3: C00747121 | B3: RED SENATE | C3: 2020 | D3: Q3 | E3: 2.0201016e+17 | F3: 11AI | G3: SA11AI.16306 | H3: 1449160 | J3: IND | K3: INDIVIDUAL | N3: YOST, R DAVID | O3: O | Q3: U | R3: R DAVID | T3: YOST | V3: 502 GLENVIEW ROAD | X3: BRYN MAWR | Y3: PA | Z3: 19010 | AB3: RETIRED | AD3: 10 | AE3: NON-FEDERAL RECEIPT FROM PERSONS | AI3: 44074 | AJ3: 1000 | AK3: 1000 | BG3: G2020 | BI3: GENERAL | BJ3: 2020 | BK3: A | BL3: ADD | BM3: ITEMIZED RECEIPTS | BN3: 44152.154 | BR3: F3X | BS3: 4.1016202e+18 | BT3: t | BV3: 2020 | BW3: SA | BY3: 4.1117202e+18 | BZ3: http://docquery.fec.gov/cgi-bin/fecimg/?202010159293902663 | CA3: Contributions From Individuals/Persons Other Than Political Committees
V5: =+V3&X3&Y3&Z3 -> 502 GLENVIEW ROADBRYN MAWRPA19010 | AJ5: =SUM(AJ2:AJ4) -> 2000

Sheet Clayton Rose
A1: committee_id | B1: committee_name | C1: report_year | D1: report_type | E1: image_number | F1: line_number | G1: transaction_id | H1: file_number | I1: committee_name | J1: entity_type | K1: entity_type_desc | L1: unused_contbr_id | M1: contributor_prefix | N1: contributor_name | O1: recipient_committee_type | P1: recipient_committee_org_type | Q1: recipient_committee_designation | R1: contributor_first_name | S1: contributor_middle_name | T1: contributor_last_name | U1: contributor_suffix | V1: contributor_street_1 | W1: contributor_street_2 | X1: contributor_city | Y1: contributor_state | Z1: contributor_zip | AA1: contributor_employer | AB1: contributor_occupation | AC1: contributor_id | AD1: receipt_type | AE1: receipt_type_desc | AF1: receipt_type_full | AG1: memo_code | AH1: memo_code_full | AI1: contribution_receipt_date | AJ1: contribution_receipt_amount | AK1: contributor_aggregate_ytd | AL1: candidate_id | AM1: candidate_name | AN1: candidate_first_name | AO1: candidate_last_name | AP1: candidate_middle_name | AQ1: candidate_prefix | AR1: candidate_suffix | AS1: candidate_office | AT1: candidate_office_full | AU1: candidate_office_state | AV1: candidate_office_state_full | AW1: candidate_office_district | AX1: conduit_committee_id | AY1: conduit_committee_name | AZ1: conduit_committee_street1 | BA1: conduit_committee_street2 | BB1: conduit_committee_city | BC1: conduit_committee_state | BD1: conduit_committee_zip | BE1: donor_committee_name | BF1: national_committee_nonfederal_account | BG1: election_type | BH1: election_type_full | BI1: fec_election_type_desc | BJ1: fec_election_year | BK1: amendment_indicator | BL1: amendment_indicator_desc | BM1: schedule_type_full | BN1: load_date | BO1: original_sub_id | BP1: back_reference_transaction_id | BQ1: back_reference_schedule_name | BR1: filing_form | BS1: link_id | BT1: is_individual | BU1: memo_text | BV1: two_year_transaction_period | BW1: schedule_type | BX1: increased_limit | BY1: sub_id | BZ1: pdf_url | CA1: line_number_label
A2: C00155952 | B2: DEMOCRATIC PARTY OF VIRGINIA | C2: 2020 | D2: 30G | E2: 2.0210427e+17 | F2: 12 | G2: 10904762 | H2: 1514451 | J2: IND | K2: INDIVIDUAL | N2: ROSE, CLAYTON J | O2: Y | Q2: U | R2: CLAYTON | S2: J | T2: ROSE | V2: 100 FEDERAL ST | W2: FL 11 | X2: BOSTON | Y2: MA | Z2: 21101802 | AA2: BOWDOIN COLLEGE | AB2: PRESIDENT | AD2: 15J | AE2: MEMO (FILER'S % OF CONTRIBUTION GIVEN TO JOIN | AG2: X | AI2: 44053 | AJ2: 3926.66 | AK2: 3926.66 | BG2: P | BI2: PRIMARY | BK2: N | BL2: NO CHANGE | BM2: ITEMIZED RECEIPTS | BN2: 44325.15 | BP2: 10236887 | BQ2: SA12 | BR2: F3X | BS2: 4.0426202e+18 | BT2: t | BU2: * BIDEN VICTORY FUND | BV2: 2020 | BW2: SA | BY2: 4.0509202e+18 | BZ2: https://docquery.fec.gov/cgi-bin/fecimg/?202104269445489146 | CA2: Transfers from Authorized Committees
A3: C00016899 | B3: OHIO DEMOCRATIC PARTY | C3: 2020 | D3: 30G | E3: 2.0210512e+17 | F3: 11AI | G3: 11AI-000585531 | H3: 1515686 | J3: IND | K3: INDIVIDUAL | N3: ROSE, CLAYTON | O3: Y | Q3: U | R3: CLAYTON | T3: ROSE | V3: 100 FEDERAL STREET, 11TH FLOOR | X3: BOSTON | Y3: MA | Z3: 2110 | AA3: BOWDOIN COLLEGE | AB3: PRESIDENT | AD3: 15J | AE3: MEMO (FILER'S % OF CONTRIBUTION GIVEN TO JOIN | AG3: X | AI3: 44053 | AJ3: 3926.66 | AK3: 3926.66 | BG3: P | BI3: PRIMARY | BK3: N | BL3: NO CHANGE | BM3: ITEMIZED RECEIPTS | BN3: 44329.151 | BR3: F3X | BS3: 4.0512202e+18 | BT3: t | BU3: BIDEN VICTORY FUND | BV3: 2020 | BW3: SA | BY3: 4.0513202e+18 | BZ3: https://docquery.fec.gov/cgi-bin/fecimg/?202105119446445006 | CA3: Contributions From Individuals/Persons Other Than Political Committees
A4: C00019331 | B4: DEMOCRATIC PARTY OF WISCONSIN | C4: 2020 | D4: M10 | E4: 2.0210518e+17 | F4: 11AI | G4: 11AI-000997372 | H4: 1516564 | J4: IND | K4: INDIVIDUAL | N4: ROSE, CLAYTON | O4: Y | Q4: U | R4: CLAYTON | T4: ROSE | V4: 100 FEDERAL STREET | W4: 11TH FLOOR | X4: BOSTON | Y4: MA | Z4: 2110 | AA4: BOWDOIN COLLEGE | AB4: PRESIDENT | AD4: 15J | AE4: MEMO (FILER'S % OF CONTRIBUTION GIVEN TO JOIN | AG4: X | AI4: 44053 | AJ4: 3926.66 | AK4: 3926.66 | BG4: P | BI4: PRIMARY | BK4: N | BL4: NO CHANGE | BM4: ITEMIZED RECEIPTS | BN4: 44342.149 | BR4: F3X | BS4: 4.0519202e+18 | BT4: t | BU4: BIDEN VICTORY FUND | BV4: 2020 | BW4: SA | BY4: 4.0526202e+18 | BZ4: https://docquery.fec.gov/cgi-bin/fecimg/?202105179446842029 | CA4: Contributions From Individuals/Persons Other Than Political Committees
A5: C00003988 | B5: NEBRASKA DEMOCRATIC PARTY | C5: 2020 | D5: 30G | E5: 2.0210513e+17 | F5: 11AI | G5: 11AI-000268182 | H5: 1515964 | J5: IND | K5: INDIVIDUAL | N5: ROSE, CLAYTON | O5: Y | Q5: U | R5: CLAYTON | T5: ROSE | V5: 100 FEDERAL STREET, 11TH FLOOR | X5: BOSTON | Y5: MA | Z5: 2110 | AA5: BOWDOIN COLLEGE | AB5: PRESIDENT | AD5: 15J | AE5: MEMO (FILER'S % OF CONTRIBUTION GIVEN TO JOIN | AG5: X | AI5: 44053 | AJ5: 3926.67 | AK5: 3926.67 | BG5: P | BI5: PRIMARY | BK5: N | BL5: NO CHANGE | BM5: ITEMIZED RECEIPTS | BN5: 44330.15 | BR5: F3X | BS5: 4.0513202e+18 | BT5: t | BU5: BIDEN VICTORY FUND | BV5: 2020 | BW5: SA | BY5: 4.0514202e+18 | BZ5: https://docquery.fec.gov/cgi-bin/fecimg/?202105129446683549 | CA5: Contributions From Individuals/Persons Other Than Political Committees
A6: C00025254 | B6: MINNESOTA DEMOCRATIC-FARMER-LABOR PARTY | C6: 2020 | D6: 12G | E6: 2.0210506e+17 | F6: 12 | G6: 3839018 | H6: 1515203 | J6: IND | K6: INDIVIDUAL | N6: ROSE, CLAYTON | O6: Y | Q6: U | R6: CLAYTON | T6: ROSE | V6: 100 FEDERAL ST | W6: FL 11 | X6: BOSTON | Y6: MA | Z6: 21101802 | AA6: BOWDOIN COLLEGE | AB6: PRESIDENT | AD6: 15J | AE6: MEMO (FILER'S % OF CONTRIBUTION GIVEN TO JOIN | AG6: X | AI6: 44053 | AJ6: 3926.67 | AK6: 3926.67 | BG6: P | BI6: PRIMARY | BK6: N | BL6: NO CHANGE | BM6: ITEMIZED RECEIPTS | BN6: 44324.199 | BP6: 3835551 | BQ6: SA12 | BR6: F3X | BS6: 4.0506202e+18 | BT6: t | BU6: * BIDEN VICTORY FUND | BV6: 2020 | BW6: SA | BY6: 4.0508202e+18 | BZ6: https://docquery.fec.gov/cgi-bin/fecimg/?202105059446291974 | CA6: Transfers from Authorized Committees
A7: C00099267 | B7: TEXAS DEMOCRATIC PARTY | C7: 2020 | D7: 30G | E7: 2.0210521e+17 | F7: 11AI | G7: 11AI-000791467 | H7: 1517435 | J7: IND | K7: INDIVIDUAL | N7: ROSE, CLAYTON | O7: Y | Q7: U | R7: CLAYTON | T7: ROSE | V7: 100 FEDERAL STREET | W7: 11TH FLOOR | X7: BOSTON | Y7: MA | Z7: 2110 | AA7: BOWDOIN COLLEGE | AB7: PRESIDENT | AD7: 15J | AE7: MEMO (FILER'S % OF CONTRIBUTION GIVEN TO JOIN | AG7: X | AI7: 44053 | AJ7: 3926.66 | AK7: 3926.66 | BG7: P | BI7: PRIMARY | BK7: N | BL7: NO CHANGE | BM7: ITEMIZED RECEIPTS | BN7: 44343.161 | BR7: F3X | BS7: 4.0521202e+18 | BT7: t | BU7: BIDEN VICTORY FUND | BV7: 2020 | BW7: SA | BY7: 4.0527202e+18 | BZ7: https://docquery.fec.gov/cgi-bin/fecimg/?202105209447030036 | CA7: Contributions From Individuals/Persons Other Than Political Committees
A8: C00099267 | B8: TEXAS DEMOCRATIC PARTY | C8: 2020 | D8: 30G | E8: 2.0210521e+17 | F8: 11AI | G8: 11AI-000793757 | H8: 1517435 | J8: IND | K8: INDIVIDUAL | N8: ROSE, CLAYTON | O8: Y | Q8: U | R8: CLAYTON | T8: ROSE | V8: 100 FEDERAL STREET | W8: 11TH FLOOR | X8: BOSTON | Y8: MA | Z8: 2110 | AA8: BOWDOIN COLLEGE | AB8: PRESIDENT | AD8: 15J | AE8: MEMO (FILER'S % OF CONTRIBUTION GIVEN TO JOIN | AG8: X | AI8: 44053 | AJ8: 3926.66 | AK8: 7853.32 | BG8: P | BI8: PRIMARY | BK8: N | BL8: NO CHANGE | BM8: ITEMIZED RECEIPTS | BN8: 44343.161 | BR8: F3X | BS8: 4.0521202e+18 | BT8: t | BU8: BIDEN VICTORY FUND | BV8: 2020 | BW8: SA | BY8: 4.0527202e+18 | BZ8: https://docquery.fec.gov/cgi-bin/fecimg/?202105209447030617 | CA8: Contributions From Individuals/Persons Other Than Political Committees
A9: C00744946 | B9: BIDEN VICTORY FUND | C9: 2020 | D9: Q3 | E9: 2.0210115e+17 | F9: 11AI | G9: 9254118 | H9: 1487959 | J9: IND | K9: INDIVIDUAL | N9: ROSE, CLAYTON | O9: N | Q9: J | R9: CLAYTON | T9: ROSE | V9: 100 FEDERAL ST | X9: BOSTON | Y9: MA | Z9: 21101802 | AA9: BOWDOIN COLLEGE | AB9: PRESIDENT | AD9: 15 | AE9: CONTRIBUTION | AI9: 44053 | AJ9: 100000 | AK9: 100000 | BG9: P | BI9: PRIMARY | BK9: A | BL9: ADD | BM9: ITEMIZED RECEIPTS | BN9: 44231.444 | BR9: F3X | BS9: 4.0115202e+18 | BT9: t | BV9: 2020 | BW9: SA | BY9: 4.0203202e+18 | BZ9: https://docquery.fec.gov/cgi-bin/fecimg/?202101149404678131 | CA9: Contributions From Individuals/Persons Other Than Political Committees
A10: C00208991 | B10: NEVADA STATE DEMOCRATIC PARTY | C10: 2020 | D10: 12G | E10: 2.0210112e+17 | F10: 11AI | G10: 11AI-000087847 | H10: 1486674 | J10: IND | K10: INDIVIDUAL | N10: ROSE, CLAYTON | O10: Y | Q10: U | R10: CLAYTON | T10: ROSE | V10: 100 FEDERAL STREET | W10: 11TH FLOOR | X10: BOSTON | Y10: MA | Z10: 2110 | AA10: BOWDOIN COLLEGE | AB10: PRESIDENT | AD10: 15J | AE10: MEMO (FILER'S % OF CONTRIBUTION GIVEN TO JOIN | AG10: X | AI10: 44053 | AJ10: 3926.67 | AK10: 3926.67 | BG10: P | BI10: PRIMARY | BK10: N | BL10: NO CHANGE | BM10: ITEMIZED RECEIPTS | BN10: 44226.157 | BR10: F3X | BS10: 4.0112202e+18 | BT10: t | BU10: BIDEN VICTORY FUND | BV10: 2020 | BW10: SA | BY10: 4.0130202e+18 | BZ10: https://docquery.fec.gov/cgi-bin/fecimg/?202101119398389220 | CA10: Contributions From Individuals/Persons Other Than Political Committees
A11: C00166710 | B11: ARIZONA DEMOCRATIC PARTY | C11: 2020 | D11: 12G | E11: 2.021042e+17 | F11: 11AI | G11: 11AI-000428114 | H11: 1513234 | J11: IND | K11: INDIVIDUAL | N11: ROSE, CLAYTON | O11: Y | Q11: U | R11: CLAYTON | T11: ROSE | V11: 100 FEDERAL STREET | W11: 11TH FLOOR | X11: BOSTON | Y11: MA | Z11: 2110 | AA11: BOWDOIN COLLEGE | AB11: PRESIDENT | AD11: 15J | AE11: MEMO (FILER'S % OF CONTRIBUTION GIVEN TO JOIN | AG11: X | AI11: 44053 | AJ11: 3926.67 | AK11: 3926.67 | BG11: P | BI11: PRIMARY | BK11: C | BL11: CHANGE | BM11: ITEMIZED RECEIPTS | BN11: 44316.158 | BR11: F3X | BS11: 4.0420202e+18 | BT11: t | BU11: BIDEN VICTORY FUND | BV11: 2020 | BW11: SA | BY11: 4.0430202e+18 | BZ11: https://docquery.fec.gov/cgi-bin/fecimg/?202104199443819999 | CA11: Contributions From Individuals/Persons Other Than Political Committees
A12: C00010603 | B12: DNC SERVICES CORP / DEMOCRATIC NATIONAL COMMITTEE | C12: 2020 | D12: M10 | E12: 2.0210225e+17 | F12: 12 | G12: 37439342 | H12: 1502017 | J12: IND | K12: INDIVIDUAL | N12: ROSE, CLAYTON | O12: Y | Q12: U | R12: CLAYTON | T12: ROSE | V12: 100 FEDERAL ST | X12: BOSTON | Y12: MA | Z12: 21101802 | AA12: BOWDOIN COLLEGE | AB12: PRESIDENT | AD12: 15J | AE12: MEMO (FILER'S % OF CONTRIBUTION GIVEN TO JOIN | AG12: X | AI12: 44053 | AJ12: 35500 | AK12: 35500 | BG12: G2020 | BI12: GENERAL | BJ12: 2020 | BK12: A | BL12: ADD | BM12: ITEMIZED RECEIPTS | BN12: 44253.168 | BP12: 36773706 | BQ12: SA12 | BR12: F3X | BS12: 4.0226202e+18 | BT12: t | BU12: * BIDEN VICTORY FUND | BV12: 2020 | BW12: SA | BY12: 4.0226202e+18 | BZ12: https://docquery.fec.gov/cgi-bin/fecimg/?202102249428871192 | CA12: Transfers from Authorized Committees
A13: C00167130 | B13: PENNSYLVANIA DEMOCRATIC PARTY | C13: 2020 | D13: M10 | E13: 2.0210332e+17 | F13: 11AI | G13: 11AI-000117490 | H13: 1506833 | J13: IND | K13: INDIVIDUAL | N13: ROSE, CLAYTON | O13: Y | P13: C | Q13: U | R13: CLAYTON | T13: ROSE | V13: 100 FEDERAL STREET | W13: 11TH FLOOR | X13: BOSTON | Y13: MA | Z13: 2110 | AA13: BOWDOIN COLLEGE | AB13: PRESIDENT | AD13: 15J | AE13: MEMO (FILER'S % OF CONTRIBUTION GIVEN TO JOIN | AG13: X | AI13: 44053 | AJ13: 3926.66 | AK13: 3926.66 | BG13: P | BI13: PRIMARY | BK13: N | BL13: NO CHANGE | BM13: ITEMIZED RECEIPTS | BN13: 44288.167 | BR13: F3X | BS13: 4.0401202e+18 | BT13: t | BU13: BIDEN VICTORY FUND | BV13: 2020 | BW13: SA | BY13: 4.0402202e+18 | BZ13: https://docquery.fec.gov/cgi-bin/fecimg/?202103319442966378 | CA13: Contributions From Individuals/Persons Other Than Political Committees
V15: =+V13&X13&Y13&Z12 -> 100 FEDERAL STREETBOSTONMA21101802
A18: Row Labels | B18: Sum of contribution_receipt_amount
A19: ARIZONA DEMOCRATIC PARTY | B19: 3926.67 | C19: D
A20: BIDEN VICTORY FUND | B20: 100000 | C20: D
A21: DEMOCRATIC PARTY OF VIRGINIA | B21: 3926.66 | C21: D
A22: DEMOCRATIC PARTY OF WISCONSIN | B22: 3926.66 | C22: D
A23: DNC SERVICES CORP / DEMOCRATIC NATIONAL COMMITTEE | B23: 35500 | C23: D
A24: MINNESOTA DEMOCRATIC-FARMER-LABOR PARTY | B24: 3926.67 | C24: D
A25: NEBRASKA DEMOCRATIC PARTY | B25: 3926.67 | C25: D
A26: NEVADA STATE DEMOCRATIC PARTY | B26: 3926.67 | C26: D
A27: OHIO DEMOCRATIC PARTY | B27: 3926.66 | C27: D
A28: PENNSYLVANIA DEMOCRATIC PARTY | B28: 3926.66 | C28: D
A29: TEXAS DEMOCRATIC PARTY | B29: 7853.32 | C29: D
A30: Grand Total | B30: 174766.64

Sheet Monica Lozano
A1: committee_id | B1: committee_name | C1: report_year | D1: report_type | E1: image_number | F1: line_number | G1: transaction_id | H1: file_number | I1: committee_name | J1: entity_type | K1: entity_type_desc | L1: unused_contbr_id | M1: contributor_prefix | N1: contributor_name | O1: recipient_committee_type | P1: recipient_committee_org_type | Q1: recipient_committee_designation | R1: contributor_first_name | S1: contributor_middle_name | T1: contributor_last_name | U1: contributor_suffix | V1: contributor_street_1 | W1: contributor_street_2 | X1: contributor_city | Y1: contributor_state | Z1: contributor_zip | AA1: contributor_employer | AB1: contributor_occupation | AC1: contributor_id | AD1: receipt_type | AE1: receipt_type_desc | AF1: receipt_type_full | AG1: memo_code | AH1: memo_code_full | AI1: contribution_receipt_date | AJ1: contribution_receipt_amount | AK1: contributor_aggregate_ytd | AL1: candidate_id | AM1: candidate_name | AN1: candidate_first_name | AO1: candidate_last_name | AP1: candidate_middle_name | AQ1: candidate_prefix | AR1: candidate_suffix | AS1: candidate_office | AT1: candidate_office_full | AU1: candidate_office_state | AV1: candidate_office_state_full | AW1: candidate_office_district | AX1: conduit_committee_id | AY1: conduit_committee_name | AZ1: conduit_committee_street1 | BA1: conduit_committee_street2 | BB1: conduit_committee_city | BC1: conduit_committee_state | BD1: conduit_committee_zip | BE1: donor_committee_name | BF1: national_committee_nonfederal_account | BG1: election_type | BH1: election_type_full | BI1: fec_election_type_desc | BJ1: fec_election_year | BK1: amendment_indicator | BL1: amendment_indicator_desc | BM1: schedule_type_full | BN1: load_date | BO1: original_sub_id | BP1: back_reference_transaction_id | BQ1: back_reference_schedule_name | BR1: filing_form | BS1: link_id | BT1: is_individual | BU1: memo_text | BV1: two_year_transaction_period | BW1: schedule_type | BX1: increased_limit | BY1: sub_id | BZ1: pdf_url | CA1: line_number_label
A2: C00666149 | B2: XOCHITL FOR NEW MEXICO | C2: 2019 | D2: Q2 | E2: 2.0190716e+17 | F2: 11AI | G2: VVBGKK5TBW9 | H2: 1339820 | J2: IND | K2: INDIVIDUAL | L2: C00401224 | N2: LOZANO, MONICA | O2: H | Q2: P | R2: MONICA | T2: LOZANO | V2: 5610 GOLDEN GATE AVE | X2: OAKLAND | Y2: CA | Z2: 946182113 | AA2: COLLEGE FUTURES FOUNDATION | AB2: PRESIDENT | AC2: C00401224 | AD2: 15E | AE2: EARMARKED CONTRIBUTION | AI2: 43582 | AJ2: 250 | AK2: 250 | BG2: P2020 | BI2: PRIMARY | BJ2: 2020 | BK2: A | BL2: ADD | BM2: ITEMIZED RECEIPTS | BN2: 43666.146 | BP2: VVBGKK5TBW9E | BQ2: SA11AI | BR2: F3 | BS2: 4.0715202e+18 | BT2: t | BU2: * EARMARKED CONTRIBUTION: SEE BELOW | BV2: 2020 | BW2: SA | BY2: 4.0719202e+18 | BZ2: http://docquery.fec.gov/cgi-bin/fecimg/?201907159150759713 | CA2: Contributions From Individuals/Persons Other Than Political Committees
A3: C00401224 | B3: ACTBLUE | C3: 2019 | D3: MY | E3: 2.019073e+17 | F3: 11AI | G3: SA11AI_153688256 | H3: 1344765 | J3: IND | K3: INDIVIDUAL | N3: LOZANO, MONICA | O3: W | Q3: U | R3: MONICA | T3: LOZANO | V3: 5610 GOLDEN GATE AVENUE | X3: OAKLAND | Y3: CA | Z3: 94618 | AA3: COLELGE FUTURES FOUNDATION | AB3: PRESIDENT | AF3: EARMARK | AI3: 43564 | AJ3: 100 | AK3: 100 | BK3: A | BL3: ADD | BM3: ITEMIZED RECEIPTS | BN3: 43706.637 | BR3: F3X | BS3: 4.0801202e+18 | BT3: t | BU3: EARMARKED FOR JULIAN FOR THE FUTURE (C00693044) | BV3: 2020 | BW3: SA | BY3: 4.0828202e+18 | BZ3: http://docquery.fec.gov/cgi-bin/fecimg/?201907299155217123 | CA3: Contributions From Individuals/Persons Other Than Political Committees
A4: C00650648 | B4: CISNEROS FOR CONGRESS | C4: 2019 | D4: Q3 | E4: 2.0191016e+17 | F4: 11AI | G4: 2292811 | H4: 1358125 | J4: IND | K4: INDIVIDUAL | L4: C00401224 | N4: LOZANO, MONICA | O4: H | Q4: P | R4: MONICA | T4: LOZANO | V4: 5610 GOLDEN GATE AVE | X4: OAKLAND | Y4: CA | Z4: 946182113 | AA4: COLLEGE FUTURES FOUNDATION | AB4: PHILANTHROPIST | AC4: C00401224 | AD4: 15E | AE4: EARMARKED CONTRIBUTION | AI4: 43733 | AJ4: 250 | AK4: 250 | BG4: P2020 | BI4: PRIMARY | BJ4: 2020 | BK4: A | BL4: ADD | BM4: ITEMIZED RECEIPTS | BN4: 43761.116 | BP4: 2292811E | BQ4: SA11AI | BR4: F3 | BS4: 4.1015202e+18 | BT4: t | BU4: * EARMARKED CONTRIBUTION: SEE BELOW | BV4: 2020 | BW4: SA | BY4: 4.1022202e+18 | BZ4: http://docquery.fec.gov/cgi-bin/fecimg/?201910159164206248 | CA4: Contributions From Individuals/Persons Other Than Political Committees
A5: C00703975 | B5: BIDEN FOR PRESIDENT | C5: 2019 | D5: Q2 | E5: 2.0191022e+17 | F5: 17A | G5: 516084 | H5: 1360571 | J5: IND | K5: INDIVIDUAL | L5: C00401224 | N5: LOZANO, MONICA | O5: P | Q5: P | R5: MONICA | T5: LOZANO | V5: 5610 GOLDEN GATE AVE | X5: OAKLAND | Y5: CA | Z5: 946182113 | AA5: COLLEGE FUTURES FOUNDATION | AB5: PRESIDENT | AC5: C00401224 | AD5: 15E | AE5: EARMARKED CONTRIBUTION | AI5: 43582 | AJ5: 2800 | AK5: 2800 | BG5: P2020 | BI5: PRIMARY | BJ5: 2020 | BK5: N | BL5: NO CHANGE | BM5: ITEMIZED RECEIPTS | BN5: 43768.112 | BP5: 516084E | BQ5: SA17A | BR5: F3P | BS5: 4.1021202e+18 | BT5: t | BU5: * EARMARKED CONTRIBUTION: SEE BELOW | BV5: 2020 | BW5: SA | BY5: 4.1029202e+18 | BZ5: http://docquery.fec.gov/cgi-bin/fecimg/?201910219165257480 | CA5: Contributions From Individuals/Persons Other Than Political Committees
A6: C00155952 | B6: DEMOCRATIC PARTY OF VIRGINIA | C6: 2020 | D6: 30G | E6: 2.0210427e+17 | F6: 12 | G6: 10904247 | H6: 1514451 | J6: IND | K6: INDIVIDUAL | N6: LOZANO, MONICA | O6: Y | Q6: U | R6: MONICA | T6: LOZANO | V6: 5610 GOLDEN GATE AVE | X6: OAKLAND | Y6: CA | Z6: 946182113 | AA6: COLLEGE FUTURES FOUNDATION | AB6: EXECUTIVE | AD6: 15J | AE6: MEMO (FILER'S % OF CONTRIBUTION GIVEN TO JOIN | AG6: X | AI6: 44086 | AJ6: 636.66 | AK6: 636.66 | BG6: P | BI6: PRIMARY | BK6: N | BL6: NO CHANGE | BM6: ITEMIZED RECEIPTS | BN6: 44325.15 | BP6: 10519213 | BQ6: SA12 | BR6: F3X | BS6: 4.0426202e+18 | BT6: t | BU6: * BIDEN VICTORY FUND | BV6: 2020 | BW6: SA | BY6: 4.0509202e+18 | BZ6: https://docquery.fec.gov/cgi-bin/fecimg/?202104269445489336 | CA6: Transfers from Authorized Committees
A7: C00016899 | B7: OHIO DEMOCRATIC PARTY | C7: 2020 | D7: 30G | E7: 2.0210512e+17 | F7: 11AI | G7: 11AI-000586421 | H7: 1515686 | J7: IND | K7: INDIVIDUAL | N7: LOZANO, MONICA | O7: Y | Q7: U | R7: MONICA | T7: LOZANO | V7: 5610 GOLDEN GATE AVENUE | X7: OAKLAND | Y7: CA | Z7: 94618 | AA7: COLLEGE FUTURES FOUNDATION | AB7: EXECUTIVE | AD7: 15J | AE7: MEMO (FILER'S % OF CONTRIBUTION GIVEN TO JOIN | AG7: X | AI7: 44086 | AJ7: 636.66 | AK7: 636.66 | BG7: P | BI7: PRIMARY | BK7: N | BL7: NO CHANGE | BM7: ITEMIZED RECEIPTS | BN7: 44329.151 | BR7: F3X | BS7: 4.0512202e+18 | BT7: t | BU7: BIDEN VICTORY FUND | BV7: 2020 | BW7: SA | BY7: 4.0513202e+18 | BZ7: https://docquery.fec.gov/cgi-bin/fecimg/?202105119446445367 | CA7: Contributions From Individuals/Persons Other Than Political Committees
A8: C00165688 | B8: NORTH CAROLINA DEMOCRATIC PARTY - FEDERAL | C8: 2020 | D8: M10 | E8: 2.0210305e+17 | F8: 11AI | G8: 11AI-000226869 | H8: 1502854 | J8: IND | K8: INDIVIDUAL | N8: LOZANO, MONICA | O8: Y | Q8: U | R8: MONICA | T8: LOZANO | V8: 5610 GOLDEN GATE AVENUE | X8: OAKLAND | Y8: CA | Z8: 94618 | AA8: COLLEGE FUTURES FOUNDATION | AB8: EXECUTIVE | AD8: 15J | AE8: MEMO (FILER'S % OF CONTRIBUTION GIVEN TO JOIN | AG8: X | AI8: 44086 | AJ8: 636.67 | AK8: 636.67 | BG8: P | BI8: PRIMARY | BK8: A | BL8: ADD | BM8: ITEMIZED RECEIPTS | BN8: 44264.157 | BR8: F3X | BS8: 4.0304202e+18 | BT8: t | BU8: BIDEN VICTORY FUND | BV8: 2020 | BW8: SA | BY8: 4.0309202e+18 | BZ8: https://docquery.fec.gov/cgi-bin/fecimg/?202103049440175440 | CA8: Contributions From Individuals/Persons Other Than Political Committees
A9: C00650648 | B9: CISNEROS FOR CONGRESS | C9: 2020 | D9: 12P | E9: 2.020071e+17 | F9: 11AI | G9: 2734868 | H9: 1418380 | J9: IND | K9: INDIVIDUAL | L9: C00401224 | N9: LOZANO, MONICA | O9: H | Q9: P | R9: MONICA | T9: LOZANO | V9: 5610 GOLDEN GATE AVE | X9: OAKLAND | Y9: CA | Z9: 946182113 | AA9: COLLEGE FUTURES FOUNDATION | AB9: CEO | AC9: C00401224 | AD9: 15E | AE9: EARMARKED CONTRIBUTION | AI9: 43872 | AJ9: 250 | AK9: 500 | BG9: P2020 | BI9: PRIMARY | BJ9: 2020 | BK9: N | BL9: NO CHANGE | BM9: ITEMIZED RECEIPTS | BN9: 44027.076 | BP9: 2734868E | BQ9: SA11AI | BR9: F3 | BS9: 4.0709202e+18 | BT9: t | BU9: * EARMARKED CONTRIBUTION: SEE BELOW | BV9: 2020 | BW9: SA | BY9: 4.0714202e+18 | BZ9: http://docquery.fec.gov/cgi-bin/fecimg/?202007099244397711 | CA9: Contributions From Individuals/Persons Other Than Political Committees
A10: C00010603 | B10: DNC SERVICES CORP / DEMOCRATIC NATIONAL COMMITTEE | C10: 2020 | D10: M9 | E10: 2.0201215e+17 | F10: 12 | G10: 36779590 | H10: 1482850 | J10: IND | K10: INDIVIDUAL | N10: LOZANO, MONICA | O10: Y | Q10: U | R10: MONICA | T10: LOZANO | V10: 5610 GOLDEN GATE AVE | X10: OAKLAND | Y10: CA | Z10: 946182113 | AA10: COLLEGE FUTURES FOUNDATION | AB10: EXECUTIVE | AD10: 15J | AE10: MEMO (FILER'S % OF CONTRIBUTION GIVEN TO JOIN | AG10: X | AI10: 44035 | AJ10: 25000 | AK10: 25000 | BG10: G2020 | BI10: GENERAL | BJ10: 2020 | BK10: A | BL10: ADD | BM10: ITEMIZED RECEIPTS | BN10: 44183.154 | BP10: 36524305 | BQ10: SA12 | BR10: F3X | BS10: 4.1216202e+18 | BT10: t | BU10: * BIDEN VICTORY FUND | BV10: 2020 | BW10: SA | BY10: 4.1218202e+18 | BZ10: https://docquery.fec.gov/cgi-bin/fecimg/?202012149387340909 | CA10: Transfers from Authorized Committees
A11: C00696419 | B11: AMY FOR AMERICA | C11: 2020 | D11: M3 | E11: 2.0200716e+17 | F11: 17A | G11: 1358716 | H11: 1424472 | J11: IND | K11: INDIVIDUAL | N11: LOZANO, MONICA | O11: P | Q11: P | R11: MONICA | T11: LOZANO | V11: 5610 GOLDEN GATE AVE | X11: OAKLAND | Y11: CA | Z11: 946182113 | AA11: COLLEGE FUTURES FOUNDATION | AB11: PRESIDENT | AD11: 15E | AE11: EARMARKED CONTRIBUTION | AI11: 43868 | AJ11: 1000 | AK11: 1000 | BG11: P2020 | BI11: PRIMARY | BJ11: 2020 | BK11: A | BL11: ADD | BM11: ITEMIZED RECEIPTS | BN11: 44033.136 | BP11: 1358716E | BQ11: SA17A | BR11: F3P | BS11: 4.0716202e+18 | BT11: t | BU11: * EARMARKED CONTRIBUTION: SEE BELOW | BV11: 2020 | BW11: SA | BY11: 4.0720202e+18 | BZ11: http://docquery.fec.gov/cgi-bin/fecimg/?202007159249941502 | CA11: Contributions From Individuals/Persons Other Than Political Committees
A12: C00161786 | B12: COLORADO DEMOCRATIC PARTY | C12: 2020 | D12: 30G | E12: 2.0210406e+17 | F12: 11AI | G12: 11AI-000297494 | H12: 1507807 | J12: IND | K12: INDIVIDUAL | N12: LOZANO, MONICA | O12: Y | Q12: U | R12: MONICA | T12: LOZANO | V12: 5610 GOLDEN GATE AVENUE | X12: OAKLAND | Y12: CA | Z12: 94618 | AA12: COLLEGE FUTURES FOUNDATION | AB12: EXECUTIVE | AD12: 15J | AE12: MEMO (FILER'S % OF CONTRIBUTION GIVEN TO JOIN | AG12: X | AI12: 44086 | AJ12: 636.67 | AK12: 636.67 | BG12: P | BI12: PRIMARY | BK12: N | BL12: NO CHANGE | BM12: ITEMIZED RECEIPTS | BN12: 44294.182 | BR12: F3X | BS12: 4.0407202e+18 | BT12: t | BU12: BIDEN VICTORY FUND | BV12: 2020 | BW12: SA | BY12: 4.0407202e+18 | BZ12: https://docquery.fec.gov/cgi-bin/fecimg/?202104059443068389 | CA12: Contributions From Individuals/Persons Other Than Political Committees
A13: C00703975 | B13: BIDEN FOR PRESIDENT | C13: 2020 | D13: M9 | E13: 2.0200921e+17 | F13: 18 | G13: 13826562 | H13: 1440320 | J13: IND | K13: INDIVIDUAL | N13: LOZANO, MONICA | O13: P | Q13: P | R13: MONICA | T13: LOZANO | V13: 5610 GOLDEN GATE AVE | X13: OAKLAND | Y13: CA | Z13: 946182113 | AA13: COLLEGE FUTURES FOUNDATION | AB13: EXECUTIVE | AD13: 15J | AE13: MEMO (FILER'S % OF CONTRIBUTION GIVEN TO JOIN | AG13: X | AI13: 43952 | AJ13: 2800 | AK13: 5600 | BG13: G2020 | BI13: GENERAL | BJ13: 2020 | BK13: A | BL13: ADD | BM13: ITEMIZED RECEIPTS | BN13: 44104.185 | BP13: 9226555 | BQ13: SA18 | BR13: F3P | BS13: 4.0922202e+18 | BT13: t | BU13: * BIDEN VICTORY FUND | BV13: 2020 | BW13: SA | BY13: 4.0930202e+18 | BZ13: http://docquery.fec.gov/cgi-bin/fecimg/?202009209276532811 | CA13: Transfers From Other Authorized Committees
A14: C00003988 | B14: NEBRASKA DEMOCRATIC PARTY | C14: 2020 | D14: 30G | E14: 2.0210513e+17 | F14: 11AI | G14: 11AI-000268859 | H14: 1515964 | J14: IND | K14: INDIVIDUAL | N14: LOZANO, MONICA | O14: Y | Q14: U | R14: MONICA | T14: LOZANO | V14: 5610 GOLDEN GATE AVENUE | X14: OAKLAND | Y14: CA | Z14: 94618 | AA14: COLLEGE FUTURES FOUNDATION | AB14: EXECUTIVE | AD14: 15J | AE14: MEMO (FILER'S % OF CONTRIBUTION GIVEN TO JOIN | AG14: X | AI14: 44086 | AJ14: 636.67 | AK14: 636.67 | BG14: P | BI14: PRIMARY | BK14: N | BL14: NO CHANGE | BM14: ITEMIZED RECEIPTS | BN14: 44330.15 | BR14: F3X | BS14: 4.0513202e+18 | BT14: t | BU14: BIDEN VICTORY FUND | BV14: 2020 | BW14: SA | BY14: 4.0514202e+18 | BZ14: https://docquery.fec.gov/cgi-bin/fecimg/?202105129446683762 | CA14: Contributions From Individuals/Persons Other Than Political Committees
A15: C00178038 | B15: NEW HAMPSHIRE DEMOCRATIC PARTY | C15: 2020 | D15: 30G | E15: 2.0210223e+17 | F15: 12 | G15: 10874206 | H15: 1501777 | J15: IND | K15: INDIVIDUAL | N15: LOZANO, MONICA | O15: Y | Q15: U | R15: MONICA | T15: LOZANO | V15: 5610 GOLDEN GATE AVE | X15: OAKLAND | Y15: CA | Z15: 946182113 | AA15: COLLEGE FUTURES FOUNDATION | AB15: EXECUTIVE | AD15: 15J | AE15: MEMO (FILER'S % OF CONTRIBUTION GIVEN TO JOIN | AG15: X | AI15: 44086 | AJ15: 636.67 | AK15: 636.67 | BG15: P | BI15: PRIMARY | BK15: N | BL15: NO CHANGE | BM15: ITEMIZED RECEIPTS | BN15: 44258.579 | BP15: 10873130 | BQ15: SA12 | BR15: F3X | BS15: 4.0223202e+18 | BT15: t | BU15: * BIDEN VICTORY FUND 2020 | BV15: 2020 | BW15: SA | BY15: 4.0302202e+18 | BZ15: https://docquery.fec.gov/cgi-bin/fecimg/?202102229428801573 | CA15: Transfers from Authorized Committees
A16: C00476523 | B16: KAREN BASS FOR CONGRESS | C16: 2020 | D16: Q3 | E16: 2.0201016e+17 | F16: 11AI | G16: VTE63YA8GG5 | H16: 1450186 | J16: IND | K16: INDIVIDUAL | N16: LOZANO, MONICA | O16: H | Q16: P | R16: MONICA | T16: LOZANO | V16: 5610 GOLDEN GATE AVE | X16: OAKLAND | Y16: CA | Z16: 946182113 | AA16: COLLEGE FUTURES FOUNDATION | AB16: CEO | AD16: 15 | AE16: CONTRIBUTION | AI16: 44035 | AJ16: 1000 | AK16: 1000 | BG16: G2020 | BI16: GENERAL | BJ16: 2020 | BK16: A | BL16: ADD | BM16: ITEMIZED RECEIPTS | BN16: 44121.716 | BR16: F3 | BS16: 4.1016202e+18 | BT16: t | BV16: 2020 | BW16: SA | BY16: 4.1016202e+18 | BZ16: http://docquery.fec.gov/cgi-bin/fecimg/?202010159294319294 | CA16: Contributions From Individuals/Persons Other Than Political Committees
A17: C00025254 | B17: MINNESOTA DEMOCRATIC-FARMER-LABOR PARTY | C17: 2020 | D17: 30G | E17: 2.0210506e+17 | F17: 12 | G17: 4043683 | H17: 1515204 | J17: IND | K17: INDIVIDUAL | N17: LOZANO, MONICA | O17: Y | Q17: U | R17: MONICA | T17: LOZANO | V17: 5610 GOLDEN GATE AVE | X17: OAKLAND | Y17: CA | Z17: 946182113 | AA17: COLLEGE FUTURES FOUNDATION | AB17: EXECUTIVE | AD17: 15J | AE17: MEMO (FILER'S % OF CONTRIBUTION GIVEN TO JOIN | AG17: X | AI17: 44086 | AJ17: 636.67 | AK17: 636.67 | BG17: P | BI17: PRIMARY | BK17: N | BL17: NO CHANGE | BM17: ITEMIZED RECEIPTS | BN17: 44324.199 | BP17: 4035333 | BQ17: SA12 | BR17: F3X | BS17: 4.0506202e+18 | BT17: t | BU17: * BIDEN VICTORY FUND | BV17: 2020 | BW17: SA | BY17: 4.0508202e+18 | BZ17: https://docquery.fec.gov/cgi-bin/fecimg/?202105059446293282 | CA17: Transfers from Authorized Committees
A18: C00744946 | B18: BIDEN VICTORY FUND | C18: 2020 | D18: Q2 | E18: 2.0201013e+17 | F18: 11AI | G18: 4527488 | H18: 1446418 | J18: IND | K18: INDIVIDUAL | N18: LOZANO, MONICA | O18: N | Q18: J | R18: MONICA | T18: LOZANO | V18: 5610 GOLDEN GATE AVE | X18: OAKLAND | Y18: CA | Z18: 946182113 | AA18: COLLEGE FUTURES FOUNDATION | AB18: CEO | AD18: 15 | AE18: CONTRIBUTION | AI18: 43952 | AJ18: 2800 | AK18: 2800 | BG18: P | BI18: PRIMARY | BK18: A | BL18: ADD | BM18: ITEMIZED RECEIPTS | BN18: 44125.152 | BR18: F3X | BS18: 4.1013202e+18 | BT18: t | BV18: 2020 | BW18: SA | BY18: 4.1021202e+18 | BZ18: http://docquery.fec.gov/cgi-bin/fecimg/?202010129285124833 | CA18: Contributions From Individuals/Persons Other Than Political Committees
A19: C00019331 | B19: DEMOCRATIC PARTY OF WISCONSIN | C19: 2020 | D19: 12G | E19: 2.0210519e+17 | F19: 11AI | G19: 11AI-001044851 | H19: 1516754 | J19: IND | K19: INDIVIDUAL | N19: LOZANO, MONICA | O19: Y | Q19: U | R19: MONICA | T19: LOZANO | V19: 5610 GOLDEN GATE AVENUE | X19: OAKLAND | Y19: CA | Z19: 94618 | AA19: COLLEGE FUTURES FOUNDATION | AB19: EXECUTIVE | AD19: 15J | AE19: MEMO (FILER'S % OF CONTRIBUTION GIVEN TO JOIN | AG19: X | AI19: 44086 | AJ19: 636.66 | AK19: 636.66 | BG19: P | BI19: PRIMARY | BK19: N | BL19: NO CHANGE | BM19: ITEMIZED RECEIPTS | BN19: 44343.161 | BR19: F3X | BS19: 4.0519202e+18 | BT19: t | BU19: BIDEN VICTORY FUND | BV19: 2020 | BW19: SA | BY19: 4.0527202e+18 | BZ19: https://docquery.fec.gov/cgi-bin/fecimg/?202105189446939171 | CA19: Contributions From Individuals/Persons Other Than Political Committees
A20: C00099267 | B20: TEXAS DEMOCRATIC PARTY | C20: 2020 | D20: 30G | E20: 2.0210521e+17 | F20: 11AI | G20: 11AI-000790088 | H20: 1517435 | J20: IND | K20: INDIVIDUAL | N20: LOZANO, MONICA | O20: Y | Q20: U | R20: MONICA | T20: LOZANO | V20: 5610 GOLDEN GATE AVENUE | X20: OAKLAND | Y20: CA | Z20: 94618 | AA20: COLLEGE FUTURES FOUNDATION | AB20: EXECUTIVE | AD20: 15J | AE20: MEMO (FILER'S % OF CONTRIBUTION GIVEN TO JOIN | AG20: X | AI20: 44086 | AJ20: 636.66 | AK20: 636.66 | BG20: P | BI20: PRIMARY | BK20: N | BL20: NO CHANGE | BM20: ITEMIZED RECEIPTS | BN20: 44343.161 | BR20: F3X | BS20: 4.0521202e+18 | BT20: t | BU20: BIDEN VICTORY FUND | BV20: 2020 | BW20: SA | BY20: 4.0527202e+18 | BZ20: https://docquery.fec.gov/cgi-bin/fecimg/?202105209447029705 | CA20: Contributions From Individuals/Persons Other Than Political Committees
A21: C00099267 | B21: TEXAS DEMOCRATIC PARTY | C21: 2020 | D21: 30G | E21: 2.0210521e+17 | F21: 11AI | G21: 11AI-000792313 | H21: 1517435 | J21: IND | K21: INDIVIDUAL | N21: LOZANO, MONICA | O21: Y | Q21: U | R21: MONICA | T21: LOZANO | V21: 5610 GOLDEN GATE AVENUE | X21: OAKLAND | Y21: CA | Z21: 94618 | AA21: COLLEGE FUTURES FOUNDATION | AB21: EXECUTIVE | AD21: 15J | AE21: MEMO (FILER'S % OF CONTRIBUTION GIVEN TO JOIN | AG21: X | AI21: 44086 | AJ21: 636.66 | AK21: 1273.32 | BG21: P | BI21: PRIMARY | BK21: N | BL21: NO CHANGE | BM21: ITEMIZED RECEIPTS | BN21: 44343.161 | BR21: F3X | BS21: 4.0521202e+18 | BT21: t | BU21: BIDEN VICTORY FUND | BV21: 2020 | BW21: SA | BY21: 4.0527202e+18 | BZ21: https://docquery.fec.gov/cgi-bin/fecimg/?202105209447030233 | CA21: Contributions From Individuals/Persons Other Than Political Committees
A22: C00744946 | B22: BIDEN VICTORY FUND | C22: 2020 | D22: Q3 | E22: 2.0210115e+17 | F22: 11AI | G22: 8123540 | H22: 1487959 | J22: IND | K22: INDIVIDUAL | N22: LOZANO, MONICA | O22: N | Q22: J | R22: MONICA | T22: LOZANO | V22: 5610 GOLDEN GATE AVE | X22: OAKLAND | Y22: CA | Z22: 946182113 | AA22: COLLEGE FUTURES FOUNDATION | AB22: EXECUTIVE | AD22: 15 | AE22: CONTRIBUTION | AI22: 44035 | AJ22: 25000 | AK22: 27800 | BG22: P | BI22: PRIMARY | BK22: A | BL22: ADD | BM22: ITEMIZED RECEIPTS | BN22: 44231.431 | BR22: F3X | BS22: 4.0115202e+18 | BT22: t | BV22: 2020 | BW22: SA | BY22: 4.0203202e+18 | BZ22: https://docquery.fec.gov/cgi-bin/fecimg/?202101149404578135 | CA22: Contributions From Individuals/Persons Other Than Political Committees
A23: C00744946 | B23: BIDEN VICTORY FUND | C23: 2020 | D23: Q3 | E23: 2.0210115e+17 | F23: 11AI | G23: 14460924 | H23: 1487959 | J23: IND | K23: INDIVIDUAL | N23: LOZANO, MONICA | O23: N | Q23: J | R23: MONICA | T23: LOZANO | V23: 5610 GOLDEN GATE AVE | X23: OAKLAND | Y23: CA | Z23: 946182113 | AA23: COLLEGE FUTURES FOUNDATION | AB23: EXECUTIVE | AD23: 15 | AE23: CONTRIBUTION | AI23: 44086 | AJ23: 20000 | AK23: 47850 | BG23: P | BI23: PRIMARY | BK23: A | BL23: ADD | BM23: ITEMIZED RECEIPTS | BN23: 44231.432 | BR23: F3X | BS23: 4.0115202e+18 | BT23: t | BV23: 2020 | BW23: SA | BY23: 4.0203202e+18 | BZ23: https://docquery.fec.gov/cgi-bin/fecimg/?202101149404627361 | CA23: Contributions From Individuals/Persons Other Than Political Committees
A24: C00744946 | B24: BIDEN VICTORY FUND | C24: 2020 | D24: Q3 | E24: 2.0210115e+17 | F24: 11AI | G24: 9708302 | H24: 1487959 | J24: IND | K24: INDIVIDUAL | N24: LOZANO, MONICA | O24: N | Q24: J | R24: MONICA | T24: LOZANO | V24: 5610 GOLDEN GATE AVE | X24: OAKLAND | Y24: CA | Z24: 946182113 | AA24: COLLEGE FUTURES FOUNDATION | AB24: EXECUTIVE | AD24: 15 | AE24: CONTRIBUTION | AI24: 44055 | AJ24: 50 | AK24: 27850 | BG24: P | BI24: PRIMARY | BK24: A | BL24: ADD | BM24: ITEMIZED RECEIPTS | BN24: 44231.433 | BR24: F3X | BS24: 4.0115202e+18 | BT24: t | BV24: 2020 | BW24: SA | BY24: 4.0203202e+18 | BZ24: https://docquery.fec.gov/cgi-bin/fecimg/?202101149404598724 | CA24: Contributions From Individuals/Persons Other Than Political Committees
A25: C00041269 | B25: GEORGIA FEDERAL ELECTIONS COMMITTEE | C25: 2020 | D25: M10 | E25: 2.0201204e+17 | F25: 12 | G25: 7327358 | H25: 1480291 | J25: IND | K25: INDIVIDUAL | N25: LOZANO, MONICA | O25: Y | Q25: U | R25: MONICA | T25: LOZANO | V25: 5610 GOLDEN GATE AVE | X25: OAKLAND | Y25: CA | Z25: 946182113 | AA25: COLLEGE FUTURES FOUNDATION | AB25: EXECUTIVE | AD25: 15J | AE25: MEMO (FILER'S % OF CONTRIBUTION GIVEN TO JOIN | AG25: X | AI25: 44086 | AJ25: 636.67 | AK25: 636.67 | BG25: P | BI25: PRIMARY | BK25: N | BL25: NO CHANGE | BM25: ITEMIZED RECEIPTS | BN25: 44175.153 | BP25: 7288843 | BQ25: SA12 | BR25: F3X | BS25: 4.1204202e+18 | BT25: t | BU25: * BIDEN VICTORY FUND | BV25: 2020 | BW25: SA | BY25: 4.1210202e+18 | BZ25: http://docquery.fec.gov/cgi-bin/fecimg/?202012039340789580 | CA25: Transfers from Authorized Committees
A26: C00031054 | B26: MICHIGAN DEMOCRATIC STATE CENTRAL COMMITTEE | C26: 2020 | D26: M10 | E26: 2.0210518e+17 | F26: 12 | G26: 5833017 | H26: 1516549 | J26: IND | K26: INDIVIDUAL | N26: LOZANO, MONICA | O26: Y | Q26: U | R26: MONICA | T26: LOZANO | V26: 5610 GOLDEN GATE AVE | X26: OAKLAND | Y26: CA | Z26: 946182113 | AA26: COLLEGE FUTURES FOUNDATION | AB26: EXECUTIVE | AD26: 15J | AE26: MEMO (FILER'S % OF CONTRIBUTION GIVEN TO JOIN | AG26: X | AI26: 44089 | AJ26: 636.67 | AK26: 636.67 | BG26: P | BI26: PRIMARY | BK26: N | BL26: NO CHANGE | BM26: ITEMIZED RECEIPTS | BN26: 44338.15 | BP26: 5831693 | BQ26: SA12 | BR26: F3X | BS26: 4.0518202e+18 | BT26: t | BU26: * BIDEN VICTORY FUND JOINT FUNDRAISING PROCEEDS | BV26: 2020 | BW26: SA | BY26: 4.0522202e+18 | BZ26: https://docquery.fec.gov/cgi-bin/fecimg/?202105179446836053 | CA26: Transfers from Authorized Committees
A27: C00005561 | B27: DEMOCRATIC EXECUTIVE COMMITTEE OF FLORIDA | C27: 2020 | D27: 12G | E27: 2.0210518e+17 | F27: 12 | G27: 2134975 | H27: 1516565 | J27: IND | K27: INDIVIDUAL | N27: LOZANO, MONICA | O27: Y | Q27: U | R27: MONICA | T27: LOZANO | V27: 5610 GOLDEN GATE AVE | X27: OAKLAND | Y27: CA | Z27: 946182113 | AA27: COLLEGE FUTURES FOUNDATION | AB27: EXECUTIVE | AD27: 15J | AE27: MEMO (FILER'S % OF CONTRIBUTION GIVEN TO JOIN | AG27: X | AI27: 44086 | AJ27: 636.67 | AK27: 636.67 | BG27: P | BI27: PRIMARY | BK27: A | BL27: ADD | BM27: ITEMIZED RECEIPTS | BN27: 44338.15 | BP27: 2171087 | BQ27: SA12 | BR27: F3X | BS27: 4.0519202e+18 | BT27: t | BU27: * BIDEN VICTORY FUND | BV27: 2020 | BW27: SA | BY27: 4.0522202e+18 | BZ27: https://docquery.fec.gov/cgi-bin/fecimg/?202105179446843583 | CA27: Transfers from Authorized Committees
A28: C00694455 | B28: KAMALA HARRIS FOR THE PEOPLE | C28: 2019 | D28: Q2 | E28: 2.0210728e+17 | F28: 17A | G28: 1807677 | H28: 1530939 | J28: IND | K28: INDIVIDUAL | N28: LOZANO, MONICA | O28: P | Q28: P | R28: MONICA | T28: LOZANO | V28: 5610 GOLDEN GATE AVE | X28: OAKLAND | Y28: CA | Z28: 946182113 | AA28: COLLEGE FUTURES FOUNDATION | AB28: CEO | AD28: 15 | AE28: CONTRIBUTION | AI28: 43593 | AJ28: 2800 | AK28: 2800 | BG28: P2020 | BI28: PRIMARY | BJ28: 2020 | BK28: A | BL28: ADD | BM28: ITEMIZED RECEIPTS | BN28: 44407.153 | BR28: F3P | BS28: 4.0728202e+18 | BT28: t | BV28: 2020 | BW28: SA | BY28: 4.0730202e+18 | BZ28: https://docquery.fec.gov/cgi-bin/fecimg/?202107279452029915 | CA28: Contributions From Individuals/Persons Other Than Political Committees
A29: C00208991 | B29: NEVADA STATE DEMOCRATIC PARTY | C29: 2020 | D29: 30G | E29: 2.0210532e+17 | F29: 11AI | G29: 11AI-000090538 | H29: 1518334 | J29: IND | K29: INDIVIDUAL | N29: LOZANO, MONICA | O29: Y | Q29: U | R29: MONICA | T29: LOZANO | V29: 5610 GOLDEN GATE AVENUE | X29: OAKLAND | Y29: CA | Z29: 94618 | AA29: COLLEGE FUTURES FOUNDATION | AB29: EXECUTIVE | AD29: 15J | AE29: MEMO (FILER'S % OF CONTRIBUTION GIVEN TO JOIN | AG29: X | AI29: 44086 | AJ29: 636.67 | AK29: 636.67 | BG29: P | BI29: PRIMARY | BK29: N | BL29: NO CHANGE | BM29: ITEMIZED RECEIPTS | BN29: 44351.158 | BR29: F3X | BS29: 4.0601202e+18 | BT29: t | BU29: BIDEN VICTORY FUND | BV29: 2020 | BW29: SA | BY29: 4.0603202e+18 | BZ29: https://docquery.fec.gov/cgi-bin/fecimg/?202105319447491129 | CA29: Contributions From Individuals/Persons Other Than Political Committees
A30: C00010603 | B30: DNC SERVICES CORP / DEMOCRATIC NATIONAL COMMITTEE | C30: 2020 | D30: M10 | E30: 2.0210225e+17 | F30: 12 | G30: 37440069 | H30: 1502017 | J30: IND | K30: INDIVIDUAL | N30: LOZANO, MONICA | O30: Y | Q30: U | R30: MONICA | T30: LOZANO | V30: 5610 GOLDEN GATE AVE | X30: OAKLAND | Y30: CA | Z30: 946182113 | AA30: COLLEGE FUTURES FOUNDATION | AB30: EXECUTIVE | AD30: 15J | AE30: MEMO (FILER'S % OF CONTRIBUTION GIVEN TO JOIN | AG30: X | AI30: 44055 | AJ30: 50 | AK30: 25050 | BG30: G2020 | BI30: GENERAL | BJ30: 2020 | BK30: A | BL30: ADD | BM30: ITEMIZED RECEIPTS | BN30: 44253.168 | BP30: 36773706 | BQ30: SA12 | BR30: F3X | BS30: 4.0226202e+18 | BT30: t | BU30: * BIDEN VICTORY FUND | BV30: 2020 | BW30: SA | BY30: 4.0226202e+18 | BZ30: https://docquery.fec.gov/cgi-bin/fecimg/?202102249428870928 | CA30: Transfers from Authorized Committees
A31: C00010603 | B31: DNC SERVICES CORP / DEMOCRATIC NATIONAL COMMITTEE | C31: 2020 | D31: M10 | E31: 2.0210225e+17 | F31: 12 | G31: 37448076 | H31: 1502017 | J31: IND | K31: INDIVIDUAL | N31: LOZANO, MONICA | O31: Y | Q31: U | R31: MONICA | T31: LOZANO | V31: 5610 GOLDEN GATE AVE | X31: OAKLAND | Y31: CA | Z31: 946182113 | AA31: COLLEGE FUTURES FOUNDATION | AB31: EXECUTIVE | AD31: 15J | AE31: MEMO (FILER'S % OF CONTRIBUTION GIVEN TO JOIN | AG31: X | AI31: 44086 | AJ31: 10450 | AK31: 35500 | BG31: G2020 | BI31: GENERAL | BJ31: 2020 | BK31: A | BL31: ADD | BM31: ITEMIZED RECEIPTS | BN31: 44253.169 | BP31: 37430300 | BQ31: SA12 | BR31: F3X | BS31: 4.0226202e+18 | BT31: t | BU31: * BIDEN VICTORY FUND | BV31: 2020 | BW31: SA | BY31: 4.0226202e+18 | BZ31: https://docquery.fec.gov/cgi-bin/fecimg/?202102249428873436 | CA31: Transfers from Authorized Committees
A32: C00166710 | B32: ARIZONA DEMOCRATIC PARTY | C32: 2020 | D32: 30G | E32: 2.0210305e+17 | F32: 11AI | G32: 11AI-000458119 | H32: 1502847 | J32: IND | K32: INDIVIDUAL | N32: LOZANO, MONICA | O32: Y | Q32: U | R32: MONICA | T32: LOZANO | V32: 5610 GOLDEN GATE AVENUE | X32: OAKLAND | Y32: CA | Z32: 94618 | AA32: COLLEGE FUTURES FOUNDATION | AB32: EXECUTIVE | AD32: 15J | AE32: MEMO (FILER'S % OF CONTRIBUTION GIVEN TO JOIN | AG32: X | AI32: 44086 | AJ32: 636.67 | AK32: 636.67 | BG32: P | BI32: PRIMARY | BK32: N | BL32: NO CHANGE | BM32: ITEMIZED RECEIPTS | BN32: 44261.156 | BR32: F3X | BS32: 4.0304202e+18 | BT32: t | BU32: BIDEN VICTORY FUND | BV32: 2020 | BW32: SA | BY32: 4.0306202e+18 | BZ32: https://docquery.fec.gov/cgi-bin/fecimg/?202103049440168791 | CA32: Contributions From Individuals/Persons Other Than Political Committees
A33: C00000935 | B33: DCCC | C33: 2020 | D33: M2 | E33: 2.0210324e+17 | F33: 11AI | G33: 28575715 | H33: 1506046 | J33: IND | K33: INDIVIDUAL | L33: C00401224 | N33: LOZANO, MONICA | O33: Y | Q33: U | R33: MONICA | T33: LOZANO | V33: 5610 GOLDEN GATE AVE | X33: OAKLAND | Y33: CA | Z33: 946182113 | AA33: COLLEGE FUTURES FOUNDATION | AB33: CEO | AC33: C00401224 | AD33: 15E | AE33: EARMARKED CONTRIBUTION | AI33: 43861 | AJ33: 250 | AK33: 250 | BG33: P | BI33: PRIMARY | BK33: N | BL33: NO CHANGE | BM33: ITEMIZED RECEIPTS | BN33: 44285.435 | BP33: 28575715E | BQ33: SA11AI | BR33: F3X | BS33: 4.0324202e+18 | BT33: t | BU33: * EARMARKED CONTRIBUTION: SEE BELOW EARMARKED THROUGH ACTBLUE | BV33: 2020 | BW33: SA | BY33: 4.0330202e+18 | BZ33: https://docquery.fec.gov/cgi-bin/fecimg/?202103239441845195 | CA33: Contributions From Individuals/Persons Other Than Political Committees
A34: C00167130 | B34: PENNSYLVANIA DEMOCRATIC PARTY | C34: 2020 | D34: M10 | E34: 2.0210332e+17 | F34: 11AI | G34: 11AI-000118199 | H34: 1506833 | J34: IND | K34: INDIVIDUAL | N34: LOZANO, MONICA | O34: Y | P34: C | Q34: U | R34: MONICA | T34: LOZANO | V34: 5610 GOLDEN GATE AVENUE | X34: OAKLAND | Y34: CA | Z34: 94618 | AA34: COLLEGE FUTURES FOUNDATION | AB34: EXECUTIVE | AD34: 15J | AE34: MEMO (FILER'S % OF CONTRIBUTION GIVEN TO JOIN | AG34: X | AI34: 44086 | AJ34: 636.66 | AK34: 636.66 | BG34: P | BI34: PRIMARY | BK34: N | BL34: NO CHANGE | BM34: ITEMIZED RECEIPTS | BN34: 44288.167 | BR34: F3X | BS34: 4.0401202e+18 | BT34: t | BU34: BIDEN VICTORY FUND | BV34: 2020 | BW34: SA | BY34: 4.0402202e+18 | BZ34: https://docquery.fec.gov/cgi-bin/fecimg/?202103319442966697 | CA34: Contributions From Individuals/Persons Other Than Political Committees
V36: =+V34&X34&Y34&Z34 -> 5610 GOLDEN GATE AVENUEOAKLANDCA94618
A39: Row Labels | B39: Sum of contribution_receipt_amount
A40: ACTBLUE | B40: 100 | C40: D
A41: AMY FOR AMERICA | B41: 1000 | C41: D
A42: ARIZONA DEMOCRATIC PARTY | B42: 636.67 | C42: D
A43: BIDEN FOR PRESIDENT | B43: 5600 | C43: D
A44: BIDEN VICTORY FUND | B44: 47850 | C44: D
A45: CISNEROS FOR CONGRESS | B45: 500 | C45: D
A46: COLORADO DEMOCRATIC PARTY | B46: 636.67 | C46: D
A47: DCCC | B47: 250 | C47: D
A48: DEMOCRATIC EXECUTIVE COMMITTEE OF FLORIDA | B48: 636.67 | C48: D
A49: DEMOCRATIC PARTY OF VIRGINIA | B49: 636.66 | C49: D
A50: DEMOCRATIC PARTY OF WISCONSIN | B50: 636.66 | C50: D
A51: DNC SERVICES CORP / DEMOCRATIC NATIONAL COMMITTEE | B51: 35500 | C51: D
... A64: XOCHITL FOR NEW MEXICO | B64: 250 | C64: D
A65: Grand Total | B65: 105036.66

Sheet Linda Hudson
A1: committee_id | B1: committee_name | C1: report_year | D1: report_type | E1: image_number | F1: line_number | G1: transaction_id | H1: file_number | I1: committee_name | J1: entity_type | K1: entity_type_desc | L1: unused_contbr_id | M1: contributor_prefix | N1: contributor_name | O1: recipient_committee_type | P1: recipient_committee_org_type | Q1: recipient_committee_designation | R1: contributor_first_name | S1: contributor_middle_name | T1: contributor_last_name | U1: contributor_suffix | V1: contributor_street_1 | W1: contributor_street_2 | X1: contributor_city | Y1: contributor_state | Z1: contributor_zip | AA1: contributor_employer | AB1: contributor_occupation | AC1: contributor_id | AD1: receipt_type | AE1: receipt_type_desc | AF1: receipt_type_full | AG1: memo_code | AH1: memo_code_full | AI1: contribution_receipt_date | AJ1: contribution_receipt_amount | AK1: contributor_aggregate_ytd | AL1: candidate_id | AM1: candidate_name | AN1: candidate_first_name | AO1: candidate_last_name | AP1: candidate_middle_name | AQ1: candidate_prefix | AR1: candidate_suffix | AS1: candidate_office | AT1: candidate_office_full | AU1: candidate_office_state | AV1: candidate_office_state_full | AW1: candidate_office_district | AX1: conduit_committee_id | AY1: conduit_committee_name | AZ1: conduit_committee_street1 | BA1: conduit_committee_street2 | BB1: conduit_committee_city | BC1: conduit_committee_state | BD1: conduit_committee_zip | BE1: donor_committee_name | BF1: national_committee_nonfederal_account | BG1: election_type | BH1: election_type_full | BI1: fec_election_type_desc | BJ1: fec_election_year | BK1: amendment_indicator | BL1: amendment_indicator_desc | BM1: schedule_type_full | BN1: load_date | BO1: original_sub_id | BP1: back_reference_transaction_id | BQ1: back_reference_schedule_name | BR1: filing_form | BS1: link_id | BT1: is_individual | BU1: memo_text | BV1: two_year_transaction_period | BW1: schedule_type | BX1: increased_limit | BY1: sub_id | BZ1: pdf_url | CA1: line_number_label
A2: C00641381 | B2: MCCREADY FOR CONGRESS | C2: 2019 | D2: Q2 | E2: 2.0190814e+17 | F2: 11AI | G2: VTEP0X1NDF4 | H2: 1347570 | J2: IND | K2: INDIVIDUAL | N2: HUDSON, LINDA | O2: H | Q2: P | R2: LINDA | T2: HUDSON | V2: 156 BALLANTYNE COUNTRY CLUB DR | X2: CHARLOTTE | Y2: NC | Z2: 28201 | AA2: THE CARDEA GROUP | AB2: EXECUTIVE | AD2: 15 | AE2: CONTRIBUTION | AI2: 43628 | AJ2: 500 | AK2: 500 | BG2: S2019 | BH2: SPECIAL GENERAL | BI2: SPECIAL | BJ2: 2019 | BK2: N | BL2: NO CHANGE | BM2: ITEMIZED RECEIPTS | BN2: 43692.11 | BR2: F3 | BS2: 4.0813202e+18 | BT2: t | BV2: 2020 | BW2: SA | BY2: 4.0814202e+18 | BZ2: http://docquery.fec.gov/cgi-bin/fecimg/?201908139162850079 | CA2: Contributions From Individuals/Persons Other Than Political Committees
A3: C00709410 | B3: CAL FOR NC | C3: 2020 | D3: Q2 | E3: 2.0201202e+17 | F3: 11AI | G3: VVC0QRVGNC5 | H3: 1475417 | J3: IND | K3: INDIVIDUAL | N3: HUDSON, LINDA | O3: S | Q3: P | R3: LINDA | T3: HUDSON | V3: 15611 BALLANTYNE COUNTRY CLUB DR | X3: CHARLOTTE | Y3: NC | Z3: 282771406 | AA3: THE CARDEA GROUP | AB3: CHAIRMAN | AD3: 15E | AE3: EARMARKED CONTRIBUTION | AI3: 43986 | AJ3: 1000 | AK3: 1000 | BG3: G2020 | BI3: GENERAL | BJ3: 2020 | BK3: A | BL3: ADD | BM3: ITEMIZED RECEIPTS | BN3: 44177.153 | BP3: VVC0QRVGNC5E | BQ3: SA11AI | BR3: F3 | BS3: 4.1202202e+18 | BT3: t | BU3: * EARMARKED CONTRIBUTION: SEE BELOW | BV3: 2020 | BW3: SA | BY3: 4.1212202e+18 | BZ3: http://docquery.fec.gov/cgi-bin/fecimg/?202012019337317795 | CA3: Contributions From Individuals/Persons Other Than Political Committees
A4: C00709410 | B4: CAL FOR NC | C4: 2020 | D4: Q3 | E4: 2.0201202e+17 | F4: 11AI | G4: VVC0QTXBWE8 | H4: 1475453 | J4: IND | K4: INDIVIDUAL | N4: HUDSON, LINDA | O4: S | Q4: P | R4: LINDA | T4: HUDSON | V4: 15611 BALLANTYNE COUNTRY CLUB DR | X4: CHARLOTTE | Y4: NC | Z4: 282771406 | AA4: THE CARDEA GROUP | AB4: CHAIRMAN | AD4: 15E | AE4: EARMARKED CONTRIBUTION | AI4: 44083 | AJ4: 1000 | AK4: 2000 | BG4: G2020 | BI4: GENERAL | BJ4: 2020 | BK4: A | BL4: ADD | BM4: ITEMIZED RECEIPTS | BN4: 44189.169 | BP4: VVC0QTXBWE8E | BQ4: SA11AI | BR4: F3 | BS4: 4.1202202e+18 | BT4: t | BU4: * EARMARKED CONTRIBUTION: SEE BELOW | BV4: 2020 | BW4: SA | BY4: 4.1224202e+18 | BZ4: https://docquery.fec.gov/cgi-bin/fecimg/?202012019337362836 | CA4: Contributions From Individuals/Persons Other Than Political Committees
AJ5: =SUM(AJ2:AJ4) -> 2500
V6: =+V4&X4&Y4&Z4 -> 15611 BALLANTYNE COUNTRY CLUB DRCHARLOTTENC282771406
B7: MCCREADY FOR CONGRESS | D7: D
B8: CAL FOR NC | D8: D

Sheet Brian Moynihan
A1: committee_id | B1: committee_name | C1: report_year | D1: report_type | E1: image_number | F1: line_number | G1: transaction_id | H1: file_number | I1: committee_name | J1: entity_type | K1: entity_type_desc | L1: unused_contbr_id | M1: contributor_prefix | N1: contributor_name | O1: recipient_committee_type | P1: recipient_committee_org_type | Q1: recipient_committee_designation | R1: contributor_first_name | S1: contributor_middle_name | T1: contributor_last_name | U1: contributor_suffix | V1: contributor_street_1 | W1: contributor_street_2 | X1: contributor_city | Y1: contributor_state | Z1: contributor_zip | AA1: contributor_employer | AB1: contributor_occupation | AC1: contributor_id | AD1: receipt_type | AE1: receipt_type_desc | AF1: receipt_type_full | AG1: memo_code | AH1: memo_code_full | AI1: contribution_receipt_date | AJ1: contribution_receipt_amount | AK1: contributor_aggregate_ytd | AL1: candidate_id | AM1: candidate_name | AN1: candidate_first_name | AO1: candidate_last_name | AP1: candidate_middle_name | AQ1: candidate_prefix | AR1: candidate_suffix | AS1: candidate_office | AT1: candidate_office_full | AU1: candidate_office_state | AV1: candidate_office_state_full | AW1: candidate_office_district | AX1: conduit_committee_id | AY1: conduit_committee_name | AZ1: conduit_committee_street1 | BA1: conduit_committee_street2 | BB1: conduit_committee_city | BC1: conduit_committee_state | BD1: conduit_committee_zip | BE1: donor_committee_name | BF1: national_committee_nonfederal_account | BG1: election_type | BH1: election_type_full | BI1: fec_election_type_desc | BJ1: fec_election_year | BK1: amendment_indicator | BL1: amendment_indicator_desc | BM1: schedule_type_full | BN1: load_date | BO1: original_sub_id | BP1: back_reference_transaction_id | BQ1: back_reference_schedule_name | BR1: filing_form | BS1: link_id | BT1: is_individual | BU1: memo_text | BV1: two_year_transaction_period | BW1: schedule_type | BX1: increased_limit | BY1: sub_id | BZ1: pdf_url | CA1: line_number_label
A2: C00364778 | B2: BANK OF AMERICA CORPORATION FEDERAL PAC | C2: 2019 | D2: M6 | E2: 2.0190803e+17 | F2: 11AI | G2: A2019-1081936 | H2: 1346683 | J2: IND | K2: INDIVIDUAL | N2: MOYNIHAN, BRIAN T | O2: Q | P2: C | Q2: B | R2: BRIAN | S2: T | T2: MOYNIHAN | V2: 100 N TRYON ST | X2: CHARLOTTE | Y2: NC | Z2: 28255 | AA2: BANK OF AMERICA | AB2: CHAIRMAN AND CEO | AD2: 15 | AE2: CONTRIBUTION | AI2: 43601 | AJ2: 5000 | AK2: 5000 | BG2: P | BI2: PRIMARY | BK2: N | BL2: NO CHANGE | BM2: ITEMIZED RECEIPTS | BN2: 43680.113 | BR2: F3X | BS2: 4.0802202e+18 | BT2: t | BV2: 2020 | BW2: SA | BY2: 4.0802202e+18 | BZ2: http://docquery.fec.gov/cgi-bin/fecimg/?201908029161350986 | CA2: Contributions From Individuals/Persons Other Than Political Committees
V5: =+V2&X2&Y2&Z2 -> 100 N TRYON STCHARLOTTENC28255

Sheet Jack O. Bovender
A1: committee_id | B1: committee_name | C1: report_year | D1: report_type | E1: image_number | F1: line_number | G1: transaction_id | H1: file_number | I1: committee_name | J1: entity_type | K1: entity_type_desc | L1: unused_contbr_id | M1: contributor_prefix | N1: contributor_name | O1: recipient_committee_type | P1: recipient_committee_org_type | Q1: recipient_committee_designation | R1: contributor_first_name | S1: contributor_middle_name | T1: contributor_last_name | U1: contributor_suffix | V1: contributor_street_1 | W1: contributor_street_2 | X1: contributor_city | Y1: contributor_state | Z1: contributor_zip | AA1: contributor_employer | AB1: contributor_occupation | AC1: contributor_id | AD1: receipt_type | AE1: receipt_type_desc | AF1: receipt_type_full | AG1: memo_code | AH1: memo_code_full | AI1: contribution_receipt_date | AJ1: contribution_receipt_amount | AK1: contributor_aggregate_ytd | AL1: candidate_id | AM1: candidate_name | AN1: candidate_first_name | AO1: candidate_last_name | AP1: candidate_middle_name | AQ1: candidate_prefix | AR1: candidate_suffix | AS1: candidate_office | AT1: candidate_office_full | AU1: candidate_office_state | AV1: candidate_office_state_full | AW1: candidate_office_district | AX1: conduit_committee_id | AY1: conduit_committee_name | AZ1: conduit_committee_street1 | BA1: conduit_committee_street2 | BB1: conduit_committee_city | BC1: conduit_committee_state | BD1: conduit_committee_zip | BE1: donor_committee_name | BF1: national_committee_nonfederal_account | BG1: election_type | BH1: election_type_full | BI1: fec_election_type_desc | BJ1: fec_election_year | BK1: amendment_indicator | BL1: amendment_indicator_desc | BM1: schedule_type_full | BN1: load_date | BO1: original_sub_id | BP1: back_reference_transaction_id | BQ1: back_reference_schedule_name | BR1: filing_form | BS1: link_id | BT1: is_individual | BU1: memo_text | BV1: two_year_transaction_period | BW1: schedule_type | BX1: increased_limit | BY1: sub_id | BZ1: pdf_url | CA1: line_number_label
A2: C00718627 | B2: TEAM HAGERTY | C2: 2019 | D2: Q3 | E2: 2.0191016e+17 | F2: 11AI | G2: AAF2B069FA3BD497E83C | H2: 1358443 | J2: IND | K2: INDIVIDUAL | N2: BOVENDER, JR., JACK O. | O2: S | Q2: P | R2: JACK O. | T2: BOVENDER, JR. | V2: 520 BELLE MEADE BLVD | X2: NASHVILLE | Y2: TN | Z2: 372053424 | AA2: RETIRED | AB2: RETIRED | AD2: 15 | AE2: CONTRIBUTION | AI2: 43731 | AJ2: 2800 | AK2: 5600 | BG2: G2020 | BI2: GENERAL | BJ2: 2020 | BK2: A | BL2: ADD | BM2: ITEMIZED RECEIPTS | BN2: 43763.113 | BR2: F3 | BS2: 4.1015202e+18 | BT2: t | BV2: 2020 | BW2: SA | BY2: 4.1024202e+18 | BZ2: http://docquery.fec.gov/cgi-bin/fecimg/?201910159164272166 | CA2: Contributions From Individuals/Persons Other Than Political Committees
A3: C00718627 | B3: TEAM HAGERTY | C3: 2019 | D3: Q3 | E3: 2.0191016e+17 | F3: 11AI | G3: A6F8ECAFE5CE141F79F8 | H3: 1358443 | J3: IND | K3: INDIVIDUAL | N3: BOVENDER, JR., JACK O. | O3: S | Q3: P | R3: JACK O. | T3: BOVENDER, JR. | V3: 520 BELLE MEADE BLVD | X3: NASHVILLE | Y3: TN | Z3: 372053424 | AA3: RETIRED | AB3: RETIRED | AD3: 15 | AE3: CONTRIBUTION | AI3: 43731 | AJ3: 2800 | AK3: 5600 | BG3: P2020 | BI3: PRIMARY | BJ3: 2020 | BK3: A | BL3: ADD | BM3: ITEMIZED RECEIPTS | BN3: 43763.113 | BR3: F3 | BS3: 4.1015202e+18 | BT3: t | BV3: 2020 | BW3: SA | BY3: 4.1024202e+18 | BZ3: http://docquery.fec.gov/cgi-bin/fecimg/?201910159164272261 | CA3: Contributions From Individuals/Persons Other Than Political Committees
A4: C00027466 | B4: NRSC | C4: 2019 | D4: M10 | E4: 2.0191021e+17 | F4: 11AI | G4: SA11A.14219924 | H4: 1360336 | J4: IND | K4: INDIVIDUAL | M4: MR. | N4: BOVENDER, JACK O. MR. JR. | O4: Y | Q4: U | R4: JACK | S4: O. | T4: BOVENDER | U4: JR. | V4: 520 BELLE MEADE BLVD | X4: NASHVILLE | Y4: TN | Z4: 372053424 | AA4: RETIRED | AB4: RETIRED | AD4: 15 | AE4: CONTRIBUTION | AF4: CONTRIBUTION | AI4: 43731 | AJ4: 35500 | AK4: 35500 | BG4: P | BI4: PRIMARY | BK4: A | BL4: ADD | BM4: ITEMIZED RECEIPTS | BN4: 43769.114 | BR4: F3X | BS4: 4.1020202e+18 | BT4: t | BV4: 2020 | BW4: SA | BY4: 4.1030202e+18 | BZ4: http://docquery.fec.gov/cgi-bin/fecimg/?201910209165196132 | CA4: Contributions From Individuals/Persons Other Than Political Committees
A5: C00314575 | B5: COLLINS FOR SENATOR | C5: 2020 | D5: Q3 | E5: 2.0210631e+17 | F5: 11AI | G5: AFE6E99BABCBC45C98DE | H5: 1521918 | J5: IND | K5: INDIVIDUAL | N5: BOVENDER, JACK | O5: S | Q5: P | R5: JACK | T5: BOVENDER | V5: 520 BELLE MEADE BLVD | X5: NASHVILLE | Y5: TN | Z5: 372053424 | AA5: HCA | AB5: EXECUTIVE | AD5: 15 | AE5: CONTRIBUTION | AI5: 44025 | AJ5: 2800 | AK5: 2800 | BG5: P2020 | BI5: PRIMARY | BJ5: 2020 | BK5: A | BL5: ADD | BM5: ITEMIZED RECEIPTS | BN5: 44384.149 | BR5: F3 | BS5: 4.0701202e+18 | BT5: t | BV5: 2020 | BW5: SA | BY5: 4.0707202e+18 | BZ5: https://docquery.fec.gov/cgi-bin/fecimg/?202106309450865950 | CA5: Contributions From Individuals/Persons Other Than Political Committees
A6: C00750505 | B6: STANDING WITH CONSERVATIVES | C6: 2020 | D6: M8 | E6: 2.0200821e+17 | F6: 11AI | G6: SA11AI.4232 | H6: 1434635 | J6: IND | K6: INDIVIDUAL | N6: BOVENDER, JACK O. JR. | O6: O | Q6: U | R6: JACK | S6: O. | T6: BOVENDER | U6: JR. | V6: 520 BELLE MEADE BLVD | X6: NASHVILLE | Y6: TN | Z6: 37205 | AA6: RETIRED | AB6: RETIRED | AD6: 10 | AE6: NON-FEDERAL RECEIPT FROM PERSONS | AI6: 44039 | AJ6: 20000 | AK6: 20000 | BG6: P | BI6: PRIMARY | BK6: A | BL6: ADD | BM6: ITEMIZED RECEIPTS | BN6: 44075.182 | BR6: F3X | BS6: 4.0822202e+18 | BT6: t | BV6: 2020 | BW6: SA | BY6: 4.0901202e+18 | BZ6: http://docquery.fec.gov/cgi-bin/fecimg/?202008209266413628 | CA6: Contributions From Individuals/Persons Other Than Political Committees
A7: C00724344 | B7: NRSC TARGETED STATE VICTORY | C7: 2020 | D7: Q2 | E7: 2.0200716e+17 | F7: 11AI | G7: SA11AI.4334 | H7: 1422075 | J7: IND | K7: INDIVIDUAL | N7: BOVENDER, JACK O. JR. | O7: N | Q7: J | R7: JACK | S7: O. | T7: BOVENDER | U7: JR. | V7: 520 BELLE MEADE BLVD | X7: NASHVILLE | Y7: TN | Z7: 37205 | AA7: RETIRED | AB7: RETIRED | AD7: 15 | AE7: CONTRIBUTION | AI7: 44008 | AJ7: 35500 | AK7: 35500 | BG7: P | BI7: PRIMARY | BK7: A | BL7: ADD | BM7: ITEMIZED RECEIPTS | BN7: 44029.117 | BR7: F3X | BS7: 4.0715202e+18 | BT7: t | BV7: 2020 | BW7: SA | BY7: 4.0716202e+18 | BZ7: http://docquery.fec.gov/cgi-bin/fecimg/?202007159244634217 | CA7: Contributions From Individuals/Persons Other Than Political Committees
A8: C00719971 | B8: SENATE EAGLE PAC | C8: 2020 | D8: Q2 | E8: 2.0200716e+17 | F8: 11AI | G8: ADA791344E6304AB5BD7 | H8: 1425049 | J8: IND | K8: INDIVIDUAL | N8: BOVENDER, JR., JACK O. | O8: Q | Q8: U | R8: JACK O. | T8: BOVENDER, JR. | V8: 520 BELLE MEADE BLVD | X8: NASHVILLE | Y8: TN | Z8: 372053424 | AA8: RETIRED | AB8: RETIRED | AD8: 15 | AE8: CONTRIBUTION | AI8: 43987 | AJ8: 5000 | AK8: 5000 | BG8: P | BI8: PRIMARY | BK8: A | BL8: ADD | BM8: ITEMIZED RECEIPTS | BN8: 44030.058 | BR8: F3X | BS8: 4.0716202e+18 | BT8: t | BV8: 2020 | BW8: SA | BY8: 4.0717202e+18 | BZ8: http://docquery.fec.gov/cgi-bin/fecimg/?202007159250150135 | CA8: Contributions From Individuals/Persons Other Than Political Committees
A9: C00027466 | B9: NRSC | C9: 2020 | D9: M7 | E9: 2.0200921e+17 | F9: 12 | G9: SA12.15788919 | H9: 1439993 | J9: IND | K9: INDIVIDUAL | N9: BOVENDER, JACK | O9: Y | Q9: U | R9: JACK | T9: BOVENDER | V9: 620 BELLE MEADE BLVD | X9: NASHVILLE | Y9: TN | Z9: 372053878 | AA9: RETIRED | AB9: RETIRED | AD9: 15J | AE9: MEMO (FILER'S % OF CONTRIBUTION GIVEN TO JOIN | AF9: TRANSFER | AG9: X | AI9: 44008 | AJ9: 35500 | AK9: 35500 | BG9: P | BI9: PRIMARY | BK9: A | BL9: ADD | BM9: ITEMIZED RECEIPTS | BN9: 44107.154 | BP9: SA12.15788904 | BQ9: SA12 | BR9: F3X | BS9: 4.0921202e+18 | BT9: t | BU9: JFC ATTRIB: NRSC TARGETED STATE VICTORY | BV9: 2020 | BW9: SA | BY9: 4.1003202e+18 | BZ9: http://docquery.fec.gov/cgi-bin/fecimg/?202009209275399018 | CA9: Transfers from Authorized Committees
V11: =+V9&X9&Y9&Z9 -> 620 BELLE MEADE BLVDNASHVILLETN372053878
A14: Row Labels | B14: Sum of contribution_receipt_amount
A15: COLLINS FOR SENATOR | B15: 2800 | C15: R
A16: NRSC | B16: 71000 | C16: R
A17: NRSC TARGETED STATE VICTORY | B17: 35500 | C17: R
A18: SENATE EAGLE PAC | B18: 5000 | C18: R
A19: STANDING WITH CONSERVATIVES | B19: 20000 | C19: R
A20: TEAM HAGERTY | B20: 5600 | C20: R
A21: Grand Total | B21: 139900

Sheet Company PAC
A1: From Open Secrets.com | D1: 2020
A2: Company PAC Name | D2: Political Affiliation | E2: Republican | F2: Democratic | G2: Independent | H2: %Republican | I2: %Democrat
A3: BANK OF AMERICA CORPORATION FEDERAL PAC | D3: N | H3: 0.5701 | I3: 0.4299
