Workbook

Sheet Board & Executives
A1: Company | B1: Board | C1: Exec | D1: Employer | E1: Fname | F1: MI | G1: Lname | H1: Gender | I1: State | J1: Age | K1: DOB | L1: Dem | M1: Rep | N1: Neutral | O1: Reg | P1: Address
A2: FORD | B2: Y | C2: N | D2: President Kimberly Casiano & Associates, | E2: Kimberly | F2: A | G2: Casiano | H2: F | I2: Puerto Rico | J2: 63 | Q2: Kimberly A Casiano | R2: No FEC Data
A3: FORD | B3: Y | C3: N | D3: Retired Executive Chairman of the Board Director PG&E Corporation | E3: Anthony | F3: F. | G3: Earley, Jr | H3: M | J3: 71 | L3: =+GETPIVOTDATA("contribution_receipt_amount",'Anthony Earley'!$B$35) -> 15100 | P3: 3926 OAKLAND DR BLOOMFIELD HILLS MI 48301 | Q3: Anthony F. Earley, Jr
A4: FORD | B4: Y | C4: Y | D4: A Director of Corporate Strategy, Ford Motor Company | E4: Alexandra | F4: Ford | G4: English | H4: F | J4: 33 | Q4: Alexandra Ford English | R4: No FEC Data
A5: FORD | B5: Y | C5: Y | D5: President and Chief Executive Officer, Ford Motor Company | E5: James | F5: D. | G5: Farley, Jr | H5: M | J5: 58 | Q5: James D. Farley, Jr | R5: No FEC Data
A6: FORD | B6: Y | C6: Y | D6: A Director of Investor Relations, Ford Motor Company | E6: Henry | G6: Ford III | H6: M | J6: 40 | L6: =+'Henry Ford III'!B28 -> 12700 | N6: =+'Henry Ford III'!B29 -> 210 | P6: 2000 BRUSH ST DETROIT MI 482262251 | Q6: Henry Ford III
A7: FORD | B7: Y | C7: Y | D7: Executive Chairman and Chairman of the Board Ford Motor Company | E7: William | F7: Clay | G7: Ford, Jr | H7: M | J7: 63 | L7: =+'William Clay Ford'!B18 -> 500 | M7: =+'William Clay Ford'!B16 -> 20000 | N7: =+'William Clay Ford'!B17 -> 10000 | P7: 2000 BRUSH ST STE 440 DETROIT MI 482262251 | Q7: William Clay Ford, Jr
A8: FORD | B8: Y | C8: N | D8: General Partner, Greylock Partners | E8: William | F8: W. | G8: Helman IV | H8: M | J8: 62 | L8: =+GETPIVOTDATA("contribution_receipt_amount",'William Helman'!$A$10) -> 2850 | P8: 106 7TH AVE PH 12 NEW YORK NY 10011 | Q8: William W. Helman IV
A9: FORD | B9: Y | C9: N | D9: Former Chairman, Atlantic Council and Former Chairman, Huntsman Cancer Foun | E9: Jon | F9: M. | G9: Huntsman, Jr | H9: M | J9: 61 | K9: 22001 | M9: =+'Jon Huntsman'!AJ2 -> 2800 | P9: 1605 E NEW BEDFORD DR SALT LAKE CITY UT 84103 | Q9: Jon M. Huntsman, Jr
A10: FORD | B10: Y | C10: N | D10: Chairman, Velocitas Partners LLC | E10: William | F10: E | G10: . Kennard | H10: M | J10: 64 | K10: 20839 | L10: =+'William Kennard'!B15 -> 1250 | M10: =+'William Kennard'!B16 -> 5000 | P10: 41 MEETING ST CHARLESTON SC 294012736 | Q10: William E. Kennard
A11: FORD | B11: Y | C11: N | D11: Retired Chairman and Chief Executive Officer, KeyCorp | E11: Beth | F11: E. | G11: Mooney | H11: F | J11: 66 | K11: 1955 | L11: =+GETPIVOTDATA("contribution_receipt_amount",'Beth Mooney'!$A$59) -> 33813.2 | P11: 11 COLONY LN BRATENAHL OH 441081119 | Q11: Beth E. Mooney
A12: FORD | B12: Y | C12: N | D12: Executive Chairman, Barrick Gold Corporation | E12: John | F12: L. | G12: Thornton | H12: M | J12: 67 | K12: 19726 | M12: =+GETPIVOTDATA("contribution_receipt_amount",'John Thornton'!$E$136) -> 2813.14 | P12: 5108 LEWELLYN RD LAKELAND FL 338100789 | Q12: John L. Thornton
A13: FORD | B13: Y | C13: N | D13: Retired Chairman and Chief Executive Officer, KPMG, LLP and retired Chairman of KPMG International | E13: John | F13: B. | G13: Veihmeyer | H13: M | J13: 65 | K13: 21730 | Q13: John B. Veihmeyer | R13: No FEC Data
A14: FORD | B14: Y | C14: N | D14: Former Executive Vice President & Chief Marketing Officer, Salesforce | E14: Lynn | F14: M. | G14: Vojvodich | H14: F | J14: 53 | P14: San Francisco Ca? | Q14: Lynn M. Vojvodich | R14: No FEC Data
A15: FORD | B15: Y | C15: N | D15: Co-Chief Executive Officer and Co-Chairman of the Board of Directors, Evercore Partners Inc. | E15: John | F15: S. | G15: Weinberg | H15: M | J15: 64 | P15: NY CT? | Q15: John S. Weinberg | R15: No FEC Data
A16: FORD | B16: N | C16: Y | D16: Chief Financial Officer | E16: John | F16: T. | G16: Lawler | H16: M | Q16: John T. Lawler | R16: No FEC Data
A17: FORD | B17: N | C17: Y | D17: Chief Product Platform & Operations Officer | E17: Hau | G17: Thai-Tang | J17: 55 | K17: 24362 | L17: =+GETPIVOTDATA("contribution_receipt_amount",'Hau Thai-Tang'!$A$20,"committee_name","FORD MOTOR COMPANY CIVIC ACTION FUND")*'Hau Thai-Tang'!C22 -> 1726.7328 | M17: =+GETPIVOTDATA("contribution_receipt_amount",'Hau Thai-Tang'!$A$20,"committee_name","FORD MOTOR COMPANY CIVIC ACTION FUND")*'Hau Thai-Tang'!C21 -> 3265.2672 | P17: 1362 JUNIPER LN BLOOMFIELD HILLS MI 483021959 | Q17: Hau Thai-Tang
A18: FORD | B18: N | C18: Y | D18: President Americas and International Markets | E18: Ashwani | F18: ‘‘Kumar’’ | G18: Galhotra | J18: 56 | K18: 24077 | Q18: Ashwani ‘‘Kumar’’ Galhotra | R18: No FEC Data
A19: FORD | B19: N | C19: Y | D19: Former Presidernt and CEO | E19: James | F19: P. | G19: Hackett | H19: M | J19: 66 | K19: 20201 | L19: =+GETPIVOTDATA("contribution_receipt_amount",'James P. Hackett'!$A$20,"committee_name","FORD MOTOR COMPANY CIVIC ACTION FUND")*'James P. Hackett'!F21 -> 1245.24 | M19: =+GETPIVOTDATA("contribution_receipt_amount",'James P. Hackett'!$A$20,"committee_name","FORD MOTOR COMPANY CIVIC ACTION FUND")*'James P. Hackett'!D21+GETPIVOTDATA("contribution_receipt_amount",'James P. Hackett'!$A$20,"committee_name","NRCC") -> 2604.76 | P19: 1547 BRIAR CLIFF DR. SE GRAND RAPIDS MI 495469689 | Q19: James P. Hackett
A20: FORD | B20: N | C20: Y | D20: Former Chief Financial Officer | E20: Tim | G20: Stone | H20: M | L20: =+GETPIVOTDATA("contribution_receipt_amount",'Tim Stone'!$A$14,"committee_name","FORD MOTOR COMPANY CIVIC ACTION FUND")*'Tim Stone'!F15 -> 1438.944 | M20: =+GETPIVOTDATA("contribution_receipt_amount",'Tim Stone'!$A$14,"committee_name","FORD MOTOR COMPANY CIVIC ACTION FUND")*'Tim Stone'!D15 -> 2721.056 | P20: 322 JERUSALEM COHASSET MA 20251138 | Q20: Tim Stone
L22: =SUM(L2:L21) -> 70624.117 | M22: =SUM(M2:M21) -> 39204.223 | N22: =SUM(N2:N21) -> 10210

Sheet Company PAC
A1: committee_id | B1: committee_name | D1: Political Affiliation | E1: Republican | F1: Democratic | G1: Independent | H1: %Republican | I1: %Democrat
A2: C00000422 | B2: AMERICAN MEDICAL ASSOCIATION POLITICAL ACTION COMMITTEE
A3: C00000935 | B3: DCCC | D3: D
A4: C00001180 | B4: MICHIGAN DOCTORS POLITICAL ACTION COMMITTEE - MICHIGAN STATE MEDICAL SOCIETY
A5: C00001305 | B5: REPUBLICAN PARTY OF VIRGINIA INC | D5: R
A6: C00001313 | B6: REPUBLICAN PARTY OF MINNESOTA - FEDERAL | D6: R
A7: C00002840 | B7: UAW - V - CAP (UAW VOLUNTARY COMMUNITY ACTION PROGRAM)
A8: C00003111 | B8: MAINE REPUBLICAN PARTY | D8: R
A9: C00003418 | B9: REPUBLICAN NATIONAL COMMITTEE | D9: R
A10: C00003764 | B10: NATIONAL RESTAURANT ASSOCIATION PAC (RESTAURANT PAC)
A11: C00003988 | B11: NEBRASKA DEMOCRATIC PARTY | D11: D
A12: C00004606 | B12: KANSAS REPUBLICAN PARTY | D12: R
A13: C00005561 | B13: DEMOCRATIC EXECUTIVE COMMITTEE OF FLORIDA | D13: D
A14: C00005785 | B14: WYOMING REPUBLICAN PARTY, INC. | D14: R
A15: C00005926 | B15: ILLINOIS REPUBLICAN PARTY - FEDERAL | D15: R
A16: C00006486 | B16: INDIANA REPUBLICAN STATE COMMITTEE, INC. | D16: R
A17: C00008086 | B17: MONTANA REPUBLICAN STATE CENTRAL COMMITTEE | D17: R
A18: C00008227 | B18: ARIZONA REPUBLICAN PARTY | D18: R
A19: C00008664 | B19: MISSOURI REPUBLICAN STATE COMMITTEE-FEDERAL | D19: R
A20: C00010603 | B20: DNC SERVICES CORP / DEMOCRATIC NATIONAL COMMITTEE | D20: D
A21: C00011197 | B21: KENTUCKY STATE DEMOCRATIC CENTRAL EXECUTIVE COMMITTEE | D21: D
A22: C00012229 | B22: ALASKANS FOR DON YOUNG
A23: C00012880 | B23: AMERICAN PHYSICAL THERAPY ASSOCIATION PHYSICAL THERAPY POLITICAL ACTION COMMITTEE (PT-PAC)
A24: C00014498 | B24: REPUBLICAN PARTY OF IOWA | D24: R
A25: C00016899 | B25: OHIO DEMOCRATIC PARTY | D25: D
A26: C00019331 | B26: DEMOCRATIC PARTY OF WISCONSIN | D26: D
A27: C00020818 | B27: REPUBLICAN CAMPAIGN COMMITTEE OF NEW MEXICO | D27: R
A28: C00022343 | B28: INDEPENDENT INSURANCE AGENTS & BROKERS OF AMERICA, INC. POLITICAL ACTION COMMITTEE (INSURPAC)
A29: C00024521 | B29: AMERICAN ASSOCIATION FOR JUSTICE POLITICAL ACTION COMMITTEE (AAJ PAC)
A30: C00024679 | B30: VERMONT DEMOCRATIC PARTY | D30: D
A31: C00025254 | B31: MINNESOTA DEMOCRATIC-FARMER-LABOR PARTY | D31: D
A32: C00027466 | B32: NRSC | D32: R
A33: C00030718 | B33: NATIONAL ASSOCIATION OF REALTORS POLITICAL ACTION COMMITTEE
A34: C00031054 | B34: MICHIGAN DEMOCRATIC STATE CENTRAL COMMITTEE | D34: D
A35: C00032334 | B35: NEBRASKA REPUBLICAN PARTY | D35: R
A36: C00033134 | B36: COLORADO REPUBLICAN COMMITTEE | D36: R
A37: C00038505 | B37: NORTH CAROLINA REPUBLICAN PARTY | D37: R
A38: C00040857 | B38: OAKLAND COUNTY DEMOCRATIC PARTY | D38: D
A39: C00040998 | B39: NATIONAL AUTOMOBILE DEALERS ASSOCIATION POLITICAL ACTION COMMITTEE
A40: C00041160 | B40: MICHIGAN REPUBLICAN PARTY | D40: R
A41: C00041269 | B41: GEORGIA FEDERAL ELECTIONS COMMITTEE
A42: C00042366 | B42: DSCC | D42: D
A43: C00044842 | B43: REPUBLICAN FEDERAL COMMITTEE OF PENNSYLVANIA | D43: R
A44: C00046474 | B44: FORD MOTOR COMPANY CIVIC ACTION FUND | D44: R | E44: 0.6541 | F44: R | G44: =1-E44 -> 0.3459 | H44: D
A45: C00053553 | B45: NATIONAL RIFLE ASSOCIATION OF AMERICA POLITICAL VICTORY FUND
A46: C00055582 | B46: NY REPUBLICAN FEDERAL CAMPAIGN COMMITTEE | D46: R
A47: C00065219 | B47: WINE INSTITUTE PAC
A48: C00068353 | B48: LEAHY FOR U.S. SENATOR COMMITTEE
A49: C00073791 | B49: DOLLARS FOR DEMOCRATS | D49: D
A50: C00074450 | B50: REPUBLICAN PARTY OF WISCONSIN | D50: R
A51: C00075820 | B51: NRCC | D51: R
A52: C00082040 | B52: CHAMBER OF COMMERCE OF THE UNITED STATES OF AMERICA PAC (US CHAMBER PAC)
A53: C00082917 | B53: ASSOCIATED GENERAL CONTRACTORS OF AMERICA POLITICAL ACTION COMMITTEE
A54: C00082925 | B54: NEVADA REPUBLICAN CENTRAL COMMITTEE | D54: R
A55: C00092841 | B55: GEORGIA BANKERS ASSOCIATION PAC
A56: C00096412 | B56: FRIENDS OF CHRIS SMITH
A57: C00099259 | B57: REPUBLICAN PARTY OF FLORIDA | D57: R
A58: C00099267 | B58: TEXAS DEMOCRATIC PARTY | D58: D
A59: C00101105 | B59: NATIONAL FEDERATION OF INDEPENDENT BUSINESS FEDERAL POLITICAL ACTION COMMITTEE
A60: C00104471 | B60: NEW JERSEY DEMOCRATIC STATE COMMITTEE | D60: D
A61: C00106146 | B61: AMERICAN HOSPITAL ASSOCIATION PAC
A62: C00131185 | B62: AIRCRAFT OWNERS AND PILOTS ASSOCIATION POLITICAL ACTION COMMITTEE
A63: C00135558 | B63: MISSOURI DEMOCRATIC STATE COMMITTEE | D63: D
A64: C00136457 | B64: NEW HAMPSHIRE REPUBLICAN STATE COMMITTEE | D64: R
A65: C00139071 | B65: ARCHIPAC -THE AMERICAN INSTITUTE OF ARCHITECTS
A66: C00139279 | B66: MICHIGAN CREDIT UNION LEAGUE LEGISLATIVE ACTION FUND
A67: C00140061 | B67: NATIONAL EMERGENCY MEDICINE POLITICAL ACTION COMMITTEE / AMERICAN COLLEGE OF EMERGENCY PHYSICIANS
A68: C00140590 | B68: CALIFORNIA REPUBLICAN PARTY FEDERAL ACCT. | D68: R
A69: C00143743 | B69: REPUBLICAN PARTY OF TEXAS | D69: R
A70: C00147512 | B70: CONGRESSIONAL BLACK CAUCUS PAC | D70: D
A71: C00148999 | B71: FRIENDS OF DICK DURBIN COMMITTEE | D71: D
A72: C00150672 | B72: GEORGIA REPUBLICAN PARTY INC. | D72: R
A73: C00153031 | B73: OREGON REPUBLICAN PARTY | D73: R
A74: C00155952 | B74: DEMOCRATIC PARTY OF VIRGINIA | D74: D
A75: C00156810 | B75: REPUBLICAN PARTY OF KENTUCKY | D75: R
A76: C00161786 | B76: COLORADO DEMOCRATIC PARTY | D76: D
A77: C00162339 | B77: OHIO REPUBLICAN PARTY STATE CENTRAL & EXECUTIVE COMMITTEE | D77: R
A78: C00165688 | B78: NORTH CAROLINA DEMOCRATIC PARTY - FEDERAL | D78: D
A79: C00166710 | B79: ARIZONA DEMOCRATIC PARTY | D79: D
A80: C00167130 | B80: PENNSYLVANIA DEMOCRATIC PARTY | D80: D
A81: C00173153 | B81: AMERICAN ASSOCIATION OF NURSE ANESTHETISTS SEPARATE SEGREGATED FUND (CRNA-PAC)
A82: C00178038 | B82: NEW HAMPSHIRE DEMOCRATIC PARTY | D82: D
A83: C00187450 | B83: REPUBLICAN PARTY OF LOUISIANA | D83: R
A84: C00188367 | B84: DEMOCRATIC PARTY OF OREGON | D84: D
A85: C00193342 | B85: MCCONNELL SENATE COMMITTEE | D85: R
A86: C00193433 | B86: EMILY'S LIST
A87: C00197103 | B87: AUTOMOBILE CLUB OF MICHIGAN POLITICAL ACTION COMMITTEE
A88: C00200584 | B88: UPTON FOR ALL OF US
A89: C00207993 | B89: FRIENDS OF JIM INHOFE
A90: C00208991 | B90: NEVADA STATE DEMOCRATIC PARTY | D90: D
A91: C00213512 | B91: NANCY PELOSI FOR CONGRESS | D91: D
A92: C00224717 | B92: PHILIP A. HART DEMOCRATIC CLUB | D92: D
A93: C00226928 | B93: PALLONE FOR CONGRESS
A94: C00235853 | B94: HUMAN RIGHTS CAMPAIGN PAC
A95: C00236513 | B95: ENGEL FOR CONGRESS
A96: C00238204 | B96: PAKISTANI AMERICAN PUBLIC AFFAIRS COMMITTEE PAK-PAC
A97: C00250399 | B97: AUTOMOTIVE FREE INTERNATIONAL TRADE PAC
A98: C00253260 | B98: ALASKA REPUBLICAN PARTY | D98: R
A99: C00255695 | B99: LIBERTARIAN NATIONAL COMMITTEE, INC. | D99: L
A100: C00255752 | B100: AMERICAN SOCIETY OF ANESTHESIOLOGISTS POLITICAL ACTION COMMITTEE (ASA PAC)
...

Sheet Tim Stone
A1: committee_id | B1: committee_name | C1: report_year | D1: report_type | E1: image_number | F1: line_number | G1: transaction_id | H1: file_number | I1: committee_name | J1: entity_type | K1: entity_type_desc | L1: unused_contbr_id | M1: contributor_prefix | N1: contributor_name | O1: recipient_committee_type | P1: recipient_committee_org_type | Q1: recipient_committee_designation | R1: contributor_first_name | S1: contributor_middle_name | T1: contributor_last_name | U1: contributor_suffix | V1: contributor_street_1 | W1: contributor_street_2 | X1: contributor_city | Y1: contributor_state | Z1: contributor_zip | AA1: contributor_employer | AB1: contributor_occupation | AC1: contributor_id | AD1: receipt_type | AE1: receipt_type_desc | AF1: receipt_type_full | AG1: memo_code | AH1: memo_code_full | AI1: contribution_receipt_date | AJ1: contribution_receipt_amount | AK1: contributor_aggregate_ytd | AL1: candidate_id | AM1: candidate_name | AN1: candidate_first_name | AO1: candidate_last_name | AP1: candidate_middle_name | AQ1: candidate_prefix | AR1: candidate_suffix | AS1: candidate_office | AT1: candidate_office_full | AU1: candidate_office_state | AV1: candidate_office_state_full | AW1: candidate_office_district | AX1: conduit_committee_id | AY1: conduit_committee_name | AZ1: conduit_committee_street1 | BA1: conduit_committee_street2 | BB1: conduit_committee_city | BC1: conduit_committee_state | BD1: conduit_committee_zip | BE1: donor_committee_name | BF1: national_committee_nonfederal_account | BG1: election_type | BH1: election_type_full | BI1: fec_election_type_desc | BJ1: fec_election_year | BK1: amendment_indicator | BL1: amendment_indicator_desc | BM1: schedule_type_full | BN1: load_date | BO1: original_sub_id | BP1: back_reference_transaction_id | BQ1: back_reference_schedule_name | BR1: filing_form | BS1: link_id | BT1: is_individual | BU1: memo_text | BV1: two_year_transaction_period | BW1: schedule_type | BX1: increased_limit | BY1: sub_id | BZ1: pdf_url | CA1: line_number_label
A2: C00046474 | B2: FORD MOTOR COMPANY CIVIC ACTION FUND | C2: 2019 | D2: YE | E2: 2.0200129e+17 | F2: 11AI | G2: PR929617431700 | H2: 1374056 | J2: IND | K2: INDIVIDUAL | M2: MR | N2: STONE, TIM MR | O2: Q | P2: C | Q2: B | R2: TIM | T2: STONE | V2: 2987 FRANKLIN STREET, UNIT W | X2: DETROIT | Y2: MI | Z2: 482074262 | AA2: FORD MOTOR COMPANY | AB2: EXECUTIVE VICE PRESIDENT | AD2: 15 | AE2: CONTRIBUTION | AI2: 43830 | AJ2: 416 | AK2: 1248 | BG2: P | BI2: PRIMARY | BK2: A | BL2: ADD | BM2: ITEMIZED RECEIPTS | BN2: 43859.073 | BR2: F3X | BS2: 4.0128202e+18 | BT2: t | BU2: P/R DEDUCTION ($416.00 MONTHLY) | BV2: 2020 | BW2: SA | BY2: 4.0128202e+18 | BZ2: http://docquery.fec.gov/cgi-bin/fecimg/?202001289167420499 | CA2: Contributions From Individuals/Persons Other Than Political Committees
A3: C00046474 | B3: FORD MOTOR COMPANY CIVIC ACTION FUND | C3: 2019 | D3: M12 | E3: 2.0191219e+17 | F3: 11AI | G3: PR929617431137 | H3: 1366669 | J3: IND | K3: INDIVIDUAL | M3: MR | N3: STONE, TIM MR | O3: Q | P3: C | Q3: B | R3: TIM | T3: STONE | V3: 2987 FRANKLIN STREET, UNIT W | X3: DETROIT | Y3: MI | Z3: 482074262 | AA3: FORD MOTOR COMPANY | AB3: EXECUTIVE VICE PRESIDENT | AD3: 15 | AE3: CONTRIBUTION | AI3: 43799 | AJ3: 416 | AK3: 832 | BG3: P | BI3: PRIMARY | BK3: A | BL3: ADD | BM3: ITEMIZED RECEIPTS | BN3: 43818.072 | BR3: F3X | BS3: 4.1218202e+18 | BT3: t | BU3: P/R DEDUCTION ($416.00 MONTHLY) | BV3: 2020 | BW3: SA | BY3: 4.1218202e+18 | BZ3: http://docquery.fec.gov/cgi-bin/fecimg/?201912189166359698 | CA3: Contributions From Individuals/Persons Other Than Political Committees
A4: C00046474 | B4: FORD MOTOR COMPANY CIVIC ACTION FUND | C4: 2020 | D4: M8 | E4: 2.0200815e+17 | F4: 11AI | G4: PR929617433448 | H4: 1432298 | J4: IND | K4: INDIVIDUAL | M4: MR | N4: STONE, TIM MR | O4: Q | P4: C | Q4: B | R4: TIM | T4: STONE | V4: 2987 FRANKLIN STREET, UNIT W | X4: DETROIT | Y4: MI | Z4: 482074262 | AA4: FMC US | AB4: VP, CHIEF FINANCIAL OFFICER | AD4: 15 | AE4: CONTRIBUTION | AI4: 44043 | AJ4: 416 | AK4: 2912 | BG4: P | BI4: PRIMARY | BK4: A | BL4: ADD | BM4: ITEMIZED RECEIPTS | BN4: 44065.164 | BR4: F3X | BS4: 4.0815202e+18 | BT4: t | BU4: P/R DEDUCTION ($416.00 MONTHLY) | BV4: 2020 | BW4: SA | BY4: 4.0822202e+18 | BZ4: http://docquery.fec.gov/cgi-bin/fecimg/?202008149261306926 | CA4: Contributions From Individuals/Persons Other Than Political Committees
A5: C00046474 | B5: FORD MOTOR COMPANY CIVIC ACTION FUND | C5: 2020 | D5: M2 | E5: 2.0200219e+17 | F5: 11AI | G5: PR929617431849 | H5: 1383073 | J5: IND | K5: INDIVIDUAL | M5: MR | N5: STONE, TIM MR | O5: Q | P5: C | Q5: B | R5: TIM | T5: STONE | V5: 2987 FRANKLIN STREET, UNIT W | X5: DETROIT | Y5: MI | Z5: 482074262 | AA5: FORD MOTOR COMPANY | AB5: EXECUTIVE VICE PRESIDENT | AD5: 15 | AE5: CONTRIBUTION | AI5: 43861 | AJ5: 416 | AK5: 416 | BG5: P | BI5: PRIMARY | BK5: A | BL5: ADD | BM5: ITEMIZED RECEIPTS | BN5: 43886.075 | BR5: F3X | BS5: 4.0218202e+18 | BT5: t | BU5: P/R DEDUCTION ($416.00 MONTHLY) | BV5: 2020 | BW5: SA | BY5: 4.0224202e+18 | BZ5: http://docquery.fec.gov/cgi-bin/fecimg/?202002189186515571 | CA5: Contributions From Individuals/Persons Other Than Political Committees
A6: C00046474 | B6: FORD MOTOR COMPANY CIVIC ACTION FUND | C6: 2020 | D6: M3 | E6: 2.0200319e+17 | F6: 11AI | G6: PR929617432112 | H6: 1390420 | J6: IND | K6: INDIVIDUAL | M6: MR | N6: STONE, TIM MR | O6: Q | P6: C | Q6: B | R6: TIM | T6: STONE | V6: 2987 FRANKLIN STREET, UNIT W | X6: DETROIT | Y6: MI | Z6: 482074262 | AA6: FORD MOTOR COMPANY | AB6: EXECUTIVE VICE PRESIDENT | AD6: 15 | AE6: CONTRIBUTION | AI6: 43890 | AJ6: 416 | AK6: 832 | BG6: P | BI6: PRIMARY | BK6: A | BL6: ADD | BM6: ITEMIZED RECEIPTS | BN6: 43909.096 | BR6: F3X | BS6: 4.0318202e+18 | BT6: t | BU6: P/R DEDUCTION ($416.00 MONTHLY) | BV6: 2020 | BW6: SA | BY6: 4.0318202e+18 | BZ6: http://docquery.fec.gov/cgi-bin/fecimg/?202003189203874381 | CA6: Contributions From Individuals/Persons Other Than Political Committees
A7: C00046474 | B7: FORD MOTOR COMPANY CIVIC ACTION FUND | C7: 2020 | D7: M7 | E7: 2.020071e+17 | F7: 11AI | G7: PR929617433026 | H7: 1418223 | J7: IND | K7: INDIVIDUAL | M7: MR | N7: STONE, TIM MR | O7: Q | P7: C | Q7: B | R7: TIM | T7: STONE | V7: 2987 FRANKLIN STREET, UNIT W | X7: DETROIT | Y7: MI | Z7: 482074262 | AA7: FMC US | AB7: CHIEF FINANCIAL OFFICER | AD7: 15 | AE7: CONTRIBUTION | AI7: 44012 | AJ7: 416 | AK7: 2496 | BG7: P | BI7: PRIMARY | BK7: A | BL7: ADD | BM7: ITEMIZED RECEIPTS | BN7: 44023.088 | BR7: F3X | BS7: 4.0709202e+18 | BT7: t | BU7: P/R DEDUCTION ($416.00 MONTHLY) | BV7: 2020 | BW7: SA | BY7: 4.0710202e+18 | BZ7: http://docquery.fec.gov/cgi-bin/fecimg/?202007099244394670 | CA7: Contributions From Individuals/Persons Other Than Political Committees
A8: C00046474 | B8: FORD MOTOR COMPANY CIVIC ACTION FUND | C8: 2020 | D8: M6 | E8: 2.020071e+17 | F8: 11AI | G8: PR929617432739 | H8: 1418185 | J8: IND | K8: INDIVIDUAL | M8: MR | N8: STONE, TIM MR | O8: Q | P8: C | Q8: B | R8: TIM | T8: STONE | V8: 2987 FRANKLIN STREET, UNIT W | X8: DETROIT | Y8: MI | Z8: 482074262 | AA8: FMC US | AB8: CHIEF FINANCIAL OFFICER | AD8: 15 | AE8: CONTRIBUTION | AI8: 43982 | AJ8: 416 | AK8: 2080 | BG8: P | BI8: PRIMARY | BK8: A | BL8: ADD | BM8: ITEMIZED RECEIPTS | BN8: 44024.093 | BR8: F3X | BS8: 4.0709202e+18 | BT8: t | BU8: P/R DEDUCTION ($416.00 MONTHLY) | BV8: 2020 | BW8: SA | BY8: 4.0711202e+18 | BZ8: http://docquery.fec.gov/cgi-bin/fecimg/?202007099244393517 | CA8: Contributions From Individuals/Persons Other Than Political Committees
A9: C00046474 | B9: FORD MOTOR COMPANY CIVIC ACTION FUND | C9: 2020 | D9: M9 | E9: 2.0200918e+17 | F9: 11AI | G9: PR929617433701 | H9: 1438561 | J9: IND | K9: INDIVIDUAL | M9: MR | N9: STONE, TIM MR | O9: Q | P9: C | Q9: B | R9: TIM | T9: STONE | V9: 322 JERUSALEM | X9: COHASSET | Y9: MA | Z9: 20251138 | AA9: FMC US | AB9: VP, CHIEF FINANCIAL OFFICER | AD9: 15 | AE9: CONTRIBUTION | AI9: 44074 | AJ9: 416 | AK9: 3328 | BG9: P | BI9: PRIMARY | BK9: A | BL9: ADD | BM9: ITEMIZED RECEIPTS | BN9: 44092.152 | BR9: F3X | BS9: 4.0918202e+18 | BT9: t | BU9: P/R DEDUCTION ($416.00 MONTHLY) | BV9: 2020 | BW9: SA | BY9: 4.0918202e+18 | BZ9: http://docquery.fec.gov/cgi-bin/fecimg/?202009179267222529 | CA9: Contributions From Individuals/Persons Other Than Political Committees
A10: C00046474 | B10: FORD MOTOR COMPANY CIVIC ACTION FUND | C10: 2020 | D10: 12G | E10: 2.0201022e+17 | F10: 11AI | G10: PR929617434207 | H10: 1459687 | J10: IND | K10: INDIVIDUAL | M10: MR | N10: STONE, TIM MR | O10: Q | P10: C | Q10: B | R10: TIM | T10: STONE | V10: 322 JERUSALEM | X10: COHASSET | Y10: MA | Z10: 20251138 | AA10: FORD MOTOR COMPANY | AB10: EXECUTIVE VICE PRESIDENT | AD10: 15 | AE10: CONTRIBUTION | AI10: 44118 | AJ10: 416 | AK10: 4160 | BG10: P | BI10: PRIMARY | BK10: A | BL10: ADD | BM10: ITEMIZED RECEIPTS | BN10: 44168.152 | BR10: F3X | BS10: 4.1022202e+18 | BT10: t | BU10: P/R DEDUCTION ($416.00 MONTHLY) | BV10: 2020 | BW10: SA | BY10: 4.1203202e+18 | BZ10: http://docquery.fec.gov/cgi-bin/fecimg/?202010219326755919 | CA10: Contributions From Individuals/Persons Other Than Political Committees
A11: C00046474 | B11: FORD MOTOR COMPANY CIVIC ACTION FUND | C11: 2020 | D11: M10 | E11: 2.020102e+17 | F11: 11AI | G11: PR929617434128 | H11: 1456209 | J11: IND | K11: INDIVIDUAL | M11: MR | N11: STONE, TIM MR | O11: Q | P11: C | Q11: B | R11: TIM | T11: STONE | V11: 322 JERUSALEM | X11: COHASSET | Y11: MA | Z11: 20251138 | AA11: FMC US | AB11: EXECUTIVE VICE PRESIDENT | AD11: 15 | AE11: CONTRIBUTION | AI11: 44104 | AJ11: 416 | AK11: 3744 | BG11: P | BI11: PRIMARY | BK11: A | BL11: ADD | BM11: ITEMIZED RECEIPTS | BN11: 44161.158 | BR11: F3X | BS11: 4.1020202e+18 | BT11: t | BU11: P/R DEDUCTION ($416.00 MONTHLY) | BV11: 2020 | BW11: SA | BY11: 4.1126202e+18 | BZ11: http://docquery.fec.gov/cgi-bin/fecimg/?202010199297279890 | CA11: Contributions From Individuals/Persons Other Than Political Committees
V13: =+V11&X11&Y11&Z11 -> 322 JERUSALEMCOHASSETMA20251138
A14: Row Labels | B14: Sum of contribution_receipt_amount
A15: FORD MOTOR COMPANY CIVIC ACTION FUND | B15: 4160 | D15: 0.6541 | E15: R | F15: =1-D15 -> 0.3459 | G15: D
A16: Grand Total | B16: 4160

Sheet James P. Hackett
A1: committee_id | B1: committee_name | C1: report_year | D1: report_type | E1: image_number | F1: line_number | G1: transaction_id | H1: file_number | I1: committee_name | J1: entity_type | K1: entity_type_desc | L1: unused_contbr_id | M1: contributor_prefix | N1: contributor_name | O1: recipient_committee_type | P1: recipient_committee_org_type | Q1: recipient_committee_designation | R1: contributor_first_name | S1: contributor_middle_name | T1: contributor_last_name | U1: contributor_suffix | V1: contributor_street_1 | W1: contributor_street_2 | X1: contributor_city | Y1: contributor_state | Z1: contributor_zip | AA1: contributor_employer | AB1: contributor_occupation | AC1: contributor_id | AD1: receipt_type | AE1: receipt_type_desc | AF1: receipt_type_full | AG1: memo_code | AH1: memo_code_full | AI1: contribution_receipt_date | AJ1: contribution_receipt_amount | AK1: contributor_aggregate_ytd | AL1: candidate_id | AM1: candidate_name | AN1: candidate_first_name | AO1: candidate_last_name | AP1: candidate_middle_name | AQ1: candidate_prefix | AR1: candidate_suffix | AS1: candidate_office | AT1: candidate_office_full | AU1: candidate_office_state | AV1: candidate_office_state_full | AW1: candidate_office_district | AX1: conduit_committee_id | AY1: conduit_committee_name | AZ1: conduit_committee_street1 | BA1: conduit_committee_street2 | BB1: conduit_committee_city | BC1: conduit_committee_state | BD1: conduit_committee_zip | BE1: donor_committee_name | BF1: national_committee_nonfederal_account | BG1: election_type | BH1: election_type_full | BI1: fec_election_type_desc | BJ1: fec_election_year | BK1: amendment_indicator | BL1: amendment_indicator_desc | BM1: schedule_type_full | BN1: load_date | BO1: original_sub_id | BP1: back_reference_transaction_id | BQ1: back_reference_schedule_name | BR1: filing_form | BS1: link_id | BT1: is_individual | BU1: memo_text | BV1: two_year_transaction_period | BW1: schedule_type | BX1: increased_limit | BY1: sub_id | BZ1: pdf_url | CA1: line_number_label
A2: C00046474 | B2: FORD MOTOR COMPANY CIVIC ACTION FUND | C2: 2019 | D2: YE | E2: 2.0200129e+17 | F2: 11AI | G2: PR868935031700 | H2: 1374056 | J2: IND | K2: INDIVIDUAL | N2: HACKETT, JAMES P | O2: Q | P2: C | Q2: B | R2: JAMES P | T2: HACKETT | V2: 1547 BRIARCLIFF DR. SE | X2: GRAND RAPIDS | Y2: MI | Z2: 495469689 | AA2: FORD MOTOR COMPANY | AB2: PRESIDENT & CEO | AD2: 15 | AE2: CONTRIBUTION | AI2: 43830 | AJ2: 300 | AK2: 3600 | BG2: P | BI2: PRIMARY | BK2: A | BL2: ADD | BM2: ITEMIZED RECEIPTS | BN2: 43859.073 | BR2: F3X | BS2: 4.0128202e+18 | BT2: t | BU2: P/R DEDUCTION ($300.00 MONTHLY) | BV2: 2020 | BW2: SA | BY2: 4.0128202e+18 | BZ2: http://docquery.fec.gov/cgi-bin/fecimg/?202001289167420483 | CA2: Contributions From Individuals/Persons Other Than Political Committees
A3: C00046474 | B3: FORD MOTOR COMPANY CIVIC ACTION FUND | C3: 2019 | D3: M12 | E3: 2.0191219e+17 | F3: 11AI | G3: PR868935031137 | H3: 1366669 | J3: IND | K3: INDIVIDUAL | N3: HACKETT, JAMES P | O3: Q | P3: C | Q3: B | R3: JAMES | S3: P | T3: HACKETT | V3: 1547 BRIARCLIFF DR. SE | X3: GRAND RAPIDS | Y3: MI | Z3: 495469689 | AA3: FORD MOTOR COMPANY | AB3: PRESIDENT & CEO | AD3: 15 | AE3: CONTRIBUTION | AI3: 43799 | AJ3: 300 | AK3: 3300 | BG3: P | BI3: PRIMARY | BK3: A | BL3: ADD | BM3: ITEMIZED RECEIPTS | BN3: 43818.072 | BR3: F3X | BS3: 4.1218202e+18 | BT3: t | BU3: P/R DEDUCTION ($300.00 MONTHLY) | BV3: 2020 | BW3: SA | BY3: 4.1218202e+18 | BZ3: http://docquery.fec.gov/cgi-bin/fecimg/?201912189166359682 | CA3: Contributions From Individuals/Persons Other Than Political Committees
A4: C00046474 | B4: FORD MOTOR COMPANY CIVIC ACTION FUND | C4: 2020 | D4: M8 | E4: 2.0200815e+17 | F4: 11AI | G4: PR868935033448 | H4: 1432298 | J4: IND | K4: INDIVIDUAL | N4: HACKETT, JAMES P | O4: Q | P4: C | Q4: B | R4: JAMES | S4: P | T4: HACKETT | V4: 1547 BRIARCLIFF DR. SE | X4: GRAND RAPIDS | Y4: MI | Z4: 495469689 | AA4: FMC US | AB4: PRESIDENT & CEO | AD4: 15 | AE4: CONTRIBUTION | AI4: 44043 | AJ4: 300 | AK4: 2100 | BG4: P | BI4: PRIMARY | BK4: A | BL4: ADD | BM4: ITEMIZED RECEIPTS | BN4: 44065.164 | BR4: F3X | BS4: 4.0815202e+18 | BT4: t | BU4: P/R DEDUCTION ($300.00 MONTHLY) | BV4: 2020 | BW4: SA | BY4: 4.0822202e+18 | BZ4: http://docquery.fec.gov/cgi-bin/fecimg/?202008149261306911 | CA4: Contributions From Individuals/Persons Other Than Political Committees
A5: C00046474 | B5: FORD MOTOR COMPANY CIVIC ACTION FUND | C5: 2020 | D5: M2 | E5: 2.0200219e+17 | F5: 11AI | G5: PR868935031849 | H5: 1383073 | J5: IND | K5: INDIVIDUAL | N5: HACKETT, JAMES P | O5: Q | P5: C | Q5: B | R5: JAMES P | T5: HACKETT | V5: 1547 BRIARCLIFF DR. SE | X5: GRAND RAPIDS | Y5: MI | Z5: 495469689 | AA5: FORD MOTOR COMPANY | AB5: PRESIDENT & CEO | AD5: 15 | AE5: CONTRIBUTION | AI5: 43861 | AJ5: 300 | AK5: 300 | BG5: P | BI5: PRIMARY | BK5: A | BL5: ADD | BM5: ITEMIZED RECEIPTS | BN5: 43886.075 | BR5: F3X | BS5: 4.0218202e+18 | BT5: t | BU5: P/R DEDUCTION ($300.00 MONTHLY) | BV5: 2020 | BW5: SA | BY5: 4.0224202e+18 | BZ5: http://docquery.fec.gov/cgi-bin/fecimg/?202002189186515568 | CA5: Contributions From Individuals/Persons Other Than Political Committees
A6: C00046474 | B6: FORD MOTOR COMPANY CIVIC ACTION FUND | C6: 2020 | D6: YE | E6: 2.0210116e+17 | F6: 11AI | G6: PR868935035156 | H6: 1488043 | J6: IND | K6: INDIVIDUAL | N6: HACKETT, JAMES P | O6: Q | P6: C | Q6: B | R6: JAMES | S6: P | T6: HACKETT | V6: 1547 BRIARCLIFF DR. SE | X6: GRAND RAPIDS | Y6: MI | Z6: 495469689 | AA6: FMC US | AB6: ADVISOR TO THE OCCE | AD6: 15 | AE6: CONTRIBUTION | AI6: 44196 | AJ6: 300 | AK6: 3600 | BG6: P | BI6: PRIMARY | BK6: A | BL6: ADD | BM6: ITEMIZED RECEIPTS | BN6: 44212.068 | BR6: F3X | BS6: 4.0115202e+18 | BT6: t | BU6: P/R DEDUCTION ($300.00 MONTHLY) | BV6: 2020 | BW6: SA | BY6: 4.0115202e+18 | BZ6: https://docquery.fec.gov/cgi-bin/fecimg/?202101159404713089 | CA6: Contributions From Individuals/Persons Other Than Political Committees
A7: C00046474 | B7: FORD MOTOR COMPANY CIVIC ACTION FUND | C7: 2020 | D7: M3 | E7: 2.0200319e+17 | F7: 11AI | G7: PR868935032112 | H7: 1390420 | J7: IND | K7: INDIVIDUAL | N7: HACKETT, JAMES P | O7: Q | P7: C | Q7: B | R7: JAMES | S7: P | T7: HACKETT | V7: 1547 BRIARCLIFF DR. SE | X7: GRAND RAPIDS | Y7: MI | Z7: 495469689 | AA7: FORD MOTOR COMPANY | AB7: PRESIDENT & CEO | AD7: 15 | AE7: CONTRIBUTION | AI7: 43890 | AJ7: 300 | AK7: 600 | BG7: P | BI7: PRIMARY | BK7: A | BL7: ADD | BM7: ITEMIZED RECEIPTS | BN7: 43909.096 | BR7: F3X | BS7: 4.0318202e+18 | BT7: t | BU7: P/R DEDUCTION ($300.00 MONTHLY) | BV7: 2020 | BW7: SA | BY7: 4.0318202e+18 | BZ7: http://docquery.fec.gov/cgi-bin/fecimg/?202003189203874378 | CA7: Contributions From Individuals/Persons Other Than Political Committees
A8: C00046474 | B8: FORD MOTOR COMPANY CIVIC ACTION FUND | C8: 2020 | D8: M7 | E8: 2.020071e+17 | F8: 11AI | G8: PR868935033026 | H8: 1418223 | J8: IND | K8: INDIVIDUAL | N8: HACKETT, JAMES P | O8: Q | P8: C | Q8: B | R8: JAMES | S8: P | T8: HACKETT | V8: 1547 BRIARCLIFF DR. SE | X8: GRAND RAPIDS | Y8: MI | Z8: 495469689 | AA8: FMC US | AB8: PRESIDENT & CEO | AD8: 15 | AE8: CONTRIBUTION | AI8: 44012 | AJ8: 300 | AK8: 1800 | BG8: P | BI8: PRIMARY | BK8: A | BL8: ADD | BM8: ITEMIZED RECEIPTS | BN8: 44023.088 | BR8: F3X | BS8: 4.0709202e+18 | BT8: t | BU8: P/R DEDUCTION ($300.00 MONTHLY) | BV8: 2020 | BW8: SA | BY8: 4.0710202e+18 | BZ8: http://docquery.fec.gov/cgi-bin/fecimg/?202007099244394662 | CA8: Contributions From Individuals/Persons Other Than Political Committees
A9: C00046474 | B9: FORD MOTOR COMPANY CIVIC ACTION FUND | C9: 2020 | D9: M6 | E9: 2.020071e+17 | F9: 11AI | G9: PR868935032739 | H9: 1418185 | J9: IND | K9: INDIVIDUAL | N9: HACKETT, JAMES P | O9: Q | P9: C | Q9: B | R9: JAMES | S9: P | T9: HACKETT | V9: 1547 BRIARCLIFF DR. SE | X9: GRAND RAPIDS | Y9: MI | Z9: 495469689 | AA9: FMC US | AB9: PRESIDENT & CEO | AD9: 15 | AE9: CONTRIBUTION | AI9: 43982 | AJ9: 300 | AK9: 1500 | BG9: P | BI9: PRIMARY | BK9: A | BL9: ADD | BM9: ITEMIZED RECEIPTS | BN9: 44024.093 | BR9: F3X | BS9: 4.0709202e+18 | BT9: t | BU9: P/R DEDUCTION ($300.00 MONTHLY) | BV9: 2020 | BW9: SA | BY9: 4.0711202e+18 | BZ9: http://docquery.fec.gov/cgi-bin/fecimg/?202007099244393510 | CA9: Contributions From Individuals/Persons Other Than Political Committees
A10: C00046474 | B10: FORD MOTOR COMPANY CIVIC ACTION FUND | C10: 2020 | D10: M9 | E10: 2.0200918e+17 | F10: 11AI | G10: PR868935033701 | H10: 1438561 | J10: IND | K10: INDIVIDUAL | N10: HACKETT, JAMES P | O10: Q | P10: C | Q10: B | R10: JAMES | S10: P | T10: HACKETT | V10: 1547 BRIARCLIFF DR. SE | X10: GRAND RAPIDS | Y10: MI | Z10: 495469689 | AA10: FMC US | AB10: PRESIDENT & CEO | AD10: 15 | AE10: CONTRIBUTION | AI10: 44074 | AJ10: 300 | AK10: 2400 | BG10: P | BI10: PRIMARY | BK10: A | BL10: ADD | BM10: ITEMIZED RECEIPTS | BN10: 44092.152 | BR10: F3X | BS10: 4.0918202e+18 | BT10: t | BU10: P/R DEDUCTION ($300.00 MONTHLY) | BV10: 2020 | BW10: SA | BY10: 4.0918202e+18 | BZ10: http://docquery.fec.gov/cgi-bin/fecimg/?202009179267222512 | CA10: Contributions From Individuals/Persons Other Than Political Committees
A11: C00046474 | B11: FORD MOTOR COMPANY CIVIC ACTION FUND | C11: 2020 | D11: 12G | E11: 2.0201022e+17 | F11: 11AI | G11: PR868935034207 | H11: 1459687 | J11: IND | K11: INDIVIDUAL | N11: HACKETT, JAMES P | O11: Q | P11: C | Q11: B | R11: JAMES | S11: P | T11: HACKETT | V11: 1547 BRIARCLIFF DR. SE | X11: GRAND RAPIDS | Y11: MI | Z11: 495469689 | AA11: FORD MOTOR COMPANY | AB11: PRESIDENT & CEO | AD11: 15 | AE11: CONTRIBUTION | AI11: 44118 | AJ11: 300 | AK11: 3000 | BG11: P | BI11: PRIMARY | BK11: A | BL11: ADD | BM11: ITEMIZED RECEIPTS | BN11: 44168.152 | BR11: F3X | BS11: 4.1022202e+18 | BT11: t | BU11: P/R DEDUCTION ($300.00 MONTHLY) | BV11: 2020 | BW11: SA | BY11: 4.1203202e+18 | BZ11: http://docquery.fec.gov/cgi-bin/fecimg/?202010219326755902 | CA11: Contributions From Individuals/Persons Other Than Political Committees
A12: C00075820 | B12: NRCC | C12: 2020 | D12: YE | E12: 2.0210132e+17 | F12: 11AI | G12: SA11A.21390027 | H12: 1496211 | J12: IND | K12: INDIVIDUAL | N12: HACKETT, JAMES P. | O12: Y | Q12: U | R12: JAMES | S12: P. | T12: HACKETT | V12: 8455 S HERITAGE CT | X12: OAK CREEK | Y12: WI | Z12: 531543242 | AD12: 15 | AE12: CONTRIBUTION | AF12: CONTRIBUTION | AI12: 44174 | AJ12: 250 | AK12: 250 | BG12: P | BI12: PRIMARY | BK12: A | BL12: ADD | BM12: ITEMIZED RECEIPTS | BN12: 44231.449 | BR12: F3X | BS12: 4.0201202e+18 | BT12: t | BV12: 2020 | BW12: SA | BY12: 4.0203202e+18 | BZ12: https://docquery.fec.gov/cgi-bin/fecimg/?202101319418519386 | CA12: Contributions From Individuals/Persons Other Than Political Committees
A13: C00046474 | B13: FORD MOTOR COMPANY CIVIC ACTION FUND | C13: 2020 | D13: M10 | E13: 2.020102e+17 | F13: 11AI | G13: PR868935034128 | H13: 1456209 | J13: IND | K13: INDIVIDUAL | N13: HACKETT, JAMES P | O13: Q | P13: C | Q13: B | R13: JAMES | S13: P | T13: HACKETT | V13: 1547 BRIARCLIFF DR. SE | X13: GRAND RAPIDS | Y13: MI | Z13: 495469689 | AA13: FMC US | AB13: ADVISOR TO THE OCCE | AD13: 15 | AE13: CONTRIBUTION | AI13: 44104 | AJ13: 300 | AK13: 2700 | BG13: P | BI13: PRIMARY | BK13: A | BL13: ADD | BM13: ITEMIZED RECEIPTS | BN13: 44161.158 | BR13: F3X | BS13: 4.1020202e+18 | BT13: t | BU13: P/R DEDUCTION ($300.00 MONTHLY) | BV13: 2020 | BW13: SA | BY13: 4.1126202e+18 | BZ13: http://docquery.fec.gov/cgi-bin/fecimg/?202010199297279875 | CA13: Contributions From Individuals/Persons Other Than Political Committees
A14: C00046474 | B14: FORD MOTOR COMPANY CIVIC ACTION FUND | C14: 2020 | D14: 30G | E14: 2.0201202e+17 | F14: 11AI | G14: PR868935034585 | H14: 1475097 | J14: IND | K14: INDIVIDUAL | N14: HACKETT, JAMES P P | O14: Q | P14: C | Q14: B | R14: JAMES P | S14: P | T14: HACKETT | V14: 1547 BRIARCLIFF DR. SE | X14: GRAND RAPIDS | Y14: MI | Z14: 495469689 | AA14: FORD MOTOR COMPANY | AB14: PRESIDENT & CEO | AD14: 15 | AE14: CONTRIBUTION | AI14: 44158 | AJ14: 300 | AK14: 3300 | BG14: P | BI14: PRIMARY | BK14: A | BL14: ADD | BM14: ITEMIZED RECEIPTS | BN14: 44177.155 | BR14: F3X | BS14: 4.1202202e+18 | BT14: t | BU14: P/R DEDUCTION ($300.00 MONTHLY) | BV14: 2020 | BW14: SA | BY14: 4.1212202e+18 | BZ14: http://docquery.fec.gov/cgi-bin/fecimg/?202012019337235406 | CA14: Contributions From Individuals/Persons Other Than Political Committees
V17: =+V14&X14&Y14&Z14 -> 1547 BRIARCLIFF DR. SEGRAND RAPIDSMI495469689
A20: Row Labels | B20: Sum of contribution_receipt_amount
A21: FORD MOTOR COMPANY CIVIC ACTION FUND | B21: 3600 | D21: 0.6541 | E21: R | F21: =1-D21 -> 0.3459 | G21: D
A22: NRCC | B22: 250 | C22: R
A23: Grand Total | B23: 3850

Sheet Hau Thai-Tang
A1: committee_id | B1: committee_name | C1: report_year | D1: report_type | E1: image_number | F1: line_number | G1: transaction_id | H1: file_number | I1: committee_name | J1: entity_type | K1: entity_type_desc | L1: unused_contbr_id | M1: contributor_prefix | N1: contributor_name | O1: recipient_committee_type | P1: recipient_committee_org_type | Q1: recipient_committee_designation | R1: contributor_first_name | S1: contributor_middle_name | T1: contributor_last_name | U1: contributor_suffix | V1: contributor_street_1 | W1: contributor_street_2 | X1: contributor_city | Y1: contributor_state | Z1: contributor_zip | AA1: contributor_employer | AB1: contributor_occupation | AC1: contributor_id | AD1: receipt_type | AE1: receipt_type_desc | AF1: receipt_type_full | AG1: memo_code | AH1: memo_code_full | AI1: contribution_receipt_date | AJ1: contribution_receipt_amount | AK1: contributor_aggregate_ytd | AL1: candidate_id | AM1: candidate_name | AN1: candidate_first_name | AO1: candidate_last_name | AP1: candidate_middle_name | AQ1: candidate_prefix | AR1: candidate_suffix | AS1: candidate_office | AT1: candidate_office_full | AU1: candidate_office_state | AV1: candidate_office_state_full | AW1: candidate_office_district | AX1: conduit_committee_id | AY1: conduit_committee_name | AZ1: conduit_committee_street1 | BA1: conduit_committee_street2 | BB1: conduit_committee_city | BC1: conduit_committee_state | BD1: conduit_committee_zip | BE1: donor_committee_name | BF1: national_committee_nonfederal_account | BG1: election_type | BH1: election_type_full | BI1: fec_election_type_desc | BJ1: fec_election_year | BK1: amendment_indicator | BL1: amendment_indicator_desc | BM1: schedule_type_full | BN1: load_date | BO1: original_sub_id | BP1: back_reference_transaction_id | BQ1: back_reference_schedule_name | BR1: filing_form | BS1: link_id | BT1: is_individual | BU1: memo_text | BV1: two_year_transaction_period | BW1: schedule_type | BX1: increased_limit | BY1: sub_id | BZ1: pdf_url | CA1: line_number_label
A2: C00046474 | B2: FORD MOTOR COMPANY CIVIC ACTION FUND | C2: 2019 | D2: YE | E2: 2.0200129e+17 | F2: 11AI | G2: PR209587231700 | H2: 1374056 | J2: IND | K2: INDIVIDUAL | M2: MR | N2: THAI-TANG, HAU N MR | O2: Q | P2: C | Q2: B | R2: HAU N | T2: THAI-TANG | V2: 1362 JUNIPER LN | X2: BLOOMFIELD HILLS | Y2: MI | Z2: 483021959 | AA2: FORD MOTOR COMPANY | AB2: EXECUTIVE VICE PRESIDENT | AD2: 15 | AE2: CONTRIBUTION | AI2: 43830 | AJ2: 416 | AK2: 4992 | BG2: P | BI2: PRIMARY | BK2: A | BL2: ADD | BM2: ITEMIZED RECEIPTS | BN2: 43859.073 | BR2: F3X | BS2: 4.0128202e+18 | BT2: t | BU2: P/R DEDUCTION ($416.00 MONTHLY) | BV2: 2020 | BW2: SA | BY2: 4.0128202e+18 | BZ2: http://docquery.fec.gov/cgi-bin/fecimg/?202001289167420168 | CA2: Contributions From Individuals/Persons Other Than Political Committees
A3: C00046474 | B3: FORD MOTOR COMPANY CIVIC ACTION FUND | C3: 2019 | D3: M12 | E3: 2.0191219e+17 | F3: 11AI | G3: PR209587231137 | H3: 1366669 | J3: IND | K3: INDIVIDUAL | M3: MR | N3: THAI-TANG, HAU N MR | O3: Q | P3: C | Q3: B | R3: HAU | S3: N | T3: THAI-TANG | V3: 1362 JUNIPER LN | X3: BLOOMFIELD HILLS | Y3: MI | Z3: 483021959 | AA3: FORD MOTOR COMPANY | AB3: EXECUTIVE VICE PRESIDENT | AD3: 15 | AE3: CONTRIBUTION | AI3: 43799 | AJ3: 416 | AK3: 4576 | BG3: P | BI3: PRIMARY | BK3: A | BL3: ADD | BM3: ITEMIZED RECEIPTS | BN3: 43818.072 | BR3: F3X | BS3: 4.1218202e+18 | BT3: t | BU3: P/R DEDUCTION ($416.00 MONTHLY) | BV3: 2020 | BW3: SA | BY3: 4.1218202e+18 | BZ3: http://docquery.fec.gov/cgi-bin/fecimg/?201912189166359367 | CA3: Contributions From Individuals/Persons Other Than Political Committees
A4: C00046474 | B4: FORD MOTOR COMPANY CIVIC ACTION FUND | C4: 2020 | D4: M8 | E4: 2.0200815e+17 | F4: 11AI | G4: PR209587233448 | H4: 1432298 | J4: IND | K4: INDIVIDUAL | M4: MR | N4: THAI-TANG, HAU N MR | O4: Q | P4: C | Q4: B | R4: HAU | S4: N | T4: THAI-TANG | V4: 1362 JUNIPER LN | X4: BLOOMFIELD HILLS | Y4: MI | Z4: 483021959 | AA4: FMC US | AB4: CHIEF PD & PURCHASING OFFICER | AD4: 15 | AE4: CONTRIBUTION | AI4: 44043 | AJ4: 416 | AK4: 2912 | BG4: P | BI4: PRIMARY | BK4: A | BL4: ADD | BM4: ITEMIZED RECEIPTS | BN4: 44065.164 | BR4: F3X | BS4: 4.0815202e+18 | BT4: t | BU4: P/R DEDUCTION ($416.00 MONTHLY) | BV4: 2020 | BW4: SA | BY4: 4.0822202e+18 | BZ4: http://docquery.fec.gov/cgi-bin/fecimg/?202008149261306646 | CA4: Contributions From Individuals/Persons Other Than Political Committees
A5: C00046474 | B5: FORD MOTOR COMPANY CIVIC ACTION FUND | C5: 2020 | D5: M2 | E5: 2.0200219e+17 | F5: 11AI | G5: PR209587231849 | H5: 1383073 | J5: IND | K5: INDIVIDUAL | M5: MR | N5: THAI-TANG, HAU N MR | O5: Q | P5: C | Q5: B | R5: HAU N | T5: THAI-TANG | V5: 1362 JUNIPER LN | X5: BLOOMFIELD HILLS | Y5: MI | Z5: 483021959 | AA5: FORD MOTOR COMPANY | AB5: EXECUTIVE VICE PRESIDENT | AD5: 15 | AE5: CONTRIBUTION | AI5: 43861 | AJ5: 416 | AK5: 416 | BG5: P | BI5: PRIMARY | BK5: A | BL5: ADD | BM5: ITEMIZED RECEIPTS | BN5: 43886.075 | BR5: F3X | BS5: 4.0218202e+18 | BT5: t | BU5: P/R DEDUCTION ($416.00 MONTHLY) | BV5: 2020 | BW5: SA | BY5: 4.0224202e+18 | BZ5: http://docquery.fec.gov/cgi-bin/fecimg/?202002189186515551 | CA5: Contributions From Individuals/Persons Other Than Political Committees
A6: C00046474 | B6: FORD MOTOR COMPANY CIVIC ACTION FUND | C6: 2020 | D6: YE | E6: 2.0210116e+17 | F6: 11AI | G6: PR209587235156 | H6: 1488043 | J6: IND | K6: INDIVIDUAL | M6: MR | N6: THAI-TANG, HAU N MR | O6: Q | P6: C | Q6: B | R6: HAU | S6: N | T6: THAI-TANG | V6: 1362 JUNIPER LN | X6: BLOOMFIELD HILLS | Y6: MI | Z6: 483021959 | AA6: FMC US | AB6: CHIEF PRODUCT PLATFORM & OPS | AD6: 15 | AE6: CONTRIBUTION | AI6: 44196 | AJ6: 416 | AK6: 4992 | BG6: P | BI6: PRIMARY | BK6: A | BL6: ADD | BM6: ITEMIZED RECEIPTS | BN6: 44212.068 | BR6: F3X | BS6: 4.0115202e+18 | BT6: t | BU6: P/R DEDUCTION ($416.00 MONTHLY) | BV6: 2020 | BW6: SA | BY6: 4.0115202e+18 | BZ6: https://docquery.fec.gov/cgi-bin/fecimg/?202101159404712797 | CA6: Contributions From Individuals/Persons Other Than Political Committees
A7: C00046474 | B7: FORD MOTOR COMPANY CIVIC ACTION FUND | C7: 2020 | D7: M3 | E7: 2.0200319e+17 | F7: 11AI | G7: PR209587232112 | H7: 1390420 | J7: IND | K7: INDIVIDUAL | M7: MR | N7: THAI-TANG, HAU N MR | O7: Q | P7: C | Q7: B | R7: HAU | S7: N | T7: THAI-TANG | V7: 1362 JUNIPER LN | X7: BLOOMFIELD HILLS | Y7: MI | Z7: 483021959 | AA7: FORD MOTOR COMPANY | AB7: EXECUTIVE VICE PRESIDENT | AD7: 15 | AE7: CONTRIBUTION | AI7: 43890 | AJ7: 416 | AK7: 832 | BG7: P | BI7: PRIMARY | BK7: A | BL7: ADD | BM7: ITEMIZED RECEIPTS | BN7: 43909.096 | BR7: F3X | BS7: 4.0318202e+18 | BT7: t | BU7: P/R DEDUCTION ($416.00 MONTHLY) | BV7: 2020 | BW7: SA | BY7: 4.0318202e+18 | BZ7: http://docquery.fec.gov/cgi-bin/fecimg/?202003189203874360 | CA7: Contributions From Individuals/Persons Other Than Political Committees
A8: C00046474 | B8: FORD MOTOR COMPANY CIVIC ACTION FUND | C8: 2020 | D8: M7 | E8: 2.020071e+17 | F8: 11AI | G8: PR209587233026 | H8: 1418223 | J8: IND | K8: INDIVIDUAL | M8: MR | N8: THAI-TANG, HAU N MR | O8: Q | P8: C | Q8: B | R8: HAU | S8: N | T8: THAI-TANG | V8: 1362 JUNIPER LN | X8: BLOOMFIELD HILLS | Y8: MI | Z8: 483021959 | AA8: FMC US | AB8: CHIEF PD & PURCHASING OFFICER | AD8: 15 | AE8: CONTRIBUTION | AI8: 44012 | AJ8: 416 | AK8: 2496 | BG8: P | BI8: PRIMARY | BK8: A | BL8: ADD | BM8: ITEMIZED RECEIPTS | BN8: 44023.088 | BR8: F3X | BS8: 4.0709202e+18 | BT8: t | BU8: P/R DEDUCTION ($416.00 MONTHLY) | BV8: 2020 | BW8: SA | BY8: 4.0710202e+18 | BZ8: http://docquery.fec.gov/cgi-bin/fecimg/?202007099244394512 | CA8: Contributions From Individuals/Persons Other Than Political Committees
A9: C00046474 | B9: FORD MOTOR COMPANY CIVIC ACTION FUND | C9: 2020 | D9: M6 | E9: 2.020071e+17 | F9: 11AI | G9: PR209587232739 | H9: 1418185 | J9: IND | K9: INDIVIDUAL | M9: MR | N9: THAI-TANG, HAU N MR | O9: Q | P9: C | Q9: B | R9: HAU | S9: N | T9: THAI-TANG | V9: 1362 JUNIPER LN | X9: BLOOMFIELD HILLS | Y9: MI | Z9: 483021959 | AA9: FMC US | AB9: CHIEF PD & PURCHASING OFFICER | AD9: 15 | AE9: CONTRIBUTION | AI9: 43982 | AJ9: 416 | AK9: 2080 | BG9: P | BI9: PRIMARY | BK9: A | BL9: ADD | BM9: ITEMIZED RECEIPTS | BN9: 44024.093 | BR9: F3X | BS9: 4.0709202e+18 | BT9: t | BU9: P/R DEDUCTION ($416.00 MONTHLY) | BV9: 2020 | BW9: SA | BY9: 4.0711202e+18 | BZ9: http://docquery.fec.gov/cgi-bin/fecimg/?202007099244393363 | CA9: Contributions From Individuals/Persons Other Than Political Committees
A10: C00046474 | B10: FORD MOTOR COMPANY CIVIC ACTION FUND | C10: 2020 | D10: M9 | E10: 2.0200918e+17 | F10: 11AI | G10: PR209587233701 | H10: 1438561 | J10: IND | K10: INDIVIDUAL | M10: MR | N10: THAI-TANG, HAU N MR | O10: Q | P10: C | Q10: B | R10: HAU | S10: N | T10: THAI-TANG | V10: 1362 JUNIPER LN | X10: BLOOMFIELD HILLS | Y10: MI | Z10: 483021959 | AA10: FMC US | AB10: CHIEF PD & PURCHASING OFFICER | AD10: 15 | AE10: CONTRIBUTION | AI10: 44074 | AJ10: 416 | AK10: 3328 | BG10: P | BI10: PRIMARY | BK10: A | BL10: ADD | BM10: ITEMIZED RECEIPTS | BN10: 44092.152 | BR10: F3X | BS10: 4.0918202e+18 | BT10: t | BU10: P/R DEDUCTION ($416.00 MONTHLY) | BV10: 2020 | BW10: SA | BY10: 4.0918202e+18 | BZ10: http://docquery.fec.gov/cgi-bin/fecimg/?202009179267222246 | CA10: Contributions From Individuals/Persons Other Than Political Committees
A11: C00046474 | B11: FORD MOTOR COMPANY CIVIC ACTION FUND | C11: 2020 | D11: 12G | E11: 2.0201022e+17 | F11: 11AI | G11: PR209587234207 | H11: 1459687 | J11: IND | K11: INDIVIDUAL | M11: MR | N11: THAI-TANG, HAU N MR | O11: Q | P11: C | Q11: B | R11: HAU | S11: N | T11: THAI-TANG | V11: 1362 JUNIPER LN | X11: BLOOMFIELD HILLS | Y11: MI | Z11: 483021959 | AA11: FORD MOTOR COMPANY | AB11: EXECUTIVE VICE PRESIDENT | AD11: 15 | AE11: CONTRIBUTION | AI11: 44118 | AJ11: 416 | AK11: 4160 | BG11: P | BI11: PRIMARY | BK11: A | BL11: ADD | BM11: ITEMIZED RECEIPTS | BN11: 44168.152 | BR11: F3X | BS11: 4.1022202e+18 | BT11: t | BU11: P/R DEDUCTION ($416.00 MONTHLY) | BV11: 2020 | BW11: SA | BY11: 4.1203202e+18 | BZ11: http://docquery.fec.gov/cgi-bin/fecimg/?202010219326755627 | CA11: Contributions From Individuals/Persons Other Than Political Committees
A12: C00046474 | B12: FORD MOTOR COMPANY CIVIC ACTION FUND | C12: 2020 | D12: M10 | E12: 2.020102e+17 | F12: 11AI | G12: PR209587234128 | H12: 1456209 | J12: IND | K12: INDIVIDUAL | M12: MR | N12: THAI-TANG, HAU N MR | O12: Q | P12: C | Q12: B | R12: HAU | S12: N | T12: THAI-TANG | V12: 1362 JUNIPER LN | X12: BLOOMFIELD HILLS | Y12: MI | Z12: 483021959 | AA12: FMC US | AB12: CHIEF PD & PURCHASING OFFICER | AD12: 15 | AE12: CONTRIBUTION | AI12: 44104 | AJ12: 416 | AK12: 3744 | BG12: P | BI12: PRIMARY | BK12: A | BL12: ADD | BM12: ITEMIZED RECEIPTS | BN12: 44161.158 | BR12: F3X | BS12: 4.1020202e+18 | BT12: t | BU12: P/R DEDUCTION ($416.00 MONTHLY) | BV12: 2020 | BW12: SA | BY12: 4.1126202e+18 | BZ12: http://docquery.fec.gov/cgi-bin/fecimg/?202010199297279613 | CA12: Contributions From Individuals/Persons Other Than Political Committees
A13: C00046474 | B13: FORD MOTOR COMPANY CIVIC ACTION FUND | C13: 2020 | D13: 30G | E13: 2.0201202e+17 | F13: 11AI | G13: PR209587234585 | H13: 1475097 | J13: IND | K13: INDIVIDUAL | M13: MR | N13: THAI-TANG, HAU N N MR | O13: Q | P13: C | Q13: B | R13: HAU N | S13: N | T13: THAI-TANG | V13: 1362 JUNIPER LN | X13: BLOOMFIELD HILLS | Y13: MI | Z13: 483021959 | AA13: FORD MOTOR COMPANY | AB13: EXECUTIVE VICE PRESIDENT | AD13: 15 | AE13: CONTRIBUTION | AI13: 44158 | AJ13: 416 | AK13: 4576 | BG13: P | BI13: PRIMARY | BK13: A | BL13: ADD | BM13: ITEMIZED RECEIPTS | BN13: 44177.155 | BR13: F3X | BS13: 4.1202202e+18 | BT13: t | BU13: P/R DEDUCTION ($416.00 MONTHLY) | BV13: 2020 | BW13: SA | BY13: 4.1212202e+18 | BZ13: http://docquery.fec.gov/cgi-bin/fecimg/?202012019337235101 | CA13: Contributions From Individuals/Persons Other Than Political Committees
V16: =+V13&X13&Y13&Z13 -> 1362 JUNIPER LNBLOOMFIELD HILLSMI483021959
A20: Row Labels | B20: Sum of contribution_receipt_amount
A21: FORD MOTOR COMPANY CIVIC ACTION FUND | B21: 4992 | C21: 0.6541 | D21: R
A22: Grand Total | B22: 4992 | C22: =1-C21 -> 0.3459 | D22: D

Sheet John Thornton
A1: committee_id | B1: committee_name | C1: report_year | D1: report_type | E1: image_number | F1: line_number | G1: transaction_id | H1: file_number | I1: committee_name | J1: entity_type | K1: entity_type_desc | L1: unused_contbr_id | M1: contributor_prefix | N1: contributor_name | O1: recipient_committee_type | P1: recipient_committee_org_type | Q1: recipient_committee_designation | R1: contributor_first_name | S1: contributor_middle_name | T1: contributor_last_name | U1: contributor_suffix | V1: contributor_street_1 | W1: contributor_street_2 | X1: contributor_city | Y1: contributor_state | Z1: contributor_zip | AA1: contributor_employer | AB1: contributor_occupation | AC1: contributor_id | AD1: receipt_type | AE1: receipt_type_desc | AF1: receipt_type_full | AG1: memo_code | AH1: memo_code_full | AI1: contribution_receipt_date | AJ1: contribution_receipt_amount | AK1: contributor_aggregate_ytd | AL1: candidate_id | AM1: candidate_name | AN1: candidate_first_name | AO1: candidate_last_name | AP1: candidate_middle_name | AQ1: candidate_prefix | AR1: candidate_suffix | AS1: candidate_office | AT1: candidate_office_full | AU1: candidate_office_state | AV1: candidate_office_state_full | AW1: candidate_office_district | AX1: conduit_committee_id | AY1: conduit_committee_name | AZ1: conduit_committee_street1 | BA1: conduit_committee_street2 | BB1: conduit_committee_city | BC1: conduit_committee_state | BD1: conduit_committee_zip | BE1: donor_committee_name | BF1: national_committee_nonfederal_account | BG1: election_type | BH1: election_type_full | BI1: fec_election_type_desc | BJ1: fec_election_year | BK1: amendment_indicator | BL1: amendment_indicator_desc | BM1: schedule_type_full | BN1: load_date | BO1: original_sub_id | BP1: back_reference_transaction_id | BQ1: back_reference_schedule_name | BR1: filing_form | BS1: link_id | BT1: is_individual | BU1: memo_text | BV1: two_year_transaction_period | BW1: schedule_type | BX1: increased_limit | BY1: sub_id | BZ1: pdf_url | CA1: line_number_label
A2: C00760124 | B2: NATIONAL VICTORY ACTION FUND | C2: 2020 | D2: YE | E2: 2.0210311e+17 | F2: 11AI | G2: A483E631E09D9431E981 | H2: 1503618 | J2: IND | K2: INDIVIDUAL | N2: THORNTON, JOHN | O2: V | Q2: U | R2: JOHN | T2: THORNTON | V2: 5108 LEWELLYN ROAD | X2: LAKELAND | Y2: FL | Z2: 33810 | AA2: RETIRED | AB2: RETIRED | AF2: CONTRIBUTION | AI2: 44166 | AJ2: 50 | AK2: 75 | BK2: A | BL2: ADD | BM2: ITEMIZED RECEIPTS | BN2: 44270.15 | BR2: F3X | BS2: 4.0311202e+18 | BT2: t | BV2: 2020 | BW2: SA | BY2: 4.0315202e+18 | BZ2: https://docquery.fec.gov/cgi-bin/fecimg/?202103109440432720 | CA2: Contributions From Individuals/Persons Other Than Political Committees
A3: C00618371 | B3: TRUMP MAKE AMERICA GREAT AGAIN COMMITTEE | C3: 2020 | D3: Q3 | E3: 2.021021e+17 | F3: 11AI | G3: SA11AI.1582602 | H3: 1499308 | J3: IND | K3: INDIVIDUAL | N3: THORNTON, ,, JOHN | O3: N | Q3: J | R3: JOHN | T3: THORNTON, , | V3: 5108 LEWELLYN RD | X3: LAKELAND | Y3: FL | Z3: 33810 | AA3: RETIRED | AB3: RETIRED | AF3: EARMARKED THROUGH WINRED [SA11AI.4498] | AI3: 44016 | AJ3: 42 | AK3: 42 | BK3: A | BL3: ADD | BM3: ITEMIZED RECEIPTS | BN3: 44249.164 | BR3: F3X | BS3: 4.0211202e+18 | BT3: t | BV3: 2020 | BW3: SA | BY3: 4.0222202e+18 | BZ3: https://docquery.fec.gov/cgi-bin/fecimg/?202102099427616884 | CA3: Contributions From Individuals/Persons Other Than Political Committees
A4: C00618371 | B4: TRUMP MAKE AMERICA GREAT AGAIN COMMITTEE | C4: 2020 | D4: Q3 | E4: 2.021021e+17 | F4: 11AI | G4: SA11AI.1582603 | H4: 1499308 | J4: IND | K4: INDIVIDUAL | N4: THORNTON, ,, JOHN | O4: N | Q4: J | R4: JOHN | T4: THORNTON, , | V4: 5108 LEWELLYN RD | X4: LAKELAND | Y4: FL | Z4: 33810 | AA4: RETIRED | AB4: RETIRED | AF4: EARMARKED THROUGH WINRED [SA11AI.4499] | AI4: 44019 | AJ4: 35 | AK4: 77 | BK4: A | BL4: ADD | BM4: ITEMIZED RECEIPTS | BN4: 44249.164 | BR4: F3X | BS4: 4.0211202e+18 | BT4: t | BV4: 2020 | BW4: SA | BY4: 4.0222202e+18 | BZ4: https://docquery.fec.gov/cgi-bin/fecimg/?202102099427616884 | CA4: Contributions From Individuals/Persons Other Than Political Committees
A5: C00618371 | B5: TRUMP MAKE AMERICA GREAT AGAIN COMMITTEE | C5: 2020 | D5: Q3 | E5: 2.021021e+17 | F5: 11AI | G5: SA11AI.1582604 | H5: 1499308 | J5: IND | K5: INDIVIDUAL | N5: THORNTON, ,, JOHN | O5: N | Q5: J | R5: JOHN | T5: THORNTON, , | V5: 5108 LEWELLYN RD | X5: LAKELAND | Y5: FL | Z5: 33810 | AA5: RETIRED | AB5: RETIRED | AF5: EARMARKED THROUGH WINRED [SA11AI.4504] | AI5: 44026 | AJ5: 42 | AK5: 119 | BK5: A | BL5: ADD | BM5: ITEMIZED RECEIPTS | BN5: 44249.164 | BR5: F3X | BS5: 4.0211202e+18 | BT5: t | BV5: 2020 | BW5: SA | BY5: 4.0222202e+18 | BZ5: https://docquery.fec.gov/cgi-bin/fecimg/?202102099427616885 | CA5: Contributions From Individuals/Persons Other Than Political Committees
A6: C00618371 | B6: TRUMP MAKE AMERICA GREAT AGAIN COMMITTEE | C6: 2020 | D6: Q3 | E6: 2.021021e+17 | F6: 11AI | G6: SA11AI.1582599 | H6: 1499308 | J6: IND | K6: INDIVIDUAL | N6: THORNTON, ,, JOHN | O6: N | Q6: J | R6: JOHN | T6: THORNTON, , | V6: 5108 LEWELLYN RD | X6: LAKELAND | Y6: FL | Z6: 33810 | AA6: RETIRED | AB6: RETIRED | AF6: EARMARKED THROUGH WINRED [SA11A1.4523] | AI6: 44047 | AJ6: 42 | AK6: 161 | BK6: A | BL6: ADD | BM6: ITEMIZED RECEIPTS | BN6: 44249.164 | BR6: F3X | BS6: 4.0211202e+18 | BT6: t | BV6: 2020 | BW6: SA | BY6: 4.0222202e+18 | BZ6: https://docquery.fec.gov/cgi-bin/fecimg/?202102099427616885 | CA6: Contributions From Individuals/Persons Other Than Political Committees
A7: C00618371 | B7: TRUMP MAKE AMERICA GREAT AGAIN COMMITTEE | C7: 2020 | D7: Q3 | E7: 2.021021e+17 | F7: 11AI | G7: SA11AI.1582600 | H7: 1499308 | J7: IND | K7: INDIVIDUAL | N7: THORNTON, ,, JOHN | O7: N | Q7: J | R7: JOHN | T7: THORNTON, , | V7: 5108 LEWELLYN RD | X7: LAKELAND | Y7: FL | Z7: 33810 | AA7: RETIRED | AB7: RETIRED | AD7: 15E | AE7: EARMARKED CONTRIBUTION | AF7: EARMARKED THROUGH WINRED [SA11A1.4540] | AI7: 44078 | AJ7: 42 | AK7: 203 | BG7: P | BI7: PRIMARY | BK7: A | BL7: ADD | BM7: ITEMIZED RECEIPTS | BN7: 44249.164 | BR7: F3X | BS7: 4.0211202e+18 | BT7: t | BV7: 2020 | BW7: SA | BY7: 4.0222202e+18 | BZ7: https://docquery.fec.gov/cgi-bin/fecimg/?202102099427616885 | CA7: Contributions From Individuals/Persons Other Than Political Committees
A8: C00694323 | B8: WINRED | C8: 2020 | D8: Q3 | E8: 2.0210126e+17 | F8: 11AI | G8: A3FB0320EE7914840B4B | H8: 1490496 | J8: IND | K8: INDIVIDUAL | L8: C00491357 | N8: THORNTON, JOHN | O8: V | Q8: U | R8: JOHN | T8: THORNTON | V8: 5108 LEWELLYN RD | X8: LAKELAND | Y8: FL | Z8: 338100789 | AA8: RETIRED | AB8: RETIRED | AC8: C00491357 | AD8: 15E | AE8: EARMARKED CONTRIBUTION | AF8: EARMARKED FOR STEVE DAINES FOR MONTANA (C00491357) | AI8: 44078 | AJ8: 10 | AK8: 1097.76 | AL8: S2MT00096 | BK8: A | BL8: ADD | BM8: ITEMIZED RECEIPTS | BN8: 44252.57 | BR8: F3X | BS8: 4.0125202e+18 | BT8: t | BV8: 2020 | BW8: SA | BY8: 4.0224202e+18 | BZ8: https://docquery.fec.gov/cgi-bin/fecimg/?202101259407874977 | CA8: Contributions From Individuals/Persons Other Than Political Committees
A9: C00618371 | B9: TRUMP MAKE AMERICA GREAT AGAIN COMMITTEE | C9: 2020 | D9: Q3 | E9: 2.021021e+17 | F9: 11AI | G9: SA11AI.1582601 | H9: 1499308 | J9: IND | K9: INDIVIDUAL | N9: THORNTON, ,, JOHN | O9: N | Q9: J | R9: JOHN | T9: THORNTON, , | V9: 5108 LEWELLYN RD | X9: LAKELAND | Y9: FL | Z9: 33810 | AA9: RETIRED | AB9: RETIRED | AD9: 15E | AE9: EARMARKED CONTRIBUTION | AF9: EARMARKED THROUGH WINRED [SA11A1.4552] | AI9: 44097 | AJ9: 10 | AK9: 213 | BG9: P | BI9: PRIMARY | BK9: A | BL9: ADD | BM9: ITEMIZED RECEIPTS | BN9: 44249.164 | BR9: F3X | BS9: 4.0211202e+18 | BT9: t | BV9: 2020 | BW9: SA | BY9: 4.0222202e+18 | BZ9: https://docquery.fec.gov/cgi-bin/fecimg/?202102099427616886 | CA9: Contributions From Individuals/Persons Other Than Political Committees
A10: C00694323 | B10: WINRED | C10: 2020 | D10: Q3 | E10: 2.0210126e+17 | F10: 11AI | G10: AF6F8E7866BAB4671B11 | H10: 1490496 | J10: IND | K10: INDIVIDUAL | L10: C00458828 | N10: THORNTON, JOHN | O10: V | Q10: U | R10: JOHN | T10: THORNTON | V10: 5108 LEWELLYN RD | X10: LAKELAND | Y10: FL | Z10: 338100789 | AA10: RETIRED | AB10: RETIRED | AC10: C00458828 | AD10: 15E | AE10: EARMARKED CONTRIBUTION | AF10: EARMARKED FOR TEAM GRAHAM, INC. (C00458828) | AI10: 44095 | AJ10: 10 | AK10: 1177.76 | AL10: S0SC00149 | BK10: A | BL10: ADD | BM10: ITEMIZED RECEIPTS | BN10: 44252.579 | BR10: F3X | BS10: 4.0125202e+18 | BT10: t | BV10: 2020 | BW10: SA | BY10: 4.0224202e+18 | BZ10: https://docquery.fec.gov/cgi-bin/fecimg/?202101259408605706 | CA10: Contributions From Individuals/Persons Other Than Political Committees
A11: C00694323 | B11: WINRED | C11: 2020 | D11: Q3 | E11: 2.0210126e+17 | F11: 11AI | G11: A3F98367D591F4264B1A | H11: 1490496 | J11: IND | K11: INDIVIDUAL | L11: C00705236 | N11: THORNTON, JOHN | O11: V | Q11: U | R11: JOHN | T11: THORNTON | V11: 5108 LEWELLYN RD | X11: LAKELAND | Y11: FL | Z11: 338100789 | AA11: RETIRED | AB11: RETIRED | AC11: C00705236 | AD11: 15E | AE11: EARMARKED CONTRIBUTION | AF11: EARMARKED FOR JOE COLLINS FOR CONGRESS (C00705236) | AI11: 44104 | AJ11: 10 | AK11: 1312.76 | AL11: H0CA43108 | BK11: A | BL11: ADD | BM11: ITEMIZED RECEIPTS | BN11: 44252.572 | BR11: F3X | BS11: 4.0125202e+18 | BT11: t | BV11: 2020 | BW11: SA | BY11: 4.0224202e+18 | BZ11: https://docquery.fec.gov/cgi-bin/fecimg/?202101259409207202 | CA11: Contributions From Individuals/Persons Other Than Political Committees
A12: C00694323 | B12: WINRED | C12: 2020 | D12: Q3 | E12: 2.0210126e+17 | F12: 11AI | G12: A32BED74D3B85487DA14 | H12: 1490496 | J12: IND | K12: INDIVIDUAL | L12: C00711689 | N12: THORNTON, JOHN | O12: V | Q12: U | R12: JOHN | T12: THORNTON | V12: 5108 LEWELLYN RD | X12: LAKELAND | Y12: FL | Z12: 338100789 | AA12: RETIRED | AB12: RETIRED | AC12: C00711689 | AD12: 15E | AE12: EARMARKED CONTRIBUTION | AF12: EARMARKED FOR LACY JOHNSON FOR CONGRESS (C00711689) | AI12: 44052 | AJ12: 15 | AK12: 868 | AL12: H0MN05178 | BK12: A | BL12: ADD | BM12: ITEMIZED RECEIPTS | BN12: 44252.575 | BR12: F3X | BS12: 4.0125202e+18 | BT12: t | BV12: 2020 | BW12: SA | BY12: 4.0224202e+18 | BZ12: https://docquery.fec.gov/cgi-bin/fecimg/?202101259406737909 | CA12: Contributions From Individuals/Persons Other Than Political Committees
A13: C00694323 | B13: WINRED | C13: 2020 | D13: Q3 | E13: 2.0210126e+17 | F13: 11AI | G13: A416D250CCD364110B11 | H13: 1490496 | J13: IND | K13: INDIVIDUAL | L13: C00666040 | N13: THORNTON, JOHN | O13: V | Q13: U | R13: JOHN | T13: THORNTON | V13: 5108 LEWELLYN RD | X13: LAKELAND | Y13: FL | Z13: 338100789 | AA13: RETIRED | AB13: RETIRED | AC13: C00666040 | AD13: 15E | AE13: EARMARKED CONTRIBUTION | AF13: EARMARKED FOR MCSALLY FOR SENATE INC (C00666040) | AI13: 44102 | AJ13: 10 | AK13: 1292.76 | AL13: S8AZ00221 | BK13: A | BL13: ADD | BM13: ITEMIZED RECEIPTS | BN13: 44252.572 | BR13: F3X | BS13: 4.0125202e+18 | BT13: t | BV13: 2020 | BW13: SA | BY13: 4.0224202e+18 | BZ13: https://docquery.fec.gov/cgi-bin/fecimg/?202101259409014897 | CA13: Contributions From Individuals/Persons Other Than Political Committees
A14: C00694323 | B14: WINRED | C14: 2020 | D14: Q3 | E14: 2.0210126e+17 | F14: 11AI | G14: A5E31552C130546A5B14 | H14: 1490496 | J14: IND | K14: INDIVIDUAL | L14: C00711689 | N14: THORNTON, JOHN | O14: V | Q14: U | R14: JOHN | T14: THORNTON | V14: 5108 LEWELLYN RD | X14: LAKELAND | Y14: FL | Z14: 338100789 | AA14: RETIRED | AB14: RETIRED | AC14: C00711689 | AD14: 15E | AE14: EARMARKED CONTRIBUTION | AF14: EARMARKED FOR LACY JOHNSON FOR CONGRESS (C00711689) | AI14: 44057 | AJ14: 5 | AK14: 920.76 | AL14: H0MN05178 | BK14: A | BL14: ADD | BM14: ITEMIZED RECEIPTS | BN14: 44252.575 | BR14: F3X | BS14: 4.0125202e+18 | BT14: t | BV14: 2020 | BW14: SA | BY14: 4.0224202e+18 | BZ14: https://docquery.fec.gov/cgi-bin/fecimg/?202101259406914136 | CA14: Contributions From Individuals/Persons Other Than Political Committees
A15: C00694323 | B15: WINRED | C15: 2020 | D15: Q3 | E15: 2.0210126e+17 | F15: 11AI | G15: AF735D59B56964034AFC | H15: 1490496 | J15: IND | K15: INDIVIDUAL | L15: C00618371 | N15: THORNTON, JOHN | O15: V | Q15: U | R15: JOHN | T15: THORNTON | V15: 5108 LEWELLYN RD | X15: LAKELAND | Y15: FL | Z15: 338100789 | AA15: RETIRED | AB15: RETIRED | AC15: C00618371 | AD15: 15E | AE15: EARMARKED CONTRIBUTION | AF15: EARMARKED FOR TRUMP MAKE AMERICA GREAT AGAIN COMMITTEE (C00618371) | AI15: 44026 | AJ15: 42 | AK15: 766 | BK15: A | BL15: ADD | BM15: ITEMIZED RECEIPTS | BN15: 44252.579 | BR15: F3X | BS15: 4.0125202e+18 | BT15: t | BV15: 2020 | BW15: SA | BY15: 4.0224202e+18 | BZ15: https://docquery.fec.gov/cgi-bin/fecimg/?202101259405823117 | CA15: Contributions From Individuals/Persons Other Than Political Committees
A16: C00694323 | B16: WINRED | C16: 2020 | D16: Q3 | E16: 2.0210126e+17 | F16: 11AI | G16: AF6ED570C08314B20B7A | H16: 1490496 | J16: IND | K16: INDIVIDUAL | L16: C00504530 | N16: THORNTON, JOHN | O16: V | Q16: U | R16: JOHN | T16: THORNTON | V16: 5108 LEWELLYN RD | X16: LAKELAND | Y16: FL | Z16: 338100789 | AA16: RETIRED | AB16: RETIRED | AC16: C00504530 | AD16: 15E | AE16: EARMARKED CONTRIBUTION | AF16: EARMARKED FOR CONGRESSIONAL LEADERSHIP FUND (C00504530) | AI16: 44067 | AJ16: 5 | AK16: 970.76 | BK16: A | BL16: ADD | BM16: ITEMIZED RECEIPTS | BN16: 44252.579 | BR16: F3X | BS16: 4.0125202e+18 | BT16: t | BV16: 2020 | BW16: SA | BY16: 4.0224202e+18 | BZ16: https://docquery.fec.gov/cgi-bin/fecimg/?202101259407302643 | CA16: Contributions From Individuals/Persons Other Than Political Committees
A17: C00694323 | B17: WINRED | C17: 2020 | D17: Q3 | E17: 2.0210126e+17 | F17: 11AI | G17: AED598872614C4CC0AB1 | H17: 1490496 | J17: IND | K17: INDIVIDUAL | L17: C00716860 | N17: THORNTON, JOHN | O17: V | Q17: U | R17: JOHN | T17: THORNTON | V17: 5108 LEWELLYN RD | X17: LAKELAND | Y17: FL | Z17: 338100789 | AA17: RETIRED | AB17: RETIRED | AC17: C00716860 | AD17: 15E | AE17: EARMARKED CONTRIBUTION | AF17: EARMARKED FOR JASON LEWIS FOR SENATE (C00716860) | AI17: 44098 | AJ17: 10 | AK17: 1237.76 | AL17: S0MN00328 | BK17: A | BL17: ADD | BM17: ITEMIZED RECEIPTS | BN17: 44252.58 | BR17: F3X | BS17: 4.0125202e+18 | BT17: t | BV17: 2020 | BW17: SA | BY17: 4.0224202e+18 | BZ17: https://docquery.fec.gov/cgi-bin/fecimg/?202101259408783306 | CA17: Contributions From Individuals/Persons Other Than Political Committees
A18: C00694323 | B18: WINRED | C18: 2020 | D18: Q3 | E18: 2.0210126e+17 | F18: 11AI | G18: AADE5DD626A98460CA4E | H18: 1490496 | J18: IND | K18: INDIVIDUAL | L18: C00711689 | N18: THORNTON, JOHN | O18: V | Q18: U | R18: JOHN | T18: THORNTON | V18: 5108 LEWELLYN RD | X18: LAKELAND | Y18: FL | Z18: 338100789 | AA18: RETIRED | AB18: RETIRED | AC18: C00711689 | AD18: 15E | AE18: EARMARKED CONTRIBUTION | AF18: EARMARKED FOR LACY JOHNSON FOR CONGRESS (C00711689) | AI18: 44078 | AJ18: 5 | AK18: 1097.76 | AL18: H0MN05178 | BK18: A | BL18: ADD | BM18: ITEMIZED RECEIPTS | BN18: 44252.58 | BR18: F3X | BS18: 4.0125202e+18 | BT18: t | BV18: 2020 | BW18: SA | BY18: 4.0224202e+18 | BZ18: https://docquery.fec.gov/cgi-bin/fecimg/?202101259407877839 | CA18: Contributions From Individuals/Persons Other Than Political Committees
A19: C00694323 | B19: WINRED | C19: 2020 | D19: Q3 | E19: 2.0210126e+17 | F19: 11AI | G19: AEBD490F0598641188F7 | H19: 1490496 | J19: IND | K19: INDIVIDUAL | L19: C00725853 | N19: THORNTON, JOHN | O19: V | Q19: U | R19: JOHN | T19: THORNTON | V19: 5108 LEWELLYN RD | X19: LAKELAND | Y19: FL | Z19: 338100789 | AA19: RETIRED | AB19: RETIRED | AC19: C00725853 | AD19: 15E | AE19: EARMARKED CONTRIBUTION | AF19: EARMARKED FOR BURGESS 4 UTAH (C00725853) | AI19: 44067 | AJ19: 5 | AK19: 970.76 | AL19: H0UT04076 | BK19: A | BL19: ADD | BM19: ITEMIZED RECEIPTS | BN19: 44252.582 | BR19: F3X | BS19: 4.0125202e+18 | BT19: t | BV19: 2020 | BW19: SA | BY19: 4.0224202e+18 | BZ19: https://docquery.fec.gov/cgi-bin/fecimg/?202101259407297005 | CA19: Contributions From Individuals/Persons Other Than Political Committees
A20: C00580100 | B20: DONALD J. TRUMP FOR PRESIDENT, INC. | C20: 2020 | D20: M6 | E20: 2.0200825e+17 | F20: 18 | G20: SA18.326908 | H20: 1435104 | J20: IND | K20: INDIVIDUAL | N20: THORNTON, JOHN | O20: P | Q20: P | R20: JOHN | T20: THORNTON | V20: 5108 LEWELLYN RD | X20: LAKELAND | Y20: FL | Z20: 33810 | AA20: RETIRED | AB20: RETIRED | AF20: JFC TRANSFER: TRUMP MAKE AMERICA GREAT AGAIN COMMITTEE [SA18.4848] | AG20: X | AI20: 43928 | AJ20: 3.75 | AK20: 30 | BG20: P2020 | BI20: PRIMARY | BJ20: 2020 | BK20: A | BL20: ADD | BM20: ITEMIZED RECEIPTS | BN20: 44075.182 | BR20: F3P | BS20: 4.0826202e+18 | BT20: t | BV20: 2020 | BW20: SA | BY20: 4.0901202e+18 | BZ20: http://docquery.fec.gov/cgi-bin/fecimg/?202008249266975939 | CA20: Transfers From Other Authorized Committees
A21: C00580100 | B21: DONALD J. TRUMP FOR PRESIDENT, INC. | C21: 2020 | D21: M6 | E21: 2.0200825e+17 | F21: 18 | G21: SA18.326907 | H21: 1435104 | J21: IND | K21: INDIVIDUAL | N21: THORNTON, JOHN | O21: P | Q21: P | R21: JOHN | T21: THORNTON | V21: 5108 LEWELLYN RD | X21: LAKELAND | Y21: FL | Z21: 33810 | AA21: RETIRED | AB21: RETIRED | AF21: JFC TRANSFER: TRUMP MAKE AMERICA GREAT AGAIN COMMITTEE [SA18.4848] | AG21: X | AI21: 43928 | AJ21: 26.25 | AK21: 26.25 | BG21: P2020 | BI21: PRIMARY | BJ21: 2020 | BK21: A | BL21: ADD | BM21: ITEMIZED RECEIPTS | BN21: 44075.195 | BR21: F3P | BS21: 4.0826202e+18 | BT21: t | BV21: 2020 | BW21: SA | BY21: 4.0901202e+18 | BZ21: http://docquery.fec.gov/cgi-bin/fecimg/?202008249266975938 | CA21: Transfers From Other Authorized Committees
A22: C00694323 | B22: WINRED | C22: 2020 | D22: Q3 | E22: 2.0210126e+17 | F22: 11AI | G22: A4758F2A60A3847D3867 | H22: 1490496 | J22: IND | K22: INDIVIDUAL | L22: C00710103 | N22: THORNTON, JOHN | O22: V | Q22: U | R22: JOHN | T22: THORNTON | V22: 5108 LEWELLYN RD | X22: LAKELAND | Y22: FL | Z22: 338100789 | AA22: RETIRED | AB22: RETIRED | AC22: C00710103 | AD22: 15E | AE22: EARMARKED CONTRIBUTION | AF22: EARMARKED FOR NANCY MACE FOR CONGRESS (C00710103) | AI22: 44096 | AJ22: 10 | AK22: 1197.76 | AL22: H0SC01394 | BK22: A | BL22: ADD | BM22: ITEMIZED RECEIPTS | BN22: 44252.586 | BR22: F3X | BS22: 4.0125202e+18 | BT22: t | BV22: 2020 | BW22: SA | BY22: 4.0224202e+18 | BZ22: https://docquery.fec.gov/cgi-bin/fecimg/?202101259408674885 | CA22: Contributions From Individuals/Persons Other Than Political Committees
A23: C00618371 | B23: TRUMP MAKE AMERICA GREAT AGAIN COMMITTEE | C23: 2020 | D23: Q2 | E23: 2.0210202e+17 | F23: 11AI | G23: SA11AI.480535 | H23: 1497918 | J23: IND | K23: INDIVIDUAL | N23: THORNTON, JOHN | O23: N | Q23: J | R23: JOHN | T23: THORNTON | V23: 5108 LEWELLYN RD | X23: LAKELAND | Y23: FL | Z23: 33810 | AA23: RETIRED | AB23: RETIRED | AF23: EARMARKED THROUGH WINRED [SA11AI.4452] | AI23: 43996 | AJ23: 35 | AK23: 145 | BK23: A | BL23: ADD | BM23: ITEMIZED RECEIPTS | BN23: 44241.165 | BR23: F3X | BS23: 4.0203202e+18 | BT23: t | BV23: 2020 | BW23: SA | BY23: 4.0214202e+18 | BZ23: https://docquery.fec.gov/cgi-bin/fecimg/?202102019424870668 | CA23: Contributions From Individuals/Persons Other Than Political Committees
A24: C00694323 | B24: WINRED | C24: 2020 | D24: Q3 | E24: 2.0210126e+17 | F24: 11AI | G24: A8D43BED24634461B8F9 | H24: 1490496 | J24: IND | K24: INDIVIDUAL | L24: C00750521 | N24: THORNTON, JOHN | O24: V | Q24: U | R24: JOHN | T24: THORNTON | V24: 5108 LEWELLYN RD | X24: LAKELAND | Y24: FL | Z24: 338100789 | AA24: RETIRED | AB24: RETIRED | AC24: C00750521 | AD24: 15E | AE24: EARMARKED CONTRIBUTION | AF24: EARMARKED FOR TEAM SCALISE (C00750521) | AI24: 44086 | AJ24: 10 | AK24: 1137.76 | BK24: A | BL24: ADD | BM24: ITEMIZED RECEIPTS | BN24: 44252.586 | BR24: F3X | BS24: 4.0125202e+18 | BT24: t | BV24: 2020 | BW24: SA | BY24: 4.0224202e+18 | BZ24: https://docquery.fec.gov/cgi-bin/fecimg/?202101259408168176 | CA24: Contributions From Individuals/Persons Other Than Political Committees
A25: C00618371 | B25: TRUMP MAKE AMERICA GREAT AGAIN COMMITTEE | C25: 2020 | D25: Q2 | E25: 2.0210202e+17 | F25: 11AI | G25: SA11AI.480532 | H25: 1497918 | J25: IND | K25: INDIVIDUAL | N25: THORNTON, JOHN | O25: N | Q25: J | R25: JOHN | T25: THORNTON | V25: 5108 LEWELLYN RD | X25: LAKELAND | Y25: FL | Z25: 33810 | AA25: RETIRED | AB25: RETIRED | AF25: EARMARKED THROUGH WINRED [SA11AI.4403] | AI25: 43928 | AJ25: 35 | AK25: 40 | BK25: A | BL25: ADD | BM25: ITEMIZED RECEIPTS | BN25: 44241.165 | BR25: F3X | BS25: 4.0203202e+18 | BT25: t | BV25: 2020 | BW25: SA | BY25: 4.0214202e+18 | BZ25: https://docquery.fec.gov/cgi-bin/fecimg/?202102019424870667 | CA25: Contributions From Individuals/Persons Other Than Political Committees
A26: C00618371 | B26: TRUMP MAKE AMERICA GREAT AGAIN COMMITTEE | C26: 2020 | D26: Q2 | E26: 2.0210202e+17 | F26: 11AI | G26: SA11AI.213767 | H26: 1497918 | J26: IND | K26: INDIVIDUAL | N26: THORNTON, JOHN | O26: N | Q26: J | R26: JOHN | T26: THORNTON | V26: 5108 LEWELLYN RD | X26: LAKELAND | Y26: FL | Z26: 33810 | AA26: RETIRED | AB26: RETIRED | AF26: EARMARKED THROUGH WINRED [SA11AI.4403] | AI26: 43928 | AJ26: 5 | AK26: 5 | BK26: A | BL26: ADD | BM26: ITEMIZED RECEIPTS | BN26: 44241.165 | BR26: F3X | BS26: 4.0203202e+18 | BT26: t | BV26: 2020 | BW26: SA | BY26: 4.0214202e+18 | BZ26: https://docquery.fec.gov/cgi-bin/fecimg/?202102019424870667 | CA26: Contributions From Individuals/Persons Other Than Political Committees
A27: C00618371 | B27: TRUMP MAKE AMERICA GREAT AGAIN COMMITTEE | C27: 2020 | D27: Q2 | E27: 2.0210202e+17 | F27: 11AI | G27: SA11AI.480533 | H27: 1497918 | J27: IND | K27: INDIVIDUAL | N27: THORNTON, JOHN | O27: N | Q27: J | R27: JOHN | T27: THORNTON | V27: 5108 LEWELLYN RD | X27: LAKELAND | Y27: FL | Z27: 33810 | AA27: RETIRED | AB27: RETIRED | AF27: EARMARKED THROUGH WINRED [SA11AI.4425] | AI27: 43958 | AJ27: 35 | AK27: 75 | BK27: A | BL27: ADD | BM27: ITEMIZED RECEIPTS | BN27: 44241.165 | BR27: F3X | BS27: 4.0203202e+18 | BT27: t | BV27: 2020 | BW27: SA | BY27: 4.0214202e+18 | BZ27: https://docquery.fec.gov/cgi-bin/fecimg/?202102019424870668 | CA27: Contributions From Individuals/Persons Other Than Political Committees
A28: C00618371 | B28: TRUMP MAKE AMERICA GREAT AGAIN COMMITTEE | C28: 2020 | D28: Q2 | E28: 2.0210202e+17 | F28: 11AI | G28: SA11AI.480534 | H28: 1497918 | J28: IND | K28: INDIVIDUAL | N28: THORNTON, JOHN | O28: N | Q28: J | R28: JOHN | T28: THORNTON | V28: 5108 LEWELLYN RD | X28: LAKELAND | Y28: FL | Z28: 33810 | AA28: RETIRED | AB28: RETIRED | AF28: EARMARKED THROUGH WINRED [SA11AI.4447] | AI28: 43989 | AJ28: 35 | AK28: 110 | BK28: A | BL28: ADD | BM28: ITEMIZED RECEIPTS | BN28: 44241.165 | BR28: F3X | BS28: 4.0203202e+18 | BT28: t | BV28: 2020 | BW28: SA | BY28: 4.0214202e+18 | BZ28: https://docquery.fec.gov/cgi-bin/fecimg/?202102019424870668 | CA28: Contributions From Individuals/Persons Other Than Political Committees
A29: C00694323 | B29: WINRED | C29: 2020 | D29: Q3 | E29: 2.0210126e+17 | F29: 11AI | G29: A8D08D8FEFA9342AB81C | H29: 1490496 | J29: IND | K29: INDIVIDUAL | L29: C00733394 | N29: THORNTON, JOHN | O29: V | Q29: U | R29: JOHN | T29: THORNTON | V29: 5108 LEWELLYN RD | X29: LAKELAND | Y29: FL | Z29: 338100789 | AA29: RETIRED | AB29: RETIRED | AC29: C00733394 | AD29: 15E | AE29: EARMARKED CONTRIBUTION | AF29: EARMARKED FOR TAYLOR FOR CONGRESS 2020 (C00733394) | AI29: 44072 | AJ29: 12.5 | AK29: 1020.76 | AL29: H0VA02118 | BK29: A | BL29: ADD | BM29: ITEMIZED RECEIPTS | BN29: 44252.586 | BR29: F3X | BS29: 4.0125202e+18 | BT29: t | BV29: 2020 | BW29: SA | BY29: 4.0224202e+18 | BZ29: https://docquery.fec.gov/cgi-bin/fecimg/?202101259407567860 | CA29: Contributions From Individuals/Persons Other Than Political Committees
A30: C00694323 | B30: WINRED | C30: 2020 | D30: Q3 | E30: 2.0210126e+17 | F30: 11AI | G30: A207D3002CC8143FB9CE | H30: 1490496 | J30: IND | K30: INDIVIDUAL | L30: C00718239 | N30: THORNTON, JOHN | O30: V | Q30: U | R30: JOHN | T30: THORNTON | V30: 5108 LEWELLYN RD | X30: LAKELAND | Y30: FL | Z30: 338100789 | AA30: RETIRED | AB30: RETIRED | AC30: C00718239 | AD30: 15E | AE30: EARMARKED CONTRIBUTION | AF30: EARMARKED FOR ANNA PAULINA LUNA FOR CONGRESS (C00718239) | AI30: 44047 | AJ30: 15 | AK30: 838 | AL30: H0FL13158 | BK30: A | BL30: ADD | BM30: ITEMIZED RECEIPTS | BN30: 44252.587 | BR30: F3X | BS30: 4.0125202e+18 | BT30: t | BV30: 2020 | BW30: SA | BY30: 4.0224202e+18 | BZ30: https://docquery.fec.gov/cgi-bin/fecimg/?202101259406578004 | CA30: Contributions From Individuals/Persons Other Than Political Committees
A31: C00694323 | B31: WINRED | C31: 2020 | D31: Q3 | E31: 2.0210126e+17 | F31: 11AI | G31: A09E193ACACDE41678DD | H31: 1490496 | J31: IND | K31: INDIVIDUAL | L31: C00717322 | N31: THORNTON, JOHN | O31: V | Q31: U | R31: JOHN | T31: THORNTON | V31: 5108 LEWELLYN RD | X31: LAKELAND | Y31: FL | Z31: 338100789 | AA31: RETIRED | AB31: RETIRED | AC31: C00717322 | AD31: 15E | AE31: EARMARKED CONTRIBUTION | AF31: EARMARKED FOR RODIMER FOR CONGRESS (C00717322) | AI31: 44073 | AJ31: 10 | AK31: 1030.76 | AL31: H0NV03132 | BK31: A | BL31: ADD | BM31: ITEMIZED RECEIPTS | BN31: 44252.588 | BR31: F3X | BS31: 4.0125202e+18 | BT31: t | BV31: 2020 | BW31: SA | BY31: 4.0224202e+18 | BZ31: https://docquery.fec.gov/cgi-bin/fecimg/?202101259407612088 | CA31: Contributions From Individuals/Persons Other Than Political Committees
A32: C00580100 | B32: DONALD J. TRUMP FOR PRESIDENT, INC. | C32: 2020 | D32: 12G | E32: 2.0210304e+17 | F32: 17A | G32: SA17A.248222 | H32: 1502733 | J32: IND | K32: INDIVIDUAL | N32: THORNTON, JOHN | O32: P | Q32: P | R32: JOHN | T32: THORNTON | V32: 5108 LEWELLYN RD | X32: LAKELAND | Y32: FL | Z32: 33810 | AA32: RETIRED | AB32: RETIRED | AF32: EARMARKED THROUGH WINRED [SA17A.7586] | AI32: 44111 | AJ32: 10 | AK32: 10 | BG32: G2020 | BI32: GENERAL | BJ32: 2020 | BK32: A | BL32: ADD | BM32: ITEMIZED RECEIPTS | BN32: 44264.165 | BR32: F3P | BS32: 4.0304202e+18 | BT32: t | BV32: 2020 | BW32: SA | BY32: 4.0309202e+18 | BZ32: https://docquery.fec.gov/cgi-bin/fecimg/?202103039440152468 | CA32: Contributions From Individuals/Persons Other Than Political Committees
A33: C00618371 | B33: TRUMP MAKE AMERICA GREAT AGAIN COMMITTEE | C33: 2020 | D33: 12G | E33: 2.0210209e+17 | F33: 11AI | G33: SA11AI.208501 | H33: 1499074 | J33: IND | K33: INDIVIDUAL | N33: THORNTON, JOHN | O33: N | Q33: J | R33: JOHN | T33: THORNTON | V33: 5108 LEWELLYN RD | X33: LAKELAND | Y33: FL | Z33: 33810 | AA33: RETIRED | AB33: RETIRED | AF33: EARMARKED THROUGH WINRED [SA11A1.4593] | AI33: 44113 | AJ33: 45 | AK33: 87 | BK33: A | BL33: ADD | BM33: ITEMIZED RECEIPTS | BN33: 44246.19 | BR33: F3X | BS33: 4.0209202e+18 | BT33: t | BV33: 2020 | BW33: SA | BY33: 4.0219202e+18 | BZ33: https://docquery.fec.gov/cgi-bin/fecimg/?202102089427141210 | CA33: Contributions From Individuals/Persons Other Than Political Committees
A34: C00618371 | B34: TRUMP MAKE AMERICA GREAT AGAIN COMMITTEE | C34: 2020 | D34: Q1 | E34: 2.0200729e+17 | F34: 11AI | G34: SA11AI.124537 | H34: 1429035 | J34: IND | K34: INDIVIDUAL | N34: THORNTON, JOHN | O34: N | Q34: J | R34: JOHN | T34: THORNTON | V34: 5108 LEWELLYN RD | X34: LAKELAND | Y34: FL | Z34: 33810 | AA34: RETIRED | AB34: RETIRED | AF34: EARMARKED THROUGH WINRED [SA11AI.4362] | AI34: 43872 | AJ34: 42 | AK34: 89 | BK34: A | BL34: ADD | BM34: ITEMIZED RECEIPTS | BN34: 44047.177 | BR34: F3X | BS34: 4.0729202e+18 | BT34: t | BV34: 2020 | BW34: SA | BY34: 4.0804202e+18 | BZ34: http://docquery.fec.gov/cgi-bin/fecimg/?202007289261166360 | CA34: Contributions From Individuals/Persons Other Than Political Committees
A35: C00618371 | B35: TRUMP MAKE AMERICA GREAT AGAIN COMMITTEE | C35: 2020 | D35: Q1 | E35: 2.0200729e+17 | F35: 11AI | G35: SA11AI.124538 | H35: 1429035 | J35: IND | K35: INDIVIDUAL | N35: THORNTON, JOHN | O35: N | Q35: J | R35: JOHN | T35: THORNTON | V35: 5108 LEWELLYN RD | X35: LAKELAND | Y35: FL | Z35: 33810 | AA35: RETIRED | AB35: RETIRED | AF35: EARMARKED THROUGH WINRED [SA11AI.4374] | AI35: 43888 | AJ35: 42 | AK35: 131 | BK35: A | BL35: ADD | BM35: ITEMIZED RECEIPTS | BN35: 44047.176 | BR35: F3X | BS35: 4.0729202e+18 | BT35: t | BV35: 2020 | BW35: SA | BY35: 4.0804202e+18 | BZ35: http://docquery.fec.gov/cgi-bin/fecimg/?202007289261166360 | CA35: Contributions From Individuals/Persons Other Than Political Committees
A36: C00618371 | B36: TRUMP MAKE AMERICA GREAT AGAIN COMMITTEE | C36: 2020 | D36: Q1 | E36: 2.0200729e+17 | F36: 11AI | G36: SA11AI.124536 | H36: 1429035 | J36: IND | K36: INDIVIDUAL | N36: THORNTON, JOHN | O36: N | Q36: J | R36: JOHN | T36: THORNTON | V36: 5108 LEWELLYN RD | X36: LAKELAND | Y36: FL | Z36: 33810 | AA36: RETIRED | AB36: RETIRED | AF36: EARMARKED THROUGH WINRED [SA11AI.4353] | AI36: 43859 | AJ36: 42 | AK36: 47 | BK36: A | BL36: ADD | BM36: ITEMIZED RECEIPTS | BN36: 44047.176 | BR36: F3X | BS36: 4.0729202e+18 | BT36: t | BV36: 2020 | BW36: SA | BY36: 4.0804202e+18 | BZ36: http://docquery.fec.gov/cgi-bin/fecimg/?202007289261166359 | CA36: Contributions From Individuals/Persons Other Than Political Committees
A37: C00618371 | B37: TRUMP MAKE AMERICA GREAT AGAIN COMMITTEE | C37: 2020 | D37: Q1 | E37: 2.0200729e+17 | F37: 11AI | G37: SA11AI.124535 | H37: 1429035 | J37: IND | K37: INDIVIDUAL | N37: THORNTON, JOHN | O37: N | Q37: J | R37: JOHN | T37: THORNTON | V37: 5108 LEWELLYN RD | X37: LAKELAND | Y37: FL | Z37: 33810 | AA37: RETIRED | AB37: RETIRED | AF37: EARMARKED THROUGH WINRED [SA11AI.4340] | AI37: 43839 | AJ37: 5 | AK37: 5 | BK37: A | BL37: ADD | BM37: ITEMIZED RECEIPTS | BN37: 44047.191 | BR37: F3X | BS37: 4.0729202e+18 | BT37: t | BV37: 2020 | BW37: SA | BY37: 4.0804202e+18 | BZ37: http://docquery.fec.gov/cgi-bin/fecimg/?202007289261166359 | CA37: Contributions From Individuals/Persons Other Than Political Committees
A38: C00618371 | B38: TRUMP MAKE AMERICA GREAT AGAIN COMMITTEE | C38: 2020 | D38: Q1 | E38: 2.0200729e+17 | F38: 11AI | G38: SA11AI.124540 | H38: 1429035 | J38: IND | K38: INDIVIDUAL | N38: THORNTON, JOHN | O38: N | Q38: J | R38: JOHN | T38: THORNTON | V38: 5108 LEWELLYN RD | X38: LAKELAND | Y38: FL | Z38: 33810 | AA38: RETIRED | AB38: RETIRED | AF38: EARMARKED THROUGH WINRED [SA11AI.4381] | AI38: 43897 | AJ38: 35 | AK38: 166 | BK38: A | BL38: ADD | BM38: ITEMIZED RECEIPTS | BN38: 44047.191 | BR38: F3X | BS38: 4.0729202e+18 | BT38: t | BV38: 2020 | BW38: SA | BY38: 4.0804202e+18 | BZ38: http://docquery.fec.gov/cgi-bin/fecimg/?202007289261166361 | CA38: Contributions From Individuals/Persons Other Than Political Committees
A39: C00618371 | B39: TRUMP MAKE AMERICA GREAT AGAIN COMMITTEE | C39: 2020 | D39: Q1 | E39: 2.0200729e+17 | F39: 11AI | G39: SA11AI.124539 | H39: 1429035 | J39: IND | K39: INDIVIDUAL | N39: THORNTON, JOHN | O39: N | Q39: J | R39: JOHN | T39: THORNTON | V39: 5108 LEWELLYN RD | X39: LAKELAND | Y39: FL | Z39: 33810 | AA39: RETIRED | AB39: RETIRED | AD39: 15E | AE39: EARMARKED CONTRIBUTION | AF39: EARMARKED THROUGH WINRED [SA11AI.4396] | AI39: 43917 | AJ39: 42 | AK39: 208 | BG39: P | BI39: PRIMARY | BK39: A | BL39: ADD | BM39: ITEMIZED RECEIPTS | BN39: 44047.191 | BR39: F3X | BS39: 4.0729202e+18 | BT39: t | BV39: 2020 | BW39: SA | BY39: 4.0804202e+18 | BZ39: http://docquery.fec.gov/cgi-bin/fecimg/?202007289261166361 | CA39: Contributions From Individuals/Persons Other Than Political Committees
A40: C00694323 | B40: WINRED | C40: 2020 | D40: YE | E40: 2.021013e+17 | F40: 11AI | G40: A52252B5045AC4EA7ABE | H40: 1494216 | J40: IND | K40: INDIVIDUAL | L40: C00729608 | N40: THORNTON, JOHN | O40: V | Q40: U | R40: JOHN | T40: THORNTON | V40: 5108 LEWELLYN RD | X40: LAKELAND | Y40: FL | Z40: 338100789 | AA40: RETIRED | AB40: RETIRED | AC40: C00729608 | AD40: 15E | AE40: EARMARKED CONTRIBUTION | AF40: EARMARKED FOR GEORGIANS FOR KELLY LOEFFLER (C00729608) | AI40: 44162 | AJ40: 10 | AK40: 1795.76 | AL40: S0GA00526 | BK40: A | BL40: ADD | BM40: ITEMIZED RECEIPTS | BN40: 44265.176 | BR40: F3X | BS40: 4.0131202e+18 | BT40: t | BV40: 2020 | BW40: SA | BY40: 4.0309202e+18 | BZ40: https://docquery.fec.gov/cgi-bin/fecimg/?202101299414217529 | CA40: Contributions From Individuals/Persons Other Than Political Committees
A41: C00733329 | B41: BYRON DONALDS FOR CONGRESS | C41: 2020 | D41: Q3 | E41: 2.0201219e+17 | F41: 11AI | G41: SA11AI.43876 | H41: 1483278 | J41: IND | K41: INDIVIDUAL | N41: THORNTON, JOHN | O41: H | Q41: P | R41: JOHN | T41: THORNTON | V41: 5108 LEWELLYN RD | X41: LAKELAND | Y41: FL | Z41: 33810 | AA41: RETIRED | AB41: RETIRED | AF41: EARMARKED THROUGH WINRED [SA11A1.36202] | AI41: 44077 | AJ41: 10 | AK41: 10 | BG41: G2020 | BI41: GENERAL | BJ41: 2020 | BK41: C | BL41: CHANGE | BM41: ITEMIZED RECEIPTS | BN41: 44194.154 | BR41: F3 | BS41: 4.1219202e+18 | BT41: t | BV41: 2020 | BW41: SA | BY41: 4.1229202e+18 | BZ41: https://docquery.fec.gov/cgi-bin/fecimg/?202012189393371874 | CA41: Contributions From Individuals/Persons Other Than Political Committees
A42: C00733329 | B42: BYRON DONALDS FOR CONGRESS | C42: 2020 | D42: 12G | E42: 2.0201219e+17 | F42: 11AI | G42: SA11AI.60544 | H42: 1483282 | J42: IND | K42: INDIVIDUAL | N42: THORNTON, JOHN | O42: H | Q42: P | R42: JOHN | T42: THORNTON | V42: 5108 LEWELLYN RD | X42: LAKELAND | Y42: FL | Z42: 33810 | AA42: RETIRED | AB42: RETIRED | AF42: EARMARKED THROUGH WINRED [SA11A1.53606] | AI42: 44113 | AJ42: 1.88 | AK42: 11.88 | BG42: G2020 | BI42: GENERAL | BJ42: 2020 | BK42: C | BL42: CHANGE | BM42: ITEMIZED RECEIPTS | BN42: 44194.153 | BR42: F3 | BS42: 4.1219202e+18 | BT42: t | BV42: 2020 | BW42: SA | BY42: 4.1229202e+18 | BZ42: https://docquery.fec.gov/cgi-bin/fecimg/?202012189393373335 | CA42: Contributions From Individuals/Persons Other Than Political Committees
A43: C00618371 | B43: TRUMP MAKE AMERICA GREAT AGAIN COMMITTEE | C43: 2020 | D43: 30G | E43: 2.0210219e+17 | F43: 11AI | G43: SA11AI.323924 | H43: 1500723 | J43: IND | K43: INDIVIDUAL | N43: THORNTON, JOHN | O43: N | Q43: J | R43: JOHN | T43: THORNTON | V43: 5108 LEWELLYN RD | X43: LAKELAND | Y43: FL | Z43: 33810 | AA43: RETIRED | AB43: RETIRED | AF43: EARMARKED THROUGH WINRED [SA11A1.4612] | AI43: 44139 | AJ43: 42 | AK43: 42 | BK43: A | BL43: ADD | BM43: ITEMIZED RECEIPTS | BN43: 44258.58 | BR43: F3X | BS43: 4.0219202e+18 | BT43: t | BV43: 2020 | BW43: SA | BY43: 4.0302202e+18 | BZ43: https://docquery.fec.gov/cgi-bin/fecimg/?202102189428600545 | CA43: Contributions From Individuals/Persons Other Than Political Committees
A44: C00694323 | B44: WINRED | C44: 2020 | D44: Q1 | E44: 2.0210108e+17 | F44: 11AI | G44: ABFBB3962458642E5A5D | H44: 1485991 | J44: IND | K44: INDIVIDUAL | L44: C00618371 | N44: THORNTON, JOHN | O44: V | Q44: U | R44: JOHN | T44: THORNTON | V44: 5108 LEWELLYN RD | X44: LAKELAND | Y44: FL | Z44: 338100789 | AA44: RETIRED | AB44: RETIRED | AC44: C00618371 | AD44: 15E | AE44: EARMARKED CONTRIBUTION | AF44: EARMARKED FOR TRUMP MAKE AMERICA GREAT AGAIN COMMITTEE (C00618371) | AI44: 43917 | AJ44: 42 | AK44: 208 | BG44: P | BI44: PRIMARY | BK44: A | BL44: ADD | BM44: ITEMIZED RECEIPTS | BN44: 44239.167 | BR44: F3X | BS44: 4.0111202e+18 | BT44: t | BV44: 2020 | BW44: SA | BY44: 4.0211202e+18 | BZ44: https://docquery.fec.gov/cgi-bin/fecimg/?202101079397087244 | CA44: Contributions From Individuals/Persons Other Than Political Committees
A45: C00694323 | B45: WINRED | C45: 2020 | D45: Q3 | E45: 2.0210126e+17 | F45: 11AI | G45: AA69FEC4E59FD4325ADE | H45: 1490496 | J45: IND | K45: INDIVIDUAL | L45: C00726117 | N45: THORNTON, JOHN | O45: V | Q45: U | R45: JOHN | T45: THORNTON | V45: 5108 LEWELLYN RD | X45: LAKELAND | Y45: FL | Z45: 338100789 | AA45: RETIRED | AB45: RETIRED | AC45: C00726117 | AD45: 15E | AE45: EARMARKED CONTRIBUTION | AF45: EARMARKED FOR KIM KLACIK FOR CONGRESS (C00726117) | AI45: 44063 | AJ45: 10 | AK45: 940.76 | AL45: H0MD07197 | BK45: A | BL45: ADD | BM45: ITEMIZED RECEIPTS | BN45: 44252.59 | BR45: F3X | BS45: 4.0125202e+18 | BT45: t | BV45: 2020 | BW45: SA | BY45: 4.0224202e+18 | BZ45: https://docquery.fec.gov/cgi-bin/fecimg/?202101259407150549 | CA45: Contributions From Individuals/Persons Other Than Political Committees
A46: C00694323 | B46: WINRED | C46: 2020 | D46: Q1 | E46: 2.0210108e+17 | F46: 11AI | G46: A0763BA60B6E44DB0AE9 | H46: 1485991 | J46: IND | K46: INDIVIDUAL | N46: THORNTON, JOHN | O46: V | Q46: U | R46: JOHN | T46: THORNTON | V46: 5108 LEWELLYN RD | X46: LAKELAND | Y46: FL | Z46: 338100789 | AA46: RETIRED | AB46: RETIRED | AF46: EARMARKED FOR TRUMP MAKE AMERICA GREAT AGAIN COMMITTEE (C00618371) | AI46: 43839 | AJ46: 5 | AK46: 5 | BK46: A | BL46: ADD | BM46: ITEMIZED RECEIPTS | BN46: 44239.181 | BR46: F3X | BS46: 4.0111202e+18 | BT46: t | BV46: 2020 | BW46: SA | BY46: 4.0211202e+18 | BZ46: https://docquery.fec.gov/cgi-bin/fecimg/?202101079396158594 | CA46: Contributions From Individuals/Persons Other Than Political Committees
A47: C00694323 | B47: WINRED | C47: 2020 | D47: Q3 | E47: 2.0210126e+17 | F47: 11AI | G47: ADDF58F7D11404671A64 | H47: 1490496 | J47: IND | K47: INDIVIDUAL | L47: C00075820 | N47: THORNTON, JOHN | O47: V | Q47: U | R47: JOHN | T47: THORNTON | V47: 5108 LEWELLYN RD | X47: LAKELAND | Y47: FL | Z47: 338100789 | AA47: RETIRED | AB47: RETIRED | AC47: C00075820 | AD47: 15E | AE47: EARMARKED CONTRIBUTION | AF47: EARMARKED FOR NRCC (C00075820) | AI47: 44100 | AJ47: 10 | AK47: 1257.76 | BK47: A | BL47: ADD | BM47: ITEMIZED RECEIPTS | BN47: 44252.592 | BR47: F3X | BS47: 4.0125202e+18 | BT47: t | BV47: 2020 | BW47: SA | BY47: 4.0224202e+18 | BZ47: https://docquery.fec.gov/cgi-bin/fecimg/?202101259408909986 | CA47: Contributions From Individuals/Persons Other Than Political Committees
A48: C00694323 | B48: WINRED | C48: 2020 | D48: Q1 | E48: 2.0210108e+17 | F48: 11AI | G48: A68AB2B14DD3A4D02AFA | H48: 1485991 | J48: IND | K48: INDIVIDUAL | N48: THORNTON, JOHN | O48: V | Q48: U | R48: JOHN | T48: THORNTON | V48: 5108 LEWELLYN RD | X48: LAKELAND | Y48: FL | Z48: 338100789 | AA48: RETIRED | AB48: RETIRED | AF48: EARMARKED FOR TRUMP MAKE AMERICA GREAT AGAIN COMMITTEE (C00618371) | AI48: 43859 | AJ48: 42 | AK48: 47 | BK48: A | BL48: ADD | BM48: ITEMIZED RECEIPTS | BN48: 44239.186 | BR48: F3X | BS48: 4.0111202e+18 | BT48: t | BV48: 2020 | BW48: SA | BY48: 4.0211202e+18 | BZ48: https://docquery.fec.gov/cgi-bin/fecimg/?202101079396358827 | CA48: Contributions From Individuals/Persons Other Than Political Committees
A49: C00694323 | B49: WINRED | C49: 2020 | D49: Q1 | E49: 2.0210108e+17 | F49: 11AI | G49: A5AA71FB3EA954932A78 | H49: 1485991 | J49: IND | K49: INDIVIDUAL | N49: THORNTON, JOHN | O49: V | Q49: U | R49: JOHN | T49: THORNTON | V49: 5108 LEWELLYN RD | X49: LAKELAND | Y49: FL | Z49: 338100789 | AA49: RETIRED | AB49: RETIRED | AF49: EARMARKED FOR TRUMP MAKE AMERICA GREAT AGAIN COMMITTEE (C00618371) | AI49: 43888 | AJ49: 42 | AK49: 131 | BK49: A | BL49: ADD | BM49: ITEMIZED RECEIPTS | BN49: 44239.187 | BR49: F3X | BS49: 4.0111202e+18 | BT49: t | BV49: 2020 | BW49: SA | BY49: 4.0211202e+18 | BZ49: https://docquery.fec.gov/cgi-bin/fecimg/?202101079396758756 | CA49: Contributions From Individuals/Persons Other Than Political Committees
A50: C00694323 | B50: WINRED | C50: 2020 | D50: Q1 | E50: 2.0210108e+17 | F50: 11AI | G50: ABD020A269CA94D7099A | H50: 1485991 | J50: IND | K50: INDIVIDUAL | N50: THORNTON, JOHN | O50: V | Q50: U | R50: JOHN | T50: THORNTON | V50: 5108 LEWELLYN RD | X50: LAKELAND | Y50: FL | Z50: 338100789 | AA50: RETIRED | AB50: RETIRED | AF50: EARMARKED FOR TRUMP MAKE AMERICA GREAT AGAIN COMMITTEE (C00618371) | AI50: 43897 | AJ50: 35 | AK50: 166 | BK50: A | BL50: ADD | BM50: ITEMIZED RECEIPTS | BN50: 44239.188 | BR50: F3X | BS50: 4.0111202e+18 | BT50: t | BV50: 2020 | BW50: SA | BY50: 4.0211202e+18 | BZ50: https://docquery.fec.gov/cgi-bin/fecimg/?202101079396888286 | CA50: Contributions From Individuals/Persons Other Than Political Committees
A51: C00694323 | B51: WINRED | C51: 2020 | D51: YE | E51: 2.021013e+17 | F51: 11AI | G51: A3CD6753DF5AA42FBB3D | H51: 1494216 | J51: IND | K51: INDIVIDUAL | L51: C00729608 | N51: THORNTON, JOHN | O51: V | Q51: U | R51: JOHN | T51: THORNTON | V51: 5108 LEWELLYN RD | X51: LAKELAND | Y51: FL | Z51: 338100789 | AA51: RETIRED | AB51: RETIRED | AC51: C00729608 | AD51: 15E | AE51: EARMARKED CONTRIBUTION | AF51: EARMARKED FOR GEORGIANS FOR KELLY LOEFFLER (C00729608) | AI51: 44194 | AJ51: 20 | AK51: 1850.76 | AL51: S0GA00526 | BK51: A | BL51: ADD | BM51: ITEMIZED RECEIPTS | BN51: 44265.186 | BR51: F3X | BS51: 4.0131202e+18 | BT51: t | BV51: 2020 | BW51: SA | BY51: 4.0309202e+18 | BZ51: https://docquery.fec.gov/cgi-bin/fecimg/?202101299415575650 | CA51: Contributions From Individuals/Persons Other Than Political Committees
A52: C00694323 | B52: WINRED | C52: 2020 | D52: YE | E52: 2.021013e+17 | F52: 11AI | G52: A9D5CB93E18264F02B4A | H52: 1494216 | J52: IND | K52: INDIVIDUAL | L52: C00760124 | N52: THORNTON, JOHN | O52: V | Q52: U | R52: JOHN | T52: THORNTON | V52: 5108 LEWELLYN RD | X52: LAKELAND | Y52: FL | Z52: 338100789 | AA52: RETIRED | AB52: RETIRED | AC52: C00760124 | AD52: 15E | AE52: EARMARKED CONTRIBUTION | AF52: EARMARKED FOR NATIONAL VICTORY ACTION FUND (C00760124) | AI52: 44162 | AJ52: 35 | AK52: 1795.76 | BK52: A | BL52: ADD | BM52: ITEMIZED RECEIPTS | BN52: 44265.184 | BR52: F3X | BS52: 4.0131202e+18 | BT52: t | BV52: 2020 | BW52: SA | BY52: 4.0309202e+18 | BZ52: https://docquery.fec.gov/cgi-bin/fecimg/?202101299414221554 | CA52: Contributions From Individuals/Persons Other Than Political Committees
A53: C00694323 | B53: WINRED | C53: 2020 | D53: YE | E53: 2.021013e+17 | F53: 11AI | G53: A2F931888A1794135A41 | H53: 1494216 | J53: IND | K53: INDIVIDUAL | L53: C00547570 | N53: THORNTON, JOHN | O53: V | Q53: U | R53: JOHN | T53: THORNTON | V53: 5108 LEWELLYN RD | X53: LAKELAND | Y53: FL | Z53: 338100789 | AA53: RETIRED | AB53: RETIRED | AC53: C00547570 | AD53: 15E | AE53: EARMARKED CONTRIBUTION | AF53: EARMARKED FOR PERDUE FOR SENATE (C00547570) | AI53: 44162 | AJ53: 10 | AK53: 1795.76 | AL53: S4GA11285 | BK53: A | BL53: ADD | BM53: ITEMIZED RECEIPTS | BN53: 44265.191 | BR53: F3X | BS53: 4.0131202e+18 | BT53: t | BV53: 2020 | BW53: SA | BY53: 4.0309202e+18 | BZ53: https://docquery.fec.gov/cgi-bin/fecimg/?202101299414229753 | CA53: Contributions From Individuals/Persons Other Than Political Committees
A54: C00694323 | B54: WINRED | C54: 2020 | D54: Q3 | E54: 2.0210126e+17 | F54: 11AI | G54: ADF4FBF25AE3A4867BD1 | H54: 1490496 | J54: IND | K54: INDIVIDUAL | L54: C00725853 | N54: THORNTON, JOHN | O54: V | Q54: U | R54: JOHN | T54: THORNTON | V54: 5108 LEWELLYN RD | X54: LAKELAND | Y54: FL | Z54: 338100789 | AA54: RETIRED | AB54: RETIRED | AC54: C00725853 | AD54: 15E | AE54: EARMARKED CONTRIBUTION | AF54: EARMARKED FOR BURGESS 4 UTAH (C00725853) | AI54: 44099 | AJ54: 10 | AK54: 1247.76 | AL54: H0UT04076 | BK54: A | BL54: ADD | BM54: ITEMIZED RECEIPTS | BN54: 44252.596 | BR54: F3X | BS54: 4.0125202e+18 | BT54: t | BV54: 2020 | BW54: SA | BY54: 4.0224202e+18 | BZ54: https://docquery.fec.gov/cgi-bin/fecimg/?202101259408846430 | CA54: Contributions From Individuals/Persons Other Than Political Committees
A55: C00694323 | B55: WINRED | C55: 2020 | D55: Q2 | E55: 2.0210115e+17 | F55: 11AI | G55: A8477E06EEE1F45D6A8B | H55: 1487725 | J55: IND | K55: INDIVIDUAL | L55: C00618371 | N55: THORNTON, JOHN | O55: V | Q55: U | R55: JOHN | T55: THORNTON | V55: 5108 LEWELLYN RD | X55: LAKELAND | Y55: FL | Z55: 338100789 | AA55: RETIRED | AB55: RETIRED | AC55: C00618371 | AD55: 15E | AE55: EARMARKED CONTRIBUTION | AF55: EARMARKED FOR TRUMP MAKE AMERICA GREAT AGAIN COMMITTEE (C00618371) | AI55: 43955 | AJ55: 42 | AK55: 332 | BK55: A | BL55: ADD | BM55: ITEMIZED RECEIPTS | BN55: 44245.348 | BR55: F3X | BS55: 4.0120202e+18 | BT55: t | BV55: 2020 | BW55: SA | BY55: 4.0217202e+18 | BZ55: https://docquery.fec.gov/cgi-bin/fecimg/?202101149400597866 | CA55: Contributions From Individuals/Persons Other Than Political Committees
A56: C00694323 | B56: WINRED | C56: 2020 | D56: Q3 | E56: 2.0210126e+17 | F56: 11AI | G56: A6050150D5CD74929B86 | H56: 1490496 | J56: IND | K56: INDIVIDUAL | L56: C00711689 | N56: THORNTON, JOHN | O56: V | Q56: U | R56: JOHN | T56: THORNTON | V56: 5108 LEWELLYN RD | X56: LAKELAND | Y56: FL | Z56: 338100789 | AA56: RETIRED | AB56: RETIRED | AC56: C00711689 | AD56: 15E | AE56: EARMARKED CONTRIBUTION | AF56: EARMARKED FOR LACY JOHNSON FOR CONGRESS (C00711689) | AI56: 44103 | AJ56: 10 | AK56: 1302.76 | AL56: H0MN05178 | BK56: A | BL56: ADD | BM56: ITEMIZED RECEIPTS | BN56: 44252.597 | BR56: F3X | BS56: 4.0125202e+18 | BT56: t | BV56: 2020 | BW56: SA | BY56: 4.0224202e+18 | BZ56: https://docquery.fec.gov/cgi-bin/fecimg/?202101259409096661 | CA56: Contributions From Individuals/Persons Other Than Political Committees
A57: C00694323 | B57: WINRED | C57: 2020 | D57: Q3 | E57: 2.0210126e+17 | F57: 11AI | G57: A469DA9BDC9604F2FA85 | H57: 1490496 | J57: IND | K57: INDIVIDUAL | L57: C00711689 | N57: THORNTON, JOHN | O57: V | Q57: U | R57: JOHN | T57: THORNTON | V57: 5108 LEWELLYN RD | X57: LAKELAND | Y57: FL | Z57: 338100789 | AA57: RETIRED | AB57: RETIRED | AC57: C00711689 | AD57: 15E | AE57: EARMARKED CONTRIBUTION | AF57: EARMARKED FOR LACY JOHNSON FOR CONGRESS (C00711689) | AI57: 44102 | AJ57: 10 | AK57: 1292.76 | AL57: H0MN05178 | BK57: A | BL57: ADD | BM57: ITEMIZED RECEIPTS | BN57: 44252.599 | BR57: F3X | BS57: 4.0125202e+18 | BT57: t | BV57: 2020 | BW57: SA | BY57: 4.0224202e+18 | BZ57: https://docquery.fec.gov/cgi-bin/fecimg/?202101259409017085 | CA57: Contributions From Individuals/Persons Other Than Political Committees
A58: C00694323 | B58: WINRED | C58: 2020 | D58: Q3 | E58: 2.0210126e+17 | F58: 11AI | G58: A4858A338800346F9A29 | H58: 1490496 | J58: IND | K58: INDIVIDUAL | L58: C00546788 | N58: THORNTON, JOHN | O58: V | Q58: U | R58: JOHN | T58: THORNTON | V58: 5108 LEWELLYN RD | X58: LAKELAND | Y58: FL | Z58: 338100789 | AA58: RETIRED | AB58: RETIRED | AC58: C00546788 | AD58: 15E | AE58: EARMARKED CONTRIBUTION | AF58: EARMARKED FOR JONI FOR IOWA (C00546788) | AI58: 44064 | AJ58: 10 | AK58: 950.76 | AL58: S4IA00129 | BK58: A | BL58: ADD | BM58: ITEMIZED RECEIPTS | BN58: 44252.599 | BR58: F3X | BS58: 4.0125202e+18 | BT58: t | BV58: 2020 | BW58: SA | BY58: 4.0224202e+18 | BZ58: https://docquery.fec.gov/cgi-bin/fecimg/?202101259407193593 | CA58: Contributions From Individuals/Persons Other Than Political Committees
A59: C00694323 | B59: WINRED | C59: 2020 | D59: Q3 | E59: 2.0210126e+17 | F59: 11AI | G59: A4889F9FCD57B4D58813 | H59: 1490496 | J59: IND | K59: INDIVIDUAL | L59: C00733329 | N59: THORNTON, JOHN | O59: V | Q59: U | R59: JOHN | T59: THORNTON | V59: 5108 LEWELLYN RD | X59: LAKELAND | Y59: FL | Z59: 338100789 | AA59: RETIRED | AB59: RETIRED | AC59: C00733329 | AD59: 15E | AE59: EARMARKED CONTRIBUTION | AF59: EARMARKED FOR BYRON DONALDS FOR CONGRESS (C00733329) | AI59: 44077 | AJ59: 10 | AK59: 1040.76 | AL59: H2FL14186 | BK59: A | BL59: ADD | BM59: ITEMIZED RECEIPTS | BN59: 44252.599 | BR59: F3X | BS59: 4.0125202e+18 | BT59: t | BV59: 2020 | BW59: SA | BY59: 4.0224202e+18 | BZ59: https://docquery.fec.gov/cgi-bin/fecimg/?202101259407841203 | CA59: Contributions From Individuals/Persons Other Than Political Committees
A60: C00694323 | B60: WINRED | C60: 2020 | D60: Q1 | E60: 2.0210108e+17 | F60: 11AI | G60: ADE31D5BACCFF406CA23 | H60: 1485991 | J60: IND | K60: INDIVIDUAL | N60: THORNTON, JOHN | O60: V | Q60: U | R60: JOHN | T60: THORNTON | V60: 5108 LEWELLYN RD | X60: LAKELAND | Y60: FL | Z60: 338100789 | AA60: RETIRED | AB60: RETIRED | AF60: EARMARKED FOR TRUMP MAKE AMERICA GREAT AGAIN COMMITTEE (C00618371) | AI60: 43872 | AJ60: 42 | AK60: 89 | BK60: A | BL60: ADD | BM60: ITEMIZED RECEIPTS | BN60: 44239.199 | BR60: F3X | BS60: 4.0111202e+18 | BT60: t | BV60: 2020 | BW60: SA | BY60: 4.0211202e+18 | BZ60: https://docquery.fec.gov/cgi-bin/fecimg/?202101079396583759 | CA60: Contributions From Individuals/Persons Other Than Political Committees
A61: C00394957 | B61: SCALISE FOR CONGRESS | C61: 2020 | D61: Q3 | E61: 2.0201016e+17 | F61: 12 | G61: SA.966893.13.1 | H61: 1451445 | J61: IND | K61: INDIVIDUAL | N61: THORNTON, JOHN | O61: H | Q61: P | R61: JOHN | T61: THORNTON | V61: 5108 LEWELLYN RD | X61: LAKELAND | Y61: FL | Z61: 338100789 | AA61: RETIRED | AB61: RETIRED | AD61: 15J | AE61: MEMO (FILER'S % OF CONTRIBUTION GIVEN TO JOIN | AF61: TRANSFER | AG61: X | AI61: 44074 | AJ61: 25 | AK61: 25 | BG61: G2020 | BI61: GENERAL | BJ61: 2020 | BK61: A | BL61: ADD | BM61: ITEMIZED RECEIPTS | BN61: 44176.212 | BP61: SA12.982671 | BQ61: SA12 | BR61: F3 | BS61: 4.1016202e+18 | BT61: t | BU61: TRANSFER FROM TEAM SCALISE JFC | BV61: 2020 | BW61: SA | BY61: 4.1211202e+18 | BZ61: http://docquery.fec.gov/cgi-bin/fecimg/?202010159294902019 | CA61: Transfers from authorized committees
A62: C00694323 | B62: WINRED | C62: 2020 | D62: Q2 | E62: 2.0210115e+17 | F62: 11AI | G62: ABBAAABB8482D4476816 | H62: 1487725 | J62: IND | K62: INDIVIDUAL | L62: C00618371 | N62: THORNTON, JOHN | O62: V | Q62: U | R62: JOHN | T62: THORNTON | V62: 5108 LEWELLYN RD | X62: LAKELAND | Y62: FL | Z62: 338100789 | AA62: RETIRED | AB62: RETIRED | AC62: C00618371 | AD62: 15E | AE62: EARMARKED CONTRIBUTION | AF62: EARMARKED FOR TRUMP MAKE AMERICA GREAT AGAIN COMMITTEE (C00618371) | AI62: 43996 | AJ62: 35 | AK62: 605 | BK62: A | BL62: ADD | BM62: ITEMIZED RECEIPTS | BN62: 44245.36 | BR62: F3X | BS62: 4.0120202e+18 | BT62: t | BV62: 2020 | BW62: SA | BY62: 4.0217202e+18 | BZ62: https://docquery.fec.gov/cgi-bin/fecimg/?202101149401542596 | CA62: Contributions From Individuals/Persons Other Than Political Committees
A63: C00580100 | B63: DONALD J. TRUMP FOR PRESIDENT, INC. | C63: 2020 | D63: M7 | E63: 2.0210421e+17 | F63: 18 | G63: SA18.196896 | H63: 1513938 | J63: IND | K63: INDIVIDUAL | N63: THORNTON, JOHN | O63: P | Q63: P | R63: JOHN | T63: THORNTON | V63: 5108 LEWELLYN RD | X63: LAKELAND | Y63: FL | Z63: 33810 | AA63: RETIRED | AB63: RETIRED | AF63: JFC TRANSFER: TRUMP MAKE AMERICA GREAT AGAIN COMMITTEE [SA18.6042] | AG63: X | AI63: 43948 | AJ63: 31.5 | AK63: 31.5 | BG63: P2020 | BI63: PRIMARY | BJ63: 2020 | BK63: A | BL63: ADD | BM63: ITEMIZED RECEIPTS | BN63: 44315.166 | BR63: F3P | BS63: 4.0423202e+18 | BT63: t | BV63: 2020 | BW63: SA | BY63: 4.0428202e+18 | BZ63: https://docquery.fec.gov/cgi-bin/fecimg/?202104209444623430 | CA63: Transfers From Other Authorized Committees
A64: C00580100 | B64: DONALD J. TRUMP FOR PRESIDENT, INC. | C64: 2020 | D64: M7 | E64: 2.0210421e+17 | F64: 18 | G64: SA18.196903 | H64: 1513938 | J64: IND | K64: INDIVIDUAL | N64: THORNTON, JOHN | O64: P | Q64: P | R64: JOHN | T64: THORNTON | V64: 5108 LEWELLYN RD | X64: LAKELAND | Y64: FL | Z64: 33810 | AA64: RETIRED | AB64: RETIRED | AD64: 15J | AE64: MEMO (FILER'S % OF CONTRIBUTION GIVEN TO JOIN | AF64: JFC TRANSFER: TRUMP MAKE AMERICA GREAT AGAIN COMMITTEE [SA18.6044] | AG64: X | AI64: 43996 | AJ64: 26.25 | AK64: 236.25 | BG64: P2020 | BI64: PRIMARY | BJ64: 2020 | BK64: A | BL64: ADD | BM64: ITEMIZED RECEIPTS | BN64: 44315.166 | BR64: F3P | BS64: 4.0423202e+18 | BT64: t | BV64: 2020 | BW64: SA | BY64: 4.0428202e+18 | BZ64: https://docquery.fec.gov/cgi-bin/fecimg/?202104209444623433 | CA64: Transfers From Other Authorized Committees
A65: C00580100 | B65: DONALD J. TRUMP FOR PRESIDENT, INC. | C65: 2020 | D65: M7 | E65: 2.0210421e+17 | F65: 18 | G65: SA18.196897 | H65: 1513938 | J65: IND | K65: INDIVIDUAL | N65: THORNTON, JOHN | O65: P | Q65: P | R65: JOHN | T65: THORNTON | V65: 5108 LEWELLYN RD | X65: LAKELAND | Y65: FL | Z65: 33810 | AA65: RETIRED | AB65: RETIRED | AF65: JFC TRANSFER: TRUMP MAKE AMERICA GREAT AGAIN COMMITTEE [SA18.6042] | AG65: X | AI65: 43955 | AJ65: 31.5 | AK65: 63 | BG65: P2020 | BI65: PRIMARY | BJ65: 2020 | BK65: A | BL65: ADD | BM65: ITEMIZED RECEIPTS | BN65: 44315.166 | BR65: F3P | BS65: 4.0423202e+18 | BT65: t | BV65: 2020 | BW65: SA | BY65: 4.0428202e+18 | BZ65: https://docquery.fec.gov/cgi-bin/fecimg/?202104209444623431 | CA65: Transfers From Other Authorized Committees
A66: C00580100 | B66: DONALD J. TRUMP FOR PRESIDENT, INC. | C66: 2020 | D66: M7 | E66: 2.0210421e+17 | F66: 18 | G66: SA18.196898 | H66: 1513938 | J66: IND | K66: INDIVIDUAL | N66: THORNTON, JOHN | O66: P | Q66: P | R66: JOHN | T66: THORNTON | V66: 5108 LEWELLYN RD | X66: LAKELAND | Y66: FL | Z66: 33810 | AA66: RETIRED | AB66: RETIRED | AF66: JFC TRANSFER: TRUMP MAKE AMERICA GREAT AGAIN COMMITTEE [SA18.6042] | AG66: X | AI66: 43958 | AJ66: 26.25 | AK66: 89.25 | BG66: P2020 | BI66: PRIMARY | BJ66: 2020 | BK66: A | BL66: ADD | BM66: ITEMIZED RECEIPTS | BN66: 44315.166 | BR66: F3P | BS66: 4.0423202e+18 | BT66: t | BV66: 2020 | BW66: SA | BY66: 4.0428202e+18 | BZ66: https://docquery.fec.gov/cgi-bin/fecimg/?202104209444623431 | CA66: Transfers From Other Authorized Committees
A67: C00580100 | B67: DONALD J. TRUMP FOR PRESIDENT, INC. | C67: 2020 | D67: M7 | E67: 2.0210421e+17 | F67: 18 | G67: SA18.196899 | H67: 1513938 | J67: IND | K67: INDIVIDUAL | N67: THORNTON, JOHN | O67: P | Q67: P | R67: JOHN | T67: THORNTON | V67: 5108 LEWELLYN RD | X67: LAKELAND | Y67: FL | Z67: 33810 | AA67: RETIRED | AB67: RETIRED | AF67: JFC TRANSFER: TRUMP MAKE AMERICA GREAT AGAIN COMMITTEE [SA18.6044] | AG67: X | AI67: 43978 | AJ67: 31.5 | AK67: 120.75 | BG67: P2020 | BI67: PRIMARY | BJ67: 2020 | BK67: A | BL67: ADD | BM67: ITEMIZED RECEIPTS | BN67: 44315.166 | BR67: F3P | BS67: 4.0423202e+18 | BT67: t | BV67: 2020 | BW67: SA | BY67: 4.0428202e+18 | BZ67: https://docquery.fec.gov/cgi-bin/fecimg/?202104209444623431 | CA67: Transfers From Other Authorized Committees
A68: C00580100 | B68: DONALD J. TRUMP FOR PRESIDENT, INC. | C68: 2020 | D68: M7 | E68: 2.0210421e+17 | F68: 18 | G68: SA18.196900 | H68: 1513938 | J68: IND | K68: INDIVIDUAL | N68: THORNTON, JOHN | O68: P | Q68: P | R68: JOHN | T68: THORNTON | V68: 5108 LEWELLYN RD | X68: LAKELAND | Y68: FL | Z68: 33810 | AA68: RETIRED | AB68: RETIRED | AF68: JFC TRANSFER: TRUMP MAKE AMERICA GREAT AGAIN COMMITTEE [SA18.6044] | AG68: X | AI68: 43986 | AJ68: 31.5 | AK68: 152.25 | BG68: P2020 | BI68: PRIMARY | BJ68: 2020 | BK68: A | BL68: ADD | BM68: ITEMIZED RECEIPTS | BN68: 44315.166 | BR68: F3P | BS68: 4.0423202e+18 | BT68: t | BV68: 2020 | BW68: SA | BY68: 4.0428202e+18 | BZ68: https://docquery.fec.gov/cgi-bin/fecimg/?202104209444623432 | CA68: Transfers From Other Authorized Committees
A69: C00580100 | B69: DONALD J. TRUMP FOR PRESIDENT, INC. | C69: 2020 | D69: M7 | E69: 2.0210421e+17 | F69: 18 | G69: SA18.196901 | H69: 1513938 | J69: IND | K69: INDIVIDUAL | N69: THORNTON, JOHN | O69: P | Q69: P | R69: JOHN | T69: THORNTON | V69: 5108 LEWELLYN RD | X69: LAKELAND | Y69: FL | Z69: 33810 | AA69: RETIRED | AB69: RETIRED | AF69: JFC TRANSFER: TRUMP MAKE AMERICA GREAT AGAIN COMMITTEE [SA18.6044] | AG69: X | AI69: 43989 | AJ69: 26.25 | AK69: 178.5 | BG69: P2020 | BI69: PRIMARY | BJ69: 2020 | BK69: A | BL69: ADD | BM69: ITEMIZED RECEIPTS | BN69: 44315.166 | BR69: F3P | BS69: 4.0423202e+18 | BT69: t | BV69: 2020 | BW69: SA | BY69: 4.0428202e+18 | BZ69: https://docquery.fec.gov/cgi-bin/fecimg/?202104209444623432 | CA69: Transfers From Other Authorized Committees
A70: C00580100 | B70: DONALD J. TRUMP FOR PRESIDENT, INC. | C70: 2020 | D70: M7 | E70: 2.0210421e+17 | F70: 18 | G70: SA18.196902 | H70: 1513938 | J70: IND | K70: INDIVIDUAL | N70: THORNTON, JOHN | O70: P | Q70: P | R70: JOHN | T70: THORNTON | V70: 5108 LEWELLYN RD | X70: LAKELAND | Y70: FL | Z70: 33810 | AA70: RETIRED | AB70: RETIRED | AD70: 15J | AE70: MEMO (FILER'S % OF CONTRIBUTION GIVEN TO JOIN | AF70: JFC TRANSFER: TRUMP MAKE AMERICA GREAT AGAIN COMMITTEE [SA18.6044] | AG70: X | AI70: 43996 | AJ70: 31.5 | AK70: 210 | BG70: P2020 | BI70: PRIMARY | BJ70: 2020 | BK70: A | BL70: ADD | BM70: ITEMIZED RECEIPTS | BN70: 44315.166 | BR70: F3P | BS70: 4.0423202e+18 | BT70: t | BV70: 2020 | BW70: SA | BY70: 4.0428202e+18 | BZ70: https://docquery.fec.gov/cgi-bin/fecimg/?202104209444623432 | CA70: Transfers From Other Authorized Committees
A71: C00694323 | B71: WINRED | C71: 2020 | D71: Q2 | E71: 2.0210115e+17 | F71: 11AI | G71: A6B1CE9802C874BD5B60 | H71: 1487725 | J71: IND | K71: INDIVIDUAL | L71: C00618371 | N71: THORNTON, JOHN | O71: V | Q71: U | R71: JOHN | T71: THORNTON | V71: 5108 LEWELLYN RD | X71: LAKELAND | Y71: FL | Z71: 338100789 | AA71: RETIRED | AB71: RETIRED | AC71: C00618371 | AD71: 15E | AE71: EARMARKED CONTRIBUTION | AF71: EARMARKED FOR TRUMP MAKE AMERICA GREAT AGAIN COMMITTEE (C00618371) | AI71: 43996 | AJ71: 42 | AK71: 605 | BK71: A | BL71: ADD | BM71: ITEMIZED RECEIPTS | BN71: 44245.363 | BR71: F3X | BS71: 4.0120202e+18 | BT71: t | BV71: 2020 | BW71: SA | BY71: 4.0217202e+18 | BZ71: https://docquery.fec.gov/cgi-bin/fecimg/?202101149401571001 | CA71: Contributions From Individuals/Persons Other Than Political Committees
A72: C00694323 | B72: WINRED | C72: 2020 | D72: YE | E72: 2.021013e+17 | F72: 11AI | G72: AC2C25D0CF9A4495D8AF | H72: 1494216 | J72: IND | K72: INDIVIDUAL | L72: C00075820 | N72: THORNTON, JOHN | O72: V | Q72: U | R72: JOHN | T72: THORNTON | V72: 5108 LEWELLYN RD | X72: LAKELAND | Y72: FL | Z72: 338100789 | AA72: RETIRED | AB72: RETIRED | AC72: C00075820 | AD72: 15E | AE72: EARMARKED CONTRIBUTION | AF72: EARMARKED FOR NRCC (C00075820) | AI72: 44183 | AJ72: 35 | AK72: 1830.76 | BK72: A | BL72: ADD | BM72: ITEMIZED RECEIPTS | BN72: 44265.195 | BR72: F3X | BS72: 4.0131202e+18 | BT72: t | BV72: 2020 | BW72: SA | BY72: 4.0309202e+18 | BZ72: https://docquery.fec.gov/cgi-bin/fecimg/?202101299415211502 | CA72: Contributions From Individuals/Persons Other Than Political Committees
A73: C00694323 | B73: WINRED | C73: 2020 | D73: Q3 | E73: 2.0210126e+17 | F73: 11AI | G73: A39422630645546A7A0E | H73: 1490496 | J73: IND | K73: INDIVIDUAL | L73: C00504530 | N73: THORNTON, JOHN | O73: V | Q73: U | R73: JOHN | T73: THORNTON | V73: 5108 LEWELLYN RD | X73: LAKELAND | Y73: FL | Z73: 338100789 | AA73: RETIRED | AB73: RETIRED | AC73: C00504530 | AD73: 15E | AE73: EARMARKED CONTRIBUTION | AF73: EARMARKED FOR CONGRESSIONAL LEADERSHIP FUND (C00504530) | AI73: 44086 | AJ73: 1 | AK73: 1137.76 | BK73: A | BL73: ADD | BM73: ITEMIZED RECEIPTS | BN73: 44252.6 | BR73: F3X | BS73: 4.0125202e+18 | BT73: t | BV73: 2020 | BW73: SA | BY73: 4.0224202e+18 | BZ73: https://docquery.fec.gov/cgi-bin/fecimg/?202101259408171157 | CA73: Contributions From Individuals/Persons Other Than Political Committees
A74: C00694323 | B74: WINRED | C74: 2020 | D74: Q2 | E74: 2.0210115e+17 | F74: 11AI | G74: A5CAE41F5A1EE4C0E9B4 | H74: 1487725 | J74: IND | K74: INDIVIDUAL | L74: C00618371 | N74: THORNTON, JOHN | O74: V | Q74: U | R74: JOHN | T74: THORNTON | V74: 5108 LEWELLYN RD | X74: LAKELAND | Y74: FL | Z74: 338100789 | AA74: RETIRED | AB74: RETIRED | AC74: C00618371 | AD74: 15E | AE74: EARMARKED CONTRIBUTION | AF74: EARMARKED FOR TRUMP MAKE AMERICA GREAT AGAIN COMMITTEE (C00618371) | AI74: 43986 | AJ74: 42 | AK74: 493 | BK74: A | BL74: ADD | BM74: ITEMIZED RECEIPTS | BN74: 44245.365 | BR74: F3X | BS74: 4.0120202e+18 | BT74: t | BV74: 2020 | BW74: SA | BY74: 4.0217202e+18 | BZ74: https://docquery.fec.gov/cgi-bin/fecimg/?202101149401310135 | CA74: Contributions From Individuals/Persons Other Than Political Committees
A75: C00694323 | B75: WINRED | C75: 2020 | D75: Q3 | E75: 2.0210126e+17 | F75: 11AI | G75: A24EF2E7DCE8E4D0A8EA | H75: 1490496 | J75: IND | K75: INDIVIDUAL | L75: C00711689 | N75: THORNTON, JOHN | O75: V | Q75: U | R75: JOHN | T75: THORNTON | V75: 5108 LEWELLYN RD | X75: LAKELAND | Y75: FL | Z75: 338100789 | AA75: RETIRED | AB75: RETIRED | AC75: C00711689 | AD75: 15E | AE75: EARMARKED CONTRIBUTION | AF75: EARMARKED FOR LACY JOHNSON FOR CONGRESS (C00711689) | AI75: 44044 | AJ75: 15 | AK75: 781 | AL75: H0MN05178 | BK75: A | BL75: ADD | BM75: ITEMIZED RECEIPTS | BN75: 44252.601 | BR75: F3X | BS75: 4.0125202e+18 | BT75: t | BV75: 2020 | BW75: SA | BY75: 4.0224202e+18 | BZ75: https://docquery.fec.gov/cgi-bin/fecimg/?202101259406486360 | CA75: Contributions From Individuals/Persons Other Than Political Committees
A76: C00694323 | B76: WINRED | C76: 2020 | D76: Q3 | E76: 2.0210126e+17 | F76: 11AI | G76: A8C4449CBA75640B1A0A | H76: 1490496 | J76: IND | K76: INDIVIDUAL | L76: C00618371 | N76: THORNTON, JOHN | O76: V | Q76: U | R76: JOHN | T76: THORNTON | V76: 5108 LEWELLYN RD | X76: LAKELAND | Y76: FL | Z76: 338100789 | AA76: RETIRED | AB76: RETIRED | AC76: C00618371 | AD76: 15E | AE76: EARMARKED CONTRIBUTION | AF76: EARMARKED FOR TRUMP MAKE AMERICA GREAT AGAIN COMMITTEE (C00618371) | AI76: 44078 | AJ76: 42 | AK76: 1097.76 | BK76: A | BL76: ADD | BM76: ITEMIZED RECEIPTS | BN76: 44252.603 | BR76: F3X | BS76: 4.0125202e+18 | BT76: t | BV76: 2020 | BW76: SA | BY76: 4.0224202e+18 | BZ76: https://docquery.fec.gov/cgi-bin/fecimg/?202101259407876099 | CA76: Contributions From Individuals/Persons Other Than Political Committees
A77: C00694323 | B77: WINRED | C77: 2020 | D77: Q3 | E77: 2.0210126e+17 | F77: 11AI | G77: A19DE04875623497C957 | H77: 1490496 | J77: IND | K77: INDIVIDUAL | L77: C00618371 | N77: THORNTON, JOHN | O77: V | Q77: U | R77: JOHN | T77: THORNTON | V77: 5108 LEWELLYN RD | X77: LAKELAND | Y77: FL | Z77: 338100789 | AA77: RETIRED | AB77: RETIRED | AC77: C00618371 | AD77: 15E | AE77: EARMARKED CONTRIBUTION | AF77: EARMARKED FOR TRUMP MAKE AMERICA GREAT AGAIN COMMITTEE (C00618371) | AI77: 44016 | AJ77: 42 | AK77: 689 | BK77: A | BL77: ADD | BM77: ITEMIZED RECEIPTS | BN77: 44252.602 | BR77: F3X | BS77: 4.0125202e+18 | BT77: t | BV77: 2020 | BW77: SA | BY77: 4.0224202e+18 | BZ77: https://docquery.fec.gov/cgi-bin/fecimg/?202101259405534724 | CA77: Contributions From Individuals/Persons Other Than Political Committees
A78: C00694323 | B78: WINRED | C78: 2020 | D78: Q3 | E78: 2.0210126e+17 | F78: 11AI | G78: A947AA031B3614792997 | H78: 1490496 | J78: IND | K78: INDIVIDUAL | L78: C00458828 | N78: THORNTON, JOHN | O78: V | Q78: U | R78: JOHN | T78: THORNTON | V78: 5108 LEWELLYN RD | X78: LAKELAND | Y78: FL | Z78: 338100789 | AA78: RETIRED | AB78: RETIRED | AC78: C00458828 | AD78: 15E | AE78: EARMARKED CONTRIBUTION | AF78: EARMARKED FOR TEAM GRAHAM, INC. (C00458828) | AI78: 44057 | AJ78: 15 | AK78: 920.76 | AL78: S0SC00149 | BK78: A | BL78: ADD | BM78: ITEMIZED RECEIPTS | BN78: 44252.603 | BR78: F3X | BS78: 4.0125202e+18 | BT78: t | BV78: 2020 | BW78: SA | BY78: 4.0224202e+18 | BZ78: https://docquery.fec.gov/cgi-bin/fecimg/?202101259406916986 | CA78: Contributions From Individuals/Persons Other Than Political Committees
A79: C00694323 | B79: WINRED | C79: 2020 | D79: Q2 | E79: 2.0210115e+17 | F79: 11AI | G79: A23DE9B600A0F47E79D8 | H79: 1487725 | J79: IND | K79: INDIVIDUAL | L79: C00618371 | N79: THORNTON, JOHN | O79: V | Q79: U | R79: JOHN | T79: THORNTON | V79: 5108 LEWELLYN RD | X79: LAKELAND | Y79: FL | Z79: 338100789 | AA79: RETIRED | AB79: RETIRED | AC79: C00618371 | AD79: 15E | AE79: EARMARKED CONTRIBUTION | AF79: EARMARKED FOR TRUMP MAKE AMERICA GREAT AGAIN COMMITTEE (C00618371) | AI79: 43928 | AJ79: 35 | AK79: 248 | BK79: A | BL79: ADD | BM79: ITEMIZED RECEIPTS | BN79: 44245.366 | BR79: F3X | BS79: 4.0120202e+18 | BT79: t | BV79: 2020 | BW79: SA | BY79: 4.0217202e+18 | BZ79: https://docquery.fec.gov/cgi-bin/fecimg/?202101149400088459 | CA79: Contributions From Individuals/Persons Other Than Political Committees
A80: C00694323 | B80: WINRED | C80: 2020 | D80: Q3 | E80: 2.0210126e+17 | F80: 11AI | G80: A836B2C3FDBD547798F3 | H80: 1490496 | J80: IND | K80: INDIVIDUAL | L80: C00725853 | N80: THORNTON, JOHN | O80: V | Q80: U | R80: JOHN | T80: THORNTON | V80: 5108 LEWELLYN RD | X80: LAKELAND | Y80: FL | Z80: 338100789 | AA80: RETIRED | AB80: RETIRED | AC80: C00725853 | AD80: 15E | AE80: EARMARKED CONTRIBUTION | AF80: EARMARKED FOR BURGESS 4 UTAH (C00725853) | AI80: 44086 | AJ80: 9 | AK80: 1137.76 | AL80: H0UT04076 | BK80: A | BL80: ADD | BM80: ITEMIZED RECEIPTS | BN80: 44252.606 | BR80: F3X | BS80: 4.0125202e+18 | BT80: t | BV80: 2020 | BW80: SA | BY80: 4.0224202e+18 | BZ80: https://docquery.fec.gov/cgi-bin/fecimg/?202101259408172207 | CA80: Contributions From Individuals/Persons Other Than Political Committees
A81: C00694323 | B81: WINRED | C81: 2020 | D81: 30G | E81: 2.0210304e+17 | F81: 11AI | G81: AF35BEDF47E2A49908D6 | H81: 1502683 | J81: IND | K81: INDIVIDUAL | L81: C00711689 | N81: THORNTON, JOHN | O81: V | Q81: U | R81: JOHN | T81: THORNTON | V81: 5108 LEWELLYN RD | X81: LAKELAND | Y81: FL | Z81: 338100789 | AA81: RETIRED | AB81: RETIRED | AC81: C00711689 | AD81: 15E | AE81: EARMARKED CONTRIBUTION | AF81: EARMARKED FOR LACY JOHNSON FOR CONGRESS (C00711689) | AI81: 44127 | AJ81: 10 | AK81: 1578.76 | BK81: A | BL81: ADD | BM81: ITEMIZED RECEIPTS | BN81: 44260.607 | BR81: F3X | BS81: 4.0304202e+18 | BT81: t | BV81: 2020 | BW81: SA | BY81: 4.0304202e+18 | BZ81: https://docquery.fec.gov/cgi-bin/fecimg/?202103039432247668 | CA81: Contributions From Individuals/Persons Other Than Political Committees
A82: C00694323 | B82: WINRED | C82: 2020 | D82: 30G | E82: 2.0210304e+17 | F82: 11AI | G82: A85FB4EBD0B0047EBA3C | H82: 1502683 | J82: IND | K82: INDIVIDUAL | L82: C00725853 | N82: THORNTON, JOHN | O82: V | Q82: U | R82: JOHN | T82: THORNTON | V82: 5108 LEWELLYN RD | X82: LAKELAND | Y82: FL | Z82: 338100789 | AA82: RETIRED | AB82: RETIRED | AC82: C00725853 | AD82: 15E | AE82: EARMARKED CONTRIBUTION | AF82: EARMARKED FOR BURGESS 4 UTAH (C00725853) | AI82: 44134 | AJ82: 10 | AK82: 1638.76 | BK82: A | BL82: ADD | BM82: ITEMIZED RECEIPTS | BN82: 44260.604 | BR82: F3X | BS82: 4.0304202e+18 | BT82: t | BV82: 2020 | BW82: SA | BY82: 4.0304202e+18 | BZ82: https://docquery.fec.gov/cgi-bin/fecimg/?202103039433072214 | CA82: Contributions From Individuals/Persons Other Than Political Committees
A83: C00694323 | B83: WINRED | C83: 2020 | D83: 30G | E83: 2.0210304e+17 | F83: 11AI | G83: A3A5A13DBA6DF47BD9F9 | H83: 1502683 | J83: IND | K83: INDIVIDUAL | L83: C00711689 | N83: THORNTON, JOHN | O83: V | Q83: U | R83: JOHN | T83: THORNTON | V83: 5108 LEWELLYN RD | X83: LAKELAND | Y83: FL | Z83: 338100789 | AA83: RETIRED | AB83: RETIRED | AC83: C00711689 | AD83: 15E | AE83: EARMARKED CONTRIBUTION | AF83: EARMARKED FOR LACY JOHNSON FOR CONGRESS (C00711689) | AI83: 44134 | AJ83: 10 | AK83: 1638.76 | BK83: A | BL83: ADD | BM83: ITEMIZED RECEIPTS | BN83: 44260.614 | BR83: F3X | BS83: 4.0304202e+18 | BT83: t | BV83: 2020 | BW83: SA | BY83: 4.0304202e+18 | BZ83: https://docquery.fec.gov/cgi-bin/fecimg/?202103039433070026 | CA83: Contributions From Individuals/Persons Other Than Political Committees
A84: C00694323 | B84: WINRED | C84: 2020 | D84: 30G | E84: 2.0210304e+17 | F84: 11AI | G84: A63B8E8EFA1534C6CB04 | H84: 1502683 | J84: IND | K84: INDIVIDUAL | L84: C00733329 | N84: THORNTON, JOHN | O84: V | Q84: U | R84: JOHN | T84: THORNTON | V84: 5108 LEWELLYN RD | X84: LAKELAND | Y84: FL | Z84: 338100789 | AA84: RETIRED | AB84: RETIRED | AC84: C00733329 | AD84: 15E | AE84: EARMARKED CONTRIBUTION | AF84: EARMARKED FOR BYRON DONALDS FOR CONGRESS (C00733329) | AI84: 44130 | AJ84: 10 | AK84: 1608.76 | BK84: A | BL84: ADD | BM84: ITEMIZED RECEIPTS | BN84: 44260.616 | BR84: F3X | BS84: 4.0304202e+18 | BT84: t | BV84: 2020 | BW84: SA | BY84: 4.0304202e+18 | BZ84: https://docquery.fec.gov/cgi-bin/fecimg/?202103039432518673 | CA84: Contributions From Individuals/Persons Other Than Political Committees
A85: C00694323 | B85: WINRED | C85: 2020 | D85: 30G | E85: 2.0210304e+17 | F85: 11AI | G85: A7F2F0760A78A429FA6E | H85: 1502683 | J85: IND | K85: INDIVIDUAL | L85: C00618371 | N85: THORNTON, JOHN | O85: V | Q85: U | R85: JOHN | T85: THORNTON | V85: 5108 LEWELLYN RD | X85: LAKELAND | Y85: FL | Z85: 338100789 | AA85: RETIRED | AB85: RETIRED | AC85: C00618371 | AD85: 15E | AE85: EARMARKED CONTRIBUTION | AF85: EARMARKED FOR TRUMP MAKE AMERICA GREAT AGAIN COMMITTEE (C00618371) | AI85: 44139 | AJ85: 42 | AK85: 1680.76 | BK85: A | BL85: ADD | BM85: ITEMIZED RECEIPTS | BN85: 44260.616 | BR85: F3X | BS85: 4.0304202e+18 | BT85: t | BV85: 2020 | BW85: SA | BY85: 4.0304202e+18 | BZ85: https://docquery.fec.gov/cgi-bin/fecimg/?202103039433866306 | CA85: Contributions From Individuals/Persons Other Than Political Committees
A86: C00694323 | B86: WINRED | C86: 2020 | D86: 30G | E86: 2.0210304e+17 | F86: 11AI | G86: A22912A0DFD7544E0A84 | H86: 1502683 | J86: IND | K86: INDIVIDUAL | L86: C00726117 | N86: THORNTON, JOHN | O86: V | Q86: U | R86: JOHN | T86: THORNTON | V86: 5108 LEWELLYN RD | X86: LAKELAND | Y86: FL | Z86: 338100789 | AA86: RETIRED | AB86: RETIRED | AC86: C00726117 | AD86: 15E | AE86: EARMARKED CONTRIBUTION | AF86: EARMARKED FOR KIM KLACIK FOR CONGRESS (C00726117) | AI86: 44127 | AJ86: 15 | AK86: 1578.76 | BK86: A | BL86: ADD | BM86: ITEMIZED RECEIPTS | BN86: 44260.614 | BR86: F3X | BS86: 4.0304202e+18 | BT86: t | BV86: 2020 | BW86: SA | BY86: 4.0304202e+18 | BZ86: https://docquery.fec.gov/cgi-bin/fecimg/?202103039432253439 | CA86: Contributions From Individuals/Persons Other Than Political Committees
A87: C00694323 | B87: WINRED | C87: 2020 | D87: 30G | E87: 2.0210304e+17 | F87: 11AI | G87: A63F13EB38A934B44AD8 | H87: 1502683 | J87: IND | K87: INDIVIDUAL | L87: C00716860 | N87: THORNTON, JOHN | O87: V | Q87: U | R87: JOHN | T87: THORNTON | V87: 5108 LEWELLYN RD | X87: LAKELAND | Y87: FL | Z87: 338100789 | AA87: RETIRED | AB87: RETIRED | AC87: C00716860 | AD87: 15E | AE87: EARMARKED CONTRIBUTION | AF87: EARMARKED FOR JASON LEWIS FOR SENATE (C00716860) | AI87: 44130 | AJ87: 10 | AK87: 1608.76 | BK87: A | BL87: ADD | BM87: ITEMIZED RECEIPTS | BN87: 44260.616 | BR87: F3X | BS87: 4.0304202e+18 | BT87: t | BV87: 2020 | BW87: SA | BY87: 4.0304202e+18 | BZ87: https://docquery.fec.gov/cgi-bin/fecimg/?202103039432547436 | CA87: Contributions From Individuals/Persons Other Than Political Committees
A88: C00694323 | B88: WINRED | C88: 2020 | D88: 30G | E88: 2.0210304e+17 | F88: 11AI | G88: AD3F074B7ED114B70A67 | H88: 1502683 | J88: IND | K88: INDIVIDUAL | L88: C00193342 | N88: THORNTON, JOHN | O88: V | Q88: U | R88: JOHN | T88: THORNTON | V88: 5108 LEWELLYN RD | X88: LAKELAND | Y88: FL | Z88: 338100789 | AA88: RETIRED | AB88: RETIRED | AC88: C00193342 | AD88: 15E | AE88: EARMARKED CONTRIBUTION | AF88: EARMARKED FOR MCCONNELL SENATE COMMITTEE (C00193342) | AI88: 44147 | AJ88: 35 | AK88: 1725.76 | BK88: A | BL88: ADD | BM88: ITEMIZED RECEIPTS | BN88: 44260.62 | BR88: F3X | BS88: 4.0304202e+18 | BT88: t | BV88: 2020 | BW88: SA | BY88: 4.0304202e+18 | BZ88: https://docquery.fec.gov/cgi-bin/fecimg/?202103039434808668 | CA88: Contributions From Individuals/Persons Other Than Political Committees
A89: C00694323 | B89: WINRED | C89: 2020 | D89: 30G | E89: 2.0210304e+17 | F89: 11AI | G89: AA822D53DB336433B92B | H89: 1502683 | J89: IND | K89: INDIVIDUAL | L89: C00762237 | N89: THORNTON, JOHN | O89: V | Q89: U | R89: JOHN | T89: THORNTON | V89: 5108 LEWELLYN RD | X89: LAKELAND | Y89: FL | Z89: 338100789 | AA89: RETIRED | AB89: RETIRED | AC89: C00762237 | AD89: 15E | AE89: EARMARKED CONTRIBUTION | AF89: EARMARKED FOR DEVOLDER SANTOS FOR CONGRESS RECOUNT (C00762237) | AI89: 44145 | AJ89: 10 | AK89: 1690.76 | BK89: A | BL89: ADD | BM89: ITEMIZED RECEIPTS | BN89: 44260.62 | BR89: F3X | BS89: 4.0304202e+18 | BT89: t | BV89: 2020 | BW89: SA | BY89: 4.0304202e+18 | BZ89: https://docquery.fec.gov/cgi-bin/fecimg/?202103039434610345 | CA89: Contributions From Individuals/Persons Other Than Political Committees
A90: C00694323 | B90: WINRED | C90: 2020 | D90: 30G | E90: 2.0210304e+17 | F90: 11AI | G90: AF74155CF00FF45F6AEA | H90: 1502683 | J90: IND | K90: INDIVIDUAL | L90: C00666859 | N90: THORNTON, JOHN | O90: V | Q90: U | R90: JOHN | T90: THORNTON | V90: 5108 LEWELLYN RD | X90: LAKELAND | Y90: FL | Z90: 338100789 | AA90: RETIRED | AB90: RETIRED | AC90: C00666859 | AD90: 15E | AE90: EARMARKED CONTRIBUTION | AF90: EARMARKED FOR MARYOTT FOR CONGRESS (C00666859) | AI90: 44129 | AJ90: 10 | AK90: 1588.76 | BK90: A | BL90: ADD | BM90: ITEMIZED RECEIPTS | BN90: 44260.62 | BR90: F3X | BS90: 4.0304202e+18 | BT90: t | BV90: 2020 | BW90: SA | BY90: 4.0304202e+18 | BZ90: https://docquery.fec.gov/cgi-bin/fecimg/?202103039432469022 | CA90: Contributions From Individuals/Persons Other Than Political Committees
A91: C00694323 | B91: WINRED | C91: 2020 | D91: 30G | E91: 2.0210304e+17 | F91: 11AI | G91: A3CBED133A3334F7183F | H91: 1502683 | J91: IND | K91: INDIVIDUAL | L91: C00027466 | N91: THORNTON, JOHN | O91: V | Q91: U | R91: JOHN | T91: THORNTON | V91: 5108 LEWELLYN RD | X91: LAKELAND | Y91: FL | Z91: 338100789 | AA91: RETIRED | AB91: RETIRED | AC91: C00027466 | AD91: 15E | AE91: EARMARKED CONTRIBUTION | AF91: EARMARKED FOR NRSC (C00027466) | AI91: 44153 | AJ91: 15 | AK91: 1740.76 | BK91: A | BL91: ADD | BM91: ITEMIZED RECEIPTS | BN91: 44260.63 | BR91: F3X | BS91: 4.0304202e+18 | BT91: t | BV91: 2020 | BW91: SA | BY91: 4.0304202e+18 | BZ91: https://docquery.fec.gov/cgi-bin/fecimg/?202103039435215042 | CA91: Contributions From Individuals/Persons Other Than Political Committees
A92: C00694323 | B92: WINRED | C92: 2020 | D92: 30G | E92: 2.0210304e+17 | F92: 11AI | G92: A1B04EF9CFC5647FB93A | H92: 1502683 | J92: IND | K92: INDIVIDUAL | L92: C00458828 | N92: THORNTON, JOHN | O92: V | Q92: U | R92: JOHN | T92: THORNTON | V92: 5108 LEWELLYN RD | X92: LAKELAND | Y92: FL | Z92: 338100789 | AA92: RETIRED | AB92: RETIRED | AC92: C00458828 | AD92: 15E | AE92: EARMARKED CONTRIBUTION | AF92: EARMARKED FOR TEAM GRAHAM, INC. (C00458828) | AI92: 44127 | AJ92: 10 | AK92: 1578.76 | BK92: A | BL92: ADD | BM92: ITEMIZED RECEIPTS | BN92: 44260.631 | BR92: F3X | BS92: 4.0304202e+18 | BT92: t | BV92: 2020 | BW92: SA | BY92: 4.0304202e+18 | BZ92: https://docquery.fec.gov/cgi-bin/fecimg/?202103039432247498 | CA92: Contributions From Individuals/Persons Other Than Political Committees
... A96: C00694323 | B96: WINRED | C96: 2020 | D96: Q3 | E96: 2.0210126e+17 | F96: 11AI | G96: AA9D2D34DFBA7419A9E7 | H96: 1490496 | J96: IND | K96: INDIVIDUAL | L96: C00750521 | N96: THORNTON, JOHN | O96: V | Q96: U | R96: JOHN | T96: THORNTON | V96: 5108 LEWELLYN RD | X96: LAKELAND | Y96: FL | Z96: 338100789 | AA96: RETIRED | AB96: RETIRED | AC96: C00750521 | AD96: 15E | AE96: EARMARKED CONTRIBUTION | AF96: EARMARKED FOR TEAM SCALISE (C00750521) | AI96: 44069 | AJ96: 25 | AK96: 995.76 | BK96: A | BL96: ADD | BM96: ITEMIZED RECEIPTS | BN96: 44252.608 | BR96: F3X | BS96: 4.0125202e+18 | BT96: t | BV96: 2020 | BW96: SA | BY96: 4.0224202e+18 | BZ96: https://docquery.fec.gov/cgi-bin/fecimg/?202101259407391401 | CA96: Contributions From Individuals/Persons Other Than Political Committees
A97: C00003418 | B97: REPUBLICAN NATIONAL COMMITTEE | C97: 2020 | D97: 30G | E97: 2.0210625e+17 | F97: 12 | G97: SA.103016300.1.TM32 | H97: 1521551 | J97: IND | K97: INDIVIDUAL | N97: THORNTON, JOHN | O97: Y | Q97: U | R97: JOHN | T97: THORNTON | V97: 5108 LEWELLYN RD | X97: LAKELAND | Y97: FL | Z97: 338100789 | AA97: RETIRED | AB97: RETIRED | AD97: 15J | AE97: MEMO (FILER'S % OF CONTRIBUTION GIVEN TO JOIN | AF97: CONTRIBUTION | AG97: X | AI97: 44139 | AJ97: 39.9 | AK97: 236.25 | BG97: P | BI97: PRIMARY | BK97: A | BL97: ADD | BM97: ITEMIZED RECEIPTS | BN97: 44377.239 | BP97: SA12.102118449 | BQ97: SA12 | BR97: F3X | BS97: 4.0626202e+18 | BT97: t | BU97: TRANSFER FROM TRUMP MAKE AMERICA GREAT AGAIN COMMITTEE | BV97: 2020 | BW97: SA | BY97: 4.0630202e+18 | BZ97: https://docquery.fec.gov/cgi-bin/fecimg/?202106249450452972 | CA97: Transfers from Authorized Committees
A98: C00760124 | B98: NATIONAL VICTORY ACTION FUND | C98: 2020 | D98: 30G | E98: 2.0210311e+17 | F98: 11AI | G98: ADF85EF67D1B1457CBC3 | H98: 1503611 | J98: IND | K98: INDIVIDUAL | N98: THORNTON, JOHN | O98: V | Q98: U | R98: JOHN | T98: THORNTON | V98: 5108 LEWELLYN ROAD | X98: LAKELAND | Y98: FL | Z98: 33810 | AA98: RETIRED | AB98: RETIRED | AF98: EARMARKED (NON-DIRECTED) THROUGH WINRED | AI98: 44125 | AJ98: 25 | AK98: 25 | BK98: A | BL98: ADD | BM98: ITEMIZED RECEIPTS | BN98: 44268.163 | BR98: F3X | BS98: 4.0311202e+18 | BT98: t | BV98: 2020 | BW98: SA | BY98: 4.0313202e+18 | BZ98: https://docquery.fec.gov/cgi-bin/fecimg/?202103109440381751 | CA98: Contributions From Individuals/Persons Other Than Political Committees
A99: C00003418 | B99: REPUBLICAN NATIONAL COMMITTEE | C99: 2020 | D99: 30G | E99: 2.0210625e+17 | F99: 12 | G99: SA.94045662.1.TM31 | H99: 1521551 | J99: IND | K99: INDIVIDUAL | N99: THORNTON, JOHN | O99: Y | Q99: U | R99: JOHN | T99: THORNTON | V99: 5108 LEWELLYN RD | X99: LAKELAND | Y99: FL | Z99: 338100789 | AA99: RETIRED | AB99: RETIRED | AD99: 15J | AE99: MEMO (FILER'S % OF CONTRIBUTION GIVEN TO JOIN | AF99: CONTRIBUTION | AG99: X | AI99: 44047 | AJ99: 10.5 | AK99: 236.25 | BG99: P | BI99: PRIMARY | BK99: A | BL99: ADD | BM99: ITEMIZED RECEIPTS | BN99: 44377.243 | BP99: SA12.102118448 | BQ99: SA12 | BR99: F3X | BS99: 4.0626202e+18 | BT99: t | BU99: TRANSFER FROM TRUMP MAKE AMERICA GREAT AGAIN COMMITTEE | BV99: 2020 | BW99: SA | BY99: 4.0630202e+18 | BZ99: https://docquery.fec.gov/cgi-bin/fecimg/?202106249450361554 | CA99: Transfers from Authorized Committees
A100: C00003418 | B100: REPUBLICAN NATIONAL COMMITTEE | C100: 2020 | D100: 30G | E100: 2.0210625e+17 | F100: 12 | G100: SA.96452392.1.TM31 | H100: 1521551 | J100: IND | K100: INDIVIDUAL | N100: THORNTON, JOHN | O100: Y | Q100: U | R100: JOHN | T100: THORNTON | V100: 5108 LEWELLYN RD | X100: LAKELAND | Y100: FL | Z100: 338100789 | AA100: RETIRED | AB100: RETIRED | AD100: 15J | AE100: MEMO (FILER'S % OF CONTRIBUTION GIVEN TO JOIN | AF100: CONTRIBUTION | AG100: X | AI100: 44078 | AJ100: 2.1 | AK100: 236.25 | BG100: P | BI100: PRIMARY | BK100: A | BL100: ADD | BM100: ITEMIZED RECEIPTS | BN100: 44377.243 | BP100: SA12.102118448 | BQ100: SA12 | BR100: F3X | BS100: 4.0626202e+18 | BT100: t | BU100: TRANSFER FROM TRUMP MAKE AMERICA GREAT AGAIN COMMITTEE | BV100: 2020 | BW100: SA | BY100: 4.0630202e+18 | BZ100: https://docquery.fec.gov/cgi-bin/fecimg/?202106249450361554 | CA100: Transfers from Authorized Committees
A101: C00003418 | B101: REPUBLICAN NATIONAL COMMITTEE | C101: 2020 | D101: 30G | E101: 2.0210625e+17 | F101: 12 | G101: SA.97757655.1.TM31 | H101: 1521551 | J101: IND | K101: INDIVIDUAL | N101: THORNTON, JOHN | O101: Y | Q101: U | R101: JOHN | T101: THORNTON | V101: 5108 LEWELLYN RD | X101: LAKELAND | Y101: FL | Z101: 338100789 | AA101: RETIRED | AB101: RETIRED | AD101: 15J | AE101: MEMO (FILER'S % OF CONTRIBUTION GIVEN TO JOIN | AF101: CONTRIBUTION | AG101: X | AI101: 44097 | AJ101: 0.5 | AK101: 236.25 | BG101: P | BI101: PRIMARY | BK101: A | BL101: ADD | BM101: ITEMIZED RECEIPTS | BN101: 44377.245 | BP101: SA12.102118447 | BQ101: SA12 | BR101: F3X | BS101: 4.0626202e+18 | BT101: t | BU101: TRANSFER FROM TRUMP MAKE AMERICA GREAT AGAIN COMMITTEE | BV101: 2020 | BW101: SA | BY101: 4.0630202e+18 | BZ101: https://docquery.fec.gov/cgi-bin/fecimg/?202106249450252767 | CA101: Transfers from Authorized Committees
A102: C00003418 | B102: REPUBLICAN NATIONAL COMMITTEE | C102: 2020 | D102: 30G | E102: 2.0210625e+17 | F102: 12 | G102: SA.99540947.1.TM31 | H102: 1521551 | J102: IND | K102: INDIVIDUAL | N102: THORNTON, JOHN | O102: Y | Q102: U | R102: JOHN | T102: THORNTON | V102: 5108 LEWELLYN RD | X102: LAKELAND | Y102: FL | Z102: 338100789 | AA102: RETIRED | AB102: RETIRED | AD102: 15J | AE102: MEMO (FILER'S % OF CONTRIBUTION GIVEN TO JOIN | AF102: CONTRIBUTION | AG102: X | AI102: 44113 | AJ102: 2.25 | AK102: 236.25 | BG102: P | BI102: PRIMARY | BK102: A | BL102: ADD | BM102: ITEMIZED RECEIPTS | BN102: 44377.245 | BP102: SA12.102118447 | BQ102: SA12 | BR102: F3X | BS102: 4.0626202e+18 | BT102: t | BU102: TRANSFER FROM TRUMP MAKE AMERICA GREAT AGAIN COMMITTEE | BV102: 2020 | BW102: SA | BY102: 4.0630202e+18 | BZ102: https://docquery.fec.gov/cgi-bin/fecimg/?202106249450252767 | CA102: Transfers from Authorized Committees
A103: C00694323 | B103: WINRED | C103: 2020 | D103: Q3 | E103: 2.0210126e+17 | F103: 11AI | G103: A8124683110CA4598A4E | H103: 1490496 | J103: IND | K103: INDIVIDUAL | L103: C00458828 | N103: THORNTON, JOHN | O103: V | Q103: U | R103: JOHN | T103: THORNTON | V103: 5108 LEWELLYN RD | X103: LAKELAND | Y103: FL | Z103: 338100789 | AA103: RETIRED | AB103: RETIRED | AC103: C00458828 | AD103: 15E | AE103: EARMARKED CONTRIBUTION | AF103: EARMARKED FOR TEAM GRAHAM, INC. (C00458828) | AI103: 44083 | AJ103: 10 | AK103: 1107.76 | AL103: S0SC00149 | BK103: A | BL103: ADD | BM103: ITEMIZED RECEIPTS | BN103: 44252.609 | BR103: F3X | BS103: 4.0125202e+18 | BT103: t | BV103: 2020 | BW103: SA | BY103: 4.0224202e+18 | BZ103: https://docquery.fec.gov/cgi-bin/fecimg/?202101259408054042 | CA103: Contributions From Individuals/Persons Other Than Political Committees
...

Sheet Beth Mooney
A1: committee_id | B1: committee_name | C1: report_year | D1: report_type | E1: image_number | F1: line_number | G1: transaction_id | H1: file_number | I1: committee_name | J1: entity_type | K1: entity_type_desc | L1: unused_contbr_id | M1: contributor_prefix | N1: contributor_name | O1: recipient_committee_type | P1: recipient_committee_org_type | Q1: recipient_committee_designation | R1: contributor_first_name | S1: contributor_middle_name | T1: contributor_last_name | U1: contributor_suffix | V1: contributor_street_1 | W1: contributor_street_2 | X1: contributor_city | Y1: contributor_state | Z1: contributor_zip | AA1: contributor_employer | AB1: contributor_occupation | AC1: contributor_id | AD1: receipt_type | AE1: receipt_type_desc | AF1: receipt_type_full | AG1: memo_code | AH1: memo_code_full | AI1: contribution_receipt_date | AJ1: contribution_receipt_amount | AK1: contributor_aggregate_ytd | AL1: candidate_id | AM1: candidate_name | AN1: candidate_first_name | AO1: candidate_last_name | AP1: candidate_middle_name | AQ1: candidate_prefix | AR1: candidate_suffix | AS1: candidate_office | AT1: candidate_office_full | AU1: candidate_office_state | AV1: candidate_office_state_full | AW1: candidate_office_district | AX1: conduit_committee_id | AY1: conduit_committee_name | AZ1: conduit_committee_street1 | BA1: conduit_committee_street2 | BB1: conduit_committee_city | BC1: conduit_committee_state | BD1: conduit_committee_zip | BE1: donor_committee_name | BF1: national_committee_nonfederal_account | BG1: election_type | BH1: election_type_full | BI1: fec_election_type_desc | BJ1: fec_election_year | BK1: amendment_indicator | BL1: amendment_indicator_desc | BM1: schedule_type_full | BN1: load_date | BO1: original_sub_id | BP1: back_reference_transaction_id | BQ1: back_reference_schedule_name | BR1: filing_form | BS1: link_id | BT1: is_individual | BU1: memo_text | BV1: two_year_transaction_period | BW1: schedule_type | BX1: increased_limit | BY1: sub_id | BZ1: pdf_url | CA1: line_number_label
A2: C00507368 | B2: BEATTY FOR CONGRESS | C2: 2020 | D2: Q1 | E2: 2.0210415e+17 | F2: 11AI | G2: VPF6NSKQWT7 | H2: 1510510 | J2: IND | K2: INDIVIDUAL | N2: MOONEY, BETH E | O2: H | Q2: P | R2: BETH | S2: E | T2: MOONEY | V2: 11 COLONY LN | X2: BRATENAHL | Y2: OH | Z2: 441081119 | AA2: KEY BANK | AB2: CHAIRMAN & CEO | AD2: 15 | AE2: CONTRIBUTION | AI2: 43900 | AJ2: 1500 | AK2: 1500 | BG2: P2020 | BI2: PRIMARY | BJ2: 2020 | BK2: N | BL2: NO CHANGE | BM2: ITEMIZED RECEIPTS | BN2: 44304.148 | BR2: F3 | BS2: 4.0415202e+18 | BT2: t | BV2: 2020 | BW2: SA | BY2: 4.0418202e+18 | BZ2: https://docquery.fec.gov/cgi-bin/fecimg/?202104149443336091 | CA2: Contributions From Individuals/Persons Other Than Political Committees
A3: C00073155 | B3: KEYCORP ADVOCATES FUND | C3: 2019 | D3: MY | E3: 2.0191008e+17 | F3: 11AI | G3: 0BE4E100B6834D5AB3BA | H3: 1355016 | J3: IND | K3: INDIVIDUAL | N3: MOONEY, BETH | O3: Q | P3: C | Q3: B | R3: BETH | T3: MOONEY | V3: 11 COLONY LN | X3: BRATENAHL | Y3: OH | Z3: 441081119 | AA3: KEYCORP | AB3: CHAIRMAN OF THE BOARD & CEO | AD3: 15 | AE3: CONTRIBUTION | AI3: 43490 | AJ3: 192.3 | AK3: 2499.9 | BG3: P | BI3: PRIMARY | BK3: A | BL3: ADD | BM3: ITEMIZED RECEIPTS | BN3: 43747.109 | BR3: F3X | BS3: 4.1007202e+18 | BT3: t | BV3: 2020 | BW3: SA | BY3: 4.1008202e+18 | BZ3: http://docquery.fec.gov/cgi-bin/fecimg/?201910079163758562 | CA3: Contributions From Individuals/Persons Other Than Political Committees
A4: C00073155 | B4: KEYCORP ADVOCATES FUND | C4: 2019 | D4: MY | E4: 2.0191008e+17 | F4: 11AI | G4: 05458006B5F948F89D89 | H4: 1355016 | J4: IND | K4: INDIVIDUAL | N4: MOONEY, BETH | O4: Q | P4: C | Q4: B | R4: BETH | T4: MOONEY | V4: 11 COLONY LN | X4: BRATENAHL | Y4: OH | Z4: 441081119 | AA4: KEYCORP | AB4: CHAIRMAN OF THE BOARD & CEO | AD4: 15 | AE4: CONTRIBUTION | AI4: 43504 | AJ4: 192.3 | AK4: 2499.9 | BG4: P | BI4: PRIMARY | BK4: A | BL4: ADD | BM4: ITEMIZED RECEIPTS | BN4: 43747.109 | BR4: F3X | BS4: 4.1007202e+18 | BT4: t | BV4: 2020 | BW4: SA | BY4: 4.1008202e+18 | BZ4: http://docquery.fec.gov/cgi-bin/fecimg/?201910079163758562 | CA4: Contributions From Individuals/Persons Other Than Political Committees
A5: C00073155 | B5: KEYCORP ADVOCATES FUND | C5: 2019 | D5: MY | E5: 2.0191008e+17 | F5: 11AI | G5: E4A7510B69E049E3B856 | H5: 1355016 | J5: IND | K5: INDIVIDUAL | N5: MOONEY, BETH | O5: Q | P5: C | Q5: B | R5: BETH | T5: MOONEY | V5: 11 COLONY LN | X5: BRATENAHL | Y5: OH | Z5: 441081119 | AA5: KEYCORP | AB5: CHAIRMAN OF THE BOARD & CEO | AD5: 15 | AE5: CONTRIBUTION | AI5: 43518 | AJ5: 192.3 | AK5: 2499.9 | BG5: P | BI5: PRIMARY | BK5: A | BL5: ADD | BM5: ITEMIZED RECEIPTS | BN5: 43747.109 | BR5: F3X | BS5: 4.1007202e+18 | BT5: t | BV5: 2020 | BW5: SA | BY5: 4.1008202e+18 | BZ5: http://docquery.fec.gov/cgi-bin/fecimg/?201910079163758562 | CA5: Contributions From Individuals/Persons Other Than Political Committees
A6: C00073155 | B6: KEYCORP ADVOCATES FUND | C6: 2019 | D6: MY | E6: 2.0191008e+17 | F6: 11AI | G6: E00EBC83F24F4475B036 | H6: 1355016 | J6: IND | K6: INDIVIDUAL | N6: MOONEY, BETH | O6: Q | P6: C | Q6: B | R6: BETH | T6: MOONEY | V6: 11 COLONY LN | X6: BRATENAHL | Y6: OH | Z6: 441081119 | AA6: KEYCORP | AB6: CHAIRMAN OF THE BOARD & CEO | AD6: 15 | AE6: CONTRIBUTION | AI6: 43532 | AJ6: 192.3 | AK6: 2499.9 | BG6: P | BI6: PRIMARY | BK6: A | BL6: ADD | BM6: ITEMIZED RECEIPTS | BN6: 43747.109 | BR6: F3X | BS6: 4.1007202e+18 | BT6: t | BV6: 2020 | BW6: SA | BY6: 4.1008202e+18 | BZ6: http://docquery.fec.gov/cgi-bin/fecimg/?201910079163758563 | CA6: Contributions From Individuals/Persons Other Than Political Committees
A7: C00073155 | B7: KEYCORP ADVOCATES FUND | C7: 2019 | D7: MY | E7: 2.0191008e+17 | F7: 11AI | G7: 95E0140E364547AB8475 | H7: 1355016 | J7: IND | K7: INDIVIDUAL | N7: MOONEY, BETH | O7: Q | P7: C | Q7: B | R7: BETH | T7: MOONEY | V7: 11 COLONY LN | X7: BRATENAHL | Y7: OH | Z7: 441081119 | AA7: KEYCORP | AB7: CHAIRMAN OF THE BOARD & CEO | AD7: 15 | AE7: CONTRIBUTION | AI7: 43546 | AJ7: 192.3 | AK7: 2499.9 | BG7: P | BI7: PRIMARY | BK7: A | BL7: ADD | BM7: ITEMIZED RECEIPTS | BN7: 43747.109 | BR7: F3X | BS7: 4.1007202e+18 | BT7: t | BV7: 2020 | BW7: SA | BY7: 4.1008202e+18 | BZ7: http://docquery.fec.gov/cgi-bin/fecimg/?201910079163758563 | CA7: Contributions From Individuals/Persons Other Than Political Committees
A8: C00073155 | B8: KEYCORP ADVOCATES FUND | C8: 2019 | D8: MY | E8: 2.0191008e+17 | F8: 11AI | G8: 83E3F9636DA74CDCA47B | H8: 1355016 | J8: IND | K8: INDIVIDUAL | N8: MOONEY, BETH | O8: Q | P8: C | Q8: B | R8: BETH | T8: MOONEY | V8: 11 COLONY LN | X8: BRATENAHL | Y8: OH | Z8: 441081119 | AA8: KEYCORP | AB8: CHAIRMAN OF THE BOARD & CEO | AD8: 15 | AE8: CONTRIBUTION | AI8: 43560 | AJ8: 192.3 | AK8: 2499.9 | BG8: P | BI8: PRIMARY | BK8: A | BL8: ADD | BM8: ITEMIZED RECEIPTS | BN8: 43747.109 | BR8: F3X | BS8: 4.1007202e+18 | BT8: t | BV8: 2020 | BW8: SA | BY8: 4.1008202e+18 | BZ8: http://docquery.fec.gov/cgi-bin/fecimg/?201910079163758563 | CA8: Contributions From Individuals/Persons Other Than Political Committees
A9: C00073155 | B9: KEYCORP ADVOCATES FUND | C9: 2019 | D9: MY | E9: 2.0191008e+17 | F9: 11AI | G9: 4C40E82803FF44B680FB | H9: 1355016 | J9: IND | K9: INDIVIDUAL | N9: MOONEY, BETH | O9: Q | P9: C | Q9: B | R9: BETH | T9: MOONEY | V9: 11 COLONY LN | X9: BRATENAHL | Y9: OH | Z9: 441081119 | AA9: KEYCORP | AB9: CHAIRMAN OF THE BOARD & CEO | AD9: 15 | AE9: CONTRIBUTION | AI9: 43574 | AJ9: 192.3 | AK9: 2499.9 | BG9: P | BI9: PRIMARY | BK9: A | BL9: ADD | BM9: ITEMIZED RECEIPTS | BN9: 43747.109 | BR9: F3X | BS9: 4.1007202e+18 | BT9: t | BV9: 2020 | BW9: SA | BY9: 4.1008202e+18 | BZ9: http://docquery.fec.gov/cgi-bin/fecimg/?201910079163758564 | CA9: Contributions From Individuals/Persons Other Than Political Committees
A10: C00073155 | B10: KEYCORP ADVOCATES FUND | C10: 2019 | D10: MY | E10: 2.0191008e+17 | F10: 11AI | G10: 79EF0749BBAD433F819E | H10: 1355016 | J10: IND | K10: INDIVIDUAL | N10: MOONEY, BETH | O10: Q | P10: C | Q10: B | R10: BETH | T10: MOONEY | V10: 11 COLONY LN | X10: BRATENAHL | Y10: OH | Z10: 441081119 | AA10: KEYCORP | AB10: CHAIRMAN OF THE BOARD & CEO | AD10: 15 | AE10: CONTRIBUTION | AI10: 43588 | AJ10: 192.3 | AK10: 2499.9 | BG10: P | BI10: PRIMARY | BK10: A | BL10: ADD | BM10: ITEMIZED RECEIPTS | BN10: 43747.109 | BR10: F3X | BS10: 4.1007202e+18 | BT10: t | BV10: 2020 | BW10: SA | BY10: 4.1008202e+18 | BZ10: http://docquery.fec.gov/cgi-bin/fecimg/?201910079163758564 | CA10: Contributions From Individuals/Persons Other Than Political Committees
A11: C00073155 | B11: KEYCORP ADVOCATES FUND | C11: 2019 | D11: MY | E11: 2.0191008e+17 | F11: 11AI | G11: D7FC5E6B10C1469BBB2F | H11: 1355016 | J11: IND | K11: INDIVIDUAL | N11: MOONEY, BETH | O11: Q | P11: C | Q11: B | R11: BETH | T11: MOONEY | V11: 11 COLONY LN | X11: BRATENAHL | Y11: OH | Z11: 441081119 | AA11: KEYCORP | AB11: CHAIRMAN OF THE BOARD & CEO | AD11: 15 | AE11: CONTRIBUTION | AI11: 43602 | AJ11: 192.3 | AK11: 2499.9 | BG11: P | BI11: PRIMARY | BK11: A | BL11: ADD | BM11: ITEMIZED RECEIPTS | BN11: 43747.109 | BR11: F3X | BS11: 4.1007202e+18 | BT11: t | BV11: 2020 | BW11: SA | BY11: 4.1008202e+18 | BZ11: http://docquery.fec.gov/cgi-bin/fecimg/?201910079163758564 | CA11: Contributions From Individuals/Persons Other Than Political Committees
A12: C00073155 | B12: KEYCORP ADVOCATES FUND | C12: 2019 | D12: MY | E12: 2.0191008e+17 | F12: 11AI | G12: 294AF0C6645847AC961B | H12: 1355016 | J12: IND | K12: INDIVIDUAL | N12: MOONEY, BETH | O12: Q | P12: C | Q12: B | R12: BETH | T12: MOONEY | V12: 11 COLONY LN | X12: BRATENAHL | Y12: OH | Z12: 441081119 | AA12: KEYCORP | AB12: CHAIRMAN OF THE BOARD & CEO | AD12: 15 | AE12: CONTRIBUTION | AI12: 43616 | AJ12: 192.3 | AK12: 2499.9 | BG12: P | BI12: PRIMARY | BK12: A | BL12: ADD | BM12: ITEMIZED RECEIPTS | BN12: 43747.109 | BR12: F3X | BS12: 4.1007202e+18 | BT12: t | BV12: 2020 | BW12: SA | BY12: 4.1008202e+18 | BZ12: http://docquery.fec.gov/cgi-bin/fecimg/?201910079163758565 | CA12: Contributions From Individuals/Persons Other Than Political Committees
A13: C00073155 | B13: KEYCORP ADVOCATES FUND | C13: 2019 | D13: MY | E13: 2.0191008e+17 | F13: 11AI | G13: 6E098666C95F45249F12 | H13: 1355016 | J13: IND | K13: INDIVIDUAL | N13: MOONEY, BETH | O13: Q | P13: C | Q13: B | R13: BETH | T13: MOONEY | V13: 11 COLONY LN | X13: BRATENAHL | Y13: OH | Z13: 441081119 | AA13: KEYCORP | AB13: CHAIRMAN OF THE BOARD & CEO | AD13: 15 | AE13: CONTRIBUTION | AI13: 43630 | AJ13: 192.3 | AK13: 2499.9 | BG13: P | BI13: PRIMARY | BK13: A | BL13: ADD | BM13: ITEMIZED RECEIPTS | BN13: 43747.109 | BR13: F3X | BS13: 4.1007202e+18 | BT13: t | BV13: 2020 | BW13: SA | BY13: 4.1008202e+18 | BZ13: http://docquery.fec.gov/cgi-bin/fecimg/?201910079163758565 | CA13: Contributions From Individuals/Persons Other Than Political Committees
A14: C00073155 | B14: KEYCORP ADVOCATES FUND | C14: 2019 | D14: MY | E14: 2.0191008e+17 | F14: 11AI | G14: 2125829721E6465B820E | H14: 1355016 | J14: IND | K14: INDIVIDUAL | N14: MOONEY, BETH | O14: Q | P14: C | Q14: B | R14: BETH | T14: MOONEY | V14: 11 COLONY LN | X14: BRATENAHL | Y14: OH | Z14: 441081119 | AA14: KEYCORP | AB14: CHAIRMAN OF THE BOARD & CEO | AD14: 15 | AE14: CONTRIBUTION | AI14: 43644 | AJ14: 192.3 | AK14: 2499.9 | BG14: P | BI14: PRIMARY | BK14: A | BL14: ADD | BM14: ITEMIZED RECEIPTS | BN14: 43747.109 | BR14: F3X | BS14: 4.1007202e+18 | BT14: t | BV14: 2020 | BW14: SA | BY14: 4.1008202e+18 | BZ14: http://docquery.fec.gov/cgi-bin/fecimg/?201910079163758565 | CA14: Contributions From Individuals/Persons Other Than Political Committees
... A34: C00073155 | B34: KEYCORP ADVOCATES FUND | C34: 2020 | D34: M5 | E34: 2.020052e+17 | F34: 11AI | G34: DD39285E4A654D3AA07B | H34: 1406467 | J34: IND | K34: INDIVIDUAL | N34: MOONEY, BETH | O34: Q | P34: C | Q34: B | R34: BETH | T34: MOONEY | V34: 11 COLONY LN | X34: BRATENAHL | Y34: OH | Z34: 441081119 | AA34: KEYCORP | AB34: CHAIRMAN OF THE BOARD & CEO | AD34: 15 | AE34: CONTRIBUTION | AI34: 43938 | AJ34: 192.3 | AK34: 1538.4 | BG34: P | BI34: PRIMARY | BK34: A | BL34: ADD | BM34: ITEMIZED RECEIPTS | BN34: 43971.065 | BR34: F3X | BS34: 4.0519202e+18 | BT34: t | BV34: 2020 | BW34: SA | BY34: 4.0519202e+18 | BZ34: http://docquery.fec.gov/cgi-bin/fecimg/?202005199232797113 | CA34: Contributions From Individuals/Persons Other Than Political Committees
A35: C00401224 | B35: ACTBLUE | C35: 2020 | D35: M5 | E35: 2.0200521e+17 | F35: 11AI | G35: SA11AI_231197326 | H35: 1407307 | J35: IND | K35: INDIVIDUAL | N35: MOONEY, BETH | O35: V | Q35: U | R35: BETH | T35: MOONEY | V35: 11 COLONY LN | X35: BRATENAHL | Y35: OH | Z35: 441081119 | AA35: NOT EMPLOYED | AB35: NOT EMPLOYED | AF35: CONTRIBUTION TO ACT BLUE | AI35: 43951 | AJ35: 25 | AK35: 25 | BK35: A | BL35: ADD | BM35: ITEMIZED RECEIPTS | BN35: 43979.301 | BR35: F3X | BS35: 4.0521202e+18 | BT35: t | BU35: CONTRIBUTION TO ACTBLUE | BV35: 2020 | BW35: SA | BY35: 4.0527202e+18 | BZ35: http://docquery.fec.gov/cgi-bin/fecimg/?202005209237048236 | CA35: Contributions From Individuals/Persons Other Than Political Committees
A36: C00073155 | B36: KEYCORP ADVOCATES FUND | C36: 2020 | D36: M6 | E36: 2.0200619e+17 | F36: 11AI | G36: ED1A239CFF3E40649F60 | H36: 1412691 | J36: IND | K36: INDIVIDUAL | N36: MOONEY, BETH | O36: Q | P36: C | Q36: B | R36: BETH | T36: MOONEY | V36: 11 COLONY LN | X36: BRATENAHL | Y36: OH | Z36: 441081119 | AA36: KEYCORP | AB36: CHAIRMAN OF THE BOARD & CEO | AD36: 15 | AE36: CONTRIBUTION | AI36: 43952 | AJ36: 192.3 | AK36: 1923 | BG36: P | BI36: PRIMARY | BK36: A | BL36: ADD | BM36: ITEMIZED RECEIPTS | BN36: 44001.108 | BR36: F3X | BS36: 4.0618202e+18 | BT36: t | BV36: 2020 | BW36: SA | BY36: 4.0618202e+18 | BZ36: http://docquery.fec.gov/cgi-bin/fecimg/?202006189239930687 | CA36: Contributions From Individuals/Persons Other Than Political Committees
A37: C00073155 | B37: KEYCORP ADVOCATES FUND | C37: 2020 | D37: M6 | E37: 2.0200619e+17 | F37: 11AI | G37: E01C625B36C34A8390C2 | H37: 1412691 | J37: IND | K37: INDIVIDUAL | N37: MOONEY, BETH | O37: Q | P37: C | Q37: B | R37: BETH | T37: MOONEY | V37: 11 COLONY LN | X37: BRATENAHL | Y37: OH | Z37: 441081119 | AA37: KEYCORP | AB37: CHAIRMAN OF THE BOARD & CEO | AD37: 15 | AE37: CONTRIBUTION | AI37: 43966 | AJ37: 192.3 | AK37: 1923 | BG37: P | BI37: PRIMARY | BK37: A | BL37: ADD | BM37: ITEMIZED RECEIPTS | BN37: 44001.108 | BR37: F3X | BS37: 4.0618202e+18 | BT37: t | BV37: 2020 | BW37: SA | BY37: 4.0618202e+18 | BZ37: http://docquery.fec.gov/cgi-bin/fecimg/?202006189239930688 | CA37: Contributions From Individuals/Persons Other Than Political Committees
A38: C00744946 | B38: BIDEN VICTORY FUND | C38: 2020 | D38: 12G | E38: 2.0210309e+17 | F38: 11AI | G38: 19162720 | H38: 1503262 | J38: IND | K38: INDIVIDUAL | N38: MOONEY, BETH | O38: N | Q38: J | R38: BETH | T38: MOONEY | V38: 11 COLONY LN | X38: CLEVELAND | Y38: OH | Z38: 441081119 | AA38: RETIRED | AB38: RETIRED | AD38: 15 | AE38: CONTRIBUTION | AI38: 44105 | AJ38: 10000 | AK38: 10000 | BG38: P | BI38: PRIMARY | BK38: A | BL38: ADD | BM38: ITEMIZED RECEIPTS | BN38: 44329.163 | BR38: F3X | BS38: 4.0309202e+18 | BT38: t | BV38: 2020 | BW38: SA | BY38: 4.0309202e+18 | BZ38: https://docquery.fec.gov/cgi-bin/fecimg/?202103089440306952 | CA38: Contributions From Individuals/Persons Other Than Political Committees
A39: C00401224 | B39: ACTBLUE | C39: 2020 | D39: M10 | E39: 2.0201215e+17 | F39: 11AI | G39: SA11AI_303383429 | H39: 1482832 | J39: IND | K39: INDIVIDUAL | N39: MOONEY, BETH | O39: V | Q39: U | R39: BETH | T39: MOONEY | V39: 11 COLONY LN | X39: BRATENAHL | Y39: OH | Z39: 441081119 | AA39: NOT EMPLOYED | AB39: NOT EMPLOYED | AF39: EARMARK | AI39: 44095 | AJ39: 50 | AK39: 150 | BF39: _x000D_ | BK39: A | BL39: ADD | BM39: ITEMIZED RECEIPTS | BN39: 44218.661 | BR39: F3X | BS39: 4.1216202e+18 | BT39: t | BU39: EARMARKED FOR CAL FOR NC (C00709410) | BV39: 2020 | BW39: SA | BY39: 4.0121202e+18 | BZ39: https://docquery.fec.gov/cgi-bin/fecimg/?202012149378724967 | CA39: Contributions From Individuals/Persons Other Than Political Committees
A40: C00401224 | B40: ACTBLUE | C40: 2020 | D40: M8 | E40: 2.0200821e+17 | F40: 11AI | G40: SA11AI_268086757 | H40: 1434463 | J40: IND | K40: INDIVIDUAL | N40: MOONEY, BETH | O40: V | Q40: U | R40: BETH | T40: MOONEY | V40: 11 COLONY LN | X40: BRATENAHL | Y40: OH | Z40: 441081119 | AA40: NOT EMPLOYED | AB40: NOT EMPLOYED | AF40: EARMARK | AI40: 44033 | AJ40: 50 | AK40: 50 | BK40: A | BL40: ADD | BM40: ITEMIZED RECEIPTS | BN40: 44090.28 | BR40: F3X | BS40: 4.0822202e+18 | BT40: t | BU40: EARMARKED FOR CAL FOR NC (C00709410) | BV40: 2020 | BW40: SA | BY40: 4.0915202e+18 | BZ40: http://docquery.fec.gov/cgi-bin/fecimg/?202008209263174372 | CA40: Contributions From Individuals/Persons Other Than Political Committees
A41: C00703975 | B41: BIDEN FOR PRESIDENT | C41: 2020 | D41: 12G | E41: 2.0201023e+17 | F41: 18 | G41: 24543330 | H41: 1463690 | J41: IND | K41: INDIVIDUAL | N41: MOONEY, BETH | O41: P | Q41: P | R41: BETH | T41: MOONEY | V41: 11 COLONY LN | X41: CLEVELAND | Y41: OH | Z41: 441081119 | AA41: RETIRED | AB41: RETIRED | AD41: 15J | AE41: MEMO (FILER'S % OF CONTRIBUTION GIVEN TO JOIN | AG41: X | AI41: 44105 | AJ41: 2800 | AK41: 2800 | BG41: G2020 | BI41: GENERAL | BJ41: 2020 | BK41: A | BL41: ADD | BM41: ITEMIZED RECEIPTS | BN41: 44132.177 | BP41: 20811383 | BQ41: SA18 | BR41: F3P | BS41: 4.1024202e+18 | BT41: t | BU41: * BIDEN VICTORY FUND | BV41: 2020 | BW41: SA | BY41: 4.1028202e+18 | BZ41: http://docquery.fec.gov/cgi-bin/fecimg/?202010229336149752 | CA41: Transfers From Other Authorized Committees
A42: C00709899 | B42: SARA GIDEON FOR MAINE | C42: 2020 | D42: 12G | E42: 2.0201023e+17 | F42: 11AI | G42: VVC97WKAKS7 | H42: 1464149 | J42: IND | K42: INDIVIDUAL | L42: C00401224 | N42: MOONEY, BETH | O42: S | Q42: P | R42: BETH | T42: MOONEY | V42: 11 COLONY LN | X42: BRATENAHL | Y42: OH | Z42: 441081119 | AA42: KEYCORP | AB42: CEO | AC42: C00401224 | AD42: 15E | AE42: EARMARKED CONTRIBUTION | AI42: 44106 | AJ42: 1000 | AK42: 2000 | BG42: G2020 | BI42: GENERAL | BJ42: 2020 | BK42: A | BL42: ADD | BM42: ITEMIZED RECEIPTS | BN42: 44174.155 | BP42: VVC97WKAKS7E | BQ42: SA11AI | BR42: F3 | BS42: 4.1024202e+18 | BT42: t | BU42: * EARMARKED CONTRIBUTION: SEE BELOW | BV42: 2020 | BW42: SA | BY42: 4.1209202e+18 | BZ42: http://docquery.fec.gov/cgi-bin/fecimg/?202010229336438001 | CA42: Contributions From Individuals/Persons Other Than Political Committees
A43: C00696526 | B43: MARK KELLY FOR SENATE | C43: 2020 | D43: 12G | E43: 2.0201023e+17 | F43: 11AI | G43: VVC31WMVSB3 | H43: 1463342 | J43: IND | K43: INDIVIDUAL | L43: C00401224 | N43: MOONEY, BETH | O43: S | Q43: P | R43: BETH | T43: MOONEY | V43: 11 COLONY LN | X43: BRATENAHL | Y43: OH | Z43: 441081119 | AA43: KEYCORP | AB43: CHAIRMAN OF THE BOARD & CEO | AC43: C00401224 | AD43: 15E | AE43: EARMARKED CONTRIBUTION | AI43: 44106 | AJ43: 1000 | AK43: 1000 | BG43: G2020 | BI43: GENERAL | BJ43: 2020 | BK43: A | BL43: ADD | BM43: ITEMIZED RECEIPTS | BN43: 44160.165 | BP43: VVC31WMVSB3E | BQ43: SA11AI | BR43: F3 | BS43: 4.1024202e+18 | BT43: t | BU43: * EARMARKED CONTRIBUTION: SEE BELOW | BV43: 2020 | BW43: SA | BY43: 4.1125202e+18 | BZ43: http://docquery.fec.gov/cgi-bin/fecimg/?202010229335411854 | CA43: Contributions From Individuals/Persons Other Than Political Committees
A44: C00649350 | B44: MJ FOR TEXAS | C44: 2020 | D44: Q3 | E44: 2.0201016e+17 | F44: 11AI | G44: VTR3QQTFS10 | H44: 1450337 | J44: IND | K44: INDIVIDUAL | L44: C00401224 | N44: MOONEY, BETH | O44: S | Q44: P | R44: BETH | T44: MOONEY | V44: 11 COLONY LN | X44: BRATENAHL | Y44: OH | Z44: 441081119 | AA44: KEYCORP | AB44: CEO | AC44: C00401224 | AD44: 15E | AE44: EARMARKED CONTRIBUTION | AI44: 44033 | AJ44: 500 | AK44: 500 | BG44: G2020 | BI44: GENERAL | BJ44: 2020 | BK44: A | BL44: ADD | BM44: ITEMIZED RECEIPTS | BN44: 44170.154 | BP44: VTR3QQTFS10E | BQ44: SA11AI | BR44: F3 | BS44: 4.1016202e+18 | BT44: t | BU44: * EARMARKED CONTRIBUTION: SEE BELOW | BV44: 2020 | BW44: SA | BY44: 4.1205202e+18 | BZ44: http://docquery.fec.gov/cgi-bin/fecimg/?202010159294380116 | CA44: Contributions From Individuals/Persons Other Than Political Committees
A45: C00709410 | B45: CAL FOR NC | C45: 2020 | D45: 12G | E45: 2.0201202e+17 | F45: 11AI | G45: VVC0QWJWNT6 | H45: 1475521 | J45: IND | K45: INDIVIDUAL | N45: MOONEY, BETH | O45: S | Q45: P | R45: BETH | T45: MOONEY | V45: 11 COLONY LN | X45: BRATENAHL | Y45: OH | Z45: 441081119 | AA45: NOT EMPLOYED | AB45: NOT EMPLOYED | AD45: 15E | AE45: EARMARKED CONTRIBUTION | AI45: 44106 | AJ45: 500 | AK45: 650 | BG45: G2020 | BI45: GENERAL | BJ45: 2020 | BK45: A | BL45: ADD | BM45: ITEMIZED RECEIPTS | BN45: 44177.158 | BP45: VVC0QWJWNT6E | BQ45: SA11AI | BR45: F3 | BS45: 4.1202202e+18 | BT45: t | BU45: * EARMARKED CONTRIBUTION: SEE BELOW | BV45: 2020 | BW45: SA | BY45: 4.1212202e+18 | BZ45: http://docquery.fec.gov/cgi-bin/fecimg/?202012019337378775 | CA45: Contributions From Individuals/Persons Other Than Political Committees
A46: C00716720 | B46: HICKENLOOPER FOR COLORADO | C46: 2020 | D46: 12G | E46: 2.0210318e+17 | F46: 11AI | G46: 7656532 | H46: 1504591 | J46: IND | K46: INDIVIDUAL | N46: MOONEY, BETH | O46: S | Q46: P | R46: BETH | T46: MOONEY | V46: 11 COLONY LN | X46: BRATENAHL | Y46: OH | Z46: 441081119 | AA46: NOT EMPLOYED | AB46: NOT EMPLOYED | AD46: 15E | AE46: EARMARKED CONTRIBUTION | AI46: 44106 | AJ46: 1000 | AK46: 1000 | BG46: G2020 | BI46: GENERAL | BJ46: 2020 | BK46: A | BL46: ADD | BM46: ITEMIZED RECEIPTS | BN46: 44279.557 | BP46: 7656532E | BQ46: SA11AI | BR46: F3 | BS46: 4.0318202e+18 | BT46: t | BU46: * EARMARKED CONTRIBUTION: SEE BELOW | BV46: 2020 | BW46: SA | BY46: 4.0324202e+18 | BZ46: https://docquery.fec.gov/cgi-bin/fecimg/?202103179440593570 | CA46: Contributions From Individuals/Persons Other Than Political Committees
A47: C00401224 | B47: ACTBLUE | C47: 2020 | D47: 30G | E47: 2.0201205e+17 | F47: 11AI | G47: SA11AI_331049850 | H47: 1481637 | J47: IND | K47: INDIVIDUAL | L47: C00709410 | N47: MOONEY, BETH | O47: V | Q47: U | R47: BETH | T47: MOONEY | V47: 11 COLONY LN | X47: BRATENAHL | Y47: OH | Z47: 441081119 | AA47: NOT EMPLOYED | AB47: NOT EMPLOYED | AC47: C00709410 | AD47: 24T | AE47: EARMARKED INTERMEDIARY TREASURY OUT | AF47: EARMARK | AI47: 44125 | AJ47: 50 | AK47: 700 | AL47: S0NC00202 | BF47: _x000D_ | BK47: A | BL47: ADD | BM47: ITEMIZED RECEIPTS | BN47: 44201.544 | BR47: F3X | BS47: 4.1205202e+18 | BT47: t | BU47: EARMARKED FOR CAL FOR NC (C00709410) | BV47: 2020 | BW47: SA | BY47: 4.0104202e+18 | BZ47: https://docquery.fec.gov/cgi-bin/fecimg/?202012049356891062 | CA47: Contributions From Individuals/Persons Other Than Political Committees
A48: C00010603 | B48: DNC SERVICES CORP / DEMOCRATIC NATIONAL COMMITTEE | C48: 2020 | D48: 12G | E48: 2.0201023e+17 | F48: 12 | G48: 37455716 | H48: 1463691 | J48: IND | K48: INDIVIDUAL | N48: MOONEY, BETH E | O48: Y | Q48: U | R48: BETH | S48: E | T48: MOONEY | V48: 11 COLONY LN | X48: BRATENAHL | Y48: OH | Z48: 441081119 | AA48: RETIRED | AB48: RETIRED | AD48: 15J | AE48: MEMO (FILER'S % OF CONTRIBUTION GIVEN TO JOIN | AG48: X | AI48: 44105 | AJ48: 7200 | AK48: 7200 | BG48: G2020 | BI48: GENERAL | BJ48: 2020 | BK48: A | BL48: ADD | BM48: ITEMIZED RECEIPTS | BN48: 44155.299 | BP48: 37430496 | BQ48: SA12 | BR48: F3X | BS48: 4.1024202e+18 | BT48: t | BU48: * BIDEN VICTORY FUND | BV48: 2020 | BW48: SA | BY48: 4.1119202e+18 | BZ48: http://docquery.fec.gov/cgi-bin/fecimg/?202010229336242490 | CA48: Transfers from Authorized Committees
A49: C00709899 | B49: SARA GIDEON FOR MAINE | C49: 2020 | D49: Q3 | E49: 2.0201204e+17 | F49: 11AI | G49: VVC97SG31D6 | H49: 1477776 | J49: IND | K49: INDIVIDUAL | N49: MOONEY, BETH | O49: S | Q49: P | R49: BETH | T49: MOONEY | V49: 11 COLONY LN | X49: BRATENAHL | Y49: OH | Z49: 441081119 | AA49: KEYCORP | AB49: CEO | AD49: 15E | AE49: EARMARKED CONTRIBUTION | AI49: 44033 | AJ49: 1000 | AK49: 1000 | BG49: G2020 | BI49: GENERAL | BJ49: 2020 | BK49: A | BL49: ADD | BM49: ITEMIZED RECEIPTS | BN49: 44202.163 | BP49: VVC97SG31D6E | BQ49: SA11AI | BR49: F3 | BS49: 4.1204202e+18 | BT49: t | BU49: * EARMARKED CONTRIBUTION: SEE BELOW | BV49: 2020 | BW49: SA | BY49: 4.0106202e+18 | BZ49: https://docquery.fec.gov/cgi-bin/fecimg/?202012039337642974 | CA49: Contributions From Individuals/Persons Other Than Political Committees
A50: C00709410 | B50: CAL FOR NC | C50: 2020 | D50: 30G | E50: 2.0201204e+17 | F50: 11AI | G50: VVC0QX645M8 | H50: 1479300 | J50: IND | K50: INDIVIDUAL | L50: C00401224 | N50: MOONEY, BETH | O50: S | Q50: P | R50: BETH | T50: MOONEY | V50: 11 COLONY LN | X50: BRATENAHL | Y50: OH | Z50: 441081119 | AA50: NOT EMPLOYED | AB50: NOT EMPLOYED | AC50: C00401224 | AD50: 15E | AE50: EARMARKED CONTRIBUTION | AI50: 44125 | AJ50: 50 | AK50: 700 | BG50: G2020 | BI50: GENERAL | BJ50: 2020 | BK50: A | BL50: ADD | BM50: ITEMIZED RECEIPTS | BN50: 44203.424 | BP50: VVC0QX645M8E | BQ50: SA11AI | BR50: F3 | BS50: 4.1204202e+18 | BT50: t | BU50: * EARMARKED CONTRIBUTION: SEE BELOW | BV50: 2020 | BW50: SA | BY50: 4.0106202e+18 | BZ50: https://docquery.fec.gov/cgi-bin/fecimg/?202012039338681029 | CA50: Contributions From Individuals/Persons Other Than Political Committees
A51: C00718866 | B51: JON OSSOFF FOR SENATE | C51: 2020 | D51: 12G | E51: 2.0210603e+17 | F51: 11AI | G51: 2009443 | H51: 1518540 | J51: IND | K51: INDIVIDUAL | L51: C00401224 | N51: MOONEY, BETH | O51: S | Q51: P | R51: BETH | T51: MOONEY | V51: 11 COLONY LN | X51: BRATENAHL | Y51: OH | Z51: 441081119 | AA51: NOT EMPLOYED | AB51: NOT EMPLOYED | AC51: C00401224 | AD51: 15E | AE51: EARMARKED CONTRIBUTION | AI51: 44106 | AJ51: 500 | AK51: 500 | BG51: G2020 | BI51: GENERAL | BJ51: 2020 | BK51: A | BL51: ADD | BM51: ITEMIZED RECEIPTS | BN51: 44352.217 | BP51: 2009443E | BQ51: SA11AI | BR51: F3 | BS51: 4.0603202e+18 | BT51: t | BU51: * EARMARKED CONTRIBUTION: SEE BELOW | BV51: 2020 | BW51: SA | BY51: 4.0605202e+18 | BZ51: https://docquery.fec.gov/cgi-bin/fecimg/?202106029448460003 | CA51: Contributions From Individuals/Persons Other Than Political Committees
A52: C00401224 | B52: ACTBLUE | C52: 2020 | D52: M9 | E52: 2.0201212e+17 | F52: 11AI | G52: SA11AI_281877637 | H52: 1482644 | J52: IND | K52: INDIVIDUAL | N52: MOONEY, BETH | O52: V | Q52: U | R52: BETH | T52: MOONEY | V52: 11 COLONY LN | X52: BRATENAHL | Y52: OH | Z52: 441081119 | AA52: NOT EMPLOYED | AB52: NOT EMPLOYED | AF52: EARMARK | AI52: 44064 | AJ52: 50 | AK52: 100 | BF52: _x000D_ | BK52: A | BL52: ADD | BM52: ITEMIZED RECEIPTS | BN52: 44209.414 | BR52: F3X | BS52: 4.1215202e+18 | BT52: t | BU52: EARMARKED FOR CAL FOR NC (C00709410) | BV52: 2020 | BW52: SA | BY52: 4.0112202e+18 | BZ52: https://docquery.fec.gov/cgi-bin/fecimg/?202012119369179565 | CA52: Contributions From Individuals/Persons Other Than Political Committees
Y54: =+V52&X52&Y52&Z52 -> 11 COLONY LNBRATENAHLOH441081119
A59: Row Labels | B59: Sum of contribution_receipt_amount
A60: ACTBLUE | B60: 225 | C60: D
A61: BEATTY FOR CONGRESS | B61: 1500 | C61: D
A62: BIDEN FOR PRESIDENT | B62: 2800 | C62: D
A63: BIDEN VICTORY FUND | B63: 10000 | C63: D
A64: CAL FOR NC | B64: 550 | C64: D
A65: DNC SERVICES CORP / DEMOCRATIC NATIONAL COMMITTEE | B65: 7200 | C65: D
A66: HICKENLOOPER FOR COLORADO | B66: 1000 | C66: D
A67: JON OSSOFF FOR SENATE | B67: 500 | C67: D
A68: KEYCORP ADVOCATES FUND | B68: 6538.2 | C68: D
A69: MARK KELLY FOR SENATE | B69: 1000 | C69: D
A70: MJ FOR TEXAS | B70: 500 | C70: D
A71: SARA GIDEON FOR MAINE | B71: 2000 | C71: D
A72: Grand Total | B72: 33813.2

Sheet William Kennard
A1: committee_id | B1: committee_name | C1: report_year | D1: report_type | E1: image_number | F1: line_number | G1: transaction_id | H1: file_number | I1: committee_name | J1: entity_type | K1: entity_type_desc | L1: unused_contbr_id | M1: contributor_prefix | N1: contributor_name | O1: recipient_committee_type | P1: recipient_committee_org_type | Q1: recipient_committee_designation | R1: contributor_first_name | S1: contributor_middle_name | T1: contributor_last_name | U1: contributor_suffix | V1: contributor_street_1 | W1: contributor_street_2 | X1: contributor_city | Y1: contributor_state | Z1: contributor_zip | AA1: contributor_employer | AB1: contributor_occupation | AC1: contributor_id | AD1: receipt_type | AE1: receipt_type_desc | AF1: receipt_type_full | AG1: memo_code | AH1: memo_code_full | AI1: contribution_receipt_date | AJ1: contribution_receipt_amount | AK1: contributor_aggregate_ytd | AL1: candidate_id | AM1: candidate_name | AN1: candidate_first_name | AO1: candidate_last_name | AP1: candidate_middle_name | AQ1: candidate_prefix | AR1: candidate_suffix | AS1: candidate_office | AT1: candidate_office_full | AU1: candidate_office_state | AV1: candidate_office_state_full | AW1: candidate_office_district | AX1: conduit_committee_id | AY1: conduit_committee_name | AZ1: conduit_committee_street1 | BA1: conduit_committee_street2 | BB1: conduit_committee_city | BC1: conduit_committee_state | BD1: conduit_committee_zip | BE1: donor_committee_name | BF1: national_committee_nonfederal_account | BG1: election_type | BH1: election_type_full | BI1: fec_election_type_desc | BJ1: fec_election_year | BK1: amendment_indicator | BL1: amendment_indicator_desc | BM1: schedule_type_full | BN1: load_date | BO1: original_sub_id | BP1: back_reference_transaction_id | BQ1: back_reference_schedule_name | BR1: filing_form | BS1: link_id | BT1: is_individual | BU1: memo_text | BV1: two_year_transaction_period | BW1: schedule_type | BX1: increased_limit | BY1: sub_id | BZ1: pdf_url | CA1: line_number_label
A2: C00083535 | B2: DUKE ENERGY CORPORATION PAC | C2: 2019 | D2: M8 | E2: 2.0190809e+17 | F2: 11AI | G2: 25111003 | H2: 1347267 | J2: IND | K2: INDIVIDUAL | N2: KENNARD, WILLIAM | O2: Q | P2: C | Q2: B | R2: WILLIAM | T2: KENNARD | V2: 41 MEETING STREET | X2: CHARLESTON | Y2: SC | Z2: 294012736 | AA2: DUKE ENERGY CORPORATION | AB2: DIRECTOR | AD2: 15 | AE2: CONTRIBUTION | AI2: 43669 | AJ2: 2500 | AK2: 2500 | BG2: P | BI2: PRIMARY | BK2: A | BL2: ADD | BM2: ITEMIZED RECEIPTS | BN2: 43687.126 | BR2: F3X | BS2: 4.0808202e+18 | BT2: t | BV2: 2020 | BW2: SA | BY2: 4.0809202e+18 | BZ2: http://docquery.fec.gov/cgi-bin/fecimg/?201908089161367786 | CA2: Contributions From Individuals/Persons Other Than Political Committees
A3: C00083535 | B3: DUKE ENERGY CORPORATION PAC | C3: 2019 | D3: M8 | E3: 2.0190809e+17 | F3: 11AI | G3: 25111011 | H3: 1347267 | J3: IND | K3: INDIVIDUAL | N3: KENNARD, WILLIAM | O3: Q | P3: C | Q3: B | R3: WILLIAM | T3: KENNARD | V3: 41 MEETING STREET | X3: CHARLESTON | Y3: SC | Z3: 294012736 | AA3: DUKE ENERGY CORPORATION | AB3: DIRECTOR | AD3: 15 | AE3: CONTRIBUTION | AI3: 43669 | AJ3: 2500 | AK3: 5000 | BG3: P | BI3: PRIMARY | BK3: A | BL3: ADD | BM3: ITEMIZED RECEIPTS | BN3: 43687.126 | BR3: F3X | BS3: 4.0808202e+18 | BT3: t | BV3: 2020 | BW3: SA | BY3: 4.0809202e+18 | BZ3: http://docquery.fec.gov/cgi-bin/fecimg/?201908089161367787 | CA3: Contributions From Individuals/Persons Other Than Political Committees
A4: C00701052 | B4: ADAIR FOR CONGRESS | C4: 2019 | D4: YE | E4: 2.0200131e+17 | F4: 11AI | G4: VVC5RQ8VSQ0 | H4: 1375706 | J4: IND | K4: INDIVIDUAL | L4: C00401224 | N4: KENNARD, WILLIAM | O4: H | Q4: P | R4: WILLIAM | T4: KENNARD | V4: 41 MEETING ST | X4: CHARLESTON | Y4: SC | Z4: 294012736 | AA4: NOT EMPLOYED | AB4: NOT EMPLOYED | AC4: C00401224 | AD4: 15E | AE4: EARMARKED CONTRIBUTION | AI4: 43776 | AJ4: 1000 | AK4: 1000 | BG4: P2020 | BI4: PRIMARY | BJ4: 2020 | BK4: A | BL4: ADD | BM4: ITEMIZED RECEIPTS | BN4: 43862.073 | BP4: VVC5RQ8VSQ0E | BQ4: SA11AI | BR4: F3 | BS4: 4.0130202e+18 | BT4: t | BU4: * EARMARKED CONTRIBUTION: SEE BELOW | BV4: 2020 | BW4: SA | BY4: 4.0131202e+18 | BZ4: http://docquery.fec.gov/cgi-bin/fecimg/?202001309182481175 | CA4: Contributions From Individuals/Persons Other Than Political Committees
A5: C00391029 | B5: JIM COSTA FOR CONGRESS | C5: 2019 | D5: YE | E5: 2.0201232e+17 | F5: 11AI | G5: AC3670C939426407ABA8 | H5: 1484857 | J5: IND | K5: INDIVIDUAL | N5: KENNARD, WILLIAM | O5: H | Q5: P | R5: WILLIAM | T5: KENNARD | V5: 41 MEETING ST | X5: CHARLESTON | Y5: SC | Z5: 294012736 | AA5: SELF EMPLOYED | AB5: INVESTOR | AD5: 15 | AE5: CONTRIBUTION | AI5: 43782 | AJ5: 250 | AK5: 250 | BG5: P2020 | BI5: PRIMARY | BJ5: 2020 | BK5: N | BL5: NO CHANGE | BM5: ITEMIZED RECEIPTS | BN5: 44203.376 | BR5: F3 | BS5: 4.0102202e+18 | BT5: t | BV5: 2020 | BW5: SA | BY5: 4.0106202e+18 | BZ5: https://docquery.fec.gov/cgi-bin/fecimg/?202012319394492388 | CA5: Contributions From Individuals/Persons Other Than Political Committees
W7: =+V5&X5&Y5&Z5 -> 41 MEETING STCHARLESTONSC294012736
A10: Row Labels | B10: Sum of contribution_receipt_amount
A11: ADAIR FOR CONGRESS | B11: 1000 | C11: D
A12: DUKE ENERGY CORPORATION PAC | B12: 5000 | C12: R
A13: JIM COSTA FOR CONGRESS | B13: 250 | C13: D
A14: Grand Total | B14: 6250
B15: =+GETPIVOTDATA("contribution_receipt_amount",$A$10,"committee_name","ADAIR FOR CONGRESS")+GETPIVOTDATA("contribution_receipt_amount",$A$10,"committee_name","JIM COSTA FOR CONGRESS") -> 1250 | C15: D
B16: =+GETPIVOTDATA("contribution_receipt_amount",$A$10,"committee_name","DUKE ENERGY CORPORATION PAC") -> 5000 | C16: R
B17: =SUM(B15:B16) -> 6250

Sheet Jon Huntsman
A1: committee_id | B1: committee_name | C1: report_year | D1: report_type | E1: image_number | F1: line_number | G1: transaction_id | H1: file_number | I1: committee_name | J1: entity_type | K1: entity_type_desc | L1: unused_contbr_id | M1: contributor_prefix | N1: contributor_name | O1: recipient_committee_type | P1: recipient_committee_org_type | Q1: recipient_committee_designation | R1: contributor_first_name | S1: contributor_middle_name | T1: contributor_last_name | U1: contributor_suffix | V1: contributor_street_1 | W1: contributor_street_2 | X1: contributor_city | Y1: contributor_state | Z1: contributor_zip | AA1: contributor_employer | AB1: contributor_occupation | AC1: contributor_id | AD1: receipt_type | AE1: receipt_type_desc | AF1: receipt_type_full | AG1: memo_code | AH1: memo_code_full | AI1: contribution_receipt_date | AJ1: contribution_receipt_amount | AK1: contributor_aggregate_ytd | AL1: candidate_id | AM1: candidate_name | AN1: candidate_first_name | AO1: candidate_last_name | AP1: candidate_middle_name | AQ1: candidate_prefix | AR1: candidate_suffix | AS1: candidate_office | AT1: candidate_office_full | AU1: candidate_office_state | AV1: candidate_office_state_full | AW1: candidate_office_district | AX1: conduit_committee_id | AY1: conduit_committee_name | AZ1: conduit_committee_street1 | BA1: conduit_committee_street2 | BB1: conduit_committee_city | BC1: conduit_committee_state | BD1: conduit_committee_zip | BE1: donor_committee_name | BF1: national_committee_nonfederal_account | BG1: election_type | BH1: election_type_full | BI1: fec_election_type_desc | BJ1: fec_election_year | BK1: amendment_indicator | BL1: amendment_indicator_desc | BM1: schedule_type_full | BN1: load_date | BO1: original_sub_id | BP1: back_reference_transaction_id | BQ1: back_reference_schedule_name | BR1: filing_form | BS1: link_id | BT1: is_individual | BU1: memo_text | BV1: two_year_transaction_period | BW1: schedule_type | BX1: increased_limit | BY1: sub_id | BZ1: pdf_url | CA1: line_number_label
A2: C00734640 | B2: FRIENDS OF KERRY W. GIBSON | C2: 2020 | D2: 12C | E2: 2.0200414e+17 | F2: 11AI | G2: A-46 | H2: 1396048 | J2: IND | K2: INDIVIDUAL | N2: HUNTSMAN, JON | O2: H | Q2: P | R2: JON | T2: HUNTSMAN | V2: 1605 E NEW BEDFORD DR | X2: SALT LAKE CITY | Y2: UT | Z2: 84103 | AA2: SELF-EMPLOYED | AB2: POLITICIAN | AD2: 15 | AE2: CONTRIBUTION | AI2: 43876 | AJ2: 2800 | AK2: 2800 | BG2: C2020 | BH2: CONVENTION-2020 | BI2: CONVENTION | BJ2: 2020 | BK2: A | BL2: ADD | BM2: ITEMIZED RECEIPTS | BN2: 43936.106 | BR2: F3 | BS2: 4.0414202e+18 | BT2: t | BV2: 2020 | BW2: SA | BY2: 4.0414202e+18 | BZ2: http://docquery.fec.gov/cgi-bin/fecimg/?202004139216666761 | CA2: Contributions From Individuals/Persons Other Than Political Committees
V5: =+V2&X2&Y2&Z2 -> 1605 E NEW BEDFORD DRSALT LAKE CITYUT84103

Sheet William Helman
A1: committee_id | B1: committee_name | C1: report_year | D1: report_type | E1: image_number | F1: line_number | G1: transaction_id | H1: file_number | I1: committee_name | J1: entity_type | K1: entity_type_desc | L1: unused_contbr_id | M1: contributor_prefix | N1: contributor_name | O1: recipient_committee_type | P1: recipient_committee_org_type | Q1: recipient_committee_designation | R1: contributor_first_name | S1: contributor_middle_name | T1: contributor_last_name | U1: contributor_suffix | V1: contributor_street_1 | W1: contributor_street_2 | X1: contributor_city | Y1: contributor_state | Z1: contributor_zip | AA1: contributor_employer | AB1: contributor_occupation | AC1: contributor_id | AD1: receipt_type | AE1: receipt_type_desc | AF1: receipt_type_full | AG1: memo_code | AH1: memo_code_full | AI1: contribution_receipt_date | AJ1: contribution_receipt_amount | AK1: contributor_aggregate_ytd | AL1: candidate_id | AM1: candidate_name | AN1: candidate_first_name | AO1: candidate_last_name | AP1: candidate_middle_name | AQ1: candidate_prefix | AR1: candidate_suffix | AS1: candidate_office | AT1: candidate_office_full | AU1: candidate_office_state | AV1: candidate_office_state_full | AW1: candidate_office_district | AX1: conduit_committee_id | AY1: conduit_committee_name | AZ1: conduit_committee_street1 | BA1: conduit_committee_street2 | BB1: conduit_committee_city | BC1: conduit_committee_state | BD1: conduit_committee_zip | BE1: donor_committee_name | BF1: national_committee_nonfederal_account | BG1: election_type | BH1: election_type_full | BI1: fec_election_type_desc | BJ1: fec_election_year | BK1: amendment_indicator | BL1: amendment_indicator_desc | BM1: schedule_type_full | BN1: load_date | BO1: original_sub_id | BP1: back_reference_transaction_id | BQ1: back_reference_schedule_name | BR1: filing_form | BS1: link_id | BT1: is_individual | BU1: memo_text | BV1: two_year_transaction_period | BW1: schedule_type | BX1: increased_limit | BY1: sub_id | BZ1: pdf_url | CA1: line_number_label
A2: C00401224 | B2: ACTBLUE | C2: 2020 | D2: M5 | E2: 2.0200521e+17 | F2: 11AI | G2: SA11AI_230059243 | H2: 1407307 | J2: IND | K2: INDIVIDUAL | N2: HELMAN, WILLIAM | O2: V | Q2: U | R2: WILLIAM | T2: HELMAN | V2: 106 7TH AVE PH 12 | X2: NEW YORK | Y2: NY | Z2: 10011 | AA2: GREYLOCK MANAGEMENT | AB2: BUSINESS | AF2: CONTRIBUTION TO ACT BLUE | AI2: 43948 | AJ2: 50 | AK2: 50 | BK2: A | BL2: ADD | BM2: ITEMIZED RECEIPTS | BN2: 43979.289 | BR2: F3X | BS2: 4.0521202e+18 | BT2: t | BU2: CONTRIBUTION TO ACTBLUE | BV2: 2020 | BW2: SA | BY2: 4.0527202e+18 | BZ2: http://docquery.fec.gov/cgi-bin/fecimg/?202005209236634258 | CA2: Contributions From Individuals/Persons Other Than Political Committees
A3: C00738336 | B3: CARUSO-CABRERA FOR NEW YORK | C3: 2020 | D3: 12P | E3: 2.0200612e+17 | F3: 11AI | G3: 4392419 | H3: 1411297 | J3: IND | K3: INDIVIDUAL | L3: C00401224 | N3: HELMAN, WILLIAM | O3: H | Q3: P | R3: WILLIAM | T3: HELMAN | V3: 106 7TH AVE | W3: PH 12 | X3: NEW YORK | Y3: NY | Z3: 100111837 | AA3: GREYLOCK MANAGEMENT | AB3: BUSINESS | AC3: C00401224 | AD3: 15E | AE3: EARMARKED CONTRIBUTION | AI3: 43948 | AJ3: 2800 | AK3: 2800 | BG3: P2020 | BI3: PRIMARY | BJ3: 2020 | BK3: A | BL3: ADD | BM3: ITEMIZED RECEIPTS | BN3: 43995.058 | BP3: 4392419E | BQ3: SA11AI | BR3: F3 | BS3: 4.0612202e+18 | BT3: t | BU3: * EARMARKED CONTRIBUTION: SEE BELOW | BV3: 2020 | BW3: SA | BY3: 4.0612202e+18 | BZ3: http://docquery.fec.gov/cgi-bin/fecimg/?202006119239761341 | CA3: Contributions From Individuals/Persons Other Than Political Committees
V9: =+V2&X2&Y2&Z2 -> 106 7TH AVE PH 12NEW YORKNY10011
A10: Row Labels | B10: Sum of contribution_receipt_amount
A11: ACTBLUE | B11: 50 | C11: D
A12: CARUSO-CABRERA FOR NEW YORK | B12: 2800 | C12: D
A13: Grand Total | B13: 2850

Sheet William Clay Ford
A1: committee_id | B1: committee_name | C1: report_year | D1: report_type | E1: image_number | F1: line_number | G1: transaction_id | H1: file_number | I1: committee_name | J1: entity_type | K1: entity_type_desc | L1: unused_contbr_id | M1: contributor_prefix | N1: contributor_name | O1: recipient_committee_type | P1: recipient_committee_org_type | Q1: recipient_committee_designation | R1: contributor_first_name | S1: contributor_middle_name | T1: contributor_last_name | U1: contributor_suffix | V1: contributor_street_1 | W1: contributor_street_2 | X1: contributor_city | Y1: contributor_state | Z1: contributor_zip | AA1: contributor_employer | AB1: contributor_occupation | AC1: contributor_id | AD1: receipt_type | AE1: receipt_type_desc | AF1: receipt_type_full | AG1: memo_code | AH1: memo_code_full | AI1: contribution_receipt_date | AJ1: contribution_receipt_amount | AK1: contributor_aggregate_ytd | AL1: candidate_id | AM1: candidate_name | AN1: candidate_first_name | AO1: candidate_last_name | AP1: candidate_middle_name | AQ1: candidate_prefix | AR1: candidate_suffix | AS1: candidate_office | AT1: candidate_office_full | AU1: candidate_office_state | AV1: candidate_office_state_full | AW1: candidate_office_district | AX1: conduit_committee_id | AY1: conduit_committee_name | AZ1: conduit_committee_street1 | BA1: conduit_committee_street2 | BB1: conduit_committee_city | BC1: conduit_committee_state | BD1: conduit_committee_zip | BE1: donor_committee_name | BF1: national_committee_nonfederal_account | BG1: election_type | BH1: election_type_full | BI1: fec_election_type_desc | BJ1: fec_election_year | BK1: amendment_indicator | BL1: amendment_indicator_desc | BM1: schedule_type_full | BN1: load_date | BO1: original_sub_id | BP1: back_reference_transaction_id | BQ1: back_reference_schedule_name | BR1: filing_form | BS1: link_id | BT1: is_individual | BU1: memo_text | BV1: two_year_transaction_period | BW1: schedule_type | BX1: increased_limit | BY1: sub_id | BZ1: pdf_url | CA1: line_number_label
A2: C00041160 | B2: MICHIGAN REPUBLICAN PARTY | C2: 2019 | D2: YE | E2: 2.0200132e+17 | F2: 11AI | G2: AC6D0363675694C048C9 | H2: 1378361 | J2: IND | K2: INDIVIDUAL | M2: MR. | N2: FORD, WILLIAM C MR. JR. | O2: Y | Q2: U | R2: WILLIAM | S2: C | T2: FORD | U2: JR. | V2: 2000 BRUSH ST | W2: STE 440 | X2: DETROIT | Y2: MI | Z2: 482262251 | AA2: FORD MOTOR COMPANY | AB2: CHAIRMAN OF THE BOARD | AD2: 15 | AE2: CONTRIBUTION | AI2: 43830 | AJ2: 10000 | AK2: 10000 | BG2: P | BI2: PRIMARY | BK2: A | BL2: ADD | BM2: ITEMIZED RECEIPTS | BN2: 43865.067 | BR2: F3X | BS2: 4.0131202e+18 | BT2: t | BV2: 2020 | BW2: SA | BY2: 4.0203202e+18 | BZ2: http://docquery.fec.gov/cgi-bin/fecimg/?202001319184822094 | CA2: Contributions From Individuals/Persons Other Than Political Committees
A3: C00041160 | B3: MICHIGAN REPUBLICAN PARTY | C3: 2019 | D3: YE | E3: 2.0200132e+17 | F3: SL1A | G3: A12D4014A0E7C477EADB | H3: 1378361 | J3: IND | K3: INDIVIDUAL | M3: MR. | N3: FORD, WILLIAM C MR. JR. | O3: Y | Q3: U | R3: WILLIAM | S3: C | T3: FORD | U3: JR. | V3: 2000 BRUSH ST | W3: STE 440 | X3: DETROIT | Y3: MI | Z3: 482262251 | AA3: FORD MOTOR COMPANY | AB3: CHAIRMAN OF THE BOARD | AD3: 10 | AE3: NON-FEDERAL RECEIPT FROM PERSONS | AI3: 43830 | AJ3: 10000 | AK3: 10000 | BF3: B07AE76AB | BG3: P | BI3: PRIMARY | BK3: A | BL3: ADD | BM3: ITEMIZED RECEIPTS | BN3: 43865.067 | BR3: F3X | BS3: 4.0131202e+18 | BT3: t | BV3: 2020 | BW3: SA | BY3: 4.0203202e+18 | BZ3: http://docquery.fec.gov/cgi-bin/fecimg/?202001319184822232 | CA3: Non-Federal Receipts from Persons Levin (L-1A)
A4: C00451153 | B4: GRIDIRON-PAC | C4: 2019 | D4: YE | E4: 2.0200132e+17 | F4: 11AI | G4: A2019-3118914 | H4: 1377045 | J4: IND | K4: INDIVIDUAL | N4: FORD, WILLIAM C JR. | O4: Q | Q4: B | R4: WILLIAM | S4: C | T4: FORD | U4: JR. | V4: C/O DETROIT LIONS | W4: 222 REPUBLIC DRIVE | X4: ALLEN PARK | Y4: MI | Z4: 48101 | AA4: DETROIT LIONS | AB4: OWNER/CHAIRMAN | AD4: 15 | AE4: CONTRIBUTION | AI4: 43815 | AJ4: 5000 | AK4: 5000 | BG4: P | BI4: PRIMARY | BK4: A | BL4: ADD | BM4: ITEMIZED RECEIPTS | BN4: 43883.092 | BR4: F3X | BS4: 4.0131202e+18 | BT4: t | BV4: 2020 | BW4: SA | BY4: 4.0221202e+18 | BZ4: http://docquery.fec.gov/cgi-bin/fecimg/?202001319184197999 | CA4: Contributions From Individuals/Persons Other Than Political Committees
A5: C00451153 | B5: GRIDIRON-PAC | C5: 2020 | D5: 30G | E5: 2.0201203e+17 | F5: 11AI | G5: A2020-2621925 | H5: 1476407 | J5: IND | K5: INDIVIDUAL | N5: FORD, WILLIAM C JR. | O5: Q | Q5: B | R5: WILLIAM | S5: C | T5: FORD | U5: JR. | V5: C/O DETROIT LIONS | W5: 222 REPUBLIC DRIVE | X5: ALLEN PARK | Y5: MI | Z5: 48101 | AA5: DETROIT LIONS | AB5: OWNER/CHAIRMAN | AD5: 15 | AE5: CONTRIBUTION | AI5: 44140 | AJ5: 5000 | AK5: 5000 | BG5: P | BI5: PRIMARY | BK5: A | BL5: ADD | BM5: ITEMIZED RECEIPTS | BN5: 44194.156 | BR5: F3X | BS5: 4.1203202e+18 | BT5: t | BV5: 2020 | BW5: SA | BY5: 4.1229202e+18 | BZ5: https://docquery.fec.gov/cgi-bin/fecimg/?202012029337427953 | CA5: Contributions From Individuals/Persons Other Than Political Committees
A6: C00437889 | B6: PETERS FOR MICHIGAN | C6: 2019 | D6: Q3 | E6: 2.021021e+17 | F6: 11AI | G6: VSH8GJ3NXZ2 | H6: 1499253 | J6: IND | K6: INDIVIDUAL | L6: C00401224 | N6: FORD, WILLIAM DAVID JR. | O6: S | Q6: P | R6: WILLIAM | S6: DAVID | T6: FORD | U6: JR. | V6: 2000 BRUSH ST | X6: DETROIT | Y6: MI | Z6: 482262251 | AA6: FORD | AB6: CHAIRMAN | AC6: C00401224 | AD6: 15E | AE6: EARMARKED CONTRIBUTION | AI6: 43664 | AJ6: 500 | AK6: 500 | BG6: P2020 | BI6: PRIMARY | BJ6: 2020 | BK6: N | BL6: NO CHANGE | BM6: ITEMIZED RECEIPTS | BN6: 44253.156 | BP6: VSH8GJ3NXZ2E | BQ6: SA11AI | BR6: F3 | BS6: 4.0209202e+18 | BT6: t | BU6: * EARMARKED CONTRIBUTION: SEE BELOW | BV6: 2020 | BW6: SA | BY6: 4.0226202e+18 | BZ6: https://docquery.fec.gov/cgi-bin/fecimg/?202102099427192923 | CA6: Contributions From Individuals/Persons Other Than Political Committees
A9: Row Labels | B9: Sum of contribution_receipt_amount | V9: =+V2&W2&X2&Y2&Z2 -> 2000 BRUSH STSTE 440DETROITMI482262251
A10: GRIDIRON-PAC | B10: 10000 | C10: N
A11: MICHIGAN REPUBLICAN PARTY | B11: 20000 | C11: R
A12: PETERS FOR MICHIGAN | B12: 500 | C12: D
A13: Grand Total | B13: 30500 | C13: R
A16: R | B16: =+GETPIVOTDATA("contribution_receipt_amount",$A$9,"committee_name","MICHIGAN REPUBLICAN PARTY") -> 20000
A17: N | B17: =+GETPIVOTDATA("contribution_receipt_amount",$A$9,"committee_name","GRIDIRON-PAC") -> 10000
A18: D | B18: =+GETPIVOTDATA("contribution_receipt_amount",$A$9,"committee_name","PETERS FOR MICHIGAN") -> 500
B19: =SUM(B16:B18) -> 30500

Sheet Henry Ford III
A1: committee_id | B1: committee_name | C1: report_year | D1: report_type | E1: image_number | F1: line_number | G1: transaction_id | H1: file_number | I1: committee_name | J1: entity_type | K1: entity_type_desc | L1: unused_contbr_id | M1: contributor_prefix | N1: contributor_name | O1: recipient_committee_type | P1: recipient_committee_org_type | Q1: recipient_committee_designation | R1: contributor_first_name | S1: contributor_middle_name | T1: contributor_last_name | U1: contributor_suffix | V1: contributor_street_1 | W1: contributor_street_2 | X1: contributor_city | Y1: contributor_state | Z1: contributor_zip | AA1: contributor_employer | AB1: contributor_occupation | AC1: contributor_id | AD1: receipt_type | AE1: receipt_type_desc | AF1: receipt_type_full | AG1: memo_code | AH1: memo_code_full | AI1: contribution_receipt_date | AJ1: contribution_receipt_amount | AK1: contributor_aggregate_ytd | AL1: candidate_id | AM1: candidate_name | AN1: candidate_first_name | AO1: candidate_last_name | AP1: candidate_middle_name | AQ1: candidate_prefix | AR1: candidate_suffix | AS1: candidate_office | AT1: candidate_office_full | AU1: candidate_office_state | AV1: candidate_office_state_full | AW1: candidate_office_district | AX1: conduit_committee_id | AY1: conduit_committee_name | AZ1: conduit_committee_street1 | BA1: conduit_committee_street2 | BB1: conduit_committee_city | BC1: conduit_committee_state | BD1: conduit_committee_zip | BE1: donor_committee_name | BF1: national_committee_nonfederal_account | BG1: election_type | BH1: election_type_full | BI1: fec_election_type_desc | BJ1: fec_election_year | BK1: amendment_indicator | BL1: amendment_indicator_desc | BM1: schedule_type_full | BN1: load_date | BO1: original_sub_id | BP1: back_reference_transaction_id | BQ1: back_reference_schedule_name | BR1: filing_form | BS1: link_id | BT1: is_individual | BU1: memo_text | BV1: two_year_transaction_period | BW1: schedule_type | BX1: increased_limit | BY1: sub_id | BZ1: pdf_url | CA1: line_number_label
A2: C00046474 | B2: FORD MOTOR COMPANY CIVIC ACTION FUND | C2: 2019 | D2: M8 | E2: 2.019081e+17 | F2: 11AI | G2: PR263716430056 | H2: 1347296 | J2: IND | K2: INDIVIDUAL | N2: FORD III, HENRY | O2: Q | P2: C | Q2: B | R2: HENRY | T2: FORD III | V2: 475 TOOTING LANE | X2: BIRMINGHAM | Y2: MI | Z2: 480091334 | AA2: FORD MOTOR COMPANY | AB2: STRATEGY SENIOR MANAGER | AD2: 15 | AE2: CONTRIBUTION | AI2: 43677 | AJ2: 30 | AK2: 210 | BG2: P | BI2: PRIMARY | BK2: A | BL2: ADD | BM2: ITEMIZED RECEIPTS | BN2: 43687.127 | BR2: F3X | BS2: 4.0809202e+18 | BT2: t | BU2: P/R DEDUCTION ($30.00 MONTHLY) | BV2: 2020 | BW2: SA | BY2: 4.0809202e+18 | BZ2: http://docquery.fec.gov/cgi-bin/fecimg/?201908099162203655 | CA2: Contributions From Individuals/Persons Other Than Political Committees
A3: C00046474 | B3: FORD MOTOR COMPANY CIVIC ACTION FUND | C3: 2019 | D3: M9 | E3: 2.0190919e+17 | F3: 11AI | G3: PR263716430283 | H3: 1352521 | J3: IND | K3: INDIVIDUAL | N3: FORD III, HENRY | O3: Q | P3: C | Q3: B | R3: HENRY | T3: FORD III | V3: 475 TOOTING LANE | X3: BIRMINGHAM | Y3: MI | Z3: 480091334 | AA3: FORD MOTOR COMPANY | AB3: STRATEGY SENIOR MANAGER | AD3: 15 | AE3: CONTRIBUTION | AI3: 43708 | AJ3: 30 | AK3: 240 | BG3: P | BI3: PRIMARY | BK3: A | BL3: ADD | BM3: ITEMIZED RECEIPTS | BN3: 43727.111 | BR3: F3X | BS3: 4.0918202e+18 | BT3: t | BU3: P/R DEDUCTION ($30.00 MONTHLY) | BV3: 2020 | BW3: SA | BY3: 4.0918202e+18 | BZ3: http://docquery.fec.gov/cgi-bin/fecimg/?201909189163369109 | CA3: Contributions From Individuals/Persons Other Than Political Committees
A4: C00046474 | B4: FORD MOTOR COMPANY CIVIC ACTION FUND | C4: 2019 | D4: M10 | E4: 2.0191018e+17 | F4: 11AI | G4: PR263716430680 | H4: 1359511 | J4: IND | K4: INDIVIDUAL | N4: FORD III, HENRY | O4: Q | P4: C | Q4: B | R4: HENRY | T4: FORD III | V4: 475 TOOTING LANE | X4: BIRMINGHAM | Y4: MI | Z4: 480091334 | AA4: FORD MOTOR COMPANY | AB4: STRATEGY SENIOR MANAGER | AD4: 15 | AE4: CONTRIBUTION | AI4: 43738 | AJ4: 30 | AK4: 270 | BG4: P | BI4: PRIMARY | BK4: A | BL4: ADD | BM4: ITEMIZED RECEIPTS | BN4: 43757.114 | BR4: F3X | BS4: 4.1017202e+18 | BT4: t | BU4: P/R DEDUCTION ($30.00 MONTHLY) | BV4: 2020 | BW4: SA | BY4: 4.1018202e+18 | BZ4: http://docquery.fec.gov/cgi-bin/fecimg/?201910179165017456 | CA4: Contributions From Individuals/Persons Other Than Political Committees
A5: C00650150 | B5: ELISSA SLOTKIN FOR CONGRESS | C5: 2019 | D5: Q3 | E5: 2.0191016e+17 | F5: 11AI | G5: VTQYSJQG6E8 | H5: 1358782 | J5: IND | K5: INDIVIDUAL | L5: C00401224 | N5: FORD, HENRY III | O5: H | Q5: P | R5: HENRY | T5: FORD | U5: III | V5: 241 LAKE SHORE RD | X5: GROSSE POINTE FARMS | Y5: MI | Z5: 482363758 | AA5: FORD MOTOR COMPANY | AB5: CONSULTANT | AC5: C00401224 | AD5: 15E | AE5: EARMARKED CONTRIBUTION | AI5: 43737 | AJ5: 2800 | AK5: 2800 | BG5: P2020 | BI5: PRIMARY | BJ5: 2020 | BK5: A | BL5: ADD | BM5: ITEMIZED RECEIPTS | BN5: 43760.113 | BP5: VTQYSJQG6E8E | BQ5: SA11AI | BR5: F3 | BS5: 4.1016202e+18 | BT5: t | BU5: * EARMARKED CONTRIBUTION: SEE BELOW | BV5: 2020 | BW5: SA | BY5: 4.1021202e+18 | BZ5: http://docquery.fec.gov/cgi-bin/fecimg/?201910159164698235 | CA5: Contributions From Individuals/Persons Other Than Political Committees
A6: C00046474 | B6: FORD MOTOR COMPANY CIVIC ACTION FUND | C6: 2019 | D6: YE | E6: 2.0200129e+17 | F6: 11AI | G6: PR263716431700 | H6: 1374056 | J6: IND | K6: INDIVIDUAL | N6: FORD III, HENRY | O6: Q | P6: C | Q6: B | R6: HENRY | T6: FORD III | V6: 475 TOOTING LANE | X6: BIRMINGHAM | Y6: MI | Z6: 480091334 | AA6: FORD MOTOR COMPANY | AB6: STRATEGY SENIOR MANAGER | AD6: 15 | AE6: CONTRIBUTION | AI6: 43830 | AJ6: 30 | AK6: 360 | BG6: P | BI6: PRIMARY | BK6: A | BL6: ADD | BM6: ITEMIZED RECEIPTS | BN6: 43859.073 | BR6: F3X | BS6: 4.0128202e+18 | BT6: t | BU6: P/R DEDUCTION ($30.00 MONTHLY) | BV6: 2020 | BW6: SA | BY6: 4.0128202e+18 | BZ6: http://docquery.fec.gov/cgi-bin/fecimg/?202001289167420439 | CA6: Contributions From Individuals/Persons Other Than Political Committees
A7: C00638650 | B7: HALEY STEVENS FOR CONGRESS | C7: 2019 | D7: Q3 | E7: 2.0191102e+17 | F7: 11AI | G7: VTEJ1XCY1H1 | H7: 1361434 | J7: IND | K7: INDIVIDUAL | L7: C00401224 | N7: FORD, HENRY III | O7: H | Q7: P | R7: HENRY | T7: FORD | U7: III | V7: 241 LAKE SHORE RD | X7: GROSSE POINTE FARMS | Y7: MI | Z7: 482363758 | AA7: FORD MOTOR COMPANY | AB7: CONSULTANT | AC7: C00401224 | AD7: 15E | AE7: EARMARKED CONTRIBUTION | AI7: 43700 | AJ7: 2800 | AK7: 5600 | BG7: G2020 | BI7: GENERAL | BJ7: 2020 | BK7: N | BL7: NO CHANGE | BM7: ITEMIZED RECEIPTS | BN7: 43773.066 | BP7: VTEJ1XCY1H1E | BQ7: SA11AI | BR7: F3 | BS7: 4.1101202e+18 | BT7: t | BU7: * EARMARKED CONTRIBUTION: SEE BELOW | BV7: 2020 | BW7: SA | BY7: 4.1103202e+18 | BZ7: http://docquery.fec.gov/cgi-bin/fecimg/?201911019165320623 | CA7: Contributions From Individuals/Persons Other Than Political Committees
A8: C00638650 | B8: HALEY STEVENS FOR CONGRESS | C8: 2019 | D8: Q3 | E8: 2.0191102e+17 | F8: 11AI | G8: VTEJ1XCY1J9 | H8: 1361434 | J8: IND | K8: INDIVIDUAL | L8: C00401224 | N8: FORD, HENRY III | O8: H | Q8: P | R8: HENRY | T8: FORD | U8: III | V8: 241 LAKE SHORE RD | X8: GROSSE POINTE FARMS | Y8: MI | Z8: 482363758 | AA8: FORD MOTOR COMPANY | AB8: CONSULTANT | AC8: C00401224 | AD8: 15E | AE8: EARMARKED CONTRIBUTION | AI8: 43700 | AJ8: 100 | AK8: 5600 | BG8: P2020 | BI8: PRIMARY | BJ8: 2020 | BK8: N | BL8: NO CHANGE | BM8: ITEMIZED RECEIPTS | BN8: 43773.066 | BP8: VTEJ1XCY1J9E | BQ8: SA11AI | BR8: F3 | BS8: 4.1101202e+18 | BT8: t | BU8: * EARMARKED CONTRIBUTION: SEE BELOW | BV8: 2020 | BW8: SA | BY8: 4.1103202e+18 | BZ8: http://docquery.fec.gov/cgi-bin/fecimg/?201911019165321080 | CA8: Contributions From Individuals/Persons Other Than Political Committees
A9: C00046474 | B9: FORD MOTOR COMPANY CIVIC ACTION FUND | C9: 2019 | D9: M12 | E9: 2.0191219e+17 | F9: 11AI | G9: PR263716431137 | H9: 1366669 | J9: IND | K9: INDIVIDUAL | N9: FORD III, HENRY | O9: Q | P9: C | Q9: B | R9: HENRY | T9: FORD III | V9: 475 TOOTING LANE | X9: BIRMINGHAM | Y9: MI | Z9: 480091334 | AA9: FORD MOTOR COMPANY | AB9: STRATEGY SENIOR MANAGER | AD9: 15 | AE9: CONTRIBUTION | AI9: 43799 | AJ9: 30 | AK9: 330 | BG9: P | BI9: PRIMARY | BK9: A | BL9: ADD | BM9: ITEMIZED RECEIPTS | BN9: 43818.072 | BR9: F3X | BS9: 4.1218202e+18 | BT9: t | BU9: P/R DEDUCTION ($30.00 MONTHLY) | BV9: 2020 | BW9: SA | BY9: 4.1218202e+18 | BZ9: http://docquery.fec.gov/cgi-bin/fecimg/?201912189166359638 | CA9: Contributions From Individuals/Persons Other Than Political Committees
A10: C00638650 | B10: HALEY STEVENS FOR CONGRESS | C10: 2019 | D10: Q1 | E10: 2.0200716e+17 | F10: 11AI | G10: VTEJ1WDRTM3 | H10: 1422134 | J10: IND | K10: INDIVIDUAL | L10: C00401224 | N10: FORD, HENRY III | O10: H | Q10: P | R10: HENRY | T10: FORD | U10: III | V10: 241 LAKE SHORE RD | X10: GROSSE POINTE FARMS | Y10: MI | Z10: 482363758 | AA10: FORD MOTOR COMPANY | AB10: CONSULTANT | AC10: C00401224 | AD10: 15E | AE10: EARMARKED CONTRIBUTION | AI10: 43474 | AJ10: 2700 | AK10: 2700 | BG10: P2020 | BI10: PRIMARY | BJ10: 2020 | BK10: C | BL10: CHANGE | BM10: ITEMIZED RECEIPTS | BN10: 44051.152 | BP10: VTEJ1WDRTM3E | BQ10: SA11AI | BR10: F3 | BS10: 4.0715202e+18 | BT10: t | BU10: * EARMARKED CONTRIBUTION: SEE BELOW | BV10: 2020 | BW10: SA | BY10: 4.0808202e+18 | BZ10: http://docquery.fec.gov/cgi-bin/fecimg/?202007159244639174 | CA10: Contributions From Individuals/Persons Other Than Political Committees
A11: C00512970 | B11: KENNEDY FOR MASSACHUSETTS | C11: 2020 | D11: Q2 | E11: 2.0200716e+17 | F11: 11AI | G11: VNHWQFGRX35 | H11: 1424896 | J11: IND | K11: INDIVIDUAL | L11: C00401224 | N11: FORD III, HENRY | O11: S | Q11: P | R11: HENRY | T11: FORD III | V11: 2000 BRUSH ST | W11: STE 440 | X11: DETROIT | Y11: MI | Z11: 482262251 | AA11: FORD | AB11: STRATEGY | AC11: C00401224 | AD11: 15E | AE11: EARMARKED CONTRIBUTION | AI11: 44012 | AJ11: 1000 | AK11: 1000 | BG11: P2020 | BI11: PRIMARY | BJ11: 2020 | BK11: A | BL11: ADD | BM11: ITEMIZED RECEIPTS | BN11: 44057.153 | BP11: VNHWQFGRX35E | BQ11: SA11AI | BR11: F3 | BS11: 4.0716202e+18 | BT11: t | BU11: * EARMARKED CONTRIBUTION: SEE BELOW | BV11: 2020 | BW11: SA | BY11: 4.0814202e+18 | BZ11: http://docquery.fec.gov/cgi-bin/fecimg/?202007159250112120 | CA11: Contributions From Individuals/Persons Other Than Political Committees
A12: C00543504 | B12: 4 MA PAC | C12: 2020 | D12: YE | E12: 2.0210132e+17 | F12: 11AI | G12: 1956274 | H12: 1496290 | J12: IND | K12: INDIVIDUAL | L12: C00401224 | N12: FORD, HENRY III | O12: Q | Q12: D | R12: HENRY | T12: FORD | U12: III | V12: 2000 BRUSH ST | W12: STE 440 | X12: DETROIT | Y12: MI | Z12: 482262251 | AA12: FORD | AB12: MANAGER | AC12: C00401224 | AD12: 15E | AE12: EARMARKED CONTRIBUTION | AI12: 44196 | AJ12: 500 | AK12: 500 | BG12: P | BI12: PRIMARY | BK12: A | BL12: ADD | BM12: ITEMIZED RECEIPTS | BN12: 44237.532 | BP12: 1956274E | BQ12: SA11AI | BR12: F3X | BS12: 4.0201202e+18 | BT12: t | BU12: * EARMARKED CONTRIBUTION: SEE BELOW | BV12: 2020 | BW12: SA | BY12: 4.0209202e+18 | BZ12: https://docquery.fec.gov/cgi-bin/fecimg/?202101319418624803 | CA12: Contributions From Individuals/Persons Other Than Political Committees
A13: C00046474 | B13: FORD MOTOR COMPANY CIVIC ACTION FUND | C13: 2020 | D13: 12G | E13: 2.0201022e+17 | F13: 11AI | G13: PR263716434207 | H13: 1459687 | J13: IND | K13: INDIVIDUAL | N13: FORD III, HENRY | O13: Q | P13: C | Q13: B | R13: HENRY | T13: FORD III | V13: 475 TOOTING LANE | X13: BIRMINGHAM | Y13: MI | Z13: 480091334 | AA13: FORD MOTOR COMPANY | AB13: DIRECTOR | AD13: 15 | AE13: CONTRIBUTION | AI13: 44118 | AJ13: 30 | AK13: 300 | BG13: P | BI13: PRIMARY | BK13: A | BL13: ADD | BM13: ITEMIZED RECEIPTS | BN13: 44168.152 | BR13: F3X | BS13: 4.1022202e+18 | BT13: t | BU13: P/R DEDUCTION ($30.00 MONTHLY) | BV13: 2020 | BW13: SA | BY13: 4.1203202e+18 | BZ13: http://docquery.fec.gov/cgi-bin/fecimg/?202010219326755864 | CA13: Contributions From Individuals/Persons Other Than Political Committees
A14: C00046474 | B14: FORD MOTOR COMPANY CIVIC ACTION FUND | C14: 2020 | D14: 30G | E14: 2.0201202e+17 | F14: 11AI | G14: PR263716434585 | H14: 1475097 | J14: IND | K14: INDIVIDUAL | N14: FORD III, HENRY | O14: Q | P14: C | Q14: B | R14: HENRY | T14: FORD III | V14: 475 TOOTING LANE | X14: BIRMINGHAM | Y14: MI | Z14: 480091334 | AA14: FORD MOTOR COMPANY | AB14: DIRECTOR | AD14: 15 | AE14: CONTRIBUTION | AI14: 44158 | AJ14: 30 | AK14: 330 | BG14: P | BI14: PRIMARY | BK14: A | BL14: ADD | BM14: ITEMIZED RECEIPTS | BN14: 44177.155 | BR14: F3X | BS14: 4.1202202e+18 | BT14: t | BU14: P/R DEDUCTION ($30.00 MONTHLY) | BV14: 2020 | BW14: SA | BY14: 4.1212202e+18 | BZ14: http://docquery.fec.gov/cgi-bin/fecimg/?202012019337235364 | CA14: Contributions From Individuals/Persons Other Than Political Committees
A15: C00437889 | B15: PETERS FOR MICHIGAN | C15: 2019 | D15: Q3 | E15: 2.021021e+17 | F15: 11AI | G15: VSH8GJD7KJ9 | H15: 1499253 | J15: IND | K15: INDIVIDUAL | L15: C00401224 | N15: FORD, HENRY III | O15: S | Q15: P | R15: HENRY | T15: FORD | U15: III | V15: 2000 BRUSH ST | X15: DETROIT | Y15: MI | Z15: 482262251 | AA15: FORD MOTOR COMPANY | AB15: STRATEGY | AC15: C00401224 | AD15: 15E | AE15: EARMARKED CONTRIBUTION | AI15: 43737 | AJ15: 2800 | AK15: 2800 | BG15: P2020 | BI15: PRIMARY | BJ15: 2020 | BK15: C | BL15: CHANGE | BM15: ITEMIZED RECEIPTS | BN15: 44253.156 | BP15: VSH8GJD7KJ9E | BQ15: SA11AI | BR15: F3 | BS15: 4.0209202e+18 | BT15: t | BU15: * EARMARKED CONTRIBUTION: SEE BELOW | BV15: 2020 | BW15: SA | BY15: 4.0226202e+18 | BZ15: https://docquery.fec.gov/cgi-bin/fecimg/?202102099427194388 | CA15: Contributions From Individuals/Persons Other Than Political Committees
V17: =+V15&X15&Y15&Z15 -> 2000 BRUSH STDETROITMI482262251
A19: Row Labels | B19: Sum of contribution_receipt_amount
A20: 4 MA PAC | B20: 500 | C20: D
A21: ELISSA SLOTKIN FOR CONGRESS | B21: 2800 | C21: D
A22: FORD MOTOR COMPANY CIVIC ACTION FUND | B22: 210 | C22: N
A23: HALEY STEVENS FOR CONGRESS | B23: 5600 | C23: D
A24: KENNEDY FOR MASSACHUSETTS | B24: 1000 | C24: D
A25: PETERS FOR MICHIGAN | B25: 2800 | C25: D
A26: Grand Total | B26: 12910
A28: D | B28: =+GETPIVOTDATA("contribution_receipt_amount",$A$19)-GETPIVOTDATA("contribution_receipt_amount",$A$19,"committee_name","FORD MOTOR COMPANY CIVIC ACTION FUND") -> 12700
A29: N | B29: =+GETPIVOTDATA("contribution_receipt_amount",$A$19,"committee_name","FORD MOTOR COMPANY CIVIC ACTION FUND") -> 210
B30: =SUM(B28:B29) -> 12910

Sheet Anthony Earley
A1: committee_id | B1: committee_name | C1: report_year | D1: report_type | E1: image_number | F1: line_number | G1: transaction_id | H1: file_number | I1: committee_name | J1: entity_type | K1: entity_type_desc | L1: unused_contbr_id | M1: contributor_prefix | N1: contributor_name | O1: recipient_committee_type | P1: recipient_committee_org_type | Q1: recipient_committee_designation | R1: contributor_first_name | S1: contributor_middle_name | T1: contributor_last_name | U1: contributor_suffix | V1: contributor_street_1 | W1: contributor_street_2 | X1: contributor_city | Y1: contributor_state | Z1: contributor_zip | AA1: contributor_employer | AB1: contributor_occupation | AC1: contributor_id | AD1: receipt_type | AE1: receipt_type_desc | AF1: receipt_type_full | AG1: memo_code | AH1: memo_code_full | AI1: contribution_receipt_date | AJ1: contribution_receipt_amount | AK1: contributor_aggregate_ytd | AL1: candidate_id | AM1: candidate_name | AN1: candidate_first_name | AO1: candidate_last_name | AP1: candidate_middle_name | AQ1: candidate_prefix | AR1: candidate_suffix | AS1: candidate_office | AT1: candidate_office_full | AU1: candidate_office_state | AV1: candidate_office_state_full | AW1: candidate_office_district | AX1: conduit_committee_id | AY1: conduit_committee_name | AZ1: conduit_committee_street1 | BA1: conduit_committee_street2 | BB1: conduit_committee_city | BC1: conduit_committee_state | BD1: conduit_committee_zip | BE1: donor_committee_name | BF1: national_committee_nonfederal_account | BG1: election_type | BH1: election_type_full | BI1: fec_election_type_desc | BJ1: fec_election_year | BK1: amendment_indicator | BL1: amendment_indicator_desc | BM1: schedule_type_full | BN1: load_date | BO1: original_sub_id | BP1: back_reference_transaction_id | BQ1: back_reference_schedule_name | BR1: filing_form | BS1: link_id | BT1: is_individual | BU1: memo_text | BV1: two_year_transaction_period | BW1: schedule_type | BX1: increased_limit | BY1: sub_id | BZ1: pdf_url | CA1: line_number_label
A2: C00706861 | B2: MARK KELLY VICTORY FUND | C2: 2020 | D2: Q3 | E2: 2.0201016e+17 | F2: 11AI | G2: VVC31W5CPX1 | H2: 1451656 | J2: IND | K2: INDIVIDUAL | L2: C00401224 | N2: EARLEY, ANTHONY | O2: N | Q2: J | R2: ANTHONY | T2: EARLEY | V2: 3926 OAKLAND DR | X2: BLOOMFIELD HILLS | Y2: MI | Z2: 483013253 | AA2: NOT EMPLOYED | AB2: RETIRED | AC2: C00401224 | AD2: 15E | AE2: EARMARKED CONTRIBUTION | AI2: 44096 | AJ2: 500 | AK2: 500 | BG2: P | BI2: PRIMARY | BK2: A | BL2: ADD | BM2: ITEMIZED RECEIPTS | BN2: 44143.152 | BP2: VVC31W5CPX1E | BQ2: SA11AI | BR2: F3X | BS2: 4.1016202e+18 | BT2: t | BU2: * EARMARKED CONTRIBUTION: SEE BELOW | BV2: 2020 | BW2: SA | BY2: 4.1108202e+18 | BZ2: http://docquery.fec.gov/cgi-bin/fecimg/?202010159295006542 | CA2: Contributions From Individuals/Persons Other Than Political Committees
A3: C00729947 | B3: GRETCHEN DRISKELL FOR CONGRESS | C3: 2019 | D3: YE | E3: 2.0200116e+17 | F3: 11AI | G3: VPFAPSJ7QZ5 | H3: 1370394 | J3: IND | K3: INDIVIDUAL | L3: C00401224 | N3: EARLEY, ANTHONY F JR. | O3: H | Q3: P | R3: ANTHONY | S3: F | T3: EARLEY | U3: JR. | V3: 3926 OAKLAND DR | X3: BLOOMFIELD | Y3: MI | Z3: 483013253 | AA3: NOT EMPLOYED | AB3: RETIRED | AC3: C00401224 | AD3: 15E | AE3: EARMARKED CONTRIBUTION | AI3: 43803 | AJ3: 250 | AK3: 250 | BG3: P2020 | BI3: PRIMARY | BJ3: 2020 | BK3: A | BL3: ADD | BM3: ITEMIZED RECEIPTS | BN3: 43846.063 | BP3: VPFAPSJ7QZ5E | BQ3: SA11AI | BR3: F3 | BS3: 4.0115202e+18 | BT3: t | BU3: * EARMARKED CONTRIBUTION: SEE BELOW | BV3: 2020 | BW3: SA | BY3: 4.0115202e+18 | BZ3: http://docquery.fec.gov/cgi-bin/fecimg/?202001159167183208 | CA3: Contributions From Individuals/Persons Other Than Political Committees
A4: C00711549 | B4: AMY MCGRATH FOR SENATE, INC. | C4: 2020 | D4: Q3 | E4: 2.0210702e+17 | F4: 11AI | G4: 11AI-001632190 | H4: 1522129 | J4: IND | K4: INDIVIDUAL | N4: EARLEY, ANTHONY | O4: S | Q4: P | R4: ANTHONY | T4: EARLEY | V4: 3926 OAKLAND DRIVE | X4: BLOOMFIELD HILLS | Y4: MI | Z4: 48301 | AA4: RETIRED | AB4: RETIRED | AG4: X | AI4: 44043 | AJ4: 100 | AK4: 100 | BG4: G2020 | BI4: GENERAL | BJ4: 2020 | BK4: A | BL4: ADD | BM4: ITEMIZED RECEIPTS | BN4: 44384.155 | BR4: F3 | BS4: 4.0702202e+18 | BT4: t | BU4: WIN THE SENATE 2020 | BV4: 2020 | BW4: SA | BY4: 4.0707202e+18 | BZ4: https://docquery.fec.gov/cgi-bin/fecimg/?202107019450911908 | CA4: Contributions From Individuals/Persons Other Than Political Committees
A5: C00711549 | B5: AMY MCGRATH FOR SENATE, INC. | C5: 2020 | D5: Q3 | E5: 2.0210702e+17 | F5: 11AI | G5: 11AI-001632191 | H5: 1522129 | J5: IND | K5: INDIVIDUAL | N5: EARLEY, ANTHONY | O5: S | Q5: P | R5: ANTHONY | T5: EARLEY | V5: 3926 OAKLAND DRIVE | X5: BLOOMFIELD HILLS | Y5: MI | Z5: 48301 | AA5: RETIRED | AB5: RETIRED | AG5: X | AI5: 44060 | AJ5: 50 | AK5: 150 | BG5: G2020 | BI5: GENERAL | BJ5: 2020 | BK5: A | BL5: ADD | BM5: ITEMIZED RECEIPTS | BN5: 44384.155 | BR5: F3 | BS5: 4.0702202e+18 | BT5: t | BU5: WIN THE SENATE 2020 | BV5: 2020 | BW5: SA | BY5: 4.0707202e+18 | BZ5: https://docquery.fec.gov/cgi-bin/fecimg/?202107019450911909 | CA5: Contributions From Individuals/Persons Other Than Political Committees
A6: C00401224 | B6: ACTBLUE | C6: 2019 | D6: YE | E6: 2.020013e+17 | F6: 11AI | G6: SA11AI_176139389 | H6: 1378435 | J6: IND | K6: INDIVIDUAL | N6: EARLEY, ANTHONY | O6: V | Q6: U | R6: ANTHONY | T6: EARLEY | V6: 3926 OAKLAND DR | X6: BLOOMFIELD HILLS | Y6: MI | Z6: 48301 | AA6: NOT EMPLOYED | AB6: NOT EMPLOYED | AF6: EARMARK | AI6: 43717 | AJ6: 100 | AK6: 100 | BF6: _x000D_ | BK6: A | BL6: ADD | BM6: ITEMIZED RECEIPTS | BN6: 43894.521 | BR6: F3X | BS6: 4.0201202e+18 | BT6: t | BU6: EARMARKED FOR DCCC (C00000935) | BV6: 2020 | BW6: SA | BY6: 4.0302202e+18 | BZ6: http://docquery.fec.gov/cgi-bin/fecimg/?202001299169454232 | CA6: Contributions From Individuals/Persons Other Than Political Committees
A7: C00401224 | B7: ACTBLUE | C7: 2019 | D7: YE | E7: 2.020013e+17 | F7: 11AI | G7: SA11AI_171568865 | H7: 1378435 | J7: IND | K7: INDIVIDUAL | N7: EARLEY, ANTHONY | O7: V | Q7: U | R7: ANTHONY | T7: EARLEY | V7: 3926 OAKLAND DR | X7: BLOOMFIELD HILLS | Y7: MI | Z7: 48301 | AA7: NOT EMPLOYED | AB7: NOT EMPLOYED | AF7: EARMARK | AI7: 43689 | AJ7: 100 | AK7: 100 | BF7: _x000D_ | BK7: A | BL7: ADD | BM7: ITEMIZED RECEIPTS | BN7: 43894.589 | BR7: F3X | BS7: 4.0201202e+18 | BT7: t | BU7: EARMARKED FOR MARK KELLY FOR SENATE (C00696526) | BV7: 2020 | BW7: SA | BY7: 4.0302202e+18 | BZ7: http://docquery.fec.gov/cgi-bin/fecimg/?202001299169454232 | CA7: Contributions From Individuals/Persons Other Than Political Committees
A8: C00437889 | B8: PETERS FOR MICHIGAN | C8: 2020 | D8: Q1 | E8: 2.0210306e+17 | F8: 11AI | G8: VSH8GK2W8Y0 | H8: 1502942 | J8: IND | K8: INDIVIDUAL | N8: EARLEY, ANTHONY | O8: S | Q8: P | R8: ANTHONY | T8: EARLEY | V8: 3926 OAKLAND DR | X8: BLOOMFIELD HILLS | Y8: MI | Z8: 483013253 | AA8: NOT EMPLOYED | AB8: RETIRED | AD8: 15E | AE8: EARMARKED CONTRIBUTION | AI8: 43860 | AJ8: 900 | AK8: 3700 | BG8: G2020 | BI8: GENERAL | BJ8: 2020 | BK8: A | BL8: ADD | BM8: ITEMIZED RECEIPTS | BN8: 44264.161 | BP8: VSH8GK2W8Y0E | BQ8: SA11AI | BR8: F3 | BS8: 4.0306202e+18 | BT8: t | BU8: * EARMARKED CONTRIBUTION: SEE BELOW | BV8: 2020 | BW8: SA | BY8: 4.0309202e+18 | BZ8: https://docquery.fec.gov/cgi-bin/fecimg/?202103059440177204 | CA8: Contributions From Individuals/Persons Other Than Political Committees
A9: C00437889 | B9: PETERS FOR MICHIGAN | C9: 2020 | D9: Q1 | E9: 2.0210306e+17 | F9: 11AI | G9: VSH8GK2QE72 | H9: 1502942 | J9: IND | K9: INDIVIDUAL | N9: EARLEY, ANTHONY | O9: S | Q9: P | R9: ANTHONY | T9: EARLEY | V9: 3926 OAKLAND DR | X9: BLOOMFIELD HILLS | Y9: MI | Z9: 483013253 | AA9: NOT EMPLOYED | AB9: RETIRED | AD9: 15E | AE9: EARMARKED CONTRIBUTION | AI9: 43860 | AJ9: 1600 | AK9: 3700 | BG9: P2020 | BI9: PRIMARY | BJ9: 2020 | BK9: A | BL9: ADD | BM9: ITEMIZED RECEIPTS | BN9: 44264.162 | BP9: VSH8GK2QE72E | BQ9: SA11AI | BR9: F3 | BS9: 4.0306202e+18 | BT9: t | BU9: * EARMARKED CONTRIBUTION: SEE BELOW | BV9: 2020 | BW9: SA | BY9: 4.0309202e+18 | BZ9: https://docquery.fec.gov/cgi-bin/fecimg/?202103059440178048 | CA9: Contributions From Individuals/Persons Other Than Political Committees
A10: C00697441 | B10: WIN THE ERA PAC | C10: 2019 | D10: YE | E10: 2.0200324e+17 | F10: 17A | G10: 2256395 | H10: 1391818 | J10: IND | K10: INDIVIDUAL | L10: C00401224 | N10: EARLEY, ANTHONY | O10: N | Q10: U | R10: ANTHONY | T10: EARLEY | V10: 3926 OAKLAND DR | X10: BLOOMFIELD HILLS | Y10: MI | Z10: 483013253 | AA10: RETIRED | AB10: RETIRED | AC10: C00401224 | AD10: 15E | AE10: EARMARKED CONTRIBUTION | AI10: 43807 | AJ10: 250 | AK10: 250 | BG10: P2020 | BH10: PRIMARY | BI10: PRIMARY | BJ10: 2020 | BK10: A | BL10: ADD | BM10: ITEMIZED RECEIPTS | BN10: 44079.157 | BP10: 2256395E | BQ10: SA17A | BR10: F3P | BS10: 4.0324202e+18 | BT10: t | BU10: * EARMARKED CONTRIBUTION: SEE BELOW | BV10: 2020 | BW10: SA | BY10: 4.0325202e+18 | BZ10: http://docquery.fec.gov/cgi-bin/fecimg/?202003239215653884 | CA10: Contributions From Individuals/Persons Other Than Political Committees
A11: C00696419 | B11: AMY FOR AMERICA | C11: 2020 | D11: M2 | E11: 2.0200716e+17 | F11: 17A | G11: 1238647 | H11: 1424437 | J11: IND | K11: INDIVIDUAL | N11: EARLEY, ANTHONY | O11: P | Q11: P | R11: ANTHONY | T11: EARLEY | V11: 3926 OAKLAND DR | X11: BLOOMFIELD HILLS | Y11: MI | Z11: 483013253 | AA11: NOT EMPLOYED | AB11: RETIRED | AD11: 15E | AE11: EARMARKED CONTRIBUTION | AI11: 43860 | AJ11: 1000 | AK11: 1500 | BG11: P2020 | BI11: PRIMARY | BJ11: 2020 | BK11: A | BL11: ADD | BM11: ITEMIZED RECEIPTS | BN11: 44033.13 | BP11: 1238647E | BQ11: SA17A | BR11: F3P | BS11: 4.0716202e+18 | BT11: t | BU11: * EARMARKED CONTRIBUTION: SEE BELOW | BV11: 2020 | BW11: SA | BY11: 4.0720202e+18 | BZ11: http://docquery.fec.gov/cgi-bin/fecimg/?202007159249894882 | CA11: Contributions From Individuals/Persons Other Than Political Committees
